Workbook
Name Lastraw: IF('[1]Vehicle Amortization'!Values_Entered,'[1]Vehicle Amortization'!Header_Row+'[1]Vehicle Amortization'!Number_of_Payments,'[1]Vehicle Amortization'!Header_Row)
Name rtr: [2]CapEx_Amortization!$G$18:$G$497

Sheet Sheet1
A1: RPP Scenario | B1: Parking Provider | C1: Parking Meter Type | D1: Enforcement Cost | E1: Parking Management Cost | F1: Cap Ex Amoritized, 10% over 5 yrs | G1: Cap Ex Amoritized, 10% over 3 yrs | H1: YOY Increase
A2: Existing | B2: ACE | C2: Multi-Space | D2: 401723 | E2: =400319+36600+173765 -> 610684 | F2: 193205.27 | G2: 294508.88 | H2: 0.04
A3: Existing | B3: ACE | C3: Single-Space | D3: 415076 | E3: =685168+36600+276025 -> 997793 | F3: 279428.01 | G3: 425940.91 | H3: 0.04
A4: Existing | B4: ACE | C4: Dual-Head | D4: 408476 | E4: =533248+36600+210996 -> 780844 | F4: 188681.41 | G4: 287613.02 | H4: 0.04
A5: Existing | B5: LAZ | C5: Multi-Space | D5: 527863.88 | E5: 321062.14 | F5: =-PMT(10%,5,'Existing RPP - KH Inhouse'!$O$53-'Existing RPP - KH Inhouse'!$O$50) -> 164401.32 | G5: =-PMT(10%,3,'Existing RPP - KH Inhouse'!$O$53-'Existing RPP - KH Inhouse'!$O$50) -> 250602.1 | H5: 0.03
A6: Existing | B6: LAZ | C6: Single-Space | D6: 527863.88 | E6: 321062.14 | F6: =-PMT(10%,5,'Existing RPP - KH Inhouse'!$M$53-'Existing RPP - KH Inhouse'!$M$50) -> 289163.1 | G6: =-PMT(10%,3,'Existing RPP - KH Inhouse'!$M$53-'Existing RPP - KH Inhouse'!$M$50) -> 440780.41 | H6: 0.03
A7: Existing | B7: LAZ | C7: Dual-Head | D7: 527863.88 | E7: 321062.14 | F7: =-PMT(10%,5,'Existing RPP - KH Inhouse'!$N$53-'Existing RPP - KH Inhouse'!$N$50) -> 177692.28 | G7: =-PMT(10%,3,'Existing RPP - KH Inhouse'!$N$53-'Existing RPP - KH Inhouse'!$N$50) -> 270861.94 | H7: 0.03
A8: Expanded | B8: ACE | C8: Multi-Space | D8: 481578 | E8: =400319+36600+173765 -> 610684 | F8: 193205.27 | G8: 294508.88 | H8: 0.04
A9: Expanded | B9: ACE | C9: Single-Space | D9: 493218 | E9: =685168+36600+276025 -> 997793 | F9: 279428.01 | G9: 425940.91 | H9: 0.04
A10: Expanded | B10: ACE | C10: Dual-Head | D10: 487994 | E10: =400319+36600+173765 -> 610684 | F10: 188681.41 | G10: 287613.02 | H10: 0.04
A11: Expanded | B11: LAZ | C11: Multi-Space | D11: 611122.4 | E11: 322043.58 | F11: =-PMT(10%,5,'Expanded RPP - KH Inhouse'!$O$53-'Expanded RPP - KH Inhouse'!$O$50) -> 164401.32 | G11: =-PMT(10%,3,'Expanded RPP - KH Inhouse'!$O$53-'Expanded RPP - KH Inhouse'!$O$50) -> 250602.1 | H11: 0.03
A12: Expanded | B12: LAZ | C12: Single-Space | D12: 611122.4 | E12: 322043.58 | F12: =-PMT(10%,5,'Expanded RPP - KH Inhouse'!$M$53-'Expanded RPP - KH Inhouse'!$M$50) -> 289163.1 | G12: =-PMT(10%,3,'Expanded RPP - KH Inhouse'!$M$53-'Expanded RPP - KH Inhouse'!$M$50) -> 440780.41 | H12: 0.03
A13: Expanded | B13: LAZ | C13: Dual-Head | D13: 611122.4 | E13: 322043.58 | F13: =-PMT(10%,5,'Expanded RPP - KH Inhouse'!$N$53-'Expanded RPP - KH Inhouse'!$N$50) -> 177692.28 | G13: =-PMT(10%,3,'Expanded RPP - KH Inhouse'!$N$53-'Expanded RPP - KH Inhouse'!$N$50) -> 270861.94 | H13: 0.03
A14: Existing | B14: In House | C14: Multi-Space | D14: =SUMIF('Existing RPP - KH Inhouse'!$K$18:$K$37,"Enforcement",'Existing RPP - KH Inhouse'!$L$18:$L$37)+SUMIF('Existing RPP - KH Inhouse'!$K$18:$K$37,"Enforcement",'Existing RPP - KH Inhouse'!$O$18:$O$37)+'Existing RPP - KH Inhouse'!$O$56*(360591.12/558732.7) -> 1089207.8 | E14: =SUMIF('Existing RPP - KH Inhouse'!$K$18:$K$37,"Parking Management",'Existing RPP - KH Inhouse'!$L$18:$L$37)+SUMIF('Existing RPP - KH Inhouse'!$K$18:$K$37,"Parking Management",'Existing RPP - KH Inhouse'!$O$18:$O$37)+'Existing RPP - KH Inhouse'!$O$56*(198141.58/558732.7) -> 682369.75 | F14: =-PMT(10%,5,'Existing RPP - KH Inhouse'!$O$53) -> 187206.87 | G14: =-PMT(10%,3,'Existing RPP - KH Inhouse'!$O$53) -> 285365.33 | H14: =3% -> 0.03
A15: Existing | B15: In House | C15: Single-Space | D15: =SUMIF('Existing RPP - KH Inhouse'!$K$18:$K$37,"Enforcement",'Existing RPP - KH Inhouse'!$L$18:$L$37)+SUMIF('Existing RPP - KH Inhouse'!$K$18:$K$37,"Enforcement",'Existing RPP - KH Inhouse'!$M$18:$M$37)+'Existing RPP - KH Inhouse'!$M$56*(360591.12/558732.7) -> 1347420.7 | E15: =SUMIF('Existing RPP - KH Inhouse'!$K$18:$K$37,"Parking Management",'Existing RPP - KH Inhouse'!$L$18:$L$37)+SUMIF('Existing RPP - KH Inhouse'!$K$18:$K$37,"Parking Management",'Existing RPP - KH Inhouse'!$M$18:$M$37)+'Existing RPP - KH Inhouse'!$M$56*(198141.58/558732.7) -> 872366.67 | F15: =-PMT(10%,5,'Existing RPP - KH Inhouse'!$M$53) -> 327281.83 | G15: =-PMT(10%,3,'Existing RPP - KH Inhouse'!$M$53) -> 498886 | H15: =3% -> 0.03
A16: Existing | B16: In House | C16: Dual-Head | D16: =SUMIF('Existing RPP - KH Inhouse'!$K$18:$K$37,"Enforcement",'Existing RPP - KH Inhouse'!$L$18:$L$37)+SUMIF('Existing RPP - KH Inhouse'!$K$18:$K$37,"Enforcement",'Existing RPP - KH Inhouse'!$N$18:$N$37)+'Existing RPP - KH Inhouse'!$N$56*(360591.12/558732.7) -> 1258550 | E16: =SUMIF('Existing RPP - KH Inhouse'!$K$18:$K$37,"Parking Management",'Existing RPP - KH Inhouse'!$L$18:$L$37)+SUMIF('Existing RPP - KH Inhouse'!$K$18:$K$37,"Parking Management",'Existing RPP - KH Inhouse'!$N$18:$N$37)+'Existing RPP - KH Inhouse'!$N$56*(198141.58/558732.7) -> 787021.03 | F16: =-PMT(10%,5,'Existing RPP - KH Inhouse'!$N$53) -> 208187.27 | G16: =-PMT(10%,3,'Existing RPP - KH Inhouse'!$N$53) -> 317346.41 | H16: =3% -> 0.03
A17: Expanded | B17: In House | C17: Multi-Space | D17: =SUMIF('Expanded RPP - KH Inhouse'!$K$18:$K$37,"Enforcement",'Expanded RPP - KH Inhouse'!$L$18:$L$37)+SUMIF('Expanded RPP - KH Inhouse'!$K$18:$K$37,"Enforcement",'Expanded RPP - KH Inhouse'!$O$18:$O$37)+'Expanded RPP - KH Inhouse'!$O$57*(360591.12/558732.7) -> 1168469.3 | E17: =SUMIF('Expanded RPP - KH Inhouse'!$K$18:$K$37,"Parking Management",'Expanded RPP - KH Inhouse'!$L$18:$L$37)+SUMIF('Expanded RPP - KH Inhouse'!$K$18:$K$37,"Parking Management",'Expanded RPP - KH Inhouse'!$O$18:$O$37)+'Expanded RPP - KH Inhouse'!$O$57*(198141.58/558732.7) -> 725923.23 | F17: =-PMT(10%,5,'Expanded RPP - KH Inhouse'!$O$53) -> 187206.87 | G17: =-PMT(10%,3,'Expanded RPP - KH Inhouse'!$O$53) -> 285365.33 | H17: =3% -> 0.03
A18: Expanded | B18: In House | C18: Single-Space | D18: =SUMIF('Expanded RPP - KH Inhouse'!$K$18:$K$37,"Enforcement",'Expanded RPP - KH Inhouse'!$L$18:$L$37)+SUMIF('Expanded RPP - KH Inhouse'!$K$18:$K$37,"Enforcement",'Expanded RPP - KH Inhouse'!$M$18:$M$37)+'Expanded RPP - KH Inhouse'!$M$57*(360591.12/558732.7) -> 1476674.3 | E18: =SUMIF('Expanded RPP - KH Inhouse'!$K$18:$K$37,"Parking Management",'Expanded RPP - KH Inhouse'!$L$18:$L$37)+SUMIF('Expanded RPP - KH Inhouse'!$K$18:$K$37,"Parking Management",'Expanded RPP - KH Inhouse'!$M$18:$M$37)+'Expanded RPP - KH Inhouse'!$M$57*(198141.58/558732.7) -> 932584.19 | F18: =-PMT(10%,5,'Expanded RPP - KH Inhouse'!$M$53) -> 327281.83 | G18: =-PMT(10%,3,'Expanded RPP - KH Inhouse'!$M$53) -> 498886 | H18: =3% -> 0.03
A19: Expanded | B19: In House | C19: Dual-Head | D19: =SUMIF('Expanded RPP - KH Inhouse'!$K$18:$K$37,"Enforcement",'Expanded RPP - KH Inhouse'!$L$18:$L$37)+SUMIF('Expanded RPP - KH Inhouse'!$K$18:$K$37,"Enforcement",'Expanded RPP - KH Inhouse'!$N$18:$N$37)+'Expanded RPP - KH Inhouse'!$N$57*(360591.12/558732.7) -> 1387803.6 | E19: =SUMIF('Expanded RPP - KH Inhouse'!$K$18:$K$37,"Parking Management",'Expanded RPP - KH Inhouse'!$L$18:$L$37)+SUMIF('Expanded RPP - KH Inhouse'!$K$18:$K$37,"Parking Management",'Expanded RPP - KH Inhouse'!$N$18:$N$37)+'Expanded RPP - KH Inhouse'!$N$57*(198141.58/558732.7) -> 847238.55 | F19: =-PMT(10%,5,'Expanded RPP - KH Inhouse'!$N$53) -> 208187.27 | G19: =-PMT(10%,3,'Expanded RPP - KH Inhouse'!$N$53) -> 317346.41 | H19: =3% -> 0.03

Sheet Inhouse Costs Summary Sheet
A1: City In-House RPP Cost Summary
A2: Consolidated cost assumptions first, followed by the City scenario comparisons — live-linked to both RPP models
A4: 1 | Consolidated Cost Inputs and Calculation Notes
A5: Category | B5: Cost Item | C5: Allocation / Treatment | D5: RPP Applicability | E5: All Scenario Cost | F5: Single-Space | G5: Dual-Head | H5: Multi-Space | I5: Source Row | J5: Calculation Note
A6: Operating | B6: ='Existing RPP - KH Inhouse'!B24 -> LPR On-going Fees | C6: ='Existing RPP - KH Inhouse'!K24 -> Enforcement | D6: Both | E6: ='Existing RPP - KH Inhouse'!L24 -> 12951 | F6: ='Existing RPP - KH Inhouse'!M24 -> 0 | G6: ='Existing RPP - KH Inhouse'!N24 -> 0 | H6: ='Existing RPP - KH Inhouse'!O24 -> 0 | I6: 24 | J6: ='Existing RPP - KH Inhouse'!P24 -> Shared Route1/Genetec annual support and licenses for two ALPR-equipped vehicles, included once across all scenarios; direct annual vendor amount of $12,951. The total fleet may range from 3 to 5 vehicles, but only two are assumed to carry ALPR equipment unless operations determine additional units are needed.
A7: Operating | B7: ='Existing RPP - KH Inhouse'!B27 -> Parking Sensor Software/Support | C7: ='Existing RPP - KH Inhouse'!K27 -> Enforcement | D7: Both | E7: ='Existing RPP - KH Inhouse'!L27 -> 6984 | F7: ='Existing RPP - KH Inhouse'!M27 -> 0 | G7: ='Existing RPP - KH Inhouse'!N27 -> 0 | H7: ='Existing RPP - KH Inhouse'!O27 -> 0 | I7: 27 | J7: ='Existing RPP - KH Inhouse'!P27 -> Shared eleven-x managed network and dashboard subscriptions included once across all selected packages: $4,200 + $2,784 = $6,984 annually.
A8: Operating | B8: ='Existing RPP - KH Inhouse'!B28 -> Turbo Data Handheld Rental | C8: ='Existing RPP - KH Inhouse'!K28 -> Enforcement | D8: Both | E8: ='Existing RPP - KH Inhouse'!L28 -> 7200 | F8: ='Existing RPP - KH Inhouse'!M28 -> 0 | G8: ='Existing RPP - KH Inhouse'!N28 -> 0 | H8: ='Existing RPP - KH Inhouse'!O28 -> 0 | I8: 28 | J8: ='Existing RPP - KH Inhouse'!P28 -> Uses LAZ's flat $7,200 annual Turbodata software-fee allowance for every scenario. No per-device rate is documented, so the cost is not scaled with handheld or officer count.
A9: Operating | B9: ='Existing RPP - KH Inhouse'!B31 -> Signs | C9: ='Existing RPP - KH Inhouse'!K31 -> Enforcement | D9: Both | E9: ='Existing RPP - KH Inhouse'!L31 -> 1800 | F9: ='Existing RPP - KH Inhouse'!M31 -> 0 | G9: ='Existing RPP - KH Inhouse'!N31 -> 0 | H9: ='Existing RPP - KH Inhouse'!O31 -> 0 | I9: 31 | J9: ='Existing RPP - KH Inhouse'!P31 -> ACE annual sign-replacement allowance; common to all scenarios.
A10: Operating | B10: ='Existing RPP - KH Inhouse'!B35 -> Vehicle Fuel | C10: ='Existing RPP - KH Inhouse'!K35 -> Enforcement | D10: Both | E10: ='Existing RPP - KH Inhouse'!L35 -> 0 | F10: ='Existing RPP - KH Inhouse'!M35 -> 14400 | G10: ='Existing RPP - KH Inhouse'!N35 -> 11520 | H10: ='Existing RPP - KH Inhouse'!O35 -> 8640 | I10: 35 | J10: ='Existing RPP - KH Inhouse'!P35 -> LAZ fuel benchmark for the 5-vehicle single-space fleet; scaled to 4 vehicles for dual-space and 3 for multi-space.
A11: Operating | B11: ='Existing RPP - KH Inhouse'!B36 -> Insurance - Vehicle | C11: ='Existing RPP - KH Inhouse'!K36 -> Enforcement | D11: Both | E11: ='Existing RPP - KH Inhouse'!L36 -> 0 | F11: ='Existing RPP - KH Inhouse'!M36 -> 15224 | G11: ='Existing RPP - KH Inhouse'!N36 -> 12179.2 | H11: ='Existing RPP - KH Inhouse'!O36 -> 9134.4 | I11: 36 | J11: ='Existing RPP - KH Inhouse'!P36 -> LAZ vehicle-insurance benchmark for the 5-vehicle single-space fleet; scaled to 4 vehicles for dual-space and 3 for multi-space.
A12: Operating | B12: ='Existing RPP - KH Inhouse'!B18 -> Recruiting/Testing/Training | C12: ='Existing RPP - KH Inhouse'!K18 -> Parking Management | D12: Both | E12: ='Existing RPP - KH Inhouse'!L18 -> 0 | F12: ='Existing RPP - KH Inhouse'!M18 -> 6000 | G12: ='Existing RPP - KH Inhouse'!N18 -> 5500 | H12: ='Existing RPP - KH Inhouse'!O18 -> 4500 | I12: 18 | J12: ='Existing RPP - KH Inhouse'!P18 -> Base Year 1 startup allowance covers 11 hires. Single-space adds 3 hires and dual-space adds 2 hires under the scenario staffing rule; each increment uses $328 per hire plus 20% contingency, rounded to $500.
A13: Operating | B13: ='Existing RPP - KH Inhouse'!B20 -> Uniforms | C13: ='Existing RPP - KH Inhouse'!K20 -> Parking Management | D13: Both | E13: ='Existing RPP - KH Inhouse'!L20 -> 0 | F13: ='Existing RPP - KH Inhouse'!M20 -> 3520 | G13: ='Existing RPP - KH Inhouse'!N20 -> 3200 | H13: ='Existing RPP - KH Inhouse'!O20 -> 2560 | I13: 20 | J13: ='Existing RPP - KH Inhouse'!P20 -> Base allowance covers 8 field staff. Single-space adds uniforms for 3 staff and dual-space for 2 staff at $320 each.
A14: Operating | B14: ='Existing RPP - KH Inhouse'!B21 -> Parking/Meter Supplies | C14: ='Existing RPP - KH Inhouse'!K21 -> Parking Management | D14: Both | E14: ='Existing RPP - KH Inhouse'!L21 -> 0 | F14: ='Existing RPP - KH Inhouse'!M21 -> 24000 | G14: ='Existing RPP - KH Inhouse'!N21 -> 14400 | H14: ='Existing RPP - KH Inhouse'!O21 -> 9000 | I14: 21 | J14: ='Existing RPP - KH Inhouse'!P21 -> Uses ACE's scenario-specific supplies allowances because meter type drives parts and consumables.
A15: Operating | B15: ='Existing RPP - KH Inhouse'!B22 -> Software License Fees | C15: ='Existing RPP - KH Inhouse'!K22 -> Parking Management | D15: Both | E15: ='Existing RPP - KH Inhouse'!L22 -> 15000 | F15: ='Existing RPP - KH Inhouse'!M22 -> 0 | G15: ='Existing RPP - KH Inhouse'!N22 -> 0 | H15: ='Existing RPP - KH Inhouse'!O22 -> 0 | I15: 22 | J15: ='Existing RPP - KH Inhouse'!P22 -> Shared Passport digital-permit license included once across all selected packages; direct annual vendor amount of $15,000.
A16: Operating | B16: ='Existing RPP - KH Inhouse'!B25 -> Meter Software / Data / Support | C16: ='Existing RPP - KH Inhouse'!K25 -> Parking Management | D16: Both | E16: ='Existing RPP - KH Inhouse'!L25 -> 0 | F16: ='Existing RPP - KH Inhouse'!M25 -> 89640 | G16: ='Existing RPP - KH Inhouse'!N25 -> 76296 | H16: ='Existing RPP - KH Inhouse'!O25 -> 72912 | I16: 25 | J16: Vendor-specific recurring component of the selected direct-purchase packages. Current selection is the cheapest option, subject to change based on actual selection: MacKay mkBeacon single-space, MacKay mkBeacon dual-space, and Flowbird CWT S4+ multi-space. Each formula subtracts the shared Passport, eleven-x sensor, and Route1/Genetec costs already included other rows.
A17: Operating | B17: ='Existing RPP - KH Inhouse'!B29 -> Telephone | C17: ='Existing RPP - KH Inhouse'!K29 -> Parking Management | D17: Both | E17: ='Existing RPP - KH Inhouse'!L29 -> 9600 | F17: ='Existing RPP - KH Inhouse'!M29 -> 0 | G17: ='Existing RPP - KH Inhouse'!N29 -> 0 | H17: ='Existing RPP - KH Inhouse'!O29 -> 0 | I17: 29 | J17: ='Existing RPP - KH Inhouse'!P29 -> Uses LAZ's flat $9,600 annual Telephone/Cellular allowance for every scenario. No per-user rate or documented user count is available, so the cost is not scaled with staffing.
A18: Operating | B18: ='Existing RPP - KH Inhouse'!B30 -> Computer Expense | C18: ='Existing RPP - KH Inhouse'!K30 -> Parking Management | D18: Both | E18: ='Existing RPP - KH Inhouse'!L30 -> 3000 | F18: ='Existing RPP - KH Inhouse'!M30 -> 0 | G18: ='Existing RPP - KH Inhouse'!N30 -> 0 | H18: ='Existing RPP - KH Inhouse'!O30 -> 0 | I18: 30 | J18: ='Existing RPP - KH Inhouse'!P30 -> Six computer users × $500 annual device/support allowance: project manager, administrator, IT, enforcement supervisor, operations supervisor, and coordinator.
A19: Operating | B19: ='Existing RPP - KH Inhouse'!B32 -> Repair and Maintenance | C19: ='Existing RPP - KH Inhouse'!K32 -> Parking Management | D19: Both | E19: ='Existing RPP - KH Inhouse'!L32 -> 0 | F19: ='Existing RPP - KH Inhouse'!M32 -> 25200 | G19: ='Existing RPP - KH Inhouse'!N32 -> 8400 | H19: ='Existing RPP - KH Inhouse'!O32 -> 2400 | I19: 32 | J19: ='Existing RPP - KH Inhouse'!P32 -> Uses ACE's scenario-specific repair and maintenance allowances because meter quantity/type drives service effort and parts.
A20: Operating | B20: ='Existing RPP - KH Inhouse'!B33 -> PCI Compliance | C20: ='Existing RPP - KH Inhouse'!K33 -> Parking Management | D20: Both | E20: ='Existing RPP - KH Inhouse'!L33 -> 300 | F20: ='Existing RPP - KH Inhouse'!M33 -> 0 | G20: ='Existing RPP - KH Inhouse'!N33 -> 0 | H20: ='Existing RPP - KH Inhouse'!O33 -> 0 | I20: 33 | J20: ='Existing RPP - KH Inhouse'!P33 -> ACE annual PCI-compliance allowance; common to all scenarios.
A21: Operating | B21: ='Existing RPP - KH Inhouse'!B34 -> Bank Fees | C21: ='Existing RPP - KH Inhouse'!K34 -> Parking Management | D21: Both | E21: ='Existing RPP - KH Inhouse'!L34 -> 264 | F21: ='Existing RPP - KH Inhouse'!M34 -> 0 | G21: ='Existing RPP - KH Inhouse'!N34 -> 0 | H21: ='Existing RPP - KH Inhouse'!O34 -> 0 | I21: 34 | J21: ='Existing RPP - KH Inhouse'!P34 -> ACE annual banking allowance; common to all scenarios. Transaction-based merchant fees remain excluded.
A22: Capital | B22: ='Existing RPP - KH Inhouse'!B49 -> Genetec Mobile LPR Units | C22: ='Existing RPP - KH Inhouse'!K49 -> Enforcement | D22: Both | E22: ='Existing RPP - KH Inhouse'!L49 -> 62474.45 | F22: ='Existing RPP - KH Inhouse'!M49 -> 0 | G22: ='Existing RPP - KH Inhouse'!N49 -> 0 | H22: ='Existing RPP - KH Inhouse'!O49 -> 0 | I22: 49 | J22: ='Existing RPP - KH Inhouse'!P49 -> Shared LAZ/Route1 Genetec mobile LPR capital package for two ALPR-equipped vehicles used in all scenarios: engineering services, hardware/software, user interface and communications, and sales tax. Selected because its lower upfront cost produces the lower five-year total than ACE. The total fleet may range from 3 to 5 vehicles, but Genetec costs are not scaled because only two vehicles are assumed to carry ALPR equipment; obtain an updated Route1 quote if additional ALPR units are required. Annual support/licenses are included separately in L24.
A23: Capital | B23: ='Existing RPP - KH Inhouse'!B50 -> Toyota Corolla | C23: ='Existing RPP - KH Inhouse'!K50 -> Enforcement | D23: Both | E23: ='Existing RPP - KH Inhouse'!L50 -> 0 | F23: ='Existing RPP - KH Inhouse'!M50 -> 144500 | G23: ='Existing RPP - KH Inhouse'!N50 -> 115600 | H23: ='Existing RPP - KH Inhouse'!O50 -> 86451 | I23: 50 | J23: ='Existing RPP - KH Inhouse'!P50 -> Purchase vehicles using ACE's scenario quantities and pricing: 5 vehicles for single-space, 4 for dual-space, and 3 for multi-space.
A24: Capital | B24: ='Existing RPP - KH Inhouse'!B51 -> Parking Sensors | C24: ='Existing RPP - KH Inhouse'!K51 -> Enforcement | D24: Both | E24: ='Existing RPP - KH Inhouse'!L51 -> 40789 | F24: ='Existing RPP - KH Inhouse'!M51 -> 0 | G24: ='Existing RPP - KH Inhouse'!N51 -> 0 | H24: ='Existing RPP - KH Inhouse'!O51 -> 0 | I24: 51 | J24: ='Existing RPP - KH Inhouse'!P51 -> Shared eleven-x installed sensor system used in all scenarios: 48 SPS-X sensors ($9,552), 3 wireless gateways ($3,285), and installation/setup ($27,952), totaling $40,789. Selected over ACE/Fybr because its lower annual cost produces the lower five-year system cost and maintains consistency with the selected LAZ technology packages.
A25: Capital | B25: ='Existing RPP - KH Inhouse'!B48 -> Meters | C25: ='Existing RPP - KH Inhouse'!K48 -> Parking Management | D25: Both | E25: ='Existing RPP - KH Inhouse'!L48 -> 0 | F25: ='Existing RPP - KH Inhouse'!M48 -> 982892.19 | G25: ='Existing RPP - KH Inhouse'!N48 -> 560330.11 | H25: ='Existing RPP - KH Inhouse'!O48 -> 509946.88 | I25: 48 | J25: Selected direct-purchase meter/pay-station capital packages: MacKay mkBeacon single-space (747 meters plus poles, tariffs, tax, shipping, and installation); MacKay mkBeacon dual-space (374 meters plus poles, tariffs, tax, shipping, and installation); and Flowbird CWT S4+ multi-space (62 pay stations plus spare-parts bundle, programming, prevailing-wage installation, freight, and sales tax). Recurring software and support are included separately.
A26: Capital | B26: ='Existing RPP - KH Inhouse'!B52 -> Passport Implementation | C26: ='Existing RPP - KH Inhouse'!K52 -> Parking Management | D26: Both | E26: ='Existing RPP - KH Inhouse'!L52 -> 10000 | F26: ='Existing RPP - KH Inhouse'!M52 -> 0 | G26: ='Existing RPP - KH Inhouse'!N52 -> 0 | H26: ='Existing RPP - KH Inhouse'!O52 -> 0 | I26: 52 | J26: One-time Passport digital-permit implementation charge shared across all scenarios. The annual $15,000 software license is included separately; usage-based permit and payment-processing fees are passed through to users and excluded from City costs.
A27: Labor-driven operating | B27: ='Existing RPP - KH Inhouse'!B37 -> Insurance - Liability | C27: ='Existing RPP - KH Inhouse'!K37 -> Enforcement | D27: Existing | E27: ='Existing RPP - KH Inhouse'!L37 -> 46307.658 | F27: ='Existing RPP - KH Inhouse'!M37 -> 10943.43 | G27: ='Existing RPP - KH Inhouse'!N37 -> 7258.98 | H27: ='Existing RPP - KH Inhouse'!O37 -> 0 | I27: 37 | J27: ='Existing RPP - KH Inhouse'!P37 -> Base planning proxy is 3% of base payroll. Single- and dual-space add 3% of incremental officer and maintenance payroll; replace with the City's actual risk-manager premium when available.
A28: Labor-driven operating | B28: ='Expanded RPP - KH Inhouse'!B37 -> Insurance - Liability | C28: ='Expanded RPP - KH Inhouse'!K37 -> Enforcement | D28: Expanded | E28: ='Expanded RPP - KH Inhouse'!L37 -> 46307.658 | F28: ='Expanded RPP - KH Inhouse'!M37 -> 60935.538 | G28: ='Expanded RPP - KH Inhouse'!N37 -> 57251.088 | H28: ='Expanded RPP - KH Inhouse'!O37 -> 0 | I28: 37 | J28: ='Expanded RPP - KH Inhouse'!P37 -> Base planning proxy is 3% of base payroll. Single- and dual-space add 3% of incremental officer and maintenance payroll; replace with the City's actual risk-manager premium when available.
A29: Labor-driven operating | B29: ='Existing RPP - KH Inhouse'!B19 -> Payroll Processing | C29: ='Existing RPP - KH Inhouse'!K19 -> Parking Management | D29: Existing | E29: ='Existing RPP - KH Inhouse'!L19 -> 0 | F29: ='Existing RPP - KH Inhouse'!M19 -> 19083.696 | G29: ='Existing RPP - KH Inhouse'!N19 -> 17855.546 | H29: ='Existing RPP - KH Inhouse'!O19 -> 15435.886 | I29: 19 | J29: ='Existing RPP - KH Inhouse'!P19 -> Base allowance is 1.0% of base payroll. Single- and dual-space add 1.0% of their incremental officer and maintenance payroll.
A30: Labor-driven operating | B30: ='Expanded RPP - KH Inhouse'!B19 -> Payroll Processing | C30: ='Expanded RPP - KH Inhouse'!K19 -> Parking Management | D30: Expanded | E30: ='Expanded RPP - KH Inhouse'!L19 -> 0 | F30: ='Expanded RPP - KH Inhouse'!M19 -> 35747.732 | G30: ='Expanded RPP - KH Inhouse'!N19 -> 34519.582 | H30: ='Expanded RPP - KH Inhouse'!O19 -> 15435.886 | I30: 19 | J30: ='Expanded RPP - KH Inhouse'!P19 -> Base allowance is 1.0% of base payroll. Single- and dual-space add 1.0% of their incremental officer and maintenance payroll.
A31: Labor | B31: Enforcement Labor | C31: Enforcement | D31: Existing | E31: ='Existing RPP - KH Inhouse'!L58 -> 0 | F31: ='Existing RPP - KH Inhouse'!M58 -> 1231610.6 | G31: ='Existing RPP - KH Inhouse'!N58 -> 1152349.1 | H31: ='Existing RPP - KH Inhouse'!O58 -> 996190.74 | I31: 58 | J31: ="Allocated 65% total labor costs to enforcement per LAZ allocation. " &'Existing RPP - KH Inhouse'!P56 -> Allocated 65% total labor costs to enforcement per LAZ allocation. Total fully burdened labor by equipment plan. Fixed roles are the project manager, administrator, part-time IT specialist, enforcement supervisor, operations supervisor, and operations coordinator. Single-space includes 6 enforcement officers and 2 maintenance workers; dual-space includes 5 officers and 2 maintenance workers; multi-space includes 4 officers and 1 maintenance worker.
A32: Labor | B32: Enforcement Labor | C32: Enforcement | D32: Expanded | E32: ='Expanded RPP - KH Inhouse'!L59 -> 0 | F32: ='Expanded RPP - KH Inhouse'!M59 -> 1310872.1 | G32: ='Expanded RPP - KH Inhouse'!N59 -> 1231610.6 | H32: ='Expanded RPP - KH Inhouse'!O59 -> 1075452.3 | I32: 59 | J32: ="Allocated 65% total labor costs to enforcement per LAZ allocation. " &'Expanded RPP - KH Inhouse'!P57 -> Allocated 65% total labor costs to enforcement per LAZ allocation. Total fully burdened labor for the expanded RPP, including one additional enforcement officer in every equipment scenario compared with the existing RPP. Fixed roles are the project manager, administrator, part-time IT specialist, enforcement supervisor, operations supervisor, and operations coordinator. Single-space includes 7 officers and 2 maintenance workers; dual-space includes 6 officers and 2 maintenance workers; multi-space includes 5 officers and 1 maintenance worker.
A33: Labor | B33: Parking Management Labor | C33: Parking Management | D33: Existing | E33: ='Existing RPP - KH Inhouse'!L57 -> 0 | F33: ='Existing RPP - KH Inhouse'!M57 -> 676758.97 | G33: ='Existing RPP - KH Inhouse'!N57 -> 633205.48 | H33: ='Existing RPP - KH Inhouse'!O57 -> 547397.86 | I33: 57 | J33: ="Allocated 35% total labor costs to enforcement per LAZ allocation." -> Allocated 35% total labor costs to enforcement per LAZ allocation.
A34: Labor | B34: Parking Management Labor | C34: Parking Management | D34: Expanded | E34: ='Expanded RPP - KH Inhouse'!L58 -> 0 | F34: ='Expanded RPP - KH Inhouse'!M58 -> 720312.46 | G34: ='Expanded RPP - KH Inhouse'!N58 -> 676758.97 | H34: ='Expanded RPP - KH Inhouse'!O58 -> 590951.35 | I34: 58 | J34: ="Allocated 35% total labor costs to enforcement per LAZ allocation." -> Allocated 35% total labor costs to enforcement per LAZ allocation.
A36: 2 | Labor Positions and Staffing Costs
A37: Position | B37: Fully Burdened Unit Cost | C37: Existing Single FTE | D37: Existing Dual FTE | E37: Existing Multi FTE | F37: Expanded Single FTE | G37: Expanded Dual FTE | H37: Expanded Multi FTE | I37: Existing Single Cost | J37: Existing Dual Cost | K37: Existing Multi Cost | L37: Expanded Single Cost | M37: Expanded Dual Cost | N37: Expanded Multi Cost
A38: Project Manager | B38: ='Existing RPP - KH Inhouse'!C56 -> 208147 | C38: 1 | D38: 1 | E38: 1 | F38: 1 | G38: 1 | H38: 1 | I38: =B38*C38 -> 208147 | J38: =B38*D38 -> 208147 | K38: =B38*E38 -> 208147 | L38: =B38*F38 -> 208147 | M38: =B38*G38 -> 208147 | N38: =B38*H38 -> 208147
A39: Administrator | B39: ='Existing RPP - KH Inhouse'!C57 -> 164139 | C39: 1 | D39: 1 | E39: 1 | F39: 1 | G39: 1 | H39: 1 | I39: =B39*C39 -> 164139 | J39: =B39*D39 -> 164139 | K39: =B39*E39 -> 164139 | L39: =B39*F39 -> 164139 | M39: =B39*G39 -> 164139 | N39: =B39*H39 -> 164139
A40: IT Specialist II - PT | B40: ='Existing RPP - KH Inhouse'!C58 -> 51313.6 | C40: 1 | D40: 1 | E40: 1 | F40: 1 | G40: 1 | H40: 1 | I40: =B40*C40 -> 51313.6 | J40: =B40*D40 -> 51313.6 | K40: =B40*E40 -> 51313.6 | L40: =B40*F40 -> 51313.6 | M40: =B40*G40 -> 51313.6 | N40: =B40*H40 -> 51313.6
A41: Parking Enforcement Supervisor | B41: ='Existing RPP - KH Inhouse'!C59 -> 186465 | C41: 1 | D41: 1 | E41: 1 | F41: 1 | G41: 1 | H41: 1 | I41: =B41*C41 -> 186465 | J41: =B41*D41 -> 186465 | K41: =B41*E41 -> 186465 | L41: =B41*F41 -> 186465 | M41: =B41*G41 -> 186465 | N41: =B41*H41 -> 186465
A42: Parking Enforcement Officer | B42: ='Existing RPP - KH Inhouse'!C60/4 -> 122815 | C42: 6 | D42: 5 | E42: 4 | F42: 7 | G42: 6 | H42: 5 | I42: =B42*C42 -> 736890 | J42: =B42*D42 -> 614075 | K42: =B42*E42 -> 491260 | L42: =B42*F42 -> 859705 | M42: =B42*G42 -> 736890 | N42: =B42*H42 -> 614075
A43: Skilled Maintenance Worker | B43: ='Existing RPP - KH Inhouse'!C61 -> 119151 | C43: 2 | D43: 2 | E43: 1 | F43: 2 | G43: 2 | H43: 1 | I43: =B43*C43 -> 238302 | J43: =B43*D43 -> 238302 | K43: =B43*E43 -> 119151 | L43: =B43*F43 -> 238302 | M43: =B43*G43 -> 238302 | N43: =B43*H43 -> 119151
A44: Parking Operations Supervisor | B44: ='Existing RPP - KH Inhouse'!C62 -> 203962 | C44: 1 | D44: 1 | E44: 1 | F44: 1 | G44: 1 | H44: 1 | I44: =B44*C44 -> 203962 | J44: =B44*D44 -> 203962 | K44: =B44*E44 -> 203962 | L44: =B44*F44 -> 203962 | M44: =B44*G44 -> 203962 | N44: =B44*H44 -> 203962
A45: Parking Operations Coordinator | B45: ='Existing RPP - KH Inhouse'!C63 -> 119151 | C45: 1 | D45: 1 | E45: 1 | F45: 1 | G45: 1 | H45: 1 | I45: =B45*C45 -> 119151 | J45: =B45*D45 -> 119151 | K45: =B45*E45 -> 119151 | L45: =B45*F45 -> 119151 | M45: =B45*G45 -> 119151 | N45: =B45*H45 -> 119151
A46: Total FTE | C46: =SUM(C38:C45) -> 14 | D46: =SUM(D38:D45) -> 13 | E46: =SUM(E38:E45) -> 11 | F46: =SUM(F38:F45) -> 15 | G46: =SUM(G38:G45) -> 14 | H46: =SUM(H38:H45) -> 12
A47: Total Fully Burdened Labor | I47: =SUM(I38:I45) -> 1908369.6 | J47: =SUM(J38:J45) -> 1785554.6 | K47: =SUM(K38:K45) -> 1543588.6 | L47: =SUM(L38:L45) -> 2031184.6 | M47: =SUM(M38:M45) -> 1908369.6 | N47: =SUM(N38:N45) -> 1666403.6
A48: Expanded RPP staffing adds one Parking Enforcement Officer to each equipment scenario; all other position counts and unit costs remain unchanged.
A50: 3 | Year-One Scenario Comparison
A51: RPP Scenario | B51: Equipment Scenario | C51: Enforcement Cost | D51: Parking Management Cost | E51: Total Operating Cost | F51: Capital Purchase | G51: 5-Year Annualized CapEx | H51: 3-Year Annualized CapEx | I51: Year 1 + 5-Yr CapEx | J51: Year 1 + 3-Yr CapEx | K51: YOY Increase | L51: Labor — Enforcement | M51: Labor — Parking Mgmt | N51: Reconciliation Difference
A52: Existing | B52: Multi-Space | C52: ='Existing RPP - KH Inhouse'!O58+SUMIF('Existing RPP - KH Inhouse'!$K$18:$K$42,"Enforcement",'Existing RPP - KH Inhouse'!$L$18:$L$42)+SUMIF('Existing RPP - KH Inhouse'!$K$18:$K$42,"Enforcement",'Existing RPP - KH Inhouse'!$O$18:$O$42) -> 1089207.8 | D52: ='Existing RPP - KH Inhouse'!O57+SUMIF('Existing RPP - KH Inhouse'!$K$18:$K$42,"Parking Management",'Existing RPP - KH Inhouse'!$L$18:$L$42)+SUMIF('Existing RPP - KH Inhouse'!$K$18:$K$42,"Parking Management",'Existing RPP - KH Inhouse'!$O$18:$O$42) -> 682369.74 | E52: =C52+D52 -> 1771577.5 | F52: ='Existing RPP - KH Inhouse'!O53 -> 709661.33 | G52: =-PMT(10%,5,F52) -> 187206.87 | H52: =-PMT(10%,3,F52) -> 285365.33 | I52: =E52+G52 -> 1958784.4 | J52: =E52+H52 -> 2056942.9 | K52: 0.03 | L52: ='Existing RPP - KH Inhouse'!O58 -> 996190.74 | M52: ='Existing RPP - KH Inhouse'!O57 -> 547397.86 | N52: =E52-'Existing RPP - KH Inhouse'!O45 -> 0
A53: Existing | B53: Single-Space | C53: ='Existing RPP - KH Inhouse'!M58+SUMIF('Existing RPP - KH Inhouse'!$K$18:$K$42,"Enforcement",'Existing RPP - KH Inhouse'!$L$18:$L$42)+SUMIF('Existing RPP - KH Inhouse'!$K$18:$K$42,"Enforcement",'Existing RPP - KH Inhouse'!$M$18:$M$42) -> 1347420.7 | D53: ='Existing RPP - KH Inhouse'!M57+SUMIF('Existing RPP - KH Inhouse'!$K$18:$K$42,"Parking Management",'Existing RPP - KH Inhouse'!$L$18:$L$42)+SUMIF('Existing RPP - KH Inhouse'!$K$18:$K$42,"Parking Management",'Existing RPP - KH Inhouse'!$M$18:$M$42) -> 872366.67 | E53: =C53+D53 -> 2219787.4 | F53: ='Existing RPP - KH Inhouse'!M53 -> 1240655.6 | G53: =-PMT(10%,5,F53) -> 327281.83 | H53: =-PMT(10%,3,F53) -> 498886 | I53: =E53+G53 -> 2547069.2 | J53: =E53+H53 -> 2718673.4 | K53: 0.03 | L53: ='Existing RPP - KH Inhouse'!M58 -> 1231610.6 | M53: ='Existing RPP - KH Inhouse'!M57 -> 676758.97 | N53: =E53-'Existing RPP - KH Inhouse'!M45 -> 0
A54: Existing | B54: Dual-Head | C54: ='Existing RPP - KH Inhouse'!N58+SUMIF('Existing RPP - KH Inhouse'!$K$18:$K$42,"Enforcement",'Existing RPP - KH Inhouse'!$L$18:$L$42)+SUMIF('Existing RPP - KH Inhouse'!$K$18:$K$42,"Enforcement",'Existing RPP - KH Inhouse'!$N$18:$N$42) -> 1258550 | D54: ='Existing RPP - KH Inhouse'!N57+SUMIF('Existing RPP - KH Inhouse'!$K$18:$K$42,"Parking Management",'Existing RPP - KH Inhouse'!$L$18:$L$42)+SUMIF('Existing RPP - KH Inhouse'!$K$18:$K$42,"Parking Management",'Existing RPP - KH Inhouse'!$N$18:$N$42) -> 787021.03 | E54: =C54+D54 -> 2045571 | F54: ='Existing RPP - KH Inhouse'!N53 -> 789193.56 | G54: =-PMT(10%,5,F54) -> 208187.27 | H54: =-PMT(10%,3,F54) -> 317346.41 | I54: =E54+G54 -> 2253758.3 | J54: =E54+H54 -> 2362917.4 | K54: 0.03 | L54: ='Existing RPP - KH Inhouse'!N58 -> 1152349.1 | M54: ='Existing RPP - KH Inhouse'!N57 -> 633205.48 | N54: =E54-'Existing RPP - KH Inhouse'!N45 -> 0
A55: Expanded | B55: Multi-Space | C55: ='Expanded RPP - KH Inhouse'!O59+SUMIF('Expanded RPP - KH Inhouse'!$K$18:$K$42,"Enforcement",'Expanded RPP - KH Inhouse'!$L$18:$L$42)+SUMIF('Expanded RPP - KH Inhouse'!$K$18:$K$42,"Enforcement",'Expanded RPP - KH Inhouse'!$O$18:$O$42) -> 1168469.3 | D55: ='Expanded RPP - KH Inhouse'!O58+SUMIF('Expanded RPP - KH Inhouse'!$K$18:$K$42,"Parking Management",'Expanded RPP - KH Inhouse'!$L$18:$L$42)+SUMIF('Expanded RPP - KH Inhouse'!$K$18:$K$42,"Parking Management",'Expanded RPP - KH Inhouse'!$O$18:$O$42) -> 725923.23 | E55: =C55+D55 -> 1894392.5 | F55: ='Expanded RPP - KH Inhouse'!O53 -> 709661.33 | G55: =-PMT(10%,5,F55) -> 187206.87 | H55: =-PMT(10%,3,F55) -> 285365.33 | I55: =E55+G55 -> 2081599.4 | J55: =E55+H55 -> 2179757.9 | K55: 0.03 | L55: ='Expanded RPP - KH Inhouse'!O59 -> 1075452.3 | M55: ='Expanded RPP - KH Inhouse'!O58 -> 590951.35 | N55: =E55-'Expanded RPP - KH Inhouse'!O45 -> 0
A56: Expanded | B56: Single-Space | C56: ='Expanded RPP - KH Inhouse'!M59+SUMIF('Expanded RPP - KH Inhouse'!$K$18:$K$42,"Enforcement",'Expanded RPP - KH Inhouse'!$L$18:$L$42)+SUMIF('Expanded RPP - KH Inhouse'!$K$18:$K$42,"Enforcement",'Expanded RPP - KH Inhouse'!$M$18:$M$42) -> 1476674.3 | D56: ='Expanded RPP - KH Inhouse'!M58+SUMIF('Expanded RPP - KH Inhouse'!$K$18:$K$42,"Parking Management",'Expanded RPP - KH Inhouse'!$L$18:$L$42)+SUMIF('Expanded RPP - KH Inhouse'!$K$18:$K$42,"Parking Management",'Expanded RPP - KH Inhouse'!$M$18:$M$42) -> 932584.19 | E56: =C56+D56 -> 2409258.5 | F56: ='Expanded RPP - KH Inhouse'!M53 -> 1240655.6 | G56: =-PMT(10%,5,F56) -> 327281.83 | H56: =-PMT(10%,3,F56) -> 498886 | I56: =E56+G56 -> 2736540.4 | J56: =E56+H56 -> 2908144.5 | K56: 0.03 | L56: ='Expanded RPP - KH Inhouse'!M59 -> 1310872.1 | M56: ='Expanded RPP - KH Inhouse'!M58 -> 720312.46 | N56: =E56-'Expanded RPP - KH Inhouse'!M45 -> 0
A57: Expanded | B57: Dual-Head | C57: ='Expanded RPP - KH Inhouse'!N59+SUMIF('Expanded RPP - KH Inhouse'!$K$18:$K$42,"Enforcement",'Expanded RPP - KH Inhouse'!$L$18:$L$42)+SUMIF('Expanded RPP - KH Inhouse'!$K$18:$K$42,"Enforcement",'Expanded RPP - KH Inhouse'!$N$18:$N$42) -> 1387803.6 | D57: ='Expanded RPP - KH Inhouse'!N58+SUMIF('Expanded RPP - KH Inhouse'!$K$18:$K$42,"Parking Management",'Expanded RPP - KH Inhouse'!$L$18:$L$42)+SUMIF('Expanded RPP - KH Inhouse'!$K$18:$K$42,"Parking Management",'Expanded RPP - KH Inhouse'!$N$18:$N$42) -> 847238.55 | E57: =C57+D57 -> 2235042.1 | F57: ='Expanded RPP - KH Inhouse'!N53 -> 789193.56 | G57: =-PMT(10%,5,F57) -> 208187.27 | H57: =-PMT(10%,3,F57) -> 317346.41 | I57: =E57+G57 -> 2443229.4 | J57: =E57+H57 -> 2552388.5 | K57: 0.03 | L57: ='Expanded RPP - KH Inhouse'!N59 -> 1231610.6 | M57: ='Expanded RPP - KH Inhouse'!N58 -> 676758.97 | N57: =E57-'Expanded RPP - KH Inhouse'!N45 -> 0
A59: 4 | Enforcement vs. Parking Management Allocation
A60: RPP Scenario | B60: Equipment Scenario | C60: Enforcement Labor | D60: Enforcement Operating | E60: Total Enforcement | F60: Parking Mgmt Labor | G60: Parking Mgmt Operating | H60: Total Parking Mgmt | I60: Total Operating | J60: Enforcement Share
A61: Existing | B61: Multi-Space | C61: ='Existing RPP - KH Inhouse'!O58 -> 996190.74 | D61: =SUMIF('Existing RPP - KH Inhouse'!$K$18:$K$42,"Enforcement",'Existing RPP - KH Inhouse'!$L$18:$L$42)+SUMIF('Existing RPP - KH Inhouse'!$K$18:$K$42,"Enforcement",'Existing RPP - KH Inhouse'!$O$18:$O$42) -> 93017.058 | E61: =C61+D61 -> 1089207.8 | F61: ='Existing RPP - KH Inhouse'!O57 -> 547397.86 | G61: =SUMIF('Existing RPP - KH Inhouse'!$K$18:$K$42,"Parking Management",'Existing RPP - KH Inhouse'!$L$18:$L$42)+SUMIF('Existing RPP - KH Inhouse'!$K$18:$K$42,"Parking Management",'Existing RPP - KH Inhouse'!$O$18:$O$42) -> 134971.89 | H61: =F61+G61 -> 682369.74 | I61: =E61+H61 -> 1771577.5 | J61: =IFERROR(E61/I61,0) -> 0.61482367
A62: Existing | B62: Single-Space | C62: ='Existing RPP - KH Inhouse'!M58 -> 1231610.6 | D62: =SUMIF('Existing RPP - KH Inhouse'!$K$18:$K$42,"Enforcement",'Existing RPP - KH Inhouse'!$L$18:$L$42)+SUMIF('Existing RPP - KH Inhouse'!$K$18:$K$42,"Enforcement",'Existing RPP - KH Inhouse'!$M$18:$M$42) -> 115810.09 | E62: =C62+D62 -> 1347420.7 | F62: ='Existing RPP - KH Inhouse'!M57 -> 676758.97 | G62: =SUMIF('Existing RPP - KH Inhouse'!$K$18:$K$42,"Parking Management",'Existing RPP - KH Inhouse'!$L$18:$L$42)+SUMIF('Existing RPP - KH Inhouse'!$K$18:$K$42,"Parking Management",'Existing RPP - KH Inhouse'!$M$18:$M$42) -> 195607.7 | H62: =F62+G62 -> 872366.67 | I62: =E62+H62 -> 2219787.4 | J62: =IFERROR(E62/I62,0) -> 0.6070044
A63: Existing | B63: Dual-Head | C63: ='Existing RPP - KH Inhouse'!N58 -> 1152349.1 | D63: =SUMIF('Existing RPP - KH Inhouse'!$K$18:$K$42,"Enforcement",'Existing RPP - KH Inhouse'!$L$18:$L$42)+SUMIF('Existing RPP - KH Inhouse'!$K$18:$K$42,"Enforcement",'Existing RPP - KH Inhouse'!$N$18:$N$42) -> 106200.84 | E63: =C63+D63 -> 1258550 | F63: ='Existing RPP - KH Inhouse'!N57 -> 633205.48 | G63: =SUMIF('Existing RPP - KH Inhouse'!$K$18:$K$42,"Parking Management",'Existing RPP - KH Inhouse'!$L$18:$L$42)+SUMIF('Existing RPP - KH Inhouse'!$K$18:$K$42,"Parking Management",'Existing RPP - KH Inhouse'!$N$18:$N$42) -> 153815.55 | H63: =F63+G63 -> 787021.03 | I63: =E63+H63 -> 2045571 | J63: =IFERROR(E63/I63,0) -> 0.61525607
A64: Expanded | B64: Multi-Space | C64: ='Expanded RPP - KH Inhouse'!O59 -> 1075452.3 | D64: =SUMIF('Expanded RPP - KH Inhouse'!$K$18:$K$42,"Enforcement",'Expanded RPP - KH Inhouse'!$L$18:$L$42)+SUMIF('Expanded RPP - KH Inhouse'!$K$18:$K$42,"Enforcement",'Expanded RPP - KH Inhouse'!$O$18:$O$42) -> 93017.058 | E64: =C64+D64 -> 1168469.3 | F64: ='Expanded RPP - KH Inhouse'!O58 -> 590951.35 | G64: =SUMIF('Expanded RPP - KH Inhouse'!$K$18:$K$42,"Parking Management",'Expanded RPP - KH Inhouse'!$L$18:$L$42)+SUMIF('Expanded RPP - KH Inhouse'!$K$18:$K$42,"Parking Management",'Expanded RPP - KH Inhouse'!$O$18:$O$42) -> 134971.89 | H64: =F64+G64 -> 725923.23 | I64: =E64+H64 -> 1894392.5 | J64: =IFERROR(E64/I64,0) -> 0.61680422
A65: Expanded | B65: Single-Space | C65: ='Expanded RPP - KH Inhouse'!M59 -> 1310872.1 | D65: =SUMIF('Expanded RPP - KH Inhouse'!$K$18:$K$42,"Enforcement",'Expanded RPP - KH Inhouse'!$L$18:$L$42)+SUMIF('Expanded RPP - KH Inhouse'!$K$18:$K$42,"Enforcement",'Expanded RPP - KH Inhouse'!$M$18:$M$42) -> 165802.2 | E65: =C65+D65 -> 1476674.3 | F65: ='Expanded RPP - KH Inhouse'!M58 -> 720312.46 | G65: =SUMIF('Expanded RPP - KH Inhouse'!$K$18:$K$42,"Parking Management",'Expanded RPP - KH Inhouse'!$L$18:$L$42)+SUMIF('Expanded RPP - KH Inhouse'!$K$18:$K$42,"Parking Management",'Expanded RPP - KH Inhouse'!$M$18:$M$42) -> 212271.73 | H65: =F65+G65 -> 932584.19 | I65: =E65+H65 -> 2409258.5 | J65: =IFERROR(E65/I65,0) -> 0.61291651
A66: Expanded | B66: Dual-Head | C66: ='Expanded RPP - KH Inhouse'!N59 -> 1231610.6 | D66: =SUMIF('Expanded RPP - KH Inhouse'!$K$18:$K$42,"Enforcement",'Expanded RPP - KH Inhouse'!$L$18:$L$42)+SUMIF('Expanded RPP - KH Inhouse'!$K$18:$K$42,"Enforcement",'Expanded RPP - KH Inhouse'!$N$18:$N$42) -> 156192.95 | E66: =C66+D66 -> 1387803.6 | F66: ='Expanded RPP - KH Inhouse'!N58 -> 676758.97 | G66: =SUMIF('Expanded RPP - KH Inhouse'!$K$18:$K$42,"Parking Management",'Expanded RPP - KH Inhouse'!$L$18:$L$42)+SUMIF('Expanded RPP - KH Inhouse'!$K$18:$K$42,"Parking Management",'Expanded RPP - KH Inhouse'!$N$18:$N$42) -> 170479.58 | H66: =F66+G66 -> 847238.55 | I66: =E66+H66 -> 2235042.1 | J66: =IFERROR(E66/I66,0) -> 0.62092949
A68: 5 | Equipment and Capital by RPP Scenario
A69: RPP Scenario | B69: Equipment Scenario | C69: Meters / Pay Stations | D69: Mobile LPR Units | E69: Purchased Vehicles | F69: Parking Sensors | G69: Passport Implementation | H69: Total Capital | I69: Enforcement CapEx | J69: Parking Mgmt CapEx | K69: 5-Year Annualized | L69: 3-Year Annualized
A70: Existing | B70: Multi-Space | C70: ='Existing RPP - KH Inhouse'!O48+'Existing RPP - KH Inhouse'!$L$48 -> 509946.88 | D70: ='Existing RPP - KH Inhouse'!O49+'Existing RPP - KH Inhouse'!$L$49 -> 62474.45 | E70: ='Existing RPP - KH Inhouse'!O50+'Existing RPP - KH Inhouse'!$L$50 -> 86451 | F70: ='Existing RPP - KH Inhouse'!O51+'Existing RPP - KH Inhouse'!$L$51 -> 40789 | G70: ='Existing RPP - KH Inhouse'!O52+'Existing RPP - KH Inhouse'!$L$52 -> 10000 | H70: =SUM(C70:G70) -> 709661.33 | I70: =D70+E70+F70 -> 189714.45 | J70: =C70+G70 -> 519946.88 | K70: =-PMT(10%,5,H70) -> 187206.87 | L70: =-PMT(10%,3,H70) -> 285365.33
A71: Existing | B71: Single-Space | C71: ='Existing RPP - KH Inhouse'!M48+'Existing RPP - KH Inhouse'!$L$48 -> 982892.19 | D71: ='Existing RPP - KH Inhouse'!M49+'Existing RPP - KH Inhouse'!$L$49 -> 62474.45 | E71: ='Existing RPP - KH Inhouse'!M50+'Existing RPP - KH Inhouse'!$L$50 -> 144500 | F71: ='Existing RPP - KH Inhouse'!M51+'Existing RPP - KH Inhouse'!$L$51 -> 40789 | G71: ='Existing RPP - KH Inhouse'!M52+'Existing RPP - KH Inhouse'!$L$52 -> 10000 | H71: =SUM(C71:G71) -> 1240655.6 | I71: =D71+E71+F71 -> 247763.45 | J71: =C71+G71 -> 992892.19 | K71: =-PMT(10%,5,H71) -> 327281.83 | L71: =-PMT(10%,3,H71) -> 498886
A72: Existing | B72: Dual-Head | C72: ='Existing RPP - KH Inhouse'!N48+'Existing RPP - KH Inhouse'!$L$48 -> 560330.11 | D72: ='Existing RPP - KH Inhouse'!N49+'Existing RPP - KH Inhouse'!$L$49 -> 62474.45 | E72: ='Existing RPP - KH Inhouse'!N50+'Existing RPP - KH Inhouse'!$L$50 -> 115600 | F72: ='Existing RPP - KH Inhouse'!N51+'Existing RPP - KH Inhouse'!$L$51 -> 40789 | G72: ='Existing RPP - KH Inhouse'!N52+'Existing RPP - KH Inhouse'!$L$52 -> 10000 | H72: =SUM(C72:G72) -> 789193.56 | I72: =D72+E72+F72 -> 218863.45 | J72: =C72+G72 -> 570330.11 | K72: =-PMT(10%,5,H72) -> 208187.27 | L72: =-PMT(10%,3,H72) -> 317346.41
A73: Expanded | B73: Multi-Space | C73: ='Expanded RPP - KH Inhouse'!O48+'Expanded RPP - KH Inhouse'!$L$48 -> 509946.88 | D73: ='Expanded RPP - KH Inhouse'!O49+'Expanded RPP - KH Inhouse'!$L$49 -> 62474.45 | E73: ='Expanded RPP - KH Inhouse'!O50+'Expanded RPP - KH Inhouse'!$L$50 -> 86451 | F73: ='Expanded RPP - KH Inhouse'!O51+'Expanded RPP - KH Inhouse'!$L$51 -> 40789 | G73: ='Expanded RPP - KH Inhouse'!O52+'Expanded RPP - KH Inhouse'!$L$52 -> 10000 | H73: =SUM(C73:G73) -> 709661.33 | I73: =D73+E73+F73 -> 189714.45 | J73: =C73+G73 -> 519946.88 | K73: =-PMT(10%,5,H73) -> 187206.87 | L73: =-PMT(10%,3,H73) -> 285365.33
A74: Expanded | B74: Single-Space | C74: ='Expanded RPP - KH Inhouse'!M48+'Expanded RPP - KH Inhouse'!$L$48 -> 982892.19 | D74: ='Expanded RPP - KH Inhouse'!M49+'Expanded RPP - KH Inhouse'!$L$49 -> 62474.45 | E74: ='Expanded RPP - KH Inhouse'!M50+'Expanded RPP - KH Inhouse'!$L$50 -> 144500 | F74: ='Expanded RPP - KH Inhouse'!M51+'Expanded RPP - KH Inhouse'!$L$51 -> 40789 | G74: ='Expanded RPP - KH Inhouse'!M52+'Expanded RPP - KH Inhouse'!$L$52 -> 10000 | H74: =SUM(C74:G74) -> 1240655.6 | I74: =D74+E74+F74 -> 247763.45 | J74: =C74+G74 -> 992892.19 | K74: =-PMT(10%,5,H74) -> 327281.83 | L74: =-PMT(10%,3,H74) -> 498886
A75: Expanded | B75: Dual-Head | C75: ='Expanded RPP - KH Inhouse'!N48+'Expanded RPP - KH Inhouse'!$L$48 -> 560330.11 | D75: ='Expanded RPP - KH Inhouse'!N49+'Expanded RPP - KH Inhouse'!$L$49 -> 62474.45 | E75: ='Expanded RPP - KH Inhouse'!N50+'Expanded RPP - KH Inhouse'!$L$50 -> 115600 | F75: ='Expanded RPP - KH Inhouse'!N51+'Expanded RPP - KH Inhouse'!$L$51 -> 40789 | G75: ='Expanded RPP - KH Inhouse'!N52+'Expanded RPP - KH Inhouse'!$L$52 -> 10000 | H75: =SUM(C75:G75) -> 789193.56 | I75: =D75+E75+F75 -> 218863.45 | J75: =C75+G75 -> 570330.11 | K75: =-PMT(10%,5,H75) -> 208187.27 | L75: =-PMT(10%,3,H75) -> 317346.41
A77: Calculation Conventions
A78: Labor allocation | B78: 64.54% Enforcement / 35.46% Parking Management, following the LAZ benchmark.
A79: Capital ownership | B79: City purchases vehicles and equipment; no recurring vehicle lease is included.
A80: Annualization | B80: PMT at 10% over either 5 years or 3 years.
A81: Escalation | B81: 3% year-over-year for all in-house scenarios.

Sheet Expanded RPP - KH Inhouse
B2: Current RPP - Year One Costs
C3: ACE | G3: LAZ | K3: In-House
B4: Operating Expenses | C4: Universal Costs | D4: Single Space | E4: Dual Space | F4: Multi Space | G4: Universal Costs | H4: Single Space | I4: Dual Space | J4: Multi Space | K4: Included in Inhouse Operating Costs? | L4: Universal Costs | M4: Single Space | N4: Dual Space | O4: Multi Space | P4: Calculation Notes
B5: Area Manager Allocation | C5: 18000 | K5: No
B6: Project Manager Wages | C6: 112320 | K6: No
B7: Administrator Wages | C7: 72800 | K7: No
B8: Enforcement Officer Wages | C8: 149760 | K8: No
B9: Meter Support Wages | D9: 187200 | E9: 124800 | F9: 62352 | K9: No
B10: Vacation/Holiday/Sick | D10: 32405 | E10: 27581 | F10: 23822 | G10: ='[3]Budget-Existing_RPP'!P6 -> 23178.96 | K10: No
B11: Payroll Overhead | D11: 147987 | E11: 130610 | F11: 113443 | G11: ='[3]Budget-Existing_RPP'!P8 -> 50572.628 | K11: No
B12: Health and Welfare | D12: 89236 | E12: 76488 | F12: 63740 | G12: ='[3]Budget-Existing_RPP'!P9+'[3]Budget-Existing_RPP'!P11 -> 94801.946 | K12: No
B13: 401k Company Match | G13: ='[3]Budget-Existing_RPP'!P10 -> 3863.16 | K13: No
B14: Safety / Audit Fees | G14: ='[3]Budget-Existing_RPP'!P13 -> 5320 | K14: No
B15: Business License / Parking Bond | G15: ='[3]Budget-Existing_RPP'!P14 -> 2500 | K15: No
B16: IT and Technology / Reporting | G16: ='[3]Budget-Existing_RPP'!P40 -> 9000 | K16: No
B17: Total Labor | D17: 809708 | E17: 712359 | F17: 616036 | G17: ='[3]Budget-Existing_RPP'!P5 -> 386316 | K17: n/a
B18: Recruiting/Testing/Training | D18: 1800 | E18: 900 | F18: 600 | G18: ='[3]Budget-Existing_RPP'!P15 -> 3280 | K18: Parking Management | M18: =CEILING(328*3*1.2,500)+$O$18 -> 6000 | N18: =CEILING(328*2*1.2,500)+O18 -> 5500 | O18: =CEILING(328*11*1.2,500) -> 4500 | P18: Base Year 1 startup allowance covers 11 hires. Single-space adds 3 hires and dual-space adds 2 hires under the scenario staffing rule; each increment uses $328 per hire plus 20% contingency, rounded to $500.
B19: Payroll Processing | D19: 2160 | E19: 1920 | F19: 1680 | G19: ='[3]Budget-Existing_RPP'!P17 -> 3863.16 | K19: Parking Management | M19: =(M57-$L57)*1%+O19 -> 35747.732 | N19: =(N57-$L57)*1%+O19 -> 34519.582 | O19: =SUM($C$57:$C$64)*1% -> 15435.886 | P19: Base allowance is 1.0% of base payroll. Single- and dual-space add 1.0% of their incremental officer and maintenance payroll.
B20: Uniforms | D20: 3240 | E20: 2880 | F20: 2520 | G20: ='[3]Budget-Existing_RPP'!P38 -> 3840 | K20: Parking Management | M20: =320*3+O20 -> 3520 | N20: =320*2+O20 -> 3200 | O20: =320*8 -> 2560 | P20: Base allowance covers 8 field staff. Single-space adds uniforms for 3 staff and dual-space for 2 staff at $320 each.
B21: Parking/Meter Supplies | D21: 24000 | E21: 14400 | F21: 9000 | G21: ='[3]Budget-Existing_RPP'!P34+'[3]Budget-Existing_RPP'!P37+'[3]Budget-Existing_RPP'!P36 -> 8400 | K21: Parking Management | M21: =$D21 -> 24000 | N21: =$E21 -> 14400 | O21: =$F21 -> 9000 | P21: Uses ACE's scenario-specific supplies allowances because meter type drives parts and consumables.
B22: Software License Fees | C22: 780 | G22: ='[3]Budget-Existing_RPP'!P27 -> 15000 | K22: Parking Management | L22: =$G22 -> 15000 | P22: Shared Passport digital-permit license included once across all selected packages; direct annual vendor amount of $15,000.
B23: Vehicles Lease 5 years | G23: ='[3]Budget-Existing_RPP'!P22 -> 30340.78 | K23: No - Purchase as Capital | P23: No recurring lease assumed. The City purchases the vehicles up front; purchase costs are included in capital expenses on row 50.
B24: LPR On-going Fees | G24: ='[3]Budget-Existing_RPP'!P23 -> 12951 | K24: Enforcement | L24: =$G24 -> 12951 | P24: Shared Route1/Genetec annual support and licenses for two ALPR-equipped vehicles, included once across all scenarios; direct annual vendor amount of $12,951. The total fleet may range from 3 to 5 vehicles, but only two are assumed to carry ALPR equipment unless operations determine additional units are needed.
B25: Meter Software / Data / Support | D25: 175172 | E25: 110143 | F25: 72912 | K25: Parking Management | M25: ='[3]Technology Scenarios Total'!G157-$L$22-$L$24-$L$27 -> 89640 | N25: ='[3]Technology Scenarios Total'!G236-$L$22-$L$24-$L$27 -> 76296 | O25: ='[3]Technology Scenarios Total'!G45-$L$22-$L$24-$L$27 -> 72912 | P25: Vendor-specific recurring component of the selected direct-purchase packages: MacKay mkBeacon single-space, MacKay mkBeacon dual-space, and Flowbird CWT S4+ multi-space. Each formula subtracts the shared Passport, eleven-x sensor, and Route1/Genetec costs already included in L22, L27, and L24 from the package annual total.
B26: Genetec Software/Support | C26: 11433 | K26: No - Duplicate | P26: Excluded to avoid double counting. Route1/Genetec annual support and licenses are already included once in L24 as a shared component of every selected technology package.
B27: Parking Sensor Software/Support | C27: 8640 | G27: ='[3]Budget-Existing_RPP'!P30 -> 6984 | K27: Enforcement | L27: =6984 -> 6984 | P27: Shared eleven-x managed network and dashboard subscriptions included once across all selected packages: $4,200 + $2,784 = $6,984 annually.
B28: Turbo Data Handheld Rental | C28: 12600 | G28: ='[3]Budget-Existing_RPP'!P41 -> 7200 | K28: Enforcement | L28: =$G28 -> 7200 | P28: Uses LAZ's flat $7,200 annual Turbodata software-fee allowance for every scenario. No per-device rate is documented, so the cost is not scaled with handheld or officer count.
B29: Telephone | C29: 3000 | G29: ='[3]Budget-Existing_RPP'!P42 -> 9600 | K29: Parking Management | L29: =$G29 -> 9600 | P29: Uses LAZ's flat $9,600 annual Telephone/Cellular allowance for every scenario. No per-user rate or documented user count is available, so the cost is not scaled with staffing.
B30: Computer Expense | C30: 1200 | G30: ='[3]Budget-Existing_RPP'!P43 -> 2500 | K30: Parking Management | L30: =500*6 -> 3000 | P30: Six computer users × $500 annual device/support allowance: project manager, administrator, IT, enforcement supervisor, operations supervisor, and coordinator.
B31: Signs | C31: 1800 | K31: Enforcement | L31: =$C31 -> 1800 | P31: ACE annual sign-replacement allowance; common to all scenarios.
B32: Repair and Maintenance | D32: 25200 | E32: 8400 | F32: 2400 | G32: ='[3]Budget-Existing_RPP'!P32+'[3]Budget-Existing_RPP'!P33 -> 12000 | K32: Parking Management | M32: =$D32 -> 25200 | N32: =$E32 -> 8400 | O32: =$F32 -> 2400 | P32: Uses ACE's scenario-specific repair and maintenance allowances because meter quantity/type drives service effort and parts.
B33: PCI Compliance | C33: 300 | K33: Parking Management | L33: =$C33 -> 300 | P33: ACE annual PCI-compliance allowance; common to all scenarios.
B34: Bank Fees | C34: 264 | K34: Parking Management | L34: =$C34 -> 264 | P34: ACE annual banking allowance; common to all scenarios. Transaction-based merchant fees remain excluded.
B35: Vehicle Fuel | C35: 10200 | G35: ='[3]Budget-Existing_RPP'!P35 -> 14400 | K35: Enforcement | M35: =$G35 -> 14400 | N35: =$G35*4/5 -> 11520 | O35: =$G35*3/5 -> 8640 | P35: LAZ fuel benchmark for the 5-vehicle single-space fleet; scaled to 4 vehicles for dual-space and 3 for multi-space.
B36: Insurance - Vehicle | D36: 79200 | E36: 63360 | F36: 47520 | G36: ='[3]Budget-Existing_RPP'!P20 -> 15224 | K36: Enforcement | M36: =$G36 -> 15224 | N36: =$G36*4/5 -> 12179.2 | O36: =$G36*3/5 -> 9134.4 | P36: LAZ vehicle-insurance benchmark for the 5-vehicle single-space fleet; scaled to 4 vehicles for dual-space and 3 for multi-space.
B37: Insurance - Liability | C37: 9504 | G37: ='[3]Budget-Existing_RPP'!P19 -> 21968.977 | K37: Enforcement | L37: =SUM($C$57:$C$64)*3% -> 46307.658 | M37: =(M57-$L57)*3% -> 60935.538 | N37: =(N57-$L57)*3% -> 57251.088 | P37: Base planning proxy is 3% of base payroll. Single- and dual-space add 3% of incremental officer and maintenance payroll; replace with the City's actual risk-manager premium when available.
B38: Equipment Amortization | D38: 213727 | E38: 150294 | F38: 155855 | G38: ='[3]Budget-Existing_RPP'!P24+'[3]Budget-Existing_RPP'!P29+'[3]Budget-Existing_RPP'!P30+'[3]Budget-Existing_RPP'!P26 -> 40713.41 | K38: No
B39: Storage Space Rental | C39: 6600 | K39: No
B40: Office Space Rental | C40: 30000 | K40: No
B41: Clerical Fee | D41: 11400 | E41: 10200 | F41: 9000 | K41: No
B42: Management Fee | D42: 84000 | E42: 72000 | F42: 60000 | G42: ='[3]Budget-Existing_RPP'!P16 -> 42000 | K42: No
B43: Operating Expenses | D43: 1525928 | E43: 1243177 | F43: 1073844 | G43: ='[3]Budget-Existing_RPP'!P53 -> 848926.02 | K43: n/a | L43: =SUM(L18:L37) -> 103406.66 | M43: =$L43+SUM(M18:M37) -> 378073.93 | N43: =$L43+SUM(N18:N37) -> 326672.53 | O43: =$L43+SUM(O18:O37) -> 227988.94 | P43: Recurring non-labor operating costs use complete direct-vendor technology packages: MacKay single-space, MacKay dual-space, and Flowbird multi-space (cheapest equipment options). Shared Passport, eleven-x, and Route1/Genetec charges are counted once; Turbodata and telephone remain flat LAZ allowances; vehicle leasing is excluded.
B44: Payment Bond (1.20%) | C44: =C43*1.2% -> 0 | D44: 18311 | E44: 14918 | F44: 12886 | K44: n/a | P44: No payment bond assumed for direct City operations.
B45: Total Expenses | C45: =C43+C44 -> 0 | D45: 1544239 | E45: 1258095 | F45: 1086730 | G45: =SUM(G5:G44) -> 1674744 | K45: n/a | M45: =$M43+$M57 -> 2409258.5 | N45: =$N43+$N57 -> 2235042.1 | O45: =$O43+$O57 -> 1894392.5 | P45: Total annual expanded in-house expense equals recurring non-labor operating costs plus expanded-program staffing, which adds one enforcement officer to every equipment scenario. Capital purchases remain separate.
B47: Capital Expenses | C47: Universal Costs | D47: Single Space | E47: Dual Space | F47: Multi Space | G47: Universal Costs | H47: Single Space | I47: Dual Space | J47: Multi Space | K47: Included in Inhouse Capital Costs? | L47: Universal Costs | M47: Single Space | N47: Dual Space | O47: Multi Space | P47: Calculation Notes
B48: Meters | D48: 575690 | E48: 355800 | F48: 406760 | H48: 250608 | I48: 142860 | J48: 130020 | K48: Parking Management | M48: =SUM('[3]Technology Scenarios Total'!F124:F131) -> 982892.19 | N48: =SUM('[3]Technology Scenarios Total'!F203:F210) -> 560330.11 | O48: =SUM('[3]Technology Scenarios Total'!F6:F11) -> 509946.88 | P48: Selected direct-purchase meter/pay-station capital packages: MacKay mkBeacon single-space (747 meters plus poles, tariffs, tax, shipping, and installation); MacKay mkBeacon dual-space (374 meters plus poles, tariffs, tax, shipping, and installation); and Flowbird CWT S4+ multi-space (62 pay stations plus spare-parts bundle, programming, prevailing-wage installation, freight, and sales tax). Recurring software and support are included separately in row 25.
B49: Genetec Mobile LPR Units | D49: 83220 | E49: 83220 | F49: 83220 | K49: Enforcement | L49: =SUM('[3]Technology Scenarios Total'!F32:F35) -> 62474.45 | P49: Shared LAZ/Route1 Genetec mobile LPR capital package for two ALPR-equipped vehicles used in all scenarios: engineering services, hardware/software, user interface and communications, and sales tax. Selected because its lower upfront cost produces the lower five-year total than ACE. The total fleet may range from 3 to 5 vehicles, but Genetec costs are not scaled because only two vehicles are assumed to carry ALPR equipment; obtain an updated Route1 quote if additional ALPR units are required. Annual support/licenses are included separately in L24.
B50: Toyota Corolla | D50: 144500 | E50: 115600 | F50: 86451 | K50: Enforcement | M50: =$D50 -> 144500 | N50: =$E50 -> 115600 | O50: =$F50 -> 86451 | P50: Purchase vehicles using ACE's scenario quantities and pricing: 5 vehicles for single-space, 4 for dual-space, and 3 for multi-space.
B51: Parking Sensors | D51: 34850 | E51: 34850 | F51: 34850 | K51: Enforcement | L51: =SUM('[3]Technology Scenarios Total'!F23:F25) -> 40789 | P51: Shared eleven-x installed sensor system used in all scenarios: 48 SPS-X sensors ($9,552), 3 wireless gateways ($3,285), and installation/setup ($27,952), totaling $40,789. Selected over ACE/Fybr because its lower annual cost produces the lower five-year system cost and maintains consistency with the selected LAZ technology packages.
B52: Passport Implementation | K52: Parking Management | L52: ='[3]Technology Scenarios Total'!F29 -> 10000 | P52: One-time Passport digital-permit implementation charge shared across all scenarios. The annual $15,000 software license is included separately in row 22; usage-based permit and payment-processing fees are passed through to users and excluded from City costs.
B53: Total In-House Capital Costs | K53: Approved items only | L53: =SUM(L48:L52) -> 113263.45 | M53: =$L53+SUM(M48:M52) -> 1240655.6 | N53: =$L53+SUM(N48:N52) -> 789193.56 | O53: =$L53+SUM(O48:O52) -> 709661.33 | P53: Total in-house capital includes the selected meter/pay-station package, shared Passport implementation, the two-vehicle LAZ/Route1 Genetec LPR package, the eleven-x sensor system, and purchased vehicles. Usage-based fees are excluded because they will be passed through to users; contingency and escalation will be added later.
B56: Inhouse Staffing Plan | C56: Fully Burdened Costs | K56: Included in Inhouse Labor Costs? | L56: Universal Costs | M56: Single Space | N56: Dual Space | O56: Multi Space | P56: Calculation Notes
B57: Project Manager | C57: 208147 | K57: Yes | M57: =SUM($C$57:$C$60,$C$63:$C$64)+7*($C$61/4)+2*$C$62 -> 2031184.6 | N57: =SUM($C$57:$C$60,$C$63:$C$64)+6*($C$61/4)+2*$C$62 -> 1908369.6 | O57: =SUM($C$57:$C$60,$C$63:$C$64)+5*($C$61/4)+$C$62 -> 1666403.6 | P57: Total fully burdened labor for the expanded RPP, including one additional enforcement officer in every equipment scenario compared with the existing RPP. Fixed roles are the project manager, administrator, part-time IT specialist, enforcement supervisor, operations supervisor, and operations coordinator. Single-space includes 7 officers and 2 maintenance workers; dual-space includes 6 officers and 2 maintenance workers; multi-space includes 5 officers and 1 maintenance worker.
B58: Administrator | C58: 164139 | K58: Parking Management | M58: =M$57*'[3]Budget-Existing_RPP'!$V$4/SUM('[3]Budget-Existing_RPP'!$V$4:$W$4) -> 720312.46 | N58: =N$57*'[3]Budget-Existing_RPP'!$V$4/SUM('[3]Budget-Existing_RPP'!$V$4:$W$4) -> 676758.97 | O58: =O$57*'[3]Budget-Existing_RPP'!$V$4/SUM('[3]Budget-Existing_RPP'!$V$4:$W$4) -> 590951.35 | P58: Allocated from total labor using Budget-Existing_RPP!V4:W4.
B59: IT Specialist II - PT | C59: =49.34*20*52 -> 51313.6 | K59: Enforcement | M59: =M$57*'[3]Budget-Existing_RPP'!$W$4/SUM('[3]Budget-Existing_RPP'!$V$4:$W$4) -> 1310872.1 | N59: =N$57*'[3]Budget-Existing_RPP'!$W$4/SUM('[3]Budget-Existing_RPP'!$V$4:$W$4) -> 1231610.6 | O59: =O$57*'[3]Budget-Existing_RPP'!$W$4/SUM('[3]Budget-Existing_RPP'!$V$4:$W$4) -> 1075452.3 | P59: Allocated from total labor using Budget-Existing_RPP!V4:W4.
B60: Parking Enforcement Supervisor | C60: 186465
B61: Parking Enforcement Officer x4 | C61: =122815*4 -> 491260
B62: Skilled Maintenance Worker | C62: 119151
B63: Parking Operations Supervisor | C63: 203962
B64: Parking Operations Coordinator | C64: 119151
B65: Labor Allocation - Parking Management
B66: Labor Allocation - Enforcement

Sheet Existing RPP - KH Inhouse
B2: Current RPP - Year One Costs
C3: ACE | G3: LAZ | K3: In-House
B4: Operating Expenses | C4: Universal Costs | D4: Single Space | E4: Dual Space | F4: Multi Space | G4: Universal Costs | H4: Single Space | I4: Dual Space | J4: Multi Space | K4: Included in Inhouse Operating Costs? | L4: Universal Costs | M4: Single Space | N4: Dual Space | O4: Multi Space | P4: Calculation Notes
B5: Area Manager Allocation | C5: 18000 | K5: No
B6: Project Manager Wages | C6: 112320 | K6: No
B7: Administrator Wages | C7: 72800 | K7: No
B8: Enforcement Officer Wages | C8: 149760 | K8: No
B9: Meter Support Wages | D9: 187200 | E9: 124800 | F9: 62352 | K9: No
B10: Vacation/Holiday/Sick | D10: 32405 | E10: 27581 | F10: 23822 | G10: ='[3]Budget-Existing_RPP'!P6 -> 23178.96 | K10: No
B11: Payroll Overhead | D11: 147987 | E11: 130610 | F11: 113443 | G11: ='[3]Budget-Existing_RPP'!P8 -> 50572.628 | K11: No
B12: Health and Welfare | D12: 89236 | E12: 76488 | F12: 63740 | G12: ='[3]Budget-Existing_RPP'!P9+'[3]Budget-Existing_RPP'!P11 -> 94801.946 | K12: No
B13: 401k Company Match | G13: ='[3]Budget-Existing_RPP'!P10 -> 3863.16 | K13: No
B14: Safety / Audit Fees | G14: ='[3]Budget-Existing_RPP'!P13 -> 5320 | K14: No
B15: Business License / Parking Bond | G15: ='[3]Budget-Existing_RPP'!P14 -> 2500 | K15: No
B16: IT and Technology / Reporting | G16: ='[3]Budget-Existing_RPP'!P40 -> 9000 | K16: No
B17: Total Labor | D17: 809708 | E17: 712359 | F17: 616036 | G17: ='[3]Budget-Existing_RPP'!P5 -> 386316 | K17: n/a
B18: Recruiting/Testing/Training | D18: 1800 | E18: 900 | F18: 600 | G18: ='[3]Budget-Existing_RPP'!P15 -> 3280 | K18: Parking Management | M18: =CEILING(328*3*1.2,500)+$O$18 -> 6000 | N18: =CEILING(328*2*1.2,500)+O18 -> 5500 | O18: =CEILING(328*11*1.2,500) -> 4500 | P18: Base Year 1 startup allowance covers 11 hires. Single-space adds 3 hires and dual-space adds 2 hires under the scenario staffing rule; each increment uses $328 per hire plus 20% contingency, rounded to $500.
B19: Payroll Processing | D19: 2160 | E19: 1920 | F19: 1680 | G19: ='[3]Budget-Existing_RPP'!P17 -> 3863.16 | K19: Parking Management | M19: =(M56-$O56)*1%+O19 -> 19083.696 | N19: =(N56-$O56)*1%+O19 -> 17855.546 | O19: =SUM($C$56:$C$63)*1% -> 15435.886 | P19: Base allowance is 1.0% of base payroll. Single- and dual-space add 1.0% of their incremental officer and maintenance payroll.
B20: Uniforms | D20: 3240 | E20: 2880 | F20: 2520 | G20: ='[3]Budget-Existing_RPP'!P38 -> 3840 | K20: Parking Management | M20: =320*3+O20 -> 3520 | N20: =320*2+O20 -> 3200 | O20: =320*8 -> 2560 | P20: Base allowance covers 8 field staff. Single-space adds uniforms for 3 staff and dual-space for 2 staff at $320 each.
B21: Parking/Meter Supplies | D21: 24000 | E21: 14400 | F21: 9000 | G21: ='[3]Budget-Existing_RPP'!P34+'[3]Budget-Existing_RPP'!P37+'[3]Budget-Existing_RPP'!P36 -> 8400 | K21: Parking Management | M21: =$D21 -> 24000 | N21: =$E21 -> 14400 | O21: =$F21 -> 9000 | P21: Uses ACE's scenario-specific supplies allowances because meter type drives parts and consumables.
B22: Software License Fees | C22: 780 | G22: ='[3]Budget-Existing_RPP'!P27 -> 15000 | K22: Parking Management | L22: =$G22 -> 15000 | P22: Shared Passport digital-permit license included once across all selected packages; direct annual vendor amount of $15,000.
B23: Vehicles Lease 5 years | G23: ='[3]Budget-Existing_RPP'!P22 -> 30340.78 | K23: No - Purchase as Capital | P23: No recurring lease assumed. The City purchases the vehicles up front; purchase costs are included in capital expenses on row 50.
B24: LPR On-going Fees | G24: ='[3]Budget-Existing_RPP'!P23 -> 12951 | K24: Enforcement | L24: =$G24 -> 12951 | P24: Shared Route1/Genetec annual support and licenses for two ALPR-equipped vehicles, included once across all scenarios; direct annual vendor amount of $12,951. The total fleet may range from 3 to 5 vehicles, but only two are assumed to carry ALPR equipment unless operations determine additional units are needed.
B25: Meter Software / Data / Support | D25: 175172 | E25: 110143 | F25: 72912 | K25: Parking Management | M25: ='[3]Technology Scenarios Total'!G157-$L$22-$L$24-$L$27 -> 89640 | N25: ='[3]Technology Scenarios Total'!G236-$L$22-$L$24-$L$27 -> 76296 | O25: ='[3]Technology Scenarios Total'!G45-$L$22-$L$24-$L$27 -> 72912 | P25: Vendor-specific recurring component of the selected direct-purchase packages. Current selection is the cheapest option, subject to change based on actual selection: MacKay mkBeacon single-space, MacKay mkBeacon dual-space, and Flowbird CWT S4+ multi-space. Each formula subtracts the shared Passport, eleven-x sensor, and Route1/Genetec costs already included in L22, L27, and L24 from the package annual total.
B26: Genetec Software/Support | C26: 11433 | K26: No - Duplicate | P26: Excluded to avoid double counting. Route1/Genetec annual support and licenses are already included once in L24 as a shared component of every selected technology package.
B27: Parking Sensor Software/Support | C27: 8640 | G27: ='[3]Budget-Existing_RPP'!P30 -> 6984 | K27: Enforcement | L27: =6984 -> 6984 | P27: Shared eleven-x managed network and dashboard subscriptions included once across all selected packages: $4,200 + $2,784 = $6,984 annually.
B28: Turbo Data Handheld Rental | C28: 12600 | G28: ='[3]Budget-Existing_RPP'!P41 -> 7200 | K28: Enforcement | L28: =$G28 -> 7200 | P28: Uses LAZ's flat $7,200 annual Turbodata software-fee allowance for every scenario. No per-device rate is documented, so the cost is not scaled with handheld or officer count.
B29: Telephone | C29: 3000 | G29: ='[3]Budget-Existing_RPP'!P42 -> 9600 | K29: Parking Management | L29: =$G29 -> 9600 | P29: Uses LAZ's flat $9,600 annual Telephone/Cellular allowance for every scenario. No per-user rate or documented user count is available, so the cost is not scaled with staffing.
B30: Computer Expense | C30: 1200 | G30: ='[3]Budget-Existing_RPP'!P43 -> 2500 | K30: Parking Management | L30: =500*6 -> 3000 | P30: Six computer users × $500 annual device/support allowance: project manager, administrator, IT, enforcement supervisor, operations supervisor, and coordinator.
B31: Signs | C31: 1800 | K31: Enforcement | L31: =$C31 -> 1800 | P31: ACE annual sign-replacement allowance; common to all scenarios.
B32: Repair and Maintenance | D32: 25200 | E32: 8400 | F32: 2400 | G32: ='[3]Budget-Existing_RPP'!P32+'[3]Budget-Existing_RPP'!P33 -> 12000 | K32: Parking Management | M32: =$D32 -> 25200 | N32: =$E32 -> 8400 | O32: =$F32 -> 2400 | P32: Uses ACE's scenario-specific repair and maintenance allowances because meter quantity/type drives service effort and parts.
B33: PCI Compliance | C33: 300 | K33: Parking Management | L33: =$C33 -> 300 | P33: ACE annual PCI-compliance allowance; common to all scenarios.
B34: Bank Fees | C34: 264 | K34: Parking Management | L34: =$C34 -> 264 | P34: ACE annual banking allowance; common to all scenarios. Transaction-based merchant fees remain excluded.
B35: Vehicle Fuel | C35: 10200 | G35: ='[3]Budget-Existing_RPP'!P35 -> 14400 | K35: Enforcement | M35: =$G35 -> 14400 | N35: =$G35*4/5 -> 11520 | O35: =$G35*3/5 -> 8640 | P35: LAZ fuel benchmark for the 5-vehicle single-space fleet; scaled to 4 vehicles for dual-space and 3 for multi-space.
B36: Insurance - Vehicle | D36: 79200 | E36: 63360 | F36: 47520 | G36: ='[3]Budget-Existing_RPP'!P20 -> 15224 | K36: Enforcement | M36: =$G36 -> 15224 | N36: =$G36*4/5 -> 12179.2 | O36: =$G36*3/5 -> 9134.4 | P36: LAZ vehicle-insurance benchmark for the 5-vehicle single-space fleet; scaled to 4 vehicles for dual-space and 3 for multi-space.
B37: Insurance - Liability | C37: 9504 | G37: ='[3]Budget-Existing_RPP'!P19 -> 21968.977 | K37: Enforcement | L37: =SUM($C$56:$C$63)*3% -> 46307.658 | M37: =(M56-$O56)*3% -> 10943.43 | N37: =(N56-$O56)*3% -> 7258.98 | P37: Base planning proxy is 3% of base payroll. Single- and dual-space add 3% of incremental officer and maintenance payroll; replace with the City's actual risk-manager premium when available.
B38: Equipment Amortization | D38: 213727 | E38: 150294 | F38: 155855 | G38: ='[3]Budget-Existing_RPP'!P24+'[3]Budget-Existing_RPP'!P29+'[3]Budget-Existing_RPP'!P30+'[3]Budget-Existing_RPP'!P26 -> 40713.41 | K38: No
B39: Storage Space Rental | C39: 6600 | K39: No
B40: Office Space Rental | C40: 30000 | K40: No
B41: Clerical Fee | D41: 11400 | E41: 10200 | F41: 9000 | K41: No
B42: Management Fee | D42: 84000 | E42: 72000 | F42: 60000 | G42: ='[3]Budget-Existing_RPP'!P16 -> 42000 | K42: No
B43: Operating Expenses | D43: 1525928 | E43: 1243177 | F43: 1073844 | G43: ='[3]Budget-Existing_RPP'!P53 -> 848926.02 | K43: n/a | L43: =SUM(L18:L37) -> 103406.66 | M43: =$L43+SUM(M18:M37) -> 311417.78 | N43: =$L43+SUM(N18:N37) -> 260016.38 | O43: =$L43+SUM(O18:O37) -> 227988.94 | P43: Recurring non-labor operating costs use complete direct-vendor technology packages: MacKay single-space, MacKay dual-space, and Flowbird multi-space (cheapest equipment options). Shared Passport, eleven-x, and Route1/Genetec charges are counted once; Turbodata and telephone remain flat LAZ allowances; vehicle leasing is excluded.
B44: Payment Bond (1.20%) | C44: =C43*1.2% -> 0 | D44: 18311 | E44: 14918 | F44: 12886 | K44: n/a | P44: No payment bond assumed for direct City operations.
B45: Total Expenses | C45: =C43+C44 -> 0 | D45: 1544239 | E45: 1258095 | F45: 1086730 | G45: =SUM(G5:G44) -> 1674744 | K45: n/a | M45: =$M43+$M56 -> 2219787.4 | N45: =$N43+$N56 -> 2045571 | O45: =$O43+$O56 -> 1771577.5 | P45: Total annual in-house expense equals recurring non-labor operating costs plus scenario staffing. Capital purchases remain separate in row 54.
B47: Capital Expenses | C47: Universal Costs | D47: Single Space | E47: Dual Space | F47: Multi Space | G47: Universal Costs | H47: Single Space | I47: Dual Space | J47: Multi Space | K47: Included in Inhouse Capital Costs? | L47: Universal Costs | M47: Single Space | N47: Dual Space | O47: Multi Space | P47: Calculation Notes
B48: Meters | D48: 575690 | E48: 355800 | F48: 406760 | H48: 250608 | I48: 142860 | J48: 130020 | K48: Parking Management | M48: =SUM('[3]Technology Scenarios Total'!F124:F131) -> 982892.19 | N48: =SUM('[3]Technology Scenarios Total'!F203:F210) -> 560330.11 | O48: =SUM('[3]Technology Scenarios Total'!F6:F11) -> 509946.88 | P48: Selected direct-purchase meter/pay-station capital packages: MacKay mkBeacon single-space (747 meters plus poles, tariffs, tax, shipping, and installation); MacKay mkBeacon dual-space (374 meters plus poles, tariffs, tax, shipping, and installation); and Flowbird CWT S4+ multi-space (62 pay stations plus spare-parts bundle, programming, prevailing-wage installation, freight, and sales tax). Recurring software and support are included separately in row 25.
B49: Genetec Mobile LPR Units | D49: 83220 | E49: 83220 | F49: 83220 | K49: Enforcement | L49: =SUM('[3]Technology Scenarios Total'!F32:F35) -> 62474.45 | P49: Shared LAZ/Route1 Genetec mobile LPR capital package for two ALPR-equipped vehicles used in all scenarios: engineering services, hardware/software, user interface and communications, and sales tax. Selected because its lower upfront cost produces the lower five-year total than ACE. The total fleet may range from 3 to 5 vehicles, but Genetec costs are not scaled because only two vehicles are assumed to carry ALPR equipment; obtain an updated Route1 quote if additional ALPR units are required. Annual support/licenses are included separately in L24.
B50: Toyota Corolla | D50: 144500 | E50: 115600 | F50: 86451 | K50: Enforcement | M50: =$D50 -> 144500 | N50: =$E50 -> 115600 | O50: =$F50 -> 86451 | P50: Purchase vehicles using ACE's scenario quantities and pricing: 5 vehicles for single-space, 4 for dual-space, and 3 for multi-space.
B51: Parking Sensors | D51: 34850 | E51: 34850 | F51: 34850 | K51: Enforcement | L51: =SUM('[3]Technology Scenarios Total'!F23:F25) -> 40789 | P51: Shared eleven-x installed sensor system used in all scenarios: 48 SPS-X sensors ($9,552), 3 wireless gateways ($3,285), and installation/setup ($27,952), totaling $40,789. Selected over ACE/Fybr because its lower annual cost produces the lower five-year system cost and maintains consistency with the selected LAZ technology packages.
B52: Passport Implementation | K52: Parking Management | L52: ='[3]Technology Scenarios Total'!F29 -> 10000 | P52: One-time Passport digital-permit implementation charge shared across all scenarios. The annual $15,000 software license is included separately in row 22; usage-based permit and payment-processing fees are passed through to users and excluded from City costs.
B53: Total In-House Capital Costs | K53: Approved items only | L53: =SUM(L48:L52) -> 113263.45 | M53: =$L53+SUM(M48:M52) -> 1240655.6 | N53: =$L53+SUM(N48:N52) -> 789193.56 | O53: =$L53+SUM(O48:O52) -> 709661.33 | P53: Total in-house capital includes the selected meter/pay-station package, shared Passport implementation, the two-vehicle LAZ/Route1 Genetec LPR package, the eleven-x sensor system, and purchased vehicles. Usage-based fees are excluded because they will be passed through to users; contingency and escalation will be added later.
B55: Inhouse Staffing Plan | C55: Fully Burdened Costs | K55: Included in Inhouse Labor Costs? | L55: Universal Costs | M55: Single Space | N55: Dual Space | O55: Multi Space | P55: Calculation Notes
B56: Project Manager | C56: 208147 | K56: Yes | M56: =SUM($C$56:$C$59,$C$62:$C$63)+6*($C$60/4)+2*$C$61 -> 1908369.6 | N56: =SUM($C$56:$C$59,$C$62:$C$63)+5*($C$60/4)+2*$C$61 -> 1785554.6 | O56: =SUM($C$56:$C$59,$C$62:$C$63)+$C$60+$C$61 -> 1543588.6 | P56: Total fully burdened labor by equipment plan. Fixed roles are the project manager, administrator, part-time IT specialist, enforcement supervisor, operations supervisor, and operations coordinator. Single-space includes 6 enforcement officers and 2 maintenance workers; dual-space includes 5 officers and 2 maintenance workers; multi-space includes 4 officers and 1 maintenance worker.
B57: Administrator | C57: 164139 | K57: Parking Management | M57: =M$56*'[3]Budget-Existing_RPP'!$V$4/SUM('[3]Budget-Existing_RPP'!$V$4:$W$4) -> 676758.97 | N57: =N$56*'[3]Budget-Existing_RPP'!$V$4/SUM('[3]Budget-Existing_RPP'!$V$4:$W$4) -> 633205.48 | O57: =O$56*'[3]Budget-Existing_RPP'!$V$4/SUM('[3]Budget-Existing_RPP'!$V$4:$W$4) -> 547397.86 | P57: Allocated from total labor using Budget-Existing_RPP!V4:W4.
B58: IT Specialist II - PT | C58: =49.34*20*52 -> 51313.6 | K58: Enforcement | M58: =M$56*'[3]Budget-Existing_RPP'!$W$4/SUM('[3]Budget-Existing_RPP'!$V$4:$W$4) -> 1231610.6 | N58: =N$56*'[3]Budget-Existing_RPP'!$W$4/SUM('[3]Budget-Existing_RPP'!$V$4:$W$4) -> 1152349.1 | O58: =O$56*'[3]Budget-Existing_RPP'!$W$4/SUM('[3]Budget-Existing_RPP'!$V$4:$W$4) -> 996190.74 | P58: Allocated from total labor using Budget-Existing_RPP!V4:W4.
B59: Parking Enforcement Supervisor | C59: 186465
B60: Parking Enforcement Officer x4 | C60: =122815*4 -> 491260
B61: Skilled Maintenance Worker | C61: 119151
B62: Parking Operations Supervisor | C62: 203962
B63: Parking Operations Coordinator | C63: 119151
B64: Labor Allocation - Parking Management
B65: Labor Allocation - Enforcement
