Workbook
Name _Ref155180426: '$1.5 per hr + $0.5 Projection'!#REF!
Name _Ref155180426: '$1.5 per hr + $1 Projection'!#REF!
Name _Ref155180426: '$2 per hr + $0.5 Projection'!#REF!
Name _Ref155180426: '$2 per hr + $1 Projection'!#REF!

Sheet Incl
A1: Phase 1 | B1: Phase 2
A2: 80 | B2: 154 | D2: 80
A3: 81 | B3: 155 | D3: 81
A4: 82 | B4: 156 | D4: 82
A5: 83 | D5: 83
A6: 84 | B6: 158 | D6: 84
A7: 85 | B7: 100 | D7: 85
A8: 194 | B8: 103
A9: 113 | B9: 107
A10: 117 | B10: 109
A11: 196 | B11: 110
A12: 195 | B12: 111
A13: 197 | B13: 80
A14: 120 | B14: 81
A15: 87 | B15: 82
A16: 121 | B16: 83
A17: 86 | B17: 84
A18: 206 | B18: 85
A19: 208 | B19: 194
... A42: 904 | B42: 91
B43: 90
B44: 224
B45: 225
B46: 127
B47: 129
B48: 130
B49: 132
B50: 207
B51: 902
B52: 903
B53: 904
B54: 905

Sheet Raw
A1: OBJECTID_1 * | B1: SymbolID | C1: Shape_Leng | D1: OBJECTID | E1: Join_Count | F1: TARGET_FID | G1: Name | H1: Name_v2 | I1: Field1 | J1: Segment | K1: Street | L1: From | M1: To | N1: Short Term Parking | O1: Medium Term Parking | P1: Unlimited Parking | Q1: Handicapped Parking | R1: Loading Zone | S1: Permitted Parking | T1: Space_Total | U1: Occ_Sat_10AM_CT | V1: Occ_Sat_2PM_CT | W1: Occ_Sat_4PM_CT | X1: Occ_Sat_8PM_CT | Y1: Occ_Sat_10AM_Per | Z1: Occ_Sat_2PM_Per | AA1: Occ_Sat_4PM_Per | AB1: Occ_Sat_8PM_Per | AC1: Occ_Sat_is75 | AD1: Occ_Thu_10AM_CT | AE1: Occ_Thu_2PM_CT | AF1: Occ_Thu_4PM_CT | AG1: Occ_Thu_8PM_CT | AH1: Occ_Thu_10AM_Per | AI1: Occ_Thu_2PM_Per | AJ1: Occ_Thu_4PM_Per | AK1: Occ_Thu_8PM_Per | AL1: Occ_Thu_is75 | AM1: TO_Sat_10AM_CT | AN1: TO_Sat_11AM_CT | AO1: TO_Sat_12PM_CT | AP1: TO_Sat_1PM_CT | AQ1: TO_Sat_2PM_CT | AR1: TO_Sat_3PM_CT | AS1: TO_Sat_4PM_CT | AT1: TO_Sat_5PM_CT | AU1: TO_Sat_6PM_CT | AV1: TO_Sat_7PM_CT | AW1: TO_Sat_0-1 HRS | AX1: TO_Sat_1-2 HRS | AY1: TO_Sat_2-3 HRS | AZ1: TO_Sat_3-4 HRS | BA1: TO_Sat_4-5 HRS | BB1: TO_Sat_5-6 HRS | BC1: TO_Sat_6-7 HRS | BD1: TO_Sat_7-8 HRS | BE1: TO_Sat_8-9 HRS | BF1: TO_Sat_9-10 HRS | BG1: TO_Sat_Total | BH1: TO_Sat_Rate | BI1: TO_Sat_Range | BJ1: TO_Thu_10AM_CT | BK1: TO_Thu_11AM_CT | BL1: TO_Thu_12PM_CT | BM1: TO_Thu_1PM_CT | BN1: TO_Thu_2PM_CT | BO1: TO_Thu_3PM_CT | BP1: TO_Thu_4PM_CT | BQ1: TO_Thu_5PM_CT | BR1: TO_Thu_6PM_CT | BS1: TO_Thu_7PM_CT | BT1: TO_Thu_0-1 HRS | BU1: TO_Thu_1-2 HRS | BV1: TO_Thu_2-3 HRS | BW1: TO_Thu_3-4 HRS | BX1: TO_Thu_4-5 HRS | BY1: TO_Thu_5-6 HRS | BZ1: TO_Thu_6-7 HRS | CA1: TO_Thu_7-8 HRS | CB1: TO_Thu_8-9 HRS | CC1: TO_Thu_9-10 HRS | CD1: TO_Thu_Total | CE1: TO_Thu_Rate | CF1: TO_Thu_Range | CG1: x | CH1: Shape_Length | CI1: Occ_All_is75 | CJ1: PricingBoundary1 | CK1: PricingBoundary2 | CL1: PricingBoundary3 | CM1: Length_ft | CN1: DataAvail | CO1: PricingBoundary4 | CP1: Reduction | CQ1: <Null> | CR1: =IF(COUNTIF(Incl!A:A,Raw!J1),1, "")
AW2: 1 | AX2: 2 | AY2: 3 | AZ2: 4 | BA2: 5 | BB2: 6 | BC2: 7 | BD2: 8 | BE2: 9 | BF2: 10 | BT2: 1 | BU2: 2 | BV2: 3 | BW2: 4 | BX2: 5 | BY2: 6 | BZ2: 7 | CA2: 8 | CB2: 9 | CC2: 10
AW3: 1 | AX3: 2 | AY3: 2 | AZ3: 2 | BA3: 2 | BB3: 2 | BC3: 2 | BD3: 2 | BE3: 2 | BF3: 2 | BT3: 1 | BU3: 2 | BV3: 2 | BW3: 2 | BX3: 2 | BY3: 2 | BZ3: 2 | CA3: 2 | CB3: 2 | CC3: 2
A4: 1 | B4: 1 | C4: 555.51475 | D4: 1 | E4: 1 | F4: 30 | G4: 154 | H4: 154 | I4: 154 | J4: 154 | K4: Park Pl | L4: El Camino Real | M4: Park Blvd | N4: 6 | O4: 10 | P4: NA | Q4: NA | R4: NA | S4: NA | T4: 16 | U4: 11 | V4: 10 | W4: 13 | X4: NA | Y4: 69 | Z4: 63 | AA4: 81 | AB4: 0 | AC4: 1 | AD4: 4 | AE4: 10 | AF4: 15 | AG4: NA | AH4: 25 | AI4: 63 | AJ4: 94 | AK4: 0 | AL4: 1 | AM4: 11 | AN4: 13 | AO4: 13 | AP4: 15 | AQ4: 10 | AR4: 14 | AS4: 16 | AT4: 12 | AU4: 11 | AV4: 12 | AW4: 25 | AX4: 7 | AY4: 4 | AZ4: 4 | BA4: 1 | BB4: 0 | BC4: 1 | BD4: 1 | BE4: 0 | BF4: 4 | BG4: 47 | BH4: 2.9 | BI4: 2.0 - 3.0 | BJ4: 4 | BK4: 11 | BL4: 10 | BM4: 5 | BN4: 10 | BO4: 11 | BP4: 12 | BQ4: 12 | BR4: 15 | BS4: 14 | BT4: 13 | BU4: 7 | BV4: 1 | BW4: 3 | BX4: 1 | BY4: 2 | BZ4: 0 | CA4: 2 | CB4: 1 | CC4: 2 | CD4: 32 | CE4: 2 | CF4: 2.0 - 3.0 | CG4: N | CH4: 0.001581 | CI4: 2 | CJ4: 1 | CK4: 1 | CL4: <Null> | CM4: 555.51482 | CN4: 1 | CO4: 1 | CP4: <Null> | CQ4: <Null> | CR4: =IF(COUNTIF(Incl!A:A,Raw!J4),1, "")
A5: 2 | B5: 1 | C5: 460.32238 | D5: 2 | E5: 1 | F5: 31 | G5: 155 | H5: 155 | I5: 155 | J5: 155 | K5: Park Pl | L5: Park Blvd | M5: El Camino Real | N5: 11 | O5: 7 | P5: NA | Q5: NA | R5: NA | S5: NA | T5: 18 | U5: 10 | V5: 16 | W5: 16 | X5: NA | Y5: 56 | Z5: 89 | AA5: 89 | AB5: 0 | AC5: 2 | AD5: 10 | AE5: 14 | AF5: 17 | AG5: NA | AH5: 56 | AI5: 78 | AJ5: 94 | AK5: 0 | AL5: 2 | AM5: 10 | AN5: 16 | AO5: 18 | AP5: 13 | AQ5: 16 | AR5: 17 | AS5: 17 | AT5: 16 | AU5: 16 | AV5: 16 | AW5: 43 | AX5: 6 | AY5: 8 | AZ5: 3 | BA5: 3 | BB5: 0 | BC5: 0 | BD5: 0 | BE5: 1 | BF5: 4 | BG5: 68 | BH5: 3.8 | BI5: 3.0 - 4.0 | BJ5: 10 | BK5: 12 | BL5: 14 | BM5: 11 | BN5: 14 | BO5: 15 | BP5: 13 | BQ5: 13 | BR5: 17 | BS5: 16 | BT5: 17 | BU5: 7 | BV5: 1 | BW5: 6 | BX5: 3 | BY5: 2 | BZ5: 0 | CA5: 0 | CB5: 0 | CC5: 5 | CD5: 41 | CE5: 2.3 | CF5: 2.0 - 3.0 | CG5: S | CH5: 0.001317 | CI5: 4 | CJ5: 1 | CK5: 1 | CL5: <Null> | CM5: 460.32252 | CN5: 1 | CO5: 1 | CP5: <Null> | CQ5: <Null> | CR5: =IF(COUNTIF(Incl!A:A,Raw!J5),1, "")
A6: 3 | B6: 1 | C6: 472.9842 | D6: 3 | E6: 1 | F6: 32 | G6: 156 | H6: 156 | I6: 156 | J6: 156 | K6: Park Blvd | L6: Park Pl | M6: El Camino Real | N6: 17 | O6: 8 | P6: NA | Q6: NA | R6: NA | S6: NA | T6: 25 | U6: 19 | V6: 17 | W6: 22 | X6: NA | Y6: 76 | Z6: 68 | AA6: 88 | AB6: 0 | AC6: 2 | AD6: 10 | AE6: 11 | AF6: 15 | AG6: NA | AH6: 40 | AI6: 44 | AJ6: 60 | AK6: 0 | AL6: 0 | AM6: 19 | AN6: 23 | AO6: 23 | AP6: 15 | AQ6: 17 | AR6: 10 | AS6: 15 | AT6: 17 | AU6: 22 | AV6: 23 | AW6: 82 | AX6: 15 | AY6: 5 | AZ6: 0 | BA6: 1 | BB6: 3 | BC6: 2 | BD6: 0 | BE6: 0 | BF6: 2 | BG6: 110 | BH6: 4.4 | BI6: 4.0 - 5.0 | BJ6: 10 | BK6: 10 | BL6: 9 | BM6: 13 | BN6: 11 | BO6: 13 | BP6: 14 | BQ6: 16 | BR6: 15 | BS6: 12 | BT6: 19 | BU6: 11 | BV6: 4 | BW6: 1 | BX6: 1 | BY6: 1 | BZ6: 1 | CA6: 0 | CB6: 2 | CC6: 3 | CD6: 43 | CE6: 1.7 | CF6: 1.0 - 2.0 | CG6: N | CH6: 0.001627 | CI6: 2 | CJ6: 1 | CK6: 1 | CL6: <Null> | CM6: 472.98401 | CN6: 1 | CO6: 1 | CP6: <Null> | CQ6: <Null> | CR6: =IF(COUNTIF(Incl!A:A,Raw!J6),1, "")
A7: 4 | B7: 1 | C7: 319.60566 | D7: 4 | E7: 1 | F7: 33 | G7: 157 | H7: 157 | I7: 157 | J7: 157 | K7: Park Blvd | L7: Magnolia Ave | M7: Palmito Dr | N7: NA | O7: 14 | P7: NA | Q7: NA | R7: NA | S7: NA | T7: 14 | U7: 9 | V7: 9 | W7: 9 | X7: 9 | Y7: 64 | Z7: 64 | AA7: 64 | AB7: 64 | AC7: 0 | AD7: 11 | AE7: 13 | AF7: 12 | AG7: 14 | AH7: 79 | AI7: 93 | AJ7: 86 | AK7: 100 | AL7: 4 | AM7: NA | AN7: NA | AO7: NA | AP7: NA | AQ7: NA | AR7: NA | AS7: NA | AT7: NA | AU7: NA | AV7: NA | AW7: NA | AX7: NA | AY7: NA | AZ7: NA | BA7: NA | BB7: NA | BC7: NA | BD7: NA | BE7: NA | BF7: NA | BG7: NA | BH7: NA | BI7: NA | BJ7: NA | BK7: NA | BL7: NA | BM7: NA | BN7: NA | BO7: NA | BP7: NA | BQ7: NA | BR7: NA | BS7: NA | BT7: NA | BU7: NA | BV7: NA | BW7: NA | BX7: NA | BY7: NA | BZ7: NA | CA7: NA | CB7: NA | CC7: NA | CD7: NA | CE7: NA | CF7: NA | CG7: S | CH7: 0.0011 | CI7: 4 | CJ7: 1 | CK7: 1 | CL7: <Null> | CM7: 319.60577 | CN7: 2 | CO7: 0 | CP7: <Null> | CQ7: <Null> | CR7: =IF(COUNTIF(Incl!A:A,Raw!J7),1, "")
A8: 5 | B8: 1 | C8: 175.24878 | D8: 5 | E8: 2 | F8: 34 | G8: 158 | H8: 158 | I8: 158 | J8: 158 | K8: Park Blvd | L8: Palmito Dr | M8: El Camino Real | N8: 11 | O8: NA | P8: NA | Q8: NA | R8: NA | S8: NA | T8: 11 | U8: 5 | V8: 8 | W8: 10 | X8: NA | Y8: 45 | Z8: 73 | AA8: 91 | AB8: 0 | AC8: 1 | AD8: 3 | AE8: 5 | AF8: 3 | AG8: NA | AH8: 27 | AI8: 45 | AJ8: 27 | AK8: 0 | AL8: 0 | AM8: 5 | AN8: 7 | AO8: 7 | AP8: 8 | AQ8: 8 | AR8: 3 | AS8: 4 | AT8: 8 | AU8: 10 | AV8: 11 | AW8: 39 | AX8: 7 | AY8: 2 | AZ8: 1 | BA8: 0 | BB8: 0 | BC8: 0 | BD8: 1 | BE8: 0 | BF8: 0 | BG8: 50 | BH8: 4.5 | BI8: 4.0 - 5.0 | BJ8: 3 | BK8: 5 | BL8: 5 | BM8: 7 | BN8: 5 | BO8: 4 | BP8: 3 | BQ8: 4 | BR8: 3 | BS8: 2 | BT8: 11 | BU8: 1 | BV8: 3 | BW8: 0 | BX8: 1 | BY8: 1 | BZ8: 0 | CA8: 1 | CB8: 0 | CC8: 0 | CD8: 18 | CE8: 1.6 | CF8: 1.0 - 2.0 | CG8: S | CH8: 0.000603 | CI8: 1 | CJ8: 1 | CK8: 1 | CL8: <Null> | CM8: 175.24883 | CN8: 1 | CO8: 1 | CP8: <Null> | CQ8: <Null> | CR8: =IF(COUNTIF(Incl!A:A,Raw!J8),1, "")
A9: 6 | B9: 1 | C9: 461.94848 | D9: 6 | E9: 1 | F9: 35 | G9: 100 | H9: 100 | I9: 100 | J9: 100 | K9: El Camino Real | L9: Park Pl | M9: Park Blvd | N9: 7 | O9: 12 | P9: NA | Q9: NA | R9: NA | S9: NA | T9: 19 | U9: 15 | V9: 11 | W9: 15 | X9: NA | Y9: 81 | Z9: 59 | AA9: 81 | AB9: 0 | AC9: 2 | AD9: 9 | AE9: 17 | AF9: 12 | AG9: NA | AH9: 48 | AI9: 91 | AJ9: 65 | AK9: 0 | AL9: 1 | AM9: 15 | AN9: 15 | AO9: 13 | AP9: 14 | AQ9: 11 | AR9: 9 | AS9: 8 | AT9: 12 | AU9: 15 | AV9: 15 | AW9: 32 | AX9: 12 | AY9: 5 | AZ9: 5 | BA9: 2 | BB9: 1 | BC9: 0 | BD9: 0 | BE9: 0 | BF9: 2 | BG9: 59 | BH9: 3.2 | BI9: 3.0 - 4.0 | BJ9: 9 | BK9: 17 | BL9: 15 | BM9: 12 | BN9: 17 | BO9: 17 | BP9: 15 | BQ9: 17 | BR9: 12 | BS9: 10 | BT9: 32 | BU9: 15 | BV9: 7 | BW9: 5 | BX9: 0 | BY9: 2 | BZ9: 0 | CA9: 2 | CB9: 0 | CC9: 1 | CD9: 64 | CE9: 3.4 | CF9: 3.0 - 4.0 | CG9: W | CH9: 0.001409 | CI9: 3 | CJ9: 1 | CK9: 1 | CL9: <Null> | CM9: 461.94852 | CN9: 1 | CO9: 1 | CP9: <Null> | CQ9: <Null> | CR9: =IF(COUNTIF(Incl!A:A,Raw!J9),1, "")
A10: 7 | B10: 1 | C10: 195.74436 | D10: 7 | E10: 1 | F10: 36 | G10: 101 | H10: 101 | I10: 101 | J10: 101 | K10: El Camino Real | L10: Santa Clara Ave | M10: Santa Inez Ave | N10: NA | O10: NA | P10: 5 | Q10: NA | R10: NA | S10: NA | T10: 5 | U10: 1 | V10: 1 | W10: 4 | X10: NA | Y10: 20 | Z10: 20 | AA10: 82 | AB10: 0 | AC10: 1 | AD10: 4 | AE10: 2 | AF10: 7 | AG10: NA | AH10: 82 | AI10: 41 | AJ10: 143 | AK10: 0 | AL10: 2 | AM10: 1 | AN10: 2 | AO10: 2 | AP10: 1 | AQ10: 1 | AR10: 1 | AS10: 3 | AT10: 5 | AU10: 4 | AV10: 4 | AW10: 8 | AX10: 1 | AY10: 2 | AZ10: 0 | BA10: 0 | BB10: 0 | BC10: 0 | BD10: 1 | BE10: 0 | BF10: 0 | BG10: 12 | BH10: 2.4 | BI10: 2.0 - 3.0 | BJ10: 4 | BK10: 3 | BL10: 3 | BM10: 2 | BN10: 2 | BO10: 3 | BP10: 3 | BQ10: 5 | BR10: 7 | BS10: 6 | BT10: 3 | BU10: 7 | BV10: 2 | BW10: 0 | BX10: 1 | BY10: 0 | BZ10: 0 | CA10: 0 | CB10: 0 | CC10: 1 | CD10: 14 | CE10: 2.9 | CF10: 2.0 - 3.0 | CG10: E | CH10: 0.000596 | CI10: 3 | CJ10: <Null> | CK10: <Null> | CL10: <Null> | CM10: 195.7445 | CN10: 1 | CO10: 1 | CP10: <Null> | CQ10: <Null> | CR10: =IF(COUNTIF(Incl!A:A,Raw!J10),1, "")
A11: 8 | B11: 1 | C11: 198.9532 | D11: 8 | E11: 1 | F11: 37 | G11: 102 | H11: 102 | I11: 102 | J11: 102 | K11: El Camino Real | L11: San Diego Ave | M11: Santa Clara Ave | N11: NA | O11: 8 | P11: NA | Q11: NA | R11: NA | S11: NA | T11: 8 | U11: 1 | V11: 5 | W11: 8 | X11: NA | Y11: 12 | Z11: 60 | AA11: 95 | AB11: 0 | AC11: 1 | AD11: 0 | AE11: 1 | AF11: 7 | AG11: NA | AH11: 0 | AI11: 12 | AJ11: 83 | AK11: 0 | AL11: 1 | AM11: 1 | AN11: 3 | AO11: 5 | AP11: 5 | AQ11: 5 | AR11: 5 | AS11: 4 | AT11: 6 | AU11: 8 | AV11: 8 | AW11: 6 | AX11: 6 | AY11: 6 | AZ11: 0 | BA11: 1 | BB11: 0 | BC11: 0 | BD11: 0 | BE11: 1 | BF11: 0 | BG11: 20 | BH11: 2.4 | BI11: 2.0 - 3.0 | BJ11: 0 | BK11: 0 | BL11: 0 | BM11: 0 | BN11: 1 | BO11: 2 | BP11: 1 | BQ11: 3 | BR11: 7 | BS11: 7 | BT11: 7 | BU11: 4 | BV11: 2 | BW11: 0 | BX11: 0 | BY11: 0 | BZ11: 0 | CA11: 0 | CB11: 0 | CC11: 0 | CD11: 13 | CE11: 1.5 | CF11: 1.0 - 2.0 | CG11: E | CH11: 0.000609 | CI11: 2 | CJ11: <Null> | CK11: <Null> | CL11: <Null> | CM11: 198.9531 | CN11: 1 | CO11: 1 | CP11: <Null> | CQ11: <Null> | CR11: =IF(COUNTIF(Incl!A:A,Raw!J11),1, "")
A12: 9 | B12: 1 | C12: 205.77664 | D12: 9 | E12: 1 | F12: 38 | G12: 104 | H12: 104 | I12: 104 | J12: 104 | K12: El Camino Real | L12: Santa Maria Ave | M12: San Diego Ave | N12: NA | O12: 5 | P12: NA | Q12: NA | R12: NA | S12: NA | T12: 5 | U12: 3 | V12: 2 | W12: 2 | X12: NA | Y12: 59 | Z12: 39 | AA12: 39 | AB12: 0 | AC12: 0 | AD12: 2 | AE12: 2 | AF12: 3 | AG12: NA | AH12: 39 | AI12: 39 | AJ12: 59 | AK12: 0 | AL12: 0 | AM12: 3 | AN12: 1 | AO12: 1 | AP12: 1 | AQ12: 2 | AR12: 2 | AS12: 2 | AT12: 2 | AU12: 2 | AV12: 5 | AW12: 6 | AX12: 0 | AY12: 0 | AZ12: 0 | BA12: 1 | BB12: 0 | BC12: 0 | BD12: 0 | BE12: 0 | BF12: 1 | BG12: 8 | BH12: 1.6 | BI12: 1.0 - 2.0 | BJ12: 2 | BK12: 2 | BL12: 2 | BM12: 2 | BN12: 2 | BO12: 2 | BP12: 3 | BQ12: 4 | BR12: 3 | BS12: 3 | BT12: 0 | BU12: 1 | BV12: 1 | BW12: 0 | BX12: 0 | BY12: 0 | BZ12: 0 | CA12: 0 | CB12: 0 | CC12: 2 | CD12: 4 | CE12: 0.8 | CF12: 0.0 - 1.0 | CG12: E | CH12: 0.000623 | CI12: 0 | CJ12: <Null> | CK12: <Null> | CL12: <Null> | CM12: 205.77658 | CN12: 1 | CO12: 1 | CP12: <Null> | CQ12: <Null> | CR12: =IF(COUNTIF(Incl!A:A,Raw!J12),1, "")
A13: 10 | B13: 1 | C13: 76.880035 | D13: 10 | E13: 1 | F13: 39 | G13: 67 | H13: 67 | I13: 67 | J13: 67 | K13: Palmito Dr | L13: Park Blvd | M13: Alley | N13: NA | O13: NA | P13: 4 | Q13: NA | R13: NA | S13: NA | T13: 4 | U13: 3 | V13: 4 | W13: 4 | X13: 4 | Y13: 73 | Z13: 98 | AA13: 98 | AB13: 98 | AC13: 3 | AD13: 0 | AE13: 0 | AF13: 0 | AG13: 0 | AH13: 0 | AI13: 0 | AJ13: 0 | AK13: 0 | AL13: 0 | AM13: NA | AN13: NA | AO13: NA | AP13: NA | AQ13: NA | AR13: NA | AS13: NA | AT13: NA | AU13: NA | AV13: NA | AW13: NA | AX13: NA | AY13: NA | AZ13: NA | BA13: NA | BB13: NA | BC13: NA | BD13: NA | BE13: NA | BF13: NA | BG13: NA | BH13: NA | BI13: NA | BJ13: NA | BK13: NA | BL13: NA | BM13: NA | BN13: NA | BO13: NA | BP13: NA | BQ13: NA | BR13: NA | BS13: NA | BT13: NA | BU13: NA | BV13: NA | BW13: NA | BX13: NA | BY13: NA | BZ13: NA | CA13: NA | CB13: NA | CC13: NA | CD13: NA | CE13: NA | CF13: NA | CG13: W | CH13: 0.000212 | CI13: 3 | CJ13: <Null> | CK13: <Null> | CL13: <Null> | CM13: 76.880108 | CN13: 2 | CO13: 0 | CP13: <Null> | CQ13: <Null> | CR13: =IF(COUNTIF(Incl!A:A,Raw!J13),1, "")
A14: 11 | B14: 1 | C14: 64.002595 | D14: 11 | E14: 1 | F14: 40 | G14: 68 | H14: 68 | I14: 68 | J14: 68 | K14: Palmito Dr | L14: Alley | M14: Park Blvd | N14: NA | O14: NA | P14: NA | Q14: NA | R14: NA | S14: NA | T14: 0 | U14: 4 | V14: 4 | W14: 4 | X14: 4 | Y14: 0 | Z14: 0 | AA14: 0 | AB14: 0 | AC14: 0 | AD14: 4 | AE14: 4 | AF14: 4 | AG14: 0 | AH14: 0 | AI14: 0 | AJ14: 0 | AK14: 0 | AL14: 0 | AM14: NA | AN14: NA | AO14: NA | AP14: NA | AQ14: NA | AR14: NA | AS14: NA | AT14: NA | AU14: NA | AV14: NA | AW14: NA | AX14: NA | AY14: NA | AZ14: NA | BA14: NA | BB14: NA | BC14: NA | BD14: NA | BE14: NA | BF14: NA | BG14: NA | BH14: NA | BI14: NA | BJ14: NA | BK14: NA | BL14: NA | BM14: NA | BN14: NA | BO14: NA | BP14: NA | BQ14: NA | BR14: NA | BS14: NA | BT14: NA | BU14: NA | BV14: NA | BW14: NA | BX14: NA | BY14: NA | BZ14: NA | CA14: NA | CB14: NA | CC14: NA | CD14: NA | CE14: NA | CF14: NA | CG14: E | CH14: 0.000177 | CI14: 0 | CJ14: <Null> | CK14: <Null> | CL14: <Null> | CM14: 64.002649 | CN14: 2 | CO14: 0 | CP14: <Null> | CQ14: <Null> | CR14: =IF(COUNTIF(Incl!A:A,Raw!J14),1, "")
A15: 12 | B15: 1 | C15: 575.68186 | D15: 12 | E15: 1 | F15: 41 | G15: 69 | H15: 69 | I15: 69 | J15: 69 | K15: Palmito Dr | L15: Alley | M15: Capuchino Dr | N15: NA | O15: NA | P15: 19 | Q15: NA | R15: NA | S15: NA | T15: 19 | U15: 12 | V15: 12 | W15: 12 | X15: 13 | Y15: 63 | Z15: 63 | AA15: 63 | AB15: 68 | AC15: 0 | AD15: 12 | AE15: 11 | AF15: 10 | AG15: 10 | AH15: 63 | AI15: 58 | AJ15: 52 | AK15: 52 | AL15: 0 | AM15: NA | AN15: NA | AO15: NA | AP15: NA | AQ15: NA | AR15: NA | AS15: NA | AT15: NA | AU15: NA | AV15: NA | AW15: NA | AX15: NA | AY15: NA | AZ15: NA | BA15: NA | BB15: NA | BC15: NA | BD15: NA | BE15: NA | BF15: NA | BG15: NA | BH15: NA | BI15: NA | BJ15: NA | BK15: NA | BL15: NA | BM15: NA | BN15: NA | BO15: NA | BP15: NA | BQ15: NA | BR15: NA | BS15: NA | BT15: NA | BU15: NA | BV15: NA | BW15: NA | BX15: NA | BY15: NA | BZ15: NA | CA15: NA | CB15: NA | CC15: NA | CD15: NA | CE15: NA | CF15: NA | CG15: W | CH15: 0.001747 | CI15: 0 | CJ15: <Null> | CK15: <Null> | CL15: <Null> | CM15: 575.68193 | CN15: 2 | CO15: <Null> | CP15: <Null> | CQ15: <Null> | CR15: =IF(COUNTIF(Incl!A:A,Raw!J15),1, "")
A16: 13 | B16: 1 | C16: 568.53623 | D16: 13 | E16: 2 | F16: 42 | G16: 70 | H16: 70 | I16: 70 | J16: 70 | K16: Palmito Dr | L16: Capuchino Dr | M16: Alley | N16: NA | O16: NA | P16: 25 | Q16: NA | R16: NA | S16: NA | T16: 25 | U16: 17 | V16: 16 | W16: 15 | X16: 19 | Y16: 67 | Z16: 63 | AA16: 59 | AB16: 75 | AC16: 1 | AD16: 11 | AE16: 11 | AF16: 12 | AG16: 8 | AH16: 43 | AI16: 43 | AJ16: 47 | AK16: 31 | AL16: 0 | AM16: NA | AN16: NA | AO16: NA | AP16: NA | AQ16: NA | AR16: NA | AS16: NA | AT16: NA | AU16: NA | AV16: NA | AW16: NA | AX16: NA | AY16: NA | AZ16: NA | BA16: NA | BB16: NA | BC16: NA | BD16: NA | BE16: NA | BF16: NA | BG16: NA | BH16: NA | BI16: NA | BJ16: NA | BK16: NA | BL16: NA | BM16: NA | BN16: NA | BO16: NA | BP16: NA | BQ16: NA | BR16: NA | BS16: NA | BT16: NA | BU16: NA | BV16: NA | BW16: NA | BX16: NA | BY16: NA | BZ16: NA | CA16: NA | CB16: NA | CC16: NA | CD16: NA | CE16: NA | CF16: NA | CG16: E | CH16: 0.001731 | CI16: 1 | CJ16: <Null> | CK16: <Null> | CL16: <Null> | CM16: 568.53628 | CN16: 2 | CO16: <Null> | CP16: <Null> | CQ16: <Null> | CR16: =IF(COUNTIF(Incl!A:A,Raw!J16),1, "")
A17: 14 | B17: 1 | C17: 688.26173 | D17: 14 | E17: 4 | F17: 43 | G17: 99 | H17: 99 | I17: 99 | J17: 99 | K17: Alley | L17: Capuchino Dr | M17: Palmito Dr | N17: NA | O17: NA | P17: NA | Q17: NA | R17: NA | S17: NA | T17: 0 | U17: NA | V17: NA | W17: NA | X17: NA | Y17: 0 | Z17: 0 | AA17: 0 | AB17: 0 | AC17: 0 | AD17: 0 | AE17: 0 | AF17: 0 | AG17: 0 | AH17: 0 | AI17: 0 | AJ17: 0 | AK17: 0 | AL17: 0 | AM17: NA | AN17: NA | AO17: NA | AP17: NA | AQ17: NA | AR17: NA | AS17: NA | AT17: NA | AU17: NA | AV17: NA | AW17: NA | AX17: NA | AY17: NA | AZ17: NA | BA17: NA | BB17: NA | BC17: NA | BD17: NA | BE17: NA | BF17: NA | BG17: NA | BH17: NA | BI17: NA | BJ17: NA | BK17: NA | BL17: NA | BM17: NA | BN17: NA | BO17: NA | BP17: NA | BQ17: NA | BR17: NA | BS17: NA | BT17: NA | BU17: NA | BV17: NA | BW17: NA | BX17: NA | BY17: NA | BZ17: NA | CA17: NA | CB17: NA | CC17: NA | CD17: NA | CE17: NA | CF17: NA | CG17: E | CH17: 0.002148 | CI17: 0 | CJ17: <Null> | CK17: <Null> | CL17: <Null> | CM17: 688.26192 | CN17: 2 | CO17: <Null> | CP17: <Null> | CQ17: <Null> | CR17: =IF(COUNTIF(Incl!A:A,Raw!J17),1, "")
A18: 15 | B18: 1 | C18: 577.41561 | D18: 15 | E18: 3 | F18: 44 | G18: 98 | H18: 98 | I18: 98 | J18: 98 | K18: Alley | L18: Palmito Dr | M18: Capuchino Dr | N18: NA | O18: NA | P18: NA | Q18: NA | R18: NA | S18: NA | T18: 0 | U18: NA | V18: NA | W18: NA | X18: NA | Y18: 0 | Z18: 0 | AA18: 0 | AB18: 0 | AC18: 0 | AD18: 0 | AE18: 0 | AF18: 0 | AG18: 0 | AH18: 0 | AI18: 0 | AJ18: 0 | AK18: 0 | AL18: 0 | AM18: NA | AN18: NA | AO18: NA | AP18: NA | AQ18: NA | AR18: NA | AS18: NA | AT18: NA | AU18: NA | AV18: NA | AW18: NA | AX18: NA | AY18: NA | AZ18: NA | BA18: NA | BB18: NA | BC18: NA | BD18: NA | BE18: NA | BF18: NA | BG18: NA | BH18: NA | BI18: NA | BJ18: NA | BK18: NA | BL18: NA | BM18: NA | BN18: NA | BO18: NA | BP18: NA | BQ18: NA | BR18: NA | BS18: NA | BT18: NA | BU18: NA | BV18: NA | BW18: NA | BX18: NA | BY18: NA | BZ18: NA | CA18: NA | CB18: NA | CC18: NA | CD18: NA | CE18: NA | CF18: NA | CG18: W | CH18: 0.00179 | CI18: 0 | CJ18: <Null> | CK18: <Null> | CL18: <Null> | CM18: 577.41567 | CN18: 2 | CO18: <Null> | CP18: <Null> | CQ18: <Null> | CR18: =IF(COUNTIF(Incl!A:A,Raw!J18),1, "")
A19: 16 | B19: 1 | C19: 564.70664 | D19: 16 | E19: 2 | F19: 45 | G19: 103 | H19: 103 | I19: 103 | J19: 103 | K19: El Camino Real | L19: Park Blvd | M19: Capuchino Dr | N19: 1 | O19: 14 | P19: NA | Q19: NA | R19: NA | S19: NA | T19: 15 | U19: 7 | V19: 8 | W19: 7 | X19: NA | Y19: 47 | Z19: 54 | AA19: 47 | AB19: 0 | AC19: 0 | AD19: 7 | AE19: 7 | AF19: 12 | AG19: NA | AH19: 47 | AI19: 47 | AJ19: 81 | AK19: 0 | AL19: 1 | AM19: 7 | AN19: 6 | AO19: 7 | AP19: 6 | AQ19: 8 | AR19: 6 | AS19: 7 | AT19: 6 | AU19: 7 | AV19: 11 | AW19: 33 | AX19: 3 | AY19: 0 | AZ19: 0 | BA19: 0 | BB19: 0 | BC19: 1 | BD19: 1 | BE19: 2 | BF19: 0 | BG19: 40 | BH19: 2.7 | BI19: 2.0 - 3.0 | BJ19: 7 | BK19: 14 | BL19: 10 | BM19: 6 | BN19: 7 | BO19: 8 | BP19: 9 | BQ19: 10 | BR19: 12 | BS19: 12 | BT19: 48 | BU19: 9 | BV19: 6 | BW19: 0 | BX19: 1 | BY19: 1 | BZ19: 0 | CA19: 0 | CB19: 0 | CC19: 0 | CD19: 65 | CE19: 4.4 | CF19: 4.0 - 5.0 | CG19: W | CH19: 0.001717 | CI19: 1 | CJ19: 1 | CK19: 1 | CL19: <Null> | CM19: 564.70692 | CN19: 1 | CO19: 1 | CP19: <Null> | CQ19: <Null> | CR19: =IF(COUNTIF(Incl!A:A,Raw!J19),1, "")
A20: 17 | B20: 1 | C20: 235.88177 | D20: 17 | E20: 1 | F20: 46 | G20: 105 | H20: 105 | I20: 105 | J20: 105 | K20: El Camino Real | L20: Santa Helena Ave | M20: Santa Maria Ave | N20: NA | O20: 9 | P20: NA | Q20: NA | R20: NA | S20: NA | T20: 9 | U20: 1 | V20: 6 | W20: 2 | X20: NA | Y20: 11 | Z20: 64 | AA20: 21 | AB20: 0 | AC20: 0 | AD20: 3 | AE20: 1 | AF20: 5 | AG20: NA | AH20: 32 | AI20: 11 | AJ20: 53 | AK20: 0 | AL20: 0 | AM20: 1 | AN20: 2 | AO20: 2 | AP20: 3 | AQ20: 6 | AR20: 1 | AS20: 1 | AT20: 1 | AU20: 2 | AV20: 0 | AW20: 10 | AX20: 0 | AY20: 0 | AZ20: 1 | BA20: 1 | BB20: 0 | BC20: 0 | BD20: 0 | BE20: 0 | BF20: 0 | BG20: 12 | BH20: 1.3 | BI20: 1.0 - 2.0 | BJ20: 3 | BK20: 1 | BL20: 0 | BM20: 1 | BN20: 1 | BO20: 2 | BP20: 1 | BQ20: 1 | BR20: 5 | BS20: 2 | BT20: 8 | BU20: 1 | BV20: 1 | BW20: 1 | BX20: 0 | BY20: 0 | BZ20: 0 | CA20: 0 | CB20: 0 | CC20: 0 | CD20: 11 | CE20: 1.2 | CF20: 1.0 - 2.0 | CG20: E | CH20: 0.000714 | CI20: 0 | CJ20: <Null> | CK20: <Null> | CL20: <Null> | CM20: 235.88161 | CN20: 1 | CO20: 1 | CP20: <Null> | CQ20: <Null> | CR20: =IF(COUNTIF(Incl!A:A,Raw!J20),1, "")
A21: 18 | B21: 1 | C21: 237.92852 | D21: 18 | E21: 1 | F21: 47 | G21: 106 | H21: 106 | I21: 106 | J21: 106 | K21: El Camino Real | L21: San Juan Ave | M21: Santa Helena Ave | N21: NA | O21: 9 | P21: NA | Q21: NA | R21: NA | S21: NA | T21: 9 | U21: 7 | V21: 3 | W21: 3 | X21: NA | Y21: 74 | Z21: 32 | AA21: 32 | AB21: 0 | AC21: 0 | AD21: 2 | AE21: 4 | AF21: 7 | AG21: NA | AH21: 21 | AI21: 43 | AJ21: 74 | AK21: 0 | AL21: 0 | AM21: 7 | AN21: 7 | AO21: 4 | AP21: 3 | AQ21: 3 | AR21: 1 | AS21: 2 | AT21: 6 | AU21: 3 | AV21: 2 | AW21: 20 | AX21: 4 | AY21: 2 | AZ21: 1 | BA21: 0 | BB21: 0 | BC21: 0 | BD21: 0 | BE21: 0 | BF21: 0 | BG21: 27 | BH21: 2.9 | BI21: 2.0 - 3.0 | BJ21: 2 | BK21: 2 | BL21: 3 | BM21: 4 | BN21: 4 | BO21: 8 | BP21: 5 | BQ21: 7 | BR21: 7 | BS21: 0 | BT21: 16 | BU21: 5 | BV21: 2 | BW21: 1 | BX21: 0 | BY21: 1 | BZ21: 0 | CA21: 0 | CB21: 0 | CC21: 0 | CD21: 25 | CE21: 2.7 | CF21: 2.0 - 3.0 | CG21: E | CH21: 0.000723 | CI21: 0 | CJ21: <Null> | CK21: <Null> | CL21: <Null> | CM21: 237.92854 | CN21: 1 | CO21: 1 | CP21: <Null> | CQ21: <Null> | CR21: =IF(COUNTIF(Incl!A:A,Raw!J21),1, "")
A22: 19 | B22: 1 | C22: 51.271282 | D22: 19 | E22: 1 | F22: 48 | G22: 159 | H22: 159 | I22: 159 | J22: 159 | K22: Capuchino Dr | L22: Alley | M22: Palmito Dr | N22: NA | O22: NA | P22: 4 | Q22: NA | R22: NA | S22: NA | T22: 4 | U22: 2 | V22: 3 | W22: NA | X22: NA | Y22: 45 | Z22: 68 | AA22: 0 | AB22: 0 | AC22: 0 | AD22: 2 | AE22: 2 | AF22: 1 | AG22: NA | AH22: 45 | AI22: 45 | AJ22: 23 | AK22: 0 | AL22: 0 | AM22: 2 | AN22: 3 | AO22: 2 | AP22: 2 | AQ22: 3 | AR22: 2 | AS22: 2 | AT22: 0 | AU22: 0 | AV22: 0 | AW22: 1 | AX22: 0 | AY22: 1 | AZ22: 0 | BA22: 1 | BB22: 0 | BC22: 1 | BD22: 0 | BE22: 0 | BF22: 0 | BG22: 4 | BH22: 0.9 | BI22: 0.0 - 1.0 | BJ22: 2 | BK22: 2 | BL22: 1 | BM22: 2 | BN22: 2 | BO22: 3 | BP22: 2 | BQ22: 2 | BR22: 1 | BS22: 1 | BT22: 6 | BU22: 1 | BV22: 0 | BW22: 0 | BX22: 0 | BY22: 0 | BZ22: 0 | CA22: 0 | CB22: 0 | CC22: 1 | CD22: 8 | CE22: 1.8 | CF22: 1.0 - 2.0 | CG22: N | CH22: 0.000166 | CI22: 0 | CJ22: <Null> | CK22: <Null> | CL22: <Null> | CM22: 51.271182 | CN22: 1 | CO22: <Null> | CP22: <Null> | CQ22: <Null> | CR22: =IF(COUNTIF(Incl!A:A,Raw!J22),1, "")
A23: 20 | B23: 1 | C23: 51.362904 | D23: 20 | E23: 1 | F23: 49 | G23: 160 | H23: 160 | I23: 160 | J23: 160 | K23: Capuchino Dr | L23: El Camino Real | M23: Alley | N23: NA | O23: NA | P23: 2 | Q23: NA | R23: NA | S23: NA | T23: 2 | U23: 2 | V23: 2 | W23: 2 | X23: NA | Y23: 91 | Z23: 91 | AA23: 91 | AB23: 0 | AC23: 3 | AD23: 2 | AE23: 2 | AF23: 0 | AG23: NA | AH23: 91 | AI23: 91 | AJ23: 0 | AK23: 0 | AL23: 2 | AM23: 2 | AN23: 2 | AO23: 2 | AP23: 2 | AQ23: 2 | AR23: 2 | AS23: 2 | AT23: 2 | AU23: 2 | AV23: 2 | AW23: 0 | AX23: 0 | AY23: 0 | AZ23: 0 | BA23: 0 | BB23: 0 | BC23: 0 | BD23: 0 | BE23: 0 | BF23: 2 | BG23: 2 | BH23: 0.9 | BI23: 0.0 - 1.0 | BJ23: 2 | BK23: 2 | BL23: 2 | BM23: 2 | BN23: 2 | BO23: 2 | BP23: 1 | BQ23: 1 | BR23: 0 | BS23: 0 | BT23: 1 | BU23: 0 | BV23: 0 | BW23: 0 | BX23: 1 | BY23: 0 | BZ23: 0 | CA23: 1 | CB23: 0 | CC23: 0 | CD23: 3 | CE23: 1.4 | CF23: 1.0 - 2.0 | CG23: N | CH23: 0.000165 | CI23: 5 | CJ23: <Null> | CK23: <Null> | CL23: <Null> | CM23: 51.36282 | CN23: 1 | CO23: 0 | CP23: <Null> | CQ23: <Null> | CR23: =IF(COUNTIF(Incl!A:A,Raw!J23),1, "")
A24: 21 | B24: 1 | C24: 179.87375 | D24: 21 | E24: 2 | F24: 50 | G24: 161 | H24: 161 | I24: 161 | J24: 161 | K24: Capuchino Dr | L24: Palmito Dr | M24: El Camino Real | N24: NA | O24: NA | P24: 6 | Q24: NA | R24: NA | S24: NA | T24: 6 | U24: 1 | V24: 1 | W24: NA | X24: NA | Y24: 16 | Z24: 16 | AA24: 0 | AB24: 0 | AC24: 0 | AD24: 6 | AE24: 6 | AF24: 0 | AG24: NA | AH24: 94 | AI24: 94 | AJ24: 0 | AK24: 0 | AL24: 2 | AM24: 1 | AN24: 0 | AO24: 3 | AP24: 1 | AQ24: 1 | AR24: 3 | AS24: 1 | AT24: 0 | AU24: 0 | AV24: 0 | AW24: 5 | AX24: 1 | AY24: 1 | AZ24: 0 | BA24: 0 | BB24: 0 | BC24: 0 | BD24: 0 | BE24: 0 | BF24: 0 | BG24: 7 | BH24: 1.1 | BI24: 1.0 - 2.0 | BJ24: 6 | BK24: 5 | BL24: 3 | BM24: 6 | BN24: 6 | BO24: 4 | BP24: 4 | BQ24: 1 | BR24: 0 | BS24: 0 | BT24: 8 | BU24: 3 | BV24: 2 | BW24: 0 | BX24: 0 | BY24: 0 | BZ24: 1 | CA24: 1 | CB24: 0 | CC24: 0 | CD24: 15 | CE24: 2.3 | CF24: 2.0 - 3.0 | CG24: S | CH24: 0.000573 | CI24: 2 | CJ24: <Null> | CK24: <Null> | CL24: <Null> | CM24: 179.87379 | CN24: 1 | CO24: 0 | CP24: <Null> | CQ24: <Null> | CR24: =IF(COUNTIF(Incl!A:A,Raw!J24),1, "")
A25: 22 | B25: 1 | C25: 232.03311 | D25: 22 | E25: 1 | F25: 51 | G25: 71 | H25: 71 | I25: 71 | J25: 71 | K25: Broadway | L25: Capuchino Dr | M25: Millwood Dr | N25: NA | O25: NA | P25: 8 | Q25: NA | R25: NA | S25: NA | T25: 8 | U25: 8 | V25: 8 | W25: 8 | X25: 5 | Y25: 99 | Z25: 99 | AA25: 99 | AB25: 62 | AC25: 3 | AD25: 8 | AE25: 8 | AF25: 8 | AG25: 3 | AH25: 99 | AI25: 99 | AJ25: 99 | AK25: 37 | AL25: 3 | AM25: NA | AN25: NA | AO25: NA | AP25: NA | AQ25: NA | AR25: NA | AS25: NA | AT25: NA | AU25: NA | AV25: NA | AW25: NA | AX25: NA | AY25: NA | AZ25: NA | BA25: NA | BB25: NA | BC25: NA | BD25: NA | BE25: NA | BF25: NA | BG25: NA | BH25: NA | BI25: NA | BJ25: NA | BK25: NA | BL25: NA | BM25: NA | BN25: NA | BO25: NA | BP25: NA | BQ25: NA | BR25: NA | BS25: NA | BT25: NA | BU25: NA | BV25: NA | BW25: NA | BX25: NA | BY25: NA | BZ25: NA | CA25: NA | CB25: NA | CC25: NA | CD25: NA | CE25: NA | CF25: NA | CG25: W | CH25: 0.000694 | CI25: 6 | CJ25: <Null> | CK25: <Null> | CL25: <Null> | CM25: 232.03317 | CN25: 2 | CO25: <Null> | CP25: <Null> | CQ25: <Null> | CR25: =IF(COUNTIF(Incl!A:A,Raw!J25),1, "")
A26: 23 | B26: 1 | C26: 214.87336 | D26: 23 | E26: 1 | F26: 52 | G26: 72 | H26: 72 | I26: 72 | J26: 72 | K26: Broadway | L26: Millwood Dr | M26: Capuchino Dr | N26: NA | O26: NA | P26: 9 | Q26: NA | R26: NA | S26: NA | T26: 9 | U26: 8 | V26: 8 | W26: 8 | X26: 4 | Y26: 88 | Z26: 88 | AA26: 88 | AB26: 44 | AC26: 3 | AD26: 7 | AE26: 7 | AF26: 6 | AG26: 3 | AH26: 77 | AI26: 77 | AJ26: 66 | AK26: 33 | AL26: 2 | AM26: NA | AN26: NA | AO26: NA | AP26: NA | AQ26: NA | AR26: NA | AS26: NA | AT26: NA | AU26: NA | AV26: NA | AW26: NA | AX26: NA | AY26: NA | AZ26: NA | BA26: NA | BB26: NA | BC26: NA | BD26: NA | BE26: NA | BF26: NA | BG26: NA | BH26: NA | BI26: NA | BJ26: NA | BK26: NA | BL26: NA | BM26: NA | BN26: NA | BO26: NA | BP26: NA | BQ26: NA | BR26: NA | BS26: NA | BT26: NA | BU26: NA | BV26: NA | BW26: NA | BX26: NA | BY26: NA | BZ26: NA | CA26: NA | CB26: NA | CC26: NA | CD26: NA | CE26: NA | CF26: NA | CG26: E | CH26: 0.000654 | CI26: 5 | CJ26: <Null> | CK26: <Null> | CL26: <Null> | CM26: 214.87346 | CN26: 2 | CO26: <Null> | CP26: <Null> | CQ26: <Null> | CR26: =IF(COUNTIF(Incl!A:A,Raw!J26),1, "")
A27: 24 | B27: 1 | C27: 232.81606 | D27: 24 | E27: 1 | F27: 53 | G27: 107 | H27: 107 | I27: 107 | J27: 107 | K27: El Camino Real | L27: Capuchino Dr | M27: Millwood Dr | N27: 7 | O27: NA | P27: NA | Q27: NA | R27: NA | S27: NA | T27: 7 | U27: NA | V27: NA | W27: NA | X27: NA | Y27: 0 | Z27: 0 | AA27: 0 | AB27: 0 | AC27: 0 | AD27: 0 | AE27: 2 | AF27: 0 | AG27: NA | AH27: 0 | AI27: 28 | AJ27: 0 | AK27: 0 | AL27: 0 | AM27: 0 | AN27: 0 | AO27: 1 | AP27: 0 | AQ27: 0 | AR27: 0 | AS27: 0 | AT27: 0 | AU27: 0 | AV27: 0 | AW27: 1 | AX27: 0 | AY27: 0 | AZ27: 0 | BA27: 0 | BB27: 0 | BC27: 0 | BD27: 0 | BE27: 0 | BF27: 0 | BG27: 1 | BH27: 0.1 | BI27: 0.0 - 1.0 | BJ27: 0 | BK27: 0 | BL27: 0 | BM27: 0 | BN27: 2 | BO27: 0 | BP27: 2 | BQ27: 0 | BR27: 0 | BS27: 0 | BT27: 4 | BU27: 0 | BV27: 0 | BW27: 0 | BX27: 0 | BY27: 0 | BZ27: 0 | CA27: 0 | CB27: 0 | CC27: 0 | CD27: 4 | CE27: 0.6 | CF27: 0.0 - 1.0 | CG27: W | CH27: 0.000707 | CI27: 0 | CJ27: 1 | CK27: 1 | CL27: <Null> | CM27: 232.8159 | CN27: 1 | CO27: 1 | CP27: <Null> | CQ27: <Null> | CR27: =IF(COUNTIF(Incl!A:A,Raw!J27),1, "")
A28: 25 | B28: 1 | C28: 140.85674 | D28: 25 | E28: 1 | F28: 54 | G28: 162 | H28: 162 | I28: 162 | J28: 162 | K28: Milwood Dr | L28: El Camino Real | M28: Broadway | N28: NA | O28: NA | P28: 2 | Q28: NA | R28: NA | S28: NA | T28: 2 | U28: 2 | V28: NA | W28: NA | X28: NA | Y28: 114 | Z28: 0 | AA28: 0 | AB28: 0 | AC28: 1 | AD28: 0 | AE28: 1 | AF28: 0 | AG28: NA | AH28: 0 | AI28: 57 | AJ28: 0 | AK28: 0 | AL28: 0 | AM28: 2 | AN28: 2 | AO28: 2 | AP28: 2 | AQ28: 0 | AR28: 0 | AS28: 0 | AT28: 0 | AU28: 0 | AV28: 0 | AW28: 0 | AX28: 0 | AY28: 0 | AZ28: 2 | BA28: 0 | BB28: 0 | BC28: 0 | BD28: 0 | BE28: 0 | BF28: 0 | BG28: 2 | BH28: 1.1 | BI28: 1.0 - 2.0 | BJ28: 0 | BK28: 0 | BL28: 0 | BM28: 0 | BN28: 1 | BO28: 2 | BP28: 1 | BQ28: 0 | BR28: 0 | BS28: 0 | BT28: 2 | BU28: 1 | BV28: 0 | BW28: 0 | BX28: 0 | BY28: 0 | BZ28: 0 | CA28: 0 | CB28: 0 | CC28: 0 | CD28: 3 | CE28: 1.7 | CF28: 1.0 - 2.0 | CG28: N | CH28: 0.000462 | CI28: 1 | CJ28: <Null> | CK28: <Null> | CL28: <Null> | CM28: 140.85695 | CN28: 1 | CO28: 0 | CP28: <Null> | CQ28: <Null> | CR28: =IF(COUNTIF(Incl!A:A,Raw!J28),1, "")
A29: 26 | B29: 1 | C29: 159.55663 | D29: 26 | E29: 1 | F29: 55 | G29: 163 | H29: 163 | I29: 163 | J29: 163 | K29: Milwood Dr | L29: Broadway | M29: El Camino Real | N29: NA | O29: 6 | P29: NA | Q29: NA | R29: NA | S29: NA | T29: 6 | U29: 5 | V29: 1 | W29: 6 | X29: NA | Y29: 83 | Z29: 17 | AA29: 100 | AB29: 0 | AC29: 2 | AD29: 5 | AE29: 5 | AF29: 4 | AG29: NA | AH29: 83 | AI29: 83 | AJ29: 67 | AK29: 0 | AL29: 2 | AM29: 5 | AN29: 1 | AO29: 1 | AP29: 1 | AQ29: 1 | AR29: 3 | AS29: 5 | AT29: 5 | AU29: 6 | AV29: 1 | AW29: 10 | AX29: 6 | AY29: 1 | AZ29: 1 | BA29: 0 | BB29: 0 | BC29: 0 | BD29: 0 | BE29: 0 | BF29: 0 | BG29: 18 | BH29: 3 | BI29: 2.0 - 3.0 | BJ29: 5 | BK29: 6 | BL29: 6 | BM29: 3 | BN29: 5 | BO29: 4 | BP29: 6 | BQ29: 6 | BR29: 4 | BS29: 2 | BT29: 6 | BU29: 3 | BV29: 2 | BW29: 1 | BX29: 1 | BY29: 0 | BZ29: 0 | CA29: 0 | CB29: 0 | CC29: 2 | CD29: 15 | CE29: 2.5 | CF29: 2.0 - 3.0 | CG29: S | CH29: 0.000516 | CI29: 4 | CJ29: <Null> | CK29: <Null> | CL29: <Null> | CM29: 159.5566 | CN29: 1 | CO29: 0 | CP29: <Null> | CQ29: <Null> | CR29: =IF(COUNTIF(Incl!A:A,Raw!J29),1, "")
A30: 27 | B30: 1 | C30: 1292.5164 | D30: 27 | E30: 1 | F30: 56 | G30: 108 | H30: 108 | I30: 108 | J30: 108 | K30: El Camino Real | L30: Center St | M30: San Juan Ave | N30: 28 | O30: 8 | P30: NA | Q30: NA | R30: NA | S30: NA | T30: 35 | U30: 8 | V30: 18 | W30: 31 | X30: NA | Y30: 23 | Z30: 51 | AA30: 88 | AB30: 0 | AC30: 1 | AD30: 19 | AE30: 28 | AF30: 30 | AG30: NA | AH30: 54 | AI30: 79 | AJ30: 85 | AK30: 0 | AL30: 2 | AM30: 8 | AN30: 13 | AO30: 11 | AP30: 10 | AQ30: 18 | AR30: 26 | AS30: 27 | AT30: 30 | AU30: 31 | AV30: 28 | AW30: 58 | AX30: 24 | AY30: 6 | AZ30: 6 | BA30: 0 | BB30: 1 | BC30: 0 | BD30: 1 | BE30: 0 | BF30: 4 | BG30: 100 | BH30: 2.8 | BI30: 2.0 - 3.0 | BJ30: 19 | BK30: 26 | BL30: 32 | BM30: 29 | BN30: 28 | BO30: 27 | BP30: 26 | BQ30: 31 | BR30: 30 | BS30: 24 | BT30: 63 | BU30: 28 | BV30: 5 | BW30: 3 | BX30: 2 | BY30: 2 | BZ30: 0 | CA30: 2 | CB30: 2 | CC30: 7 | CD30: 114 | CE30: 3.2 | CF30: 3.0 - 4.0 | CG30: E | CH30: 0.003899 | CI30: 3 | CJ30: <Null> | CK30: <Null> | CL30: <Null> | CM30: 1292.5166 | CN30: 1 | CO30: 1 | CP30: <Null> | CQ30: <Null> | CR30: =IF(COUNTIF(Incl!A:A,Raw!J30),1, "")
A31: 28 | B31: 1 | C31: 765.64702 | D31: 28 | E31: 1 | F31: 57 | G31: 109 | H31: 109 | I31: 109 | J31: 109 | K31: El Camino Real | L31: Millwood Dr | M31: Ludeman Ln | N31: NA | O31: 26 | P31: NA | Q31: NA | R31: NA | S31: NA | T31: 26 | U31: 11 | V31: 11 | W31: 18 | X31: NA | Y31: 42 | Z31: 42 | AA31: 69 | AB31: 0 | AC31: 0 | AD31: 23 | AE31: 15 | AF31: 17 | AG31: NA | AH31: 89 | AI31: 58 | AJ31: 66 | AK31: 0 | AL31: 1 | AM31: 11 | AN31: 8 | AO31: 10 | AP31: 10 | AQ31: 11 | AR31: 18 | AS31: 12 | AT31: 12 | AU31: 18 | AV31: 19 | AW31: 26 | AX31: 8 | AY31: 5 | AZ31: 5 | BA31: 4 | BB31: 2 | BC31: 0 | BD31: 0 | BE31: 0 | BF31: 2 | BG31: 52 | BH31: 2 | BI31: 1.0 - 2.0 | BJ31: 23 | BK31: 21 | BL31: 22 | BM31: 15 | BN31: 15 | BO31: 10 | BP31: 13 | BQ31: 15 | BR31: 17 | BS31: 19 | BT31: 54 | BU31: 9 | BV31: 4 | BW31: 2 | BX31: 2 | BY31: 0 | BZ31: 3 | CA31: 1 | CB31: 1 | CC31: 3 | CD31: 79 | CE31: 3.1 | CF31: 3.0 - 4.0 | CG31: W | CH31: 0.00232 | CI31: 1 | CJ31: 1 | CK31: 1 | CL31: <Null> | CM31: 765.6471 | CN31: 1 | CO31: 1 | CP31: <Null> | CQ31: <Null> | CR31: =IF(COUNTIF(Incl!A:A,Raw!J31),1, "")
A32: 29 | B32: 1 | C32: 173.35116 | D32: 29 | E32: 1 | F32: 58 | G32: 73 | H32: 73 | I32: 73 | J32: 73 | K32: Broadway | L32: Millwood Dr | M32: Paramount Dr | N32: NA | O32: NA | P32: 8 | Q32: NA | R32: NA | S32: NA | T32: 8 | U32: 9 | V32: 4 | W32: 4 | X32: 4 | Y32: 117 | Z32: 52 | AA32: 52 | AB32: 52 | AC32: 1 | AD32: 5 | AE32: 5 | AF32: 3 | AG32: 4 | AH32: 65 | AI32: 65 | AJ32: 39 | AK32: 52 | AL32: 0 | AM32: NA | AN32: NA | AO32: NA | AP32: NA | AQ32: NA | AR32: NA | AS32: NA | AT32: NA | AU32: NA | AV32: NA | AW32: NA | AX32: NA | AY32: NA | AZ32: NA | BA32: NA | BB32: NA | BC32: NA | BD32: NA | BE32: NA | BF32: NA | BG32: NA | BH32: NA | BI32: NA | BJ32: NA | BK32: NA | BL32: NA | BM32: NA | BN32: NA | BO32: NA | BP32: NA | BQ32: NA | BR32: NA | BS32: NA | BT32: NA | BU32: NA | BV32: NA | BW32: NA | BX32: NA | BY32: NA | BZ32: NA | CA32: NA | CB32: NA | CC32: NA | CD32: NA | CE32: NA | CF32: NA | CG32: W | CH32: 0.00052 | CI32: 1 | CJ32: <Null> | CK32: <Null> | CL32: <Null> | CM32: 173.35113 | CN32: 2 | CO32: <Null> | CP32: <Null> | CQ32: <Null> | CR32: =IF(COUNTIF(Incl!A:A,Raw!J32),1, "")
A33: 30 | B33: 1 | C33: 545.14276 | D33: 30 | E33: 1 | F33: 59 | G33: 75 | H33: 75 | I33: 75 | J33: 75 | K33: Broadway | L33: Paramount Dr | M33: Ludeman Ln | N33: NA | O33: NA | P33: 18 | Q33: NA | R33: NA | S33: NA | T33: 18 | U33: 16 | V33: 16 | W33: 14 | X33: 16 | Y33: 90 | Z33: 90 | AA33: 79 | AB33: 90 | AC33: 4 | AD33: 18 | AE33: 16 | AF33: 18 | AG33: 17 | AH33: 101 | AI33: 90 | AJ33: 101 | AK33: 96 | AL33: 4 | AM33: NA | AN33: NA | AO33: NA | AP33: NA | AQ33: NA | AR33: NA | AS33: NA | AT33: NA | AU33: NA | AV33: NA | AW33: NA | AX33: NA | AY33: NA | AZ33: NA | BA33: NA | BB33: NA | BC33: NA | BD33: NA | BE33: NA | BF33: NA | BG33: NA | BH33: NA | BI33: NA | BJ33: NA | BK33: NA | BL33: NA | BM33: NA | BN33: NA | BO33: NA | BP33: NA | BQ33: NA | BR33: NA | BS33: NA | BT33: NA | BU33: NA | BV33: NA | BW33: NA | BX33: NA | BY33: NA | BZ33: NA | CA33: NA | CB33: NA | CC33: NA | CD33: NA | CE33: NA | CF33: NA | CG33: W | CH33: 0.001647 | CI33: 8 | CJ33: <Null> | CK33: <Null> | CL33: <Null> | CM33: 545.14294 | CN33: 2 | CO33: <Null> | CP33: <Null> | CQ33: <Null> | CR33: =IF(COUNTIF(Incl!A:A,Raw!J33),1, "")
A34: 31 | B34: 1 | C34: 750.15014 | D34: 31 | E34: 1 | F34: 60 | G34: 74 | H34: 74 | I34: 74 | J34: 74 | K34: Broadway | L34: Ludeman Ln | M34: Millwood Dr | N34: NA | O34: NA | P34: 28 | Q34: NA | R34: 1 | S34: NA | T34: 29 | U34: 27 | V34: 27 | W34: 25 | X34: 27 | Y34: 95 | Z34: 95 | AA34: 88 | AB34: 95 | AC34: 4 | AD34: 28 | AE34: 24 | AF34: 20 | AG34: 23 | AH34: 98 | AI34: 84 | AJ34: 70 | AK34: 81 | AL34: 3 | AM34: NA | AN34: NA | AO34: NA | AP34: NA | AQ34: NA | AR34: NA | AS34: NA | AT34: NA | AU34: NA | AV34: NA | AW34: NA | AX34: NA | AY34: NA | AZ34: NA | BA34: NA | BB34: NA | BC34: NA | BD34: NA | BE34: NA | BF34: NA | BG34: NA | BH34: NA | BI34: NA | BJ34: NA | BK34: NA | BL34: NA | BM34: NA | BN34: NA | BO34: NA | BP34: NA | BQ34: NA | BR34: NA | BS34: NA | BT34: NA | BU34: NA | BV34: NA | BW34: NA | BX34: NA | BY34: NA | BZ34: NA | CA34: NA | CB34: NA | CC34: NA | CD34: NA | CE34: NA | CF34: NA | CG34: E | CH34: 0.002279 | CI34: 7 | CJ34: <Null> | CK34: <Null> | CL34: <Null> | CM34: 750.15007 | CN34: 2 | CO34: <Null> | CP34: <Null> | CQ34: <Null> | CR34: =IF(COUNTIF(Incl!A:A,Raw!J34),1, "")
A35: 32 | B35: 1 | C35: 116.01234 | D35: 32 | E35: 1 | F35: 61 | G35: 164 | H35: 164 | I35: 164 | J35: 164 | K35: Ludeman Ln | L35: El Camino Real | M35: Broadway | N35: 6 | O35: NA | P35: NA | Q35: NA | R35: NA | S35: NA | T35: 6 | U35: 2 | V35: NA | W35: NA | X35: NA | Y35: 31 | Z35: 0 | AA35: 0 | AB35: 0 | AC35: 0 | AD35: 6 | AE35: 1 | AF35: 1 | AG35: NA | AH35: 94 | AI35: 16 | AJ35: 16 | AK35: 0 | AL35: 1 | AM35: 2 | AN35: 1 | AO35: 1 | AP35: 1 | AQ35: 0 | AR35: 0 | AS35: 0 | AT35: 0 | AU35: 0 | AV35: 0 | AW35: 3 | AX35: 1 | AY35: 0 | AZ35: 0 | BA35: 0 | BB35: 0 | BC35: 0 | BD35: 0 | BE35: 0 | BF35: 0 | BG35: 4 | BH35: 0.6 | BI35: 0.0 - 1.0 | BJ35: 6 | BK35: 6 | BL35: 6 | BM35: 1 | BN35: 1 | BO35: 1 | BP35: 1 | BQ35: 1 | BR35: 1 | BS35: 0 | BT35: 12 | BU35: 2 | BV35: 0 | BW35: 2 | BX35: 0 | BY35: 0 | BZ35: 0 | CA35: 0 | CB35: 0 | CC35: 0 | CD35: 16 | CE35: 2.5 | CF35: 2.0 - 3.0 | CG35: N | CH35: 0.000377 | CI35: 1 | CJ35: <Null> | CK35: <Null> | CL35: <Null> | CM35: 116.01234 | CN35: 1 | CO35: 0 | CP35: <Null> | CQ35: <Null> | CR35: =IF(COUNTIF(Incl!A:A,Raw!J35),1, "")
A36: 33 | B36: 1 | C36: 161.5132 | D36: 33 | E36: 1 | F36: 62 | G36: 165 | H36: 165 | I36: 165 | J36: 165 | K36: Ludeman Ln | L36: Broadway | M36: El Camino Real | N36: NA | O36: NA | P36: 7 | Q36: NA | R36: NA | S36: NA | T36: 7 | U36: 7 | V36: 5 | W36: 6 | X36: NA | Y36: 95 | Z36: 68 | AA36: 82 | AB36: 0 | AC36: 2 | AD36: 7 | AE36: 5 | AF36: 7 | AG36: NA | AH36: 95 | AI36: 68 | AJ36: 95 | AK36: 0 | AL36: 2 | AM36: 7 | AN36: 6 | AO36: 6 | AP36: 6 | AQ36: 5 | AR36: 5 | AS36: 6 | AT36: 5 | AU36: 6 | AV36: 6 | AW36: 5 | AX36: 4 | AY36: 1 | AZ36: 0 | BA36: 1 | BB36: 0 | BC36: 1 | BD36: 0 | BE36: 0 | BF36: 3 | BG36: 15 | BH36: 2 | BI36: 1.0 - 2.0 | BJ36: 7 | BK36: 7 | BL36: 7 | BM36: 5 | BN36: 5 | BO36: 5 | BP36: 6 | BQ36: 6 | BR36: 7 | BS36: 7 | BT36: 6 | BU36: 1 | BV36: 1 | BW36: 1 | BX36: 0 | BY36: 0 | BZ36: 1 | CA36: 0 | CB36: NA | CC36: 4 | CD36: 14 | CE36: 1.9 | CF36: 1.0 - 2.0 | CG36: S | CH36: 0.000442 | CI36: 4 | CJ36: 2 | CK36: <Null> | CL36: <Null> | CM36: 136.11984 | CN36: 1 | CO36: 0 | CP36: <Null> | CQ36: <Null> | CR36: =IF(COUNTIF(Incl!A:A,Raw!J36),1, "")
A37: 34 | B37: 1 | C37: 829.07106 | D37: 34 | E37: 1 | F37: 63 | G37: 76 | H37: 76 | I37: 76 | J37: 76 | K37: Broadway | L37: Ludeman Ln | M37: Parking Lot | N37: NA | O37: NA | P37: 15 | Q37: 2 | R37: 8 | S37: NA | T37: 25 | U37: 13 | V37: 15 | W37: 10 | X37: NA | Y37: 51 | Z37: 59 | AA37: 39 | AB37: 0 | AC37: 0 | AD37: 12 | AE37: 9 | AF37: 6 | AG37: NA | AH37: 47 | AI37: 35 | AJ37: 24 | AK37: 0 | AL37: 0 | AM37: 13 | AN37: 19 | AO37: 16 | AP37: 15 | AQ37: 15 | AR37: 17 | AS37: 21 | AT37: 21 | AU37: 10 | AV37: 9 | AW37: 54 | AX37: 19 | AY37: 0 | AZ37: 3 | BA37: 3 | BB37: 5 | BC37: 1 | BD37: 0 | BE37: 0 | BF37: 0 | BG37: 85 | BH37: 3.3 | BI37: 3.0 - 4.0 | BJ37: 12 | BK37: 12 | BL37: 13 | BM37: 9 | BN37: 9 | BO37: 7 | BP37: 6 | BQ37: 6 | BR37: 6 | BS37: 13 | BT37: 12 | BU37: 6 | BV37: 3 | BW37: 0 | BX37: 1 | BY37: 0 | BZ37: 0 | CA37: 2 | CB37: 1 | CC37: 3 | CD37: 28 | CE37: 1.1 | CF37: 1.0 - 2.0 | CG37: W | CH37: 0.002403 | CI37: 0 | CJ37: 4 | CK37: <Null> | CL37: <Null> | CM37: 791.03344 | CN37: 1 | CO37: <Null> | CP37: <Null> | CQ37: <Null> | CR37: =IF(COUNTIF(Incl!A:A,Raw!J37),1, "")
A38: 35 | B38: 1 | C38: 204.18013 | D38: 35 | E38: 1 | F38: 64 | G38: 77 | H38: 77 | I38: 77 | J38: 77 | K38: Broadway | L38: Center St | M38: Ludeman Ln | N38: NA | O38: NA | P38: 9 | Q38: NA | R38: NA | S38: NA | T38: 9 | U38: 9 | V38: 7 | W38: 4 | X38: NA | Y38: 96 | Z38: 74 | AA38: 43 | AB38: 0 | AC38: 1 | AD38: 8 | AE38: 8 | AF38: 4 | AG38: NA | AH38: 85 | AI38: 85 | AJ38: 43 | AK38: 0 | AL38: 2 | AM38: 9 | AN38: 9 | AO38: 9 | AP38: 8 | AQ38: 7 | AR38: 6 | AS38: 7 | AT38: 7 | AU38: 4 | AV38: 6 | AW38: 7 | AX38: 2 | AY38: 3 | AZ38: 1 | BA38: 2 | BB38: 0 | BC38: 0 | BD38: 0 | BE38: 2 | BF38: 2 | BG38: 19 | BH38: 2 | BI38: 1.0 - 2.0 | BJ38: 8 | BK38: 8 | BL38: 8 | BM38: 8 | BN38: 8 | BO38: 7 | BP38: 7 | BQ38: 4 | BR38: 4 | BS38: 4 | BT38: 4 | BU38: 1 | BV38: 0 | BW38: 1 | BX38: 3 | BY38: 0 | BZ38: 3 | CA38: 0 | CB38: 0 | CC38: 2 | CD38: 14 | CE38: 1.5 | CF38: 1.0 - 2.0 | CG38: E | CH38: 0.000624 | CI38: 3 | CJ38: 2 | CK38: <Null> | CL38: <Null> | CM38: 204.18016 | CN38: 1 | CO38: <Null> | CP38: <Null> | CQ38: <Null> | CR38: =IF(COUNTIF(Incl!A:A,Raw!J38),1, "")
A39: 36 | B39: 1 | C39: 865.18087 | D39: 36 | E39: 1 | F39: 65 | G39: 78 | H39: 78 | I39: 78 | J39: 78 | K39: Broadway | L39: Meadow Glen Ave | M39: Center St | N39: 6 | O39: 14 | P39: 10 | Q39: NA | R39: NA | S39: NA | T39: 30 | U39: 12 | V39: 12 | W39: 6 | X39: NA | Y39: 39 | Z39: 39 | AA39: 20 | AB39: 0 | AC39: 0 | AD39: 15 | AE39: 14 | AF39: 6 | AG39: NA | AH39: 49 | AI39: 46 | AJ39: 20 | AK39: 0 | AL39: 0 | AM39: 12 | AN39: 13 | AO39: 12 | AP39: 12 | AQ39: 12 | AR39: 12 | AS39: 12 | AT39: 19 | AU39: 6 | AV39: 7 | AW39: 53 | AX39: 2 | AY39: 2 | AZ39: 1 | BA39: 0 | BB39: 0 | BC39: 2 | BD39: 2 | BE39: 0 | BF39: 2 | BG39: 64 | BH39: 2.1 | BI39: 2.0 - 3.0 | BJ39: 15 | BK39: 9 | BL39: 15 | BM39: 11 | BN39: 14 | BO39: 14 | BP39: 13 | BQ39: 11 | BR39: 6 | BS39: 8 | BT39: 27 | BU39: 11 | BV39: 2 | BW39: 0 | BX39: 2 | BY39: 3 | BZ39: 1 | CA39: 2 | CB39: 0 | CC39: 1 | CD39: 49 | CE39: 1.6 | CF39: 1.0 - 2.0 | CG39: E | CH39: 0.002644 | CI39: 0 | CJ39: 2 | CK39: <Null> | CL39: <Null> | CM39: 865.18099 | CN39: 1 | CO39: <Null> | CP39: <Null> | CQ39: <Null> | CR39: =IF(COUNTIF(Incl!A:A,Raw!J39),1, "")
A40: 37 | B40: 1 | C40: 214.5328 | D40: 37 | E40: 1 | F40: 66 | G40: 110 | H40: 110 | I40: 110 | J40: 110 | K40: El Camino Real | L40: Ludeman Ln | M40: Center St | N40: NA | O40: 11 | P40: NA | Q40: NA | R40: NA | S40: NA | T40: 11 | U40: 1 | V40: NA | W40: 3 | X40: NA | Y40: 9 | Z40: 0 | AA40: 28 | AB40: 0 | AC40: 0 | AD40: 8 | AE40: 3 | AF40: 6 | AG40: NA | AH40: 74 | AI40: 28 | AJ40: 56 | AK40: 0 | AL40: 0 | AM40: 1 | AN40: 1 | AO40: 1 | AP40: 1 | AQ40: 0 | AR40: 0 | AS40: 0 | AT40: 2 | AU40: 3 | AV40: 10 | AW40: 8 | AX40: 2 | AY40: 1 | AZ40: 1 | BA40: 0 | BB40: 0 | BC40: 0 | BD40: 0 | BE40: 0 | BF40: 0 | BG40: 12 | BH40: 1.1 | BI40: 1.0 - 2.0 | BJ40: 8 | BK40: 9 | BL40: 10 | BM40: 3 | BN40: 3 | BO40: 3 | BP40: 3 | BQ40: 3 | BR40: 6 | BS40: 6 | BT40: 11 | BU40: 6 | BV40: 2 | BW40: 0 | BX40: 0 | BY40: 0 | BZ40: 1 | CA40: 1 | CB40: 0 | CC40: 1 | CD40: 22 | CE40: 2 | CF40: 2.0 - 3.0 | CG40: W | CH40: 0.000713 | CI40: 0 | CJ40: 1 | CK40: 1 | CL40: <Null> | CM40: 234.48701 | CN40: 1 | CO40: 1 | CP40: <Null> | CQ40: <Null> | CR40: =IF(COUNTIF(Incl!A:A,Raw!J40),1, "")
A41: 38 | B41: 1 | C41: 123.4471 | D41: 38 | E41: 1 | F41: 67 | G41: 166 | H41: 166 | I41: 166 | J41: 166 | K41: Center St | L41: El Camino Real | M41: Broadway | N41: NA | O41: 3 | P41: NA | Q41: NA | R41: NA | S41: NA | T41: 3 | U41: NA | V41: NA | W41: 1 | X41: NA | Y41: 0 | Z41: 0 | AA41: 33 | AB41: 0 | AC41: 0 | AD41: 2 | AE41: 3 | AF41: 0 | AG41: NA | AH41: 67 | AI41: 100 | AJ41: 0 | AK41: 0 | AL41: 1 | AM41: 0 | AN41: 1 | AO41: 0 | AP41: 1 | AQ41: 0 | AR41: 1 | AS41: 1 | AT41: 1 | AU41: 1 | AV41: 0 | AW41: 2 | AX41: 0 | AY41: 0 | AZ41: 1 | BA41: 0 | BB41: 0 | BC41: 0 | BD41: 0 | BE41: 0 | BF41: 0 | BG41: 3 | BH41: 1 | BI41: 0.0 - 1.0 | BJ41: 2 | BK41: 1 | BL41: 2 | BM41: 3 | BN41: 3 | BO41: 3 | BP41: 2 | BQ41: 3 | BR41: 0 | BS41: 0 | BT41: 4 | BU41: 0 | BV41: 1 | BW41: 0 | BX41: 1 | BY41: 0 | BZ41: 1 | CA41: 0 | CB41: 0 | CC41: 0 | CD41: 7 | CE41: 2.3 | CF41: 2.0 - 3.0 | CG41: N | CH41: 0.000403 | CI41: 1 | CJ41: 2 | CK41: <Null> | CL41: <Null> | CM41: 123.447 | CN41: 1 | CO41: 0 | CP41: <Null> | CQ41: <Null> | CR41: =IF(COUNTIF(Incl!A:A,Raw!J41),1, "")
A42: 39 | B42: 1 | C42: 123.72527 | D42: 39 | E42: 1 | F42: 68 | G42: 167 | H42: 167 | I42: 167 | J42: 167 | K42: Center St | L42: Broadway | M42: El Camino Real | N42: NA | O42: 6 | P42: NA | Q42: NA | R42: NA | S42: NA | T42: 6 | U42: 2 | V42: 4 | W42: 2 | X42: NA | Y42: 33 | Z42: 67 | AA42: 33 | AB42: 0 | AC42: 0 | AD42: 3 | AE42: 1 | AF42: 2 | AG42: NA | AH42: 50 | AI42: 17 | AJ42: 33 | AK42: 0 | AL42: 0 | AM42: 2 | AN42: 5 | AO42: 6 | AP42: 5 | AQ42: 4 | AR42: 2 | AS42: 1 | AT42: 1 | AU42: 2 | AV42: 6 | AW42: 14 | AX42: 5 | AY42: 0 | AZ42: 0 | BA42: 0 | BB42: 0 | BC42: 0 | BD42: 0 | BE42: 0 | BF42: 1 | BG42: 20 | BH42: 3.3 | BI42: 3.0 - 4.0 | BJ42: 3 | BK42: 3 | BL42: 2 | BM42: 1 | BN42: 1 | BO42: 1 | BP42: 1 | BQ42: 1 | BR42: 2 | BS42: 2 | BT42: 3 | BU42: 2 | BV42: 2 | BW42: 1 | BX42: 0 | BY42: 0 | BZ42: 0 | CA42: 0 | CB42: 0 | CC42: 0 | CD42: 8 | CE42: 1.3 | CF42: 1.0 - 2.0 | CG42: S | CH42: 0.000405 | CI42: 0 | CJ42: 2 | CK42: <Null> | CL42: <Null> | CM42: 123.72528 | CN42: 1 | CO42: 0 | CP42: <Null> | CQ42: <Null> | CR42: =IF(COUNTIF(Incl!A:A,Raw!J42),1, "")
A43: 40 | B43: 1 | C43: 808.98971 | D43: 40 | E43: 1 | F43: 69 | G43: 111 | H43: 111 | I43: 111 | J43: 111 | K43: El Camino Real | L43: Center St | M43: Meadow Glen Ave | N43: 23 | O43: NA | P43: NA | Q43: NA | R43: NA | S43: NA | T43: 23 | U43: NA | V43: NA | W43: 1 | X43: NA | Y43: 0 | Z43: 0 | AA43: 4 | AB43: 0 | AC43: 0 | AD43: 4 | AE43: 2 | AF43: 0 | AG43: NA | AH43: 18 | AI43: 9 | AJ43: 0 | AK43: 0 | AL43: 0 | AM43: 0 | AN43: 1 | AO43: 2 | AP43: 1 | AQ43: 0 | AR43: 0 | AS43: 1 | AT43: 1 | AU43: 1 | AV43: 4 | AW43: 7 | AX43: 2 | AY43: 0 | AZ43: 0 | BA43: 0 | BB43: 0 | BC43: 0 | BD43: 0 | BE43: 0 | BF43: 0 | BG43: 9 | BH43: 0.4 | BI43: 0.0 - 1.0 | BJ43: 4 | BK43: 4 | BL43: 2 | BM43: 2 | BN43: 2 | BO43: 2 | BP43: 2 | BQ43: 2 | BR43: 0 | BS43: 1 | BT43: 6 | BU43: 0 | BV43: 0 | BW43: 0 | BX43: 0 | BY43: 0 | BZ43: 1 | CA43: 1 | CB43: 0 | CC43: 0 | CD43: 8 | CE43: 0.4 | CF43: 0.0 - 1.0 | CG43: W | CH43: 0.002512 | CI43: 0 | CJ43: 1 | CK43: 1 | CL43: <Null> | CM43: 808.98989 | CN43: 1 | CO43: 1 | CP43: <Null> | CQ43: <Null> | CR43: =IF(COUNTIF(Incl!A:A,Raw!J43),1, "")
A44: 41 | B44: 1 | C44: 799.76818 | D44: 41 | E44: 1 | F44: 70 | G44: 112 | H44: 112 | I44: 112 | J44: 112 | K44: El Camino Real | L44: Meadow Glen Ave | M44: Center St | N44: NA | O44: 26 | P44: NA | Q44: NA | R44: NA | S44: NA | T44: 26 | U44: 2 | V44: 7 | W44: 8 | X44: NA | Y44: 8 | Z44: 27 | AA44: 30 | AB44: 0 | AC44: 0 | AD44: 0 | AE44: 1 | AF44: 2 | AG44: NA | AH44: 0 | AI44: 4 | AJ44: 8 | AK44: 0 | AL44: 0 | AM44: 0 | AN44: 7 | AO44: 8 | AP44: 10 | AQ44: 7 | AR44: 2 | AS44: 0 | AT44: 0 | AU44: 8 | AV44: 8 | AW44: 13 | AX44: 17 | AY44: 1 | AZ44: 0 | BA44: 0 | BB44: 0 | BC44: 0 | BD44: 0 | BE44: 0 | BF44: 0 | BG44: 31 | BH44: 1.2 | BI44: 1.0 - 2.0 | BJ44: 0 | BK44: 1 | BL44: 1 | BM44: 1 | BN44: 1 | BO44: 2 | BP44: 3 | BQ44: 3 | BR44: 2 | BS44: 7 | BT44: 5 | BU44: 2 | BV44: 1 | BW44: 0 | BX44: 0 | BY44: 0 | BZ44: 0 | CA44: 0 | CB44: 1 | CC44: 0 | CD44: 9 | CE44: 0.3 | CF44: 0.0 - 1.0 | CG44: E | CH44: 0.002476 | CI44: 0 | CJ44: 2 | CK44: <Null> | CL44: <Null> | CM44: 800.71314 | CN44: 1 | CO44: 1 | CP44: <Null> | CQ44: <Null> | CR44: =IF(COUNTIF(Incl!A:A,Raw!J44),1, "")
A45: 42 | B45: 1 | C45: 176.01626 | D45: 42 | E45: 1 | F45: 71 | G45: 168 | H45: 168 | I45: 168 | J45: 168 | K45: Parking Lot | L45: Broadway | M45: Magnolia Ave | N45: NA | O45: 15 | P45: NA | Q45: NA | R45: NA | S45: NA | T45: 15 | U45: 1 | V45: 2 | W45: 7 | X45: 1 | Y45: 7 | Z45: 13 | AA45: 47 | AB45: 7 | AC45: 0 | AD45: 7 | AE45: 2 | AF45: 3 | AG45: 2 | AH45: 47 | AI45: 13 | AJ45: 20 | AK45: 13 | AL45: 0 | AM45: NA | AN45: NA | AO45: NA | AP45: NA | AQ45: NA | AR45: NA | AS45: NA | AT45: NA | AU45: NA | AV45: NA | AW45: NA | AX45: NA | AY45: NA | AZ45: NA | BA45: NA | BB45: NA | BC45: NA | BD45: NA | BE45: NA | BF45: NA | BG45: NA | BH45: NA | BI45: NA | BJ45: NA | BK45: NA | BL45: NA | BM45: NA | BN45: NA | BO45: NA | BP45: NA | BQ45: NA | BR45: NA | BS45: NA | BT45: NA | BU45: NA | BV45: NA | BW45: NA | BX45: NA | BY45: NA | BZ45: NA | CA45: NA | CB45: NA | CC45: NA | CD45: NA | CE45: NA | CF45: NA | CG45: N | CH45: 0.000566 | CI45: 0 | CJ45: 3 | CK45: <Null> | CL45: <Null> | CM45: 176.01646 | CN45: 2 | CO45: <Null> | CP45: <Null> | CQ45: <Null> | CR45: =IF(COUNTIF(Incl!A:A,Raw!J45),1, "")
A46: 43 | B46: 1 | C46: 181.53276 | D46: 43 | E46: 1 | F46: 72 | G46: 169 | H46: 169 | I46: 169 | J46: 169 | K46: Parking Lot | L46: Magnolia Ave | M46: Broadway | N46: NA | O46: 12 | P46: NA | Q46: NA | R46: NA | S46: NA | T46: 12 | U46: 5 | V46: 6 | W46: 11 | X46: 6 | Y46: 42 | Z46: 50 | AA46: 92 | AB46: 50 | AC46: 1 | AD46: 7 | AE46: 3 | AF46: 1 | AG46: 4 | AH46: 58 | AI46: 25 | AJ46: 8 | AK46: 33 | AL46: 0 | AM46: NA | AN46: NA | AO46: NA | AP46: NA | AQ46: NA | AR46: NA | AS46: NA | AT46: NA | AU46: NA | AV46: NA | AW46: NA | AX46: NA | AY46: NA | AZ46: NA | BA46: NA | BB46: NA | BC46: NA | BD46: NA | BE46: NA | BF46: NA | BG46: NA | BH46: NA | BI46: NA | BJ46: NA | BK46: NA | BL46: NA | BM46: NA | BN46: NA | BO46: NA | BP46: NA | BQ46: NA | BR46: NA | BS46: NA | BT46: NA | BU46: NA | BV46: NA | BW46: NA | BX46: NA | BY46: NA | BZ46: NA | CA46: NA | CB46: NA | CC46: NA | CD46: NA | CE46: NA | CF46: NA | CG46: S | CH46: 0.000592 | CI46: 1 | CJ46: 3 | CK46: <Null> | CL46: <Null> | CM46: 181.53275 | CN46: 2 | CO46: <Null> | CP46: <Null> | CQ46: <Null> | CR46: =IF(COUNTIF(Incl!A:A,Raw!J46),1, "")
A47: 44 | B47: 1 | C47: 82.034217 | D47: 44 | E47: 1 | F47: 73 | G47: 45 | H47: 45 | I47: 45 | J47: 45 | K47: Magnolia Ave | L47: Parking Lot Driveway | M47: Helen Dr | N47: NA | O47: NA | P47: 3 | Q47: NA | R47: NA | S47: NA | T47: 3 | U47: 3 | V47: 1 | W47: 3 | X47: 3 | Y47: 97 | Z47: 32 | AA47: 97 | AB47: 97 | AC47: 3 | AD47: 2 | AE47: 4 | AF47: 3 | AG47: 3 | AH47: 65 | AI47: 129 | AJ47: 97 | AK47: 97 | AL47: 3 | AM47: NA | AN47: NA | AO47: NA | AP47: NA | AQ47: NA | AR47: NA | AS47: NA | AT47: NA | AU47: NA | AV47: NA | AW47: NA | AX47: NA | AY47: NA | AZ47: NA | BA47: NA | BB47: NA | BC47: NA | BD47: NA | BE47: NA | BF47: NA | BG47: NA | BH47: NA | BI47: NA | BJ47: NA | BK47: NA | BL47: NA | BM47: NA | BN47: NA | BO47: NA | BP47: NA | BQ47: NA | BR47: NA | BS47: NA | BT47: NA | BU47: NA | BV47: NA | BW47: NA | BX47: NA | BY47: NA | BZ47: NA | CA47: NA | CB47: NA | CC47: NA | CD47: NA | CE47: NA | CF47: NA | CG47: W | CH47: 0.00025 | CI47: 6 | CJ47: 3 | CK47: <Null> | CL47: <Null> | CM47: 82.034091 | CN47: 2 | CO47: <Null> | CP47: <Null> | CQ47: <Null> | CR47: =IF(COUNTIF(Incl!A:A,Raw!J47),1, "")
A48: 45 | B48: 1 | C48: 468.82295 | D48: 45 | E48: 1 | F48: 74 | G48: 47 | H48: 47 | I48: 47 | J48: 47 | K48: Magnolia Ave | L48: Helen Dr | M48: Anita Dr | N48: NA | O48: NA | P48: 14 | Q48: NA | R48: NA | S48: NA | T48: 14 | U48: 12 | V48: 8 | W48: 12 | X48: 12 | Y48: 87 | Z48: 58 | AA48: 87 | AB48: 87 | AC48: 3 | AD48: 10 | AE48: 8 | AF48: 11 | AG48: 13 | AH48: 72 | AI48: 58 | AJ48: 80 | AK48: 94 | AL48: 2 | AM48: NA | AN48: NA | AO48: NA | AP48: NA | AQ48: NA | AR48: NA | AS48: NA | AT48: NA | AU48: NA | AV48: NA | AW48: NA | AX48: NA | AY48: NA | AZ48: NA | BA48: NA | BB48: NA | BC48: NA | BD48: NA | BE48: NA | BF48: NA | BG48: NA | BH48: NA | BI48: NA | BJ48: NA | BK48: NA | BL48: NA | BM48: NA | BN48: NA | BO48: NA | BP48: NA | BQ48: NA | BR48: NA | BS48: NA | BT48: NA | BU48: NA | BV48: NA | BW48: NA | BX48: NA | BY48: NA | BZ48: NA | CA48: NA | CB48: NA | CC48: NA | CD48: NA | CE48: NA | CF48: NA | CG48: W | CH48: 0.001411 | CI48: 5 | CJ48: 3 | CK48: <Null> | CL48: <Null> | CM48: 468.82306 | CN48: 2 | CO48: <Null> | CP48: <Null> | CQ48: <Null> | CR48: =IF(COUNTIF(Incl!A:A,Raw!J48),1, "")
A49: 46 | B49: 1 | C49: 297.88249 | D49: 46 | E49: 1 | F49: 75 | G49: 46 | H49: 46 | I49: 46 | J49: 46 | K49: Magnolia Ave | L49: Meadow Glen Ave | M49: Parking Lot Driveway | N49: NA | O49: NA | P49: 12 | Q49: NA | R49: NA | S49: NA | T49: 12 | U49: 8 | V49: 10 | W49: 10 | X49: 10 | Y49: 65 | Z49: 82 | AA49: 82 | AB49: 82 | AC49: 3 | AD49: 7 | AE49: 5 | AF49: 4 | AG49: 7 | AH49: 57 | AI49: 41 | AJ49: 33 | AK49: 57 | AL49: 0 | AM49: NA | AN49: NA | AO49: NA | AP49: NA | AQ49: NA | AR49: NA | AS49: NA | AT49: NA | AU49: NA | AV49: NA | AW49: NA | AX49: NA | AY49: NA | AZ49: NA | BA49: NA | BB49: NA | BC49: NA | BD49: NA | BE49: NA | BF49: NA | BG49: NA | BH49: NA | BI49: NA | BJ49: NA | BK49: NA | BL49: NA | BM49: NA | BN49: NA | BO49: NA | BP49: NA | BQ49: NA | BR49: NA | BS49: NA | BT49: NA | BU49: NA | BV49: NA | BW49: NA | BX49: NA | BY49: NA | BZ49: NA | CA49: NA | CB49: NA | CC49: NA | CD49: NA | CE49: NA | CF49: NA | CG49: E | CH49: 0.000896 | CI49: 3 | CJ49: 3 | CK49: <Null> | CL49: <Null> | CM49: 297.8825 | CN49: 2 | CO49: <Null> | CP49: <Null> | CQ49: <Null> | CR49: =IF(COUNTIF(Incl!A:A,Raw!J49),1, "")
A50: 47 | B50: 1 | C50: 196.04822 | D50: 47 | E50: 1 | F50: 76 | G50: 170 | H50: 170 | I50: 170 | J50: 170 | K50: Meadow Glen Ave | L50: Broadway | M50: Magnolia Ave | N50: 2 | O50: NA | P50: 6 | Q50: NA | R50: NA | S50: NA | T50: 8 | U50: 6 | V50: 5 | W50: 3 | X50: 5 | Y50: 77 | Z50: 64 | AA50: 38 | AB50: 64 | AC50: 1 | AD50: 6 | AE50: 5 | AF50: 6 | AG50: 8 | AH50: 77 | AI50: 64 | AJ50: 77 | AK50: 103 | AL50: 3 | AM50: NA | AN50: NA | AO50: NA | AP50: NA | AQ50: NA | AR50: NA | AS50: NA | AT50: NA | AU50: NA | AV50: NA | AW50: NA | AX50: NA | AY50: NA | AZ50: NA | BA50: NA | BB50: NA | BC50: NA | BD50: NA | BE50: NA | BF50: NA | BG50: NA | BH50: NA | BI50: NA | BJ50: NA | BK50: NA | BL50: NA | BM50: NA | BN50: NA | BO50: NA | BP50: NA | BQ50: NA | BR50: NA | BS50: NA | BT50: NA | BU50: NA | BV50: NA | BW50: NA | BX50: NA | BY50: NA | BZ50: NA | CA50: NA | CB50: NA | CC50: NA | CD50: NA | CE50: NA | CF50: NA | CG50: N | CH50: 0.000635 | CI50: 4 | CJ50: 3 | CK50: <Null> | CL50: <Null> | CM50: 196.04801 | CN50: 2 | CO50: <Null> | CP50: <Null> | CQ50: <Null> | CR50: =IF(COUNTIF(Incl!A:A,Raw!J50),1, "")
A51: 48 | B51: 1 | C51: 242.84886 | D51: 48 | E51: 1 | F51: 77 | G51: 79 | H51: 79 | I51: 79 | J51: 79 | K51: Broadway | L51: Parking Lot | M51: Meadow Glen Ave | N51: 2 | O51: 14 | P51: 1 | Q51: NA | R51: 1 | S51: NA | T51: 18 | U51: 6 | V51: 4 | W51: 6 | X51: NA | Y51: 33 | Z51: 22 | AA51: 33 | AB51: 0 | AC51: 0 | AD51: 0 | AE51: 5 | AF51: 9 | AG51: NA | AH51: 0 | AI51: 28 | AJ51: 50 | AK51: 0 | AL51: 0 | AM51: 6 | AN51: 4 | AO51: 5 | AP51: 4 | AQ51: 4 | AR51: 5 | AS51: 5 | AT51: 9 | AU51: 6 | AV51: 6 | AW51: 22 | AX51: 5 | AY51: 2 | AZ51: 1 | BA51: 1 | BB51: 0 | BC51: 1 | BD51: 0 | BE51: 0 | BF51: 0 | BG51: 32 | BH51: 1.8 | BI51: 1.0 - 2.0 | BJ51: 0 | BK51: 6 | BL51: 4 | BM51: 5 | BN51: 5 | BO51: 10 | BP51: 6 | BQ51: 13 | BR51: 9 | BS51: 6 | BT51: 13 | BU51: 6 | BV51: 3 | BW51: 1 | BX51: 2 | BY51: 0 | BZ51: 1 | CA51: 1 | CB51: 0 | CC51: 0 | CD51: 27 | CE51: 1.5 | CF51: 1.0 - 2.0 | CG51: W | CH51: 0.000753 | CI51: 0 | CJ51: 2 | CK51: <Null> | CL51: <Null> | CM51: 242.84888 | CN51: 1 | CO51: <Null> | CP51: <Null> | CQ51: <Null> | CR51: =IF(COUNTIF(Incl!A:A,Raw!J51),1, "")
A52: 49 | B52: 1 | C52: 152.88797 | D52: 49 | E52: 1 | F52: 78 | G52: 172 | H52: 172 | I52: 172 | J52: 172 | K52: Meadow Glen Ave | L52: El Camino Real | M52: Broadway | N52: 3 | O52: NA | P52: NA | Q52: NA | R52: NA | S52: NA | T52: 3 | U52: 3 | V52: NA | W52: 1 | X52: NA | Y52: 88 | Z52: 0 | AA52: 29 | AB52: 0 | AC52: 1 | AD52: 3 | AE52: 2 | AF52: 2 | AG52: NA | AH52: 88 | AI52: 59 | AJ52: 59 | AK52: 0 | AL52: 1 | AM52: 3 | AN52: 1 | AO52: 2 | AP52: 3 | AQ52: 0 | AR52: 0 | AS52: 1 | AT52: 1 | AU52: 1 | AV52: 1 | AW52: 7 | AX52: 1 | AY52: 0 | AZ52: 1 | BA52: 0 | BB52: 0 | BC52: 0 | BD52: 0 | BE52: 0 | BF52: 0 | BG52: 9 | BH52: 2.6 | BI52: 2.0 - 3.0 | BJ52: 3 | BK52: 1 | BL52: 1 | BM52: 1 | BN52: 2 | BO52: 1 | BP52: 2 | BQ52: 3 | BR52: 2 | BS52: 1 | BT52: 5 | BU52: 1 | BV52: 0 | BW52: 1 | BX52: 0 | BY52: 1 | BZ52: 0 | CA52: 0 | CB52: 0 | CC52: 0 | CD52: 8 | CE52: 2.4 | CF52: 2.0 - 3.0 | CG52: N | CH52: 0.000476 | CI52: 2 | CJ52: 2 | CK52: <Null> | CL52: <Null> | CM52: 152.88807 | CN52: 1 | CO52: 1 | CP52: <Null> | CQ52: <Null> | CR52: =IF(COUNTIF(Incl!A:A,Raw!J52),1, "")
A53: 50 | B53: 1 | C53: 192.11415 | D53: 50 | E53: 1 | F53: 79 | G53: 49 | H53: 49 | I53: 49 | J53: 49 | K53: Magnolia Ave | L53: Anita Dr | M53: Richmond Dr | N53: NA | O53: NA | P53: 2 | Q53: NA | R53: NA | S53: NA | T53: 2 | U53: 1 | V53: 1 | W53: 1 | X53: NA | Y53: 67 | Z53: 67 | AA53: 67 | AB53: 0 | AC53: 0 | AD53: 1 | AE53: 1 | AF53: 1 | AG53: NA | AH53: 67 | AI53: 67 | AJ53: 67 | AK53: 0 | AL53: 0 | AM53: 1 | AN53: 1 | AO53: 2 | AP53: 1 | AQ53: 1 | AR53: 1 | AS53: 1 | AT53: 1 | AU53: 1 | AV53: 2 | AW53: 2 | AX53: 0 | AY53: 0 | AZ53: 0 | BA53: 0 | BB53: 0 | BC53: 0 | BD53: 0 | BE53: 0 | BF53: 1 | BG53: 3 | BH53: 2 | BI53: 1.0 - 2.0 | BJ53: 1 | BK53: 2 | BL53: 2 | BM53: 1 | BN53: 1 | BO53: 1 | BP53: 1 | BQ53: 1 | BR53: 1 | BS53: 1 | BT53: 0 | BU53: 1 | BV53: 0 | BW53: 1 | BX53: 0 | BY53: 1 | BZ53: 0 | CA53: 0 | CB53: 0 | CC53: 0 | CD53: 3 | CE53: 2 | CF53: 2.0 - 3.0 | CG53: W | CH53: 0.000603 | CI53: 0 | CJ53: 3 | CK53: <Null> | CL53: <Null> | CM53: 192.11411 | CN53: 1 | CO53: <Null> | CP53: <Null> | CQ53: <Null> | CR53: =IF(COUNTIF(Incl!A:A,Raw!J53),1, "")
A54: 51 | B54: 1 | C54: 250.80485 | D54: 51 | E54: 1 | F54: 80 | G54: 171 | H54: 171 | I54: 171 | J54: 171 | K54: Meadow Glen Ave | L54: Magnolia Ave | M54: Broadway | N54: NA | O54: 10 | P54: NA | Q54: NA | R54: NA | S54: NA | T54: 10 | U54: 5 | V54: 4 | W54: 5 | X54: 4 | Y54: 53 | Z54: 42 | AA54: 53 | AB54: 42 | AC54: 0 | AD54: 6 | AE54: 6 | AF54: 8 | AG54: 8 | AH54: 63 | AI54: 63 | AJ54: 84 | AK54: 84 | AL54: 2 | AM54: NA | AN54: NA | AO54: NA | AP54: NA | AQ54: NA | AR54: NA | AS54: NA | AT54: NA | AU54: NA | AV54: NA | AW54: NA | AX54: NA | AY54: NA | AZ54: NA | BA54: NA | BB54: NA | BC54: NA | BD54: NA | BE54: NA | BF54: NA | BG54: NA | BH54: NA | BI54: NA | BJ54: NA | BK54: NA | BL54: NA | BM54: NA | BN54: NA | BO54: NA | BP54: NA | BQ54: NA | BR54: NA | BS54: NA | BT54: NA | BU54: NA | BV54: NA | BW54: NA | BX54: NA | BY54: NA | BZ54: NA | CA54: NA | CB54: NA | CC54: NA | CD54: NA | CE54: NA | CF54: NA | CG54: S | CH54: 0.000805 | CI54: 2 | CJ54: 3 | CK54: <Null> | CL54: <Null> | CM54: 250.80485 | CN54: 2 | CO54: <Null> | CP54: <Null> | CQ54: <Null> | CR54: =IF(COUNTIF(Incl!A:A,Raw!J54),1, "")
A55: 52 | B55: 1 | C55: 711.00839 | D55: 52 | E55: 1 | F55: 81 | G55: 48 | H55: 48 | I55: 48 | J55: 48 | K55: Magnolia Ave | L55: Library Ave | M55: Meadow Glen Ave | N55: NA | O55: 10 | P55: 17 | Q55: NA | R55: NA | S55: NA | T55: 27 | U55: 13 | V55: 12 | W55: 15 | X55: NA | Y55: 49 | Z55: 45 | AA55: 56 | AB55: 0 | AC55: 0 | AD55: 4 | AE55: 7 | AF55: 10 | AG55: NA | AH55: 15 | AI55: 26 | AJ55: 38 | AK55: 0 | AL55: 0 | AM55: 13 | AN55: 13 | AO55: 14 | AP55: 14 | AQ55: 12 | AR55: 13 | AS55: 13 | AT55: 14 | AU55: 15 | AV55: 16 | AW55: 5 | AX55: 3 | AY55: 1 | AZ55: 1 | BA55: 3 | BB55: 0 | BC55: 1 | BD55: 1 | BE55: 1 | BF55: 8 | BG55: 24 | BH55: 0.9 | BI55: 0.0 - 1.0 | BJ55: 4 | BK55: 10 | BL55: 10 | BM55: 7 | BN55: 7 | BO55: 7 | BP55: 6 | BQ55: 4 | BR55: 10 | BS55: 10 | BT55: 16 | BU55: 8 | BV55: 7 | BW55: 3 | BX55: 2 | BY55: 0 | BZ55: 0 | CA55: 0 | CB55: 0 | CC55: 0 | CD55: 36 | CE55: 1.4 | CF55: 1.0 - 2.0 | CG55: E | CH55: 0.002223 | CI55: 0 | CJ55: 3 | CK55: <Null> | CL55: <Null> | CM55: 711.00849 | CN55: 1 | CO55: <Null> | CP55: <Null> | CQ55: <Null> | CR55: =IF(COUNTIF(Incl!A:A,Raw!J55),1, "")
A56: 53 | B56: 1 | C56: 228.66928 | D56: 53 | E56: 1 | F56: 82 | G56: 50 | H56: 50 | I56: 50 | J56: 50 | K56: Magnolia Ave | L56: Richmond Dr | M56: Library Ave | N56: NA | O56: 6 | P56: NA | Q56: NA | R56: NA | S56: NA | T56: 6 | U56: NA | V56: NA | W56: NA | X56: NA | Y56: 0 | Z56: 0 | AA56: 0 | AB56: 0 | AC56: 0 | AD56: 2 | AE56: 2 | AF56: 0 | AG56: NA | AH56: 33 | AI56: 33 | AJ56: 0 | AK56: 0 | AL56: 0 | AM56: 0 | AN56: 0 | AO56: 0 | AP56: 0 | AQ56: 0 | AR56: 0 | AS56: 0 | AT56: 0 | AU56: 0 | AV56: 0 | AW56: 0 | AX56: 0 | AY56: 0 | AZ56: 0 | BA56: 0 | BB56: 0 | BC56: 0 | BD56: 0 | BE56: 0 | BF56: 0 | BG56: 0 | BH56: 0 | BI56: 0.0 - 1.0 | BJ56: 2 | BK56: 2 | BL56: 2 | BM56: 2 | BN56: 2 | BO56: 2 | BP56: 6 | BQ56: 0 | BR56: 0 | BS56: 0 | BT56: 4 | BU56: 0 | BV56: 0 | BW56: 0 | BX56: 0 | BY56: 0 | BZ56: 2 | CA56: 0 | CB56: 0 | CC56: 0 | CD56: 6 | CE56: 1 | CF56: 0.0 - 1.0 | CG56: W | CH56: 0.000736 | CI56: 0 | CJ56: 3 | CK56: <Null> | CL56: <Null> | CM56: 228.66944 | CN56: 1 | CO56: <Null> | CP56: <Null> | CQ56: <Null> | CR56: =IF(COUNTIF(Incl!A:A,Raw!J56),1, "")
A57: 54 | B57: 1 | C57: 423.4626 | D57: 54 | E57: 1 | F57: 83 | G57: 177 | H57: 177 | I57: 177 | J57: 177 | K57: Richmond Dr | L57: Poplar Ave | M57: Magnolia Ave | N57: NA | O57: 18 | P57: NA | Q57: NA | R57: NA | S57: NA | T57: 18 | U57: 2 | V57: 5 | W57: 3 | X57: 3 | Y57: 11 | Z57: 29 | AA57: 17 | AB57: 17 | AC57: 0 | AD57: 2 | AE57: 2 | AF57: 3 | AG57: 6 | AH57: 11 | AI57: 11 | AJ57: 17 | AK57: 34 | AL57: 0 | AM57: NA | AN57: NA | AO57: NA | AP57: NA | AQ57: NA | AR57: NA | AS57: NA | AT57: NA | AU57: NA | AV57: NA | AW57: NA | AX57: NA | AY57: NA | AZ57: NA | BA57: NA | BB57: NA | BC57: NA | BD57: NA | BE57: NA | BF57: NA | BG57: NA | BH57: NA | BI57: NA | BJ57: NA | BK57: NA | BL57: NA | BM57: NA | BN57: NA | BO57: NA | BP57: NA | BQ57: NA | BR57: NA | BS57: NA | BT57: NA | BU57: NA | BV57: NA | BW57: NA | BX57: NA | BY57: NA | BZ57: NA | CA57: NA | CB57: NA | CC57: NA | CD57: NA | CE57: NA | CF57: NA | CG57: S | CH57: 0.001364 | CI57: 0 | CJ57: 3 | CK57: <Null> | CL57: <Null> | CM57: 423.4625 | CN57: 2 | CO57: <Null> | CP57: <Null> | CQ57: <Null> | CR57: =IF(COUNTIF(Incl!A:A,Raw!J57),1, "")
A58: 55 | B58: 1 | C58: 413.64043 | D58: 55 | E58: 1 | F58: 84 | G58: 176 | H58: 176 | I58: 176 | J58: 176 | K58: Richmond Dr | L58: Magnolia Ave | M58: Poplar Ave | N58: NA | O58: 15 | P58: NA | Q58: NA | R58: NA | S58: NA | T58: 15 | U58: 7 | V58: 7 | W58: 7 | X58: 7 | Y58: 45 | Z58: 45 | AA58: 45 | AB58: 45 | AC58: 0 | AD58: 3 | AE58: 5 | AF58: 4 | AG58: 3 | AH58: 19 | AI58: 32 | AJ58: 26 | AK58: 19 | AL58: 0 | AM58: NA | AN58: NA | AO58: NA | AP58: NA | AQ58: NA | AR58: NA | AS58: NA | AT58: NA | AU58: NA | AV58: NA | AW58: NA | AX58: NA | AY58: NA | AZ58: NA | BA58: NA | BB58: NA | BC58: NA | BD58: NA | BE58: NA | BF58: NA | BG58: NA | BH58: NA | BI58: NA | BJ58: NA | BK58: NA | BL58: NA | BM58: NA | BN58: NA | BO58: NA | BP58: NA | BQ58: NA | BR58: NA | BS58: NA | BT58: NA | BU58: NA | BV58: NA | BW58: NA | BX58: NA | BY58: NA | BZ58: NA | CA58: NA | CB58: NA | CC58: NA | CD58: NA | CE58: NA | CF58: NA | CG58: N | CH58: 0.001335 | CI58: 0 | CJ58: 3 | CK58: <Null> | CL58: <Null> | CM58: 413.64053 | CN58: 2 | CO58: <Null> | CP58: <Null> | CQ58: <Null> | CR58: =IF(COUNTIF(Incl!A:A,Raw!J58),1, "")
A59: 56 | B59: 1 | C59: 508.49769 | D59: 56 | E59: 1 | F59: 85 | G59: 22 | H59: 22 | I59: 22 | J59: 22 | K59: Poplar Ave | L59: Richmond Dr | M59: Lansdale Ave | N59: NA | O59: NA | P59: 18 | Q59: NA | R59: NA | S59: NA | T59: 18 | U59: 14 | V59: 12 | W59: 12 | X59: 15 | Y59: 78 | Z59: 67 | AA59: 67 | AB59: 83 | AC59: 2 | AD59: 9 | AE59: 10 | AF59: 15 | AG59: 14 | AH59: 50 | AI59: 56 | AJ59: 83 | AK59: 78 | AL59: 2 | AM59: NA | AN59: NA | AO59: NA | AP59: NA | AQ59: NA | AR59: NA | AS59: NA | AT59: NA | AU59: NA | AV59: NA | AW59: NA | AX59: NA | AY59: NA | AZ59: NA | BA59: NA | BB59: NA | BC59: NA | BD59: NA | BE59: NA | BF59: NA | BG59: NA | BH59: NA | BI59: NA | BJ59: NA | BK59: NA | BL59: NA | BM59: NA | BN59: NA | BO59: NA | BP59: NA | BQ59: NA | BR59: NA | BS59: NA | BT59: NA | BU59: NA | BV59: NA | BW59: NA | BX59: NA | BY59: NA | BZ59: NA | CA59: NA | CB59: NA | CC59: NA | CD59: NA | CE59: NA | CF59: NA | CG59: W | CH59: 0.001593 | CI59: 4 | CJ59: 3 | CK59: <Null> | CL59: <Null> | CM59: 508.4976 | CN59: 2 | CO59: <Null> | CP59: <Null> | CQ59: <Null> | CR59: =IF(COUNTIF(Incl!A:A,Raw!J59),1, "")
A60: 57 | B60: 1 | C60: 204.82893 | D60: 57 | E60: 1 | F60: 86 | G60: 23 | H60: 23 | I60: 23 | J60: 23 | K60: Poplar Ave | L60: Library Ave | M60: Richmond Dr | N60: NA | O60: NA | P60: 10 | Q60: NA | R60: NA | S60: NA | T60: 10 | U60: 9 | V60: 5 | W60: 10 | X60: 10 | Y60: 87 | Z60: 48 | AA60: 96 | AB60: 96 | AC60: 3 | AD60: 7 | AE60: 3 | AF60: 7 | AG60: 7 | AH60: 67 | AI60: 29 | AJ60: 67 | AK60: 67 | AL60: 0 | AM60: NA | AN60: NA | AO60: NA | AP60: NA | AQ60: NA | AR60: NA | AS60: NA | AT60: NA | AU60: NA | AV60: NA | AW60: NA | AX60: NA | AY60: NA | AZ60: NA | BA60: NA | BB60: NA | BC60: NA | BD60: NA | BE60: NA | BF60: NA | BG60: NA | BH60: NA | BI60: NA | BJ60: NA | BK60: NA | BL60: NA | BM60: NA | BN60: NA | BO60: NA | BP60: NA | BQ60: NA | BR60: NA | BS60: NA | BT60: NA | BU60: NA | BV60: NA | BW60: NA | BX60: NA | BY60: NA | BZ60: NA | CA60: NA | CB60: NA | CC60: NA | CD60: NA | CE60: NA | CF60: NA | CG60: E | CH60: 0.000643 | CI60: 3 | CJ60: 3 | CK60: <Null> | CL60: <Null> | CM60: 204.829 | CN60: 2 | CO60: <Null> | CP60: <Null> | CQ60: <Null> | CR60: =IF(COUNTIF(Incl!A:A,Raw!J60),1, "")
A61: 58 | B61: 1 | C61: 426.82463 | D61: 58 | E61: 1 | F61: 87 | G61: 178 | H61: 178 | I61: 178 | J61: 178 | K61: Library Ave | L61: Magnolia Ave | M61: Poplar Ave | N61: NA | O61: NA | P61: NA | Q61: NA | R61: NA | S61: NA | T61: 0 | U61: NA | V61: NA | W61: NA | X61: NA | Y61: 0 | Z61: 0 | AA61: 0 | AB61: 0 | AC61: 0 | AD61: 0 | AE61: 0 | AF61: 0 | AG61: NA | AH61: 0 | AI61: 0 | AJ61: 0 | AK61: 0 | AL61: 0 | AM61: 0 | AN61: 0 | AO61: 0 | AP61: 0 | AQ61: 0 | AR61: 0 | AS61: 0 | AT61: 0 | AU61: 0 | AV61: 0 | AW61: 0 | AX61: 0 | AY61: 0 | AZ61: 0 | BA61: 0 | BB61: 0 | BC61: 0 | BD61: 0 | BE61: 0 | BF61: 0 | BG61: 0 | BH61: 0 | BI61: 0.0 - 1.0 | BJ61: 0 | BK61: 0 | BL61: 0 | BM61: 0 | BN61: 0 | BO61: 0 | BP61: 0 | BQ61: 0 | BR61: 0 | BS61: 0 | BT61: 0 | BU61: 0 | BV61: 0 | BW61: 0 | BX61: 0 | BY61: 0 | BZ61: 0 | CA61: 0 | CB61: 1 | CC61: 0 | CD61: 1 | CE61: 0 | CF61: 0.0 - 1.0 | CG61: N | CH61: 0.001373 | CI61: 0 | CJ61: 3 | CK61: <Null> | CL61: <Null> | CM61: 426.82484 | CN61: 1 | CO61: <Null> | CP61: <Null> | CQ61: <Null> | CR61: =IF(COUNTIF(Incl!A:A,Raw!J61),1, "")
A62: 59 | B62: 1 | C62: 470.8581 | D62: 59 | E62: 1 | F62: 88 | G62: 179 | H62: 179 | I62: 179 | J62: 179 | K62: Library Ave | L62: Poplar Ave | M62: Magnolia Ave | N62: NA | O62: 16 | P62: NA | Q62: NA | R62: NA | S62: NA | T62: 16 | U62: 1 | V62: 12 | W62: 9 | X62: NA | Y62: 6 | Z62: 74 | AA62: 56 | AB62: 0 | AC62: 0 | AD62: 11 | AE62: 10 | AF62: 4 | AG62: NA | AH62: 68 | AI62: 62 | AJ62: 25 | AK62: 0 | AL62: 0 | AM62: 1 | AN62: 1 | AO62: 4 | AP62: 5 | AQ62: 12 | AR62: 10 | AS62: 10 | AT62: 9 | AU62: 9 | AV62: 9 | AW62: 1 | AX62: 1 | AY62: 0 | AZ62: 0 | BA62: 0 | BB62: 6 | BC62: 1 | BD62: 3 | BE62: 0 | BF62: 0 | BG62: 12 | BH62: 0.7 | BI62: 0.0 - 1.0 | BJ62: 11 | BK62: 11 | BL62: 11 | BM62: 11 | BN62: 10 | BO62: 10 | BP62: 10 | BQ62: 6 | BR62: 4 | BS62: 0 | BT62: 2 | BU62: 0 | BV62: 1 | BW62: 1 | BX62: 0 | BY62: 2 | BZ62: 4 | CA62: 1 | CB62: 3 | CC62: 0 | CD62: 14 | CE62: 0.9 | CF62: 0.0 - 1.0 | CG62: S | CH62: 0.001519 | CI62: 0 | CJ62: 3 | CK62: <Null> | CL62: <Null> | CM62: 470.85837 | CN62: 1 | CO62: <Null> | CP62: <Null> | CQ62: <Null> | CR62: =IF(COUNTIF(Incl!A:A,Raw!J62),1, "")
A63: 60 | B63: 1 | C63: 576.08943 | D63: 60 | E63: 1 | F63: 89 | G63: 52 | H63: 52 | I63: 52 | J63: 52 | K63: Magnolia Ave | L63: Taylor Blvd | M63: Library Ave | N63: NA | O63: 15 | P63: NA | Q63: NA | R63: NA | S63: NA | T63: 15 | U63: 13 | V63: 9 | W63: 1 | X63: NA | Y63: 87 | Z63: 60 | AA63: 7 | AB63: 0 | AC63: 1 | AD63: 4 | AE63: 9 | AF63: 4 | AG63: NA | AH63: 27 | AI63: 60 | AJ63: 27 | AK63: 0 | AL63: 0 | AM63: 13 | AN63: 12 | AO63: 12 | AP63: 11 | AQ63: 9 | AR63: 7 | AS63: 8 | AT63: 1 | AU63: 1 | AV63: 2 | AW63: 37 | AX63: 8 | AY63: 3 | AZ63: 1 | BA63: 0 | BB63: 0 | BC63: 0 | BD63: 0 | BE63: 0 | BF63: 1 | BG63: 50 | BH63: 3.3 | BI63: 3.0 - 4.0 | BJ63: 4 | BK63: 6 | BL63: 2 | BM63: 9 | BN63: 9 | BO63: 9 | BP63: 9 | BQ63: 8 | BR63: 4 | BS63: 3 | BT63: 20 | BU63: 3 | BV63: 8 | BW63: 1 | BX63: 0 | BY63: 0 | BZ63: 0 | CA63: 0 | CB63: 1 | CC63: 0 | CD63: 33 | CE63: 2.2 | CF63: 2.0 - 3.0 | CG63: E | CH63: 0.001854 | CI63: 1 | CJ63: 3 | CK63: <Null> | CL63: <Null> | CM63: 576.08949 | CN63: 1 | CO63: 0 | CP63: <Null> | CQ63: <Null> | CR63: =IF(COUNTIF(Incl!A:A,Raw!J63),1, "")
A64: 61 | B64: 1 | C64: 443.92052 | D64: 61 | E64: 1 | F64: 90 | G64: 174 | H64: 174 | I64: 174 | J64: 174 | K64: Richmond Dr | L64: Poplar Ave | M64: Palm Ave | N64: NA | O64: NA | P64: 10 | Q64: NA | R64: NA | S64: NA | T64: 10 | U64: 9 | V64: 8 | W64: 10 | X64: 10 | Y64: 90 | Z64: 80 | AA64: 100 | AB64: 100 | AC64: 4 | AD64: 8 | AE64: 10 | AF64: 10 | AG64: 7 | AH64: 80 | AI64: 100 | AJ64: 100 | AK64: 70 | AL64: 3 | AM64: NA | AN64: NA | AO64: NA | AP64: NA | AQ64: NA | AR64: NA | AS64: NA | AT64: NA | AU64: NA | AV64: NA | AW64: NA | AX64: NA | AY64: NA | AZ64: NA | BA64: NA | BB64: NA | BC64: NA | BD64: NA | BE64: NA | BF64: NA | BG64: NA | BH64: NA | BI64: NA | BJ64: NA | BK64: NA | BL64: NA | BM64: NA | BN64: NA | BO64: NA | BP64: NA | BQ64: NA | BR64: NA | BS64: NA | BT64: NA | BU64: NA | BV64: NA | BW64: NA | BX64: NA | BY64: NA | BZ64: NA | CA64: NA | CB64: NA | CC64: NA | CD64: NA | CE64: NA | CF64: NA | CG64: N | CH64: 0.00118 | CI64: 7 | CJ64: 3 | CK64: <Null> | CL64: <Null> | CM64: 365.32754 | CN64: 2 | CO64: <Null> | CP64: <Null> | CQ64: <Null> | CR64: =IF(COUNTIF(Incl!A:A,Raw!J64),1, "")
A65: 62 | B65: 1 | C65: 368.59075 | D65: 62 | E65: 1 | F65: 91 | G65: 175 | H65: 175 | I65: 175 | J65: 175 | K65: Richmond Dr | L65: Palm Ave | M65: Poplar Ave | N65: NA | O65: NA | P65: 21 | Q65: NA | R65: NA | S65: NA | T65: 21 | U65: 20 | V65: 18 | W65: 19 | X65: 20 | Y65: 93 | Z65: 84 | AA65: 89 | AB65: 93 | AC65: 4 | AD65: 10 | AE65: 12 | AF65: 17 | AG65: 20 | AH65: 47 | AI65: 56 | AJ65: 79 | AK65: 93 | AL65: 2 | AM65: NA | AN65: NA | AO65: NA | AP65: NA | AQ65: NA | AR65: NA | AS65: NA | AT65: NA | AU65: NA | AV65: NA | AW65: NA | AX65: NA | AY65: NA | AZ65: NA | BA65: NA | BB65: NA | BC65: NA | BD65: NA | BE65: NA | BF65: NA | BG65: NA | BH65: NA | BI65: NA | BJ65: NA | BK65: NA | BL65: NA | BM65: NA | BN65: NA | BO65: NA | BP65: NA | BQ65: NA | BR65: NA | BS65: NA | BT65: NA | BU65: NA | BV65: NA | BW65: NA | BX65: NA | BY65: NA | BZ65: NA | CA65: NA | CB65: NA | CC65: NA | CD65: NA | CE65: NA | CF65: NA | CG65: S | CH65: 0.001185 | CI65: 6 | CJ65: 3 | CK65: <Null> | CL65: <Null> | CM65: 368.59083 | CN65: 2 | CO65: <Null> | CP65: <Null> | CQ65: <Null> | CR65: =IF(COUNTIF(Incl!A:A,Raw!J65),1, "")
A66: 63 | B66: 1 | C66: 443.93448 | D66: 63 | E66: 1 | F66: 92 | G66: 2 | H66: 2 | I66: 2 | J66: 2 | K66: Palm Ave | L66: Lansdale Ave | M66: Richmond Dr | N66: NA | O66: NA | P66: 17 | Q66: NA | R66: NA | S66: NA | T66: 17 | U66: 12 | V66: 10 | W66: 15 | X66: 13 | Y66: 71 | Z66: 59 | AA66: 89 | AB66: 77 | AC66: 2 | AD66: 9 | AE66: 8 | AF66: 12 | AG66: 15 | AH66: 53 | AI66: 47 | AJ66: 71 | AK66: 89 | AL66: 1 | AM66: NA | AN66: NA | AO66: NA | AP66: NA | AQ66: NA | AR66: NA | AS66: NA | AT66: NA | AU66: NA | AV66: NA | AW66: NA | AX66: NA | AY66: NA | AZ66: NA | BA66: NA | BB66: NA | BC66: NA | BD66: NA | BE66: NA | BF66: NA | BG66: NA | BH66: NA | BI66: NA | BJ66: NA | BK66: NA | BL66: NA | BM66: NA | BN66: NA | BO66: NA | BP66: NA | BQ66: NA | BR66: NA | BS66: NA | BT66: NA | BU66: NA | BV66: NA | BW66: NA | BX66: NA | BY66: NA | BZ66: NA | CA66: NA | CB66: NA | CC66: NA | CD66: NA | CE66: NA | CF66: NA | CG66: E | CH66: 0.001339 | CI66: 3 | CJ66: 3 | CK66: <Null> | CL66: <Null> | CM66: 443.93444 | CN66: 2 | CO66: <Null> | CP66: <Null> | CQ66: <Null> | CR66: =IF(COUNTIF(Incl!A:A,Raw!J66),1, "")
A67: 64 | B67: 1 | C67: 377.82184 | D67: 64 | E67: 1 | F67: 93 | G67: 180 | H67: 180 | I67: 180 | J67: 180 | K67: Lansdale Ave | L67: Palm Ave | M67: Poplar Ave | N67: NA | O67: NA | P67: 23 | Q67: NA | R67: NA | S67: NA | T67: 23 | U67: 24 | V67: 10 | W67: 19 | X67: 19 | Y67: 105 | Z67: 44 | AA67: 83 | AB67: 83 | AC67: 3 | AD67: 8 | AE67: 6 | AF67: 12 | AG67: 15 | AH67: 35 | AI67: 26 | AJ67: 53 | AK67: 66 | AL67: 0 | AM67: NA | AN67: NA | AO67: NA | AP67: NA | AQ67: NA | AR67: NA | AS67: NA | AT67: NA | AU67: NA | AV67: NA | AW67: NA | AX67: NA | AY67: NA | AZ67: NA | BA67: NA | BB67: NA | BC67: NA | BD67: NA | BE67: NA | BF67: NA | BG67: NA | BH67: NA | BI67: NA | BJ67: NA | BK67: NA | BL67: NA | BM67: NA | BN67: NA | BO67: NA | BP67: NA | BQ67: NA | BR67: NA | BS67: NA | BT67: NA | BU67: NA | BV67: NA | BW67: NA | BX67: NA | BY67: NA | BZ67: NA | CA67: NA | CB67: NA | CC67: NA | CD67: NA | CE67: NA | CF67: NA | CG67: N | CH67: 0.001216 | CI67: 3 | CJ67: 3 | CK67: <Null> | CL67: <Null> | CM67: 377.8217 | CN67: 2 | CO67: <Null> | CP67: <Null> | CQ67: <Null> | CR67: =IF(COUNTIF(Incl!A:A,Raw!J67),1, "")
A68: 65 | B68: 1 | C68: 609.62675 | D68: 65 | E68: 1 | F68: 94 | G68: 24 | H68: 24 | I68: 24 | J68: 24 | K68: Poplar Ave | L68: Taylor Blvd | M68: Library Ave | N68: NA | O68: 20 | P68: NA | Q68: NA | R68: NA | S68: NA | T68: 20 | U68: 8 | V68: 2 | W68: 3 | X68: 5 | Y68: 39 | Z68: 10 | AA68: 15 | AB68: 25 | AC68: 0 | AD68: 3 | AE68: 9 | AF68: 5 | AG68: 6 | AH68: 15 | AI68: 44 | AJ68: 25 | AK68: 29 | AL68: 0 | AM68: NA | AN68: NA | AO68: NA | AP68: NA | AQ68: NA | AR68: NA | AS68: NA | AT68: NA | AU68: NA | AV68: NA | AW68: NA | AX68: NA | AY68: NA | AZ68: NA | BA68: NA | BB68: NA | BC68: NA | BD68: NA | BE68: NA | BF68: NA | BG68: NA | BH68: NA | BI68: NA | BJ68: NA | BK68: NA | BL68: NA | BM68: NA | BN68: NA | BO68: NA | BP68: NA | BQ68: NA | BR68: NA | BS68: NA | BT68: NA | BU68: NA | BV68: NA | BW68: NA | BX68: NA | BY68: NA | BZ68: NA | CA68: NA | CB68: NA | CC68: NA | CD68: NA | CE68: NA | CF68: NA | CG68: E | CH68: 0.001877 | CI68: 0 | CJ68: 3 | CK68: <Null> | CL68: <Null> | CM68: 608.89854 | CN68: 2 | CO68: <Null> | CP68: <Null> | CQ68: <Null> | CR68: =IF(COUNTIF(Incl!A:A,Raw!J68),1, "")
A69: 66 | B69: 1 | C69: 530.14439 | D69: 66 | E69: 2 | F69: 95 | G69: 51 | H69: 51 | I69: 51 | J69: 51 | K69: Magnolia Ave | L69: Library Ave | M69: Taylor Blvd | N69: 10 | O69: NA | P69: NA | Q69: NA | R69: NA | S69: NA | T69: 10 | U69: 1 | V69: NA | W69: NA | X69: NA | Y69: 10 | Z69: 0 | AA69: 0 | AB69: 0 | AC69: 0 | AD69: 1 | AE69: 1 | AF69: 0 | AG69: NA | AH69: 10 | AI69: 10 | AJ69: 0 | AK69: 0 | AL69: 0 | AM69: 1 | AN69: 1 | AO69: 1 | AP69: 1 | AQ69: 0 | AR69: 0 | AS69: 0 | AT69: 0 | AU69: 0 | AV69: 0 | AW69: 1 | AX69: 0 | AY69: 1 | AZ69: 0 | BA69: 0 | BB69: 0 | BC69: 0 | BD69: 0 | BE69: 0 | BF69: 0 | BG69: 2 | BH69: 0.2 | BI69: 0.0 - 1.0 | BJ69: 1 | BK69: 2 | BL69: 1 | BM69: 1 | BN69: 1 | BO69: 1 | BP69: 1 | BQ69: 0 | BR69: 0 | BS69: 0 | BT69: 2 | BU69: 0 | BV69: 0 | BW69: 0 | BX69: 0 | BY69: 1 | BZ69: 0 | CA69: 0 | CB69: 0 | CC69: 0 | CD69: 3 | CE69: 0.3 | CF69: 0.0 - 1.0 | CG69: W | CH69: 0.001697 | CI69: 0 | CJ69: 3 | CK69: <Null> | CL69: <Null> | CM69: 530.14432 | CN69: 1 | CO69: <Null> | CP69: <Null> | CQ69: <Null> | CR69: =IF(COUNTIF(Incl!A:A,Raw!J69),1, "")
A70: 67 | B70: 1 | C70: 518.41086 | D70: 67 | E70: 1 | F70: 96 | G70: 192 | H70: 192 | I70: 192 | J70: 192 | K70: Taylor Blvd | L70: Magnolia Ave | M70: Poplar Ave | N70: NA | O70: NA | P70: NA | Q70: NA | R70: NA | S70: 20 | T70: 20 | U70: 10 | V70: 11 | W70: 8 | X70: 8 | Y70: 51 | Z70: 56 | AA70: 41 | AB70: 41 | AC70: 0 | AD70: 12 | AE70: 11 | AF70: 12 | AG70: 11 | AH70: 62 | AI70: 56 | AJ70: 62 | AK70: 56 | AL70: 0 | AM70: NA | AN70: NA | AO70: NA | AP70: NA | AQ70: NA | AR70: NA | AS70: NA | AT70: NA | AU70: NA | AV70: NA | AW70: NA | AX70: NA | AY70: NA | AZ70: NA | BA70: NA | BB70: NA | BC70: NA | BD70: NA | BE70: NA | BF70: NA | BG70: NA | BH70: NA | BI70: NA | BJ70: NA | BK70: NA | BL70: NA | BM70: NA | BN70: NA | BO70: NA | BP70: NA | BQ70: NA | BR70: NA | BS70: NA | BT70: NA | BU70: NA | BV70: NA | BW70: NA | BX70: NA | BY70: NA | BZ70: NA | CA70: NA | CB70: NA | CC70: NA | CD70: NA | CE70: NA | CF70: NA | CG70: N | CH70: 0.00161 | CI70: 0 | CJ70: 3 | CK70: <Null> | CL70: <Null> | CM70: 518.41093 | CN70: 2 | CO70: <Null> | CP70: <Null> | CQ70: <Null> | CR70: =IF(COUNTIF(Incl!A:A,Raw!J70),1, "")
A71: 68 | B71: 1 | C71: 192.46328 | D71: 68 | E71: 1 | F71: 97 | G71: 173 | H71: 173 | I71: 173 | J71: 173 | K71: Meadow Glen Ave | L71: Broadway | M71: El Camino Real | N71: NA | O71: NA | P71: NA | Q71: NA | R71: NA | S71: NA | T71: 0 | U71: NA | V71: NA | W71: NA | X71: NA | Y71: 0 | Z71: 0 | AA71: 0 | AB71: 0 | AC71: 0 | AD71: 0 | AE71: 0 | AF71: 0 | AG71: NA | AH71: 0 | AI71: 0 | AJ71: 0 | AK71: 0 | AL71: 0 | AM71: 0 | AN71: 0 | AO71: 0 | AP71: 0 | AQ71: 0 | AR71: 0 | AS71: 0 | AT71: 0 | AU71: 0 | AV71: 0 | AW71: 0 | AX71: 0 | AY71: 0 | AZ71: 0 | BA71: 0 | BB71: 0 | BC71: 0 | BD71: 0 | BE71: 0 | BF71: 0 | BG71: 0 | BH71: 0 | BI71: 0.0 - 1.0 | BJ71: 0 | BK71: 0 | BL71: 0 | BM71: 0 | BN71: 0 | BO71: 0 | BP71: 0 | BQ71: 0 | BR71: 0 | BS71: 0 | BT71: 0 | BU71: 0 | BV71: 0 | BW71: 0 | BX71: 0 | BY71: 0 | BZ71: 0 | CA71: 0 | CB71: 0 | CC71: 0 | CD71: 0 | CE71: 0 | CF71: 0.0 - 1.0 | CG71: S | CH71: 0.000597 | CI71: 0 | CJ71: 2 | CK71: <Null> | CL71: <Null> | CM71: 192.46343 | CN71: 1 | CO71: 1 | CP71: <Null> | CQ71: <Null> | CR71: =IF(COUNTIF(Incl!A:A,Raw!J71),1, "")
A72: 69 | B72: 1 | C72: 329.79941 | D72: 69 | E72: 1 | F72: 98 | G72: 80 | H72: 80 | I72: 80 | J72: 80 | K72: Broadway | L72: Meadow Glen Ave | M72: Parking Lot | N72: 19 | O72: NA | P72: NA | Q72: 2 | R72: NA | S72: NA | T72: 21 | U72: 20 | V72: 19 | W72: 20 | X72: NA | Y72: 95 | Z72: 90 | AA72: 95 | AB72: 0 | AC72: 3 | AD72: 17 | AE72: 19 | AF72: 19 | AG72: NA | AH72: 81 | AI72: 90 | AJ72: 90 | AK72: 0 | AL72: 3 | AM72: 20 | AN72: 19 | AO72: 18 | AP72: 20 | AQ72: 19 | AR72: 16 | AS72: 19 | AT72: 18 | AU72: 20 | AV72: 16 | AW72: 102 | AX72: 28 | AY72: 2 | AZ72: 0 | BA72: 1 | BB72: 1 | BC72: 0 | BD72: 0 | BE72: 0 | BF72: 1 | BG72: 135 | BH72: 6.4 | BI72: > 6.0 | BJ72: 17 | BK72: 19 | BL72: 16 | BM72: 16 | BN72: 19 | BO72: 21 | BP72: 21 | BQ72: 21 | BR72: 19 | BS72: 21 | BT72: 86 | BU72: 34 | BV72: 12 | BW72: 0 | BX72: 0 | BY72: 0 | BZ72: 0 | CA72: 0 | CB72: 0 | CC72: 0 | CD72: 132 | CE72: 6.3 | CF72: > 6.0 | CG72: W | CH72: 0.001032 | CI72: 6 | CJ72: 1 | CK72: 1 | CL72: 1 | CM72: 329.79941 | CN72: 1 | CO72: 1 | CP72: <Null> | CQ72: <Null> | CR72: =IF(COUNTIF(Incl!A:A,Raw!J72),1, "") -> 1
A73: 70 | B73: 1 | C73: 327.59974 | D73: 70 | E73: 1 | F73: 99 | G73: 81 | H73: 81 | I73: 81 | J73: 81 | K73: Broadway | L73: Crosswalk | M73: Meadow Glen Ave | N73: 18 | O73: NA | P73: NA | Q73: NA | R73: NA | S73: NA | T73: 18 | U73: 10 | V73: 11 | W73: 9 | X73: NA | Y73: 56 | Z73: 61 | AA73: 50 | AB73: 0 | AC73: 0 | AD73: 9 | AE73: 18 | AF73: 13 | AG73: NA | AH73: 50 | AI73: 100 | AJ73: 72 | AK73: 0 | AL73: 1 | AM73: 10 | AN73: 11 | AO73: 9 | AP73: 9 | AQ73: 11 | AR73: 11 | AS73: 7 | AT73: 10 | AU73: 9 | AV73: 9 | AW73: 62 | AX73: 10 | AY73: 1 | AZ73: 0 | BA73: 1 | BB73: 1 | BC73: 0 | BD73: 0 | BE73: 0 | BF73: 0 | BG73: 75 | BH73: 4.2 | BI73: 4.0 - 5.0 | BJ73: 9 | BK73: 12 | BL73: 10 | BM73: 10 | BN73: 18 | BO73: 14 | BP73: 14 | BQ73: 16 | BR73: 13 | BS73: 11 | BT73: 47 | BU73: 22 | BV73: 9 | BW73: 1 | BX73: 1 | BY73: 0 | BZ73: 0 | CA73: 0 | CB73: 0 | CC73: 0 | CD73: 80 | CE73: 4.4 | CF73: 4.0 - 5.0 | CG73: E | CH73: 0.001023 | CI73: 1 | CJ73: 1 | CK73: 1 | CL73: 1 | CM73: 327.59987 | CN73: 1 | CO73: 1 | CP73: <Null> | CQ73: <Null> | CR73: =IF(COUNTIF(Incl!A:A,Raw!J73),1, "") -> 1
A74: 71 | B74: 1 | C74: 327.52223 | D74: 71 | E74: 1 | F74: 100 | G74: 82 | H74: 82 | I74: 82 | J74: 82 | K74: Broadway | L74: Parking Lot | M74: Silva Ave | N74: 9 | O74: NA | P74: NA | Q74: NA | R74: NA | S74: NA | T74: 9 | U74: 9 | V74: 8 | W74: 9 | X74: NA | Y74: 100 | Z74: 89 | AA74: 100 | AB74: 0 | AC74: 3 | AD74: 0 | AE74: 8 | AF74: 9 | AG74: NA | AH74: 0 | AI74: 89 | AJ74: 100 | AK74: 0 | AL74: 2 | AM74: 9 | AN74: 9 | AO74: 8 | AP74: 8 | AQ74: 8 | AR74: 8 | AS74: 9 | AT74: 8 | AU74: 9 | AV74: 9 | AW74: 74 | AX74: 4 | AY74: 1 | AZ74: 0 | BA74: 0 | BB74: 0 | BC74: 0 | BD74: 0 | BE74: 0 | BF74: 0 | BG74: 79 | BH74: 8.8 | BI74: > 6.0 | BJ74: 0 | BK74: 2 | BL74: 7 | BM74: 9 | BN74: 8 | BO74: 8 | BP74: 9 | BQ74: 9 | BR74: 9 | BS74: 9 | BT74: 36 | BU74: 1 | BV74: 2 | BW74: 4 | BX74: 2 | BY74: 0 | BZ74: 0 | CA74: 0 | CB74: 0 | CC74: 0 | CD74: 45 | CE74: 5 | CF74: 4.0 - 5.0 | CG74: W | CH74: 0.001026 | CI74: 5 | CJ74: 1 | CK74: 1 | CL74: 1 | CM74: 327.52223 | CN74: 1 | CO74: 1 | CP74: <Null> | CQ74: <Null> | CR74: =IF(COUNTIF(Incl!A:A,Raw!J74),1, "") -> 1
A75: 72 | B75: 1 | C75: 358.36584 | D75: 72 | E75: 1 | F75: 101 | G75: 83 | H75: 83 | I75: 83 | J75: 83 | K75: Broadway | L75: Silva Ave | M75: Crosswalk | N75: 22 | O75: NA | P75: NA | Q75: 2 | R75: NA | S75: NA | T75: 24 | U75: 13 | V75: 9 | W75: 10 | X75: NA | Y75: 54 | Z75: 38 | AA75: 42 | AB75: 0 | AC75: 0 | AD75: 8 | AE75: 11 | AF75: 13 | AG75: NA | AH75: 33 | AI75: 46 | AJ75: 54 | AK75: 0 | AL75: 0 | AM75: 13 | AN75: 20 | AO75: 19 | AP75: 17 | AQ75: 9 | AR75: 16 | AS75: 12 | AT75: 18 | AU75: 10 | AV75: 10 | AW75: 117 | AX75: 8 | AY75: 1 | AZ75: 0 | BA75: 0 | BB75: 0 | BC75: 0 | BD75: 1 | BE75: 0 | BF75: 0 | BG75: 127 | BH75: 5.3 | BI75: 5.0 - 6.0 | BJ75: 8 | BK75: 10 | BL75: 10 | BM75: 13 | BN75: 11 | BO75: 14 | BP75: 12 | BQ75: 9 | BR75: 13 | BS75: 10 | BT75: 75 | BU75: 16 | BV75: 1 | BW75: 0 | BX75: 0 | BY75: 0 | BZ75: 0 | CA75: 0 | CB75: 0 | CC75: 0 | CD75: 92 | CE75: 3.8 | CF75: 3.0 - 4.0 | CG75: E | CH75: 0.001141 | CI75: 0 | CJ75: 1 | CK75: 1 | CL75: 1 | CM75: 362.53242 | CN75: 1 | CO75: 1 | CP75: <Null> | CQ75: <Null> | CR75: =IF(COUNTIF(Incl!A:A,Raw!J75),1, "") -> 1
A76: 73 | B76: 1 | C76: 277.06535 | D76: 73 | E76: 1 | F76: 102 | G76: 84 | H76: 84 | I76: 84 | J76: 84 | K76: Broadway | L76: Crosswalk | M76: Taylor Blvd | N76: 18 | O76: NA | P76: NA | Q76: 1 | R76: NA | S76: NA | T76: 19 | U76: 19 | V76: 14 | W76: 17 | X76: NA | Y76: 100 | Z76: 74 | AA76: 89 | AB76: 0 | AC76: 2 | AD76: 9 | AE76: 14 | AF76: 16 | AG76: NA | AH76: 47 | AI76: 74 | AJ76: 84 | AK76: 0 | AL76: 1 | AM76: 19 | AN76: 19 | AO76: 19 | AP76: 19 | AQ76: 14 | AR76: 19 | AS76: 17 | AT76: 14 | AU76: 17 | AV76: 9 | AW76: 148 | AX76: 6 | AY76: 2 | AZ76: 0 | BA76: 0 | BB76: 0 | BC76: 0 | BD76: 0 | BE76: 0 | BF76: 0 | BG76: 156 | BH76: 8.2 | BI76: > 6.0 | BJ76: 9 | BK76: 14 | BL76: 17 | BM76: 16 | BN76: 14 | BO76: 13 | BP76: 12 | BQ76: 16 | BR76: 16 | BS76: 17 | BT76: 52 | BU76: 8 | BV76: 1 | BW76: 12 | BX76: 2 | BY76: 1 | BZ76: 0 | CA76: 0 | CB76: 1 | CC76: 0 | CD76: 77 | CE76: 4.1 | CF76: 4.0 - 5.0 | CG76: W | CH76: 0.001613 | CI76: 3 | CJ76: 1 | CK76: 1 | CL76: 1 | CM76: 513.86637 | CN76: 1 | CO76: 1 | CP76: <Null> | CQ76: <Null> | CR76: =IF(COUNTIF(Incl!A:A,Raw!J76),1, "") -> 1
A77: 74 | B77: 1 | C77: 229.82167 | D77: 74 | E77: 1 | F77: 103 | G77: 85 | H77: 85 | I77: 85 | J77: 85 | K77: Broadway | L77: Taylor Blvd | M77: Silva Ave | N77: 24 | O77: NA | P77: NA | Q77: 2 | R77: NA | S77: NA | T77: 26 | U77: 25 | V77: 23 | W77: 18 | X77: NA | Y77: 96 | Z77: 88 | AA77: 69 | AB77: 0 | AC77: 2 | AD77: 15 | AE77: 18 | AF77: 17 | AG77: NA | AH77: 58 | AI77: 69 | AJ77: 65 | AK77: 0 | AL77: 0 | AM77: 25 | AN77: 24 | AO77: 23 | AP77: 22 | AQ77: 23 | AR77: 24 | AS77: 20 | AT77: 17 | AU77: 18 | AV77: 13 | AW77: 168 | AX77: 13 | AY77: 2 | AZ77: 1 | BA77: 1 | BB77: 0 | BC77: 0 | BD77: 0 | BE77: 0 | BF77: 0 | BG77: 185 | BH77: 7.1 | BI77: > 6.0 | BJ77: 15 | BK77: 12 | BL77: 15 | BM77: 23 | BN77: 18 | BO77: 21 | BP77: 18 | BQ77: 18 | BR77: 17 | BS77: 16 | BT77: 110 | BU77: 20 | BV77: 3 | BW77: 1 | BX77: 2 | BY77: 0 | BZ77: 0 | CA77: 0 | CB77: 0 | CC77: 0 | CD77: 136 | CE77: 5.2 | CF77: 5.0 - 6.0 | CG77: E | CH77: 0.001651 | CI77: 2 | CJ77: 1 | CK77: 1 | CL77: 1 | CM77: 526.97777 | CN77: 1 | CO77: 1 | CP77: <Null> | CQ77: <Null> | CR77: =IF(COUNTIF(Incl!A:A,Raw!J77),1, "") -> 1
A78: 75 | B78: 1 | C78: 162.6129 | D78: 77 | E78: 1 | F78: 106 | G78: 194 | H78: 194 | I78: 194 | J78: 194 | K78: Taylor Blvd | L78: Broadway | M78: Magnolia Ave | N78: 5 | O78: NA | P78: NA | Q78: NA | R78: NA | S78: NA | T78: 5 | U78: 2 | V78: 1 | W78: NA | X78: NA | Y78: 44 | Z78: 22 | AA78: 0 | AB78: 0 | AC78: 0 | AD78: 1 | AE78: 1 | AF78: 1 | AG78: NA | AH78: 22 | AI78: 22 | AJ78: 22 | AK78: 0 | AL78: 0 | AM78: 2 | AN78: 2 | AO78: 2 | AP78: 4 | AQ78: 1 | AR78: 0 | AS78: 0 | AT78: 0 | AU78: 0 | AV78: 1 | AW78: 12 | AX78: 0 | AY78: 0 | AZ78: 0 | BA78: 0 | BB78: 0 | BC78: 0 | BD78: 0 | BE78: 0 | BF78: 0 | BG78: 12 | BH78: 2.7 | BI78: 2.0 - 3.0 | BJ78: 1 | BK78: 1 | BL78: 1 | BM78: 1 | BN78: 1 | BO78: 1 | BP78: 1 | BQ78: 1 | BR78: 1 | BS78: 0 | BT78: 0 | BU78: 0 | BV78: 0 | BW78: 0 | BX78: 0 | BY78: 0 | BZ78: 0 | CA78: 0 | CB78: 1 | CC78: 0 | CD78: 1 | CE78: 0.2 | CF78: 0.0 - 1.0 | CG78: N | CH78: 0.000615 | CI78: 0 | CJ78: 1 | CK78: 1 | CL78: 1 | CM78: 190.59527 | CN78: 1 | CO78: 1 | CP78: <Null> | CQ78: <Null> | CR78: =IF(COUNTIF(Incl!A:A,Raw!J78),1, "") -> 1
A79: 76 | B79: 1 | C79: 203.52697 | D79: 78 | E79: 1 | F79: 107 | G79: 114 | H79: 114 | I79: 114 | J79: 114 | K79: El Camino Real | L79: 970 El Camino Driveway | M79: Meadow Glen Ave | N79: NA | O79: NA | P79: NA | Q79: NA | R79: NA | S79: NA | T79: 0 | U79: NA | V79: NA | W79: NA | X79: NA | Y79: 0 | Z79: 0 | AA79: 0 | AB79: 0 | AC79: 0 | AD79: 0 | AE79: 0 | AF79: 0 | AG79: NA | AH79: 0 | AI79: 0 | AJ79: 0 | AK79: 0 | AL79: 0 | AM79: 0 | AN79: 0 | AO79: 0 | AP79: 0 | AQ79: 0 | AR79: 0 | AS79: 0 | AT79: 0 | AU79: 0 | AV79: 0 | AW79: 0 | AX79: 0 | AY79: 0 | AZ79: 0 | BA79: 0 | BB79: 0 | BC79: 0 | BD79: 0 | BE79: 0 | BF79: 0 | BG79: 0 | BH79: 0 | BI79: 0.0 - 1.0 | BJ79: 0 | BK79: 0 | BL79: 0 | BM79: 0 | BN79: 0 | BO79: 0 | BP79: 0 | BQ79: 0 | BR79: 0 | BS79: 0 | BT79: 0 | BU79: 0 | BV79: 0 | BW79: 0 | BX79: 0 | BY79: 0 | BZ79: 0 | CA79: 0 | CB79: 0 | CC79: 0 | CD79: 0 | CE79: 0 | CF79: 0.0 - 1.0 | CG79: E | CH79: 0.000775 | CI79: 0 | CJ79: 2 | CK79: <Null> | CL79: <Null> | CM79: 246.98929 | CN79: 1 | CO79: 1 | CP79: <Null> | CQ79: <Null> | CR79: =IF(COUNTIF(Incl!A:A,Raw!J79),1, "")
A80: 77 | B80: 1 | C80: 372.07898 | D80: 79 | E80: 1 | F80: 108 | G80: 115 | H80: 115 | I80: 115 | J80: 115 | K80: El Camino Real | L80: Mateo Ave | M80: 970 El Camino Driveway | N80: 2 | O80: NA | P80: 7 | Q80: NA | R80: NA | S80: NA | T80: 8 | U80: 1 | V80: 2 | W80: 2 | X80: NA | Y80: 12 | Z80: 24 | AA80: 24 | AB80: 0 | AC80: 0 | AD80: 0 | AE80: 0 | AF80: 0 | AG80: NA | AH80: 0 | AI80: 0 | AJ80: 0 | AK80: 0 | AL80: 0 | AM80: 2 | AN80: 2 | AO80: 2 | AP80: 2 | AQ80: 2 | AR80: 2 | AS80: 2 | AT80: 2 | AU80: 1 | AV80: 1 | AW80: 0 | AX80: 0 | AY80: 0 | AZ80: 0 | BA80: 0 | BB80: 0 | BC80: 0 | BD80: 1 | BE80: 0 | BF80: 1 | BG80: 2 | BH80: 0.2 | BI80: 0.0 - 1.0 | BJ80: 0 | BK80: 0 | BL80: 0 | BM80: 0 | BN80: 0 | BO80: 0 | BP80: 0 | BQ80: 0 | BR80: 0 | BS80: 0 | BT80: 0 | BU80: 0 | BV80: 0 | BW80: 0 | BX80: 0 | BY80: 0 | BZ80: 0 | CA80: 0 | CB80: 0 | CC80: 0 | CD80: 0 | CE80: 0 | CF80: 0.0 - 1.0 | CG80: E | CH80: 0.001011 | CI80: 0 | CJ80: 2 | CK80: <Null> | CL80: <Null> | CM80: 322.38912 | CN80: 1 | CO80: 1 | CP80: <Null> | CQ80: <Null> | CR80: =IF(COUNTIF(Incl!A:A,Raw!J80),1, "")
A81: 78 | B81: 1 | C81: 562.31946 | D81: 80 | E81: 1 | F81: 109 | G81: 113 | H81: 113 | I81: 113 | J81: 113 | K81: El Camino Real | L81: Meadow Glen Ave | M81: Silva Ave | N81: NA | O81: 28 | P81: NA | Q81: NA | R81: NA | S81: NA | T81: 28 | U81: 2 | V81: 6 | W81: 2 | X81: NA | Y81: 7 | Z81: 22 | AA81: 7 | AB81: 0 | AC81: 0 | AD81: 2 | AE81: 7 | AF81: 1 | AG81: NA | AH81: 7 | AI81: 25 | AJ81: 4 | AK81: 0 | AL81: 0 | AM81: 2 | AN81: 2 | AO81: 6 | AP81: 8 | AQ81: 6 | AR81: 8 | AS81: 6 | AT81: 5 | AU81: 2 | AV81: 3 | AW81: 9 | AX81: 0 | AY81: 1 | AZ81: 0 | BA81: 0 | BB81: 2 | BC81: 0 | BD81: 3 | BE81: 0 | BF81: 0 | BG81: 15 | BH81: 0.5 | BI81: 0.0 - 1.0 | BJ81: 2 | BK81: 3 | BL81: 8 | BM81: 6 | BN81: 7 | BO81: 4 | BP81: 5 | BQ81: 4 | BR81: 1 | BS81: 0 | BT81: 4 | BU81: 0 | BV81: 2 | BW81: 0 | BX81: 0 | BY81: 1 | BZ81: 0 | CA81: 3 | CB81: 0 | CC81: 0 | CD81: 10 | CE81: 0.4 | CF81: 0.0 - 1.0 | CG81: W | CH81: 0.002585 | CI81: 0 | CJ81: 1 | CK81: 1 | CL81: 1 | CM81: 825.27255 | CN81: 1 | CO81: 1 | CP81: <Null> | CQ81: <Null> | CR81: =IF(COUNTIF(Incl!A:A,Raw!J81),1, "") -> 1
A82: 79 | B82: 1 | C82: 183.10826 | D82: 81 | E82: 1 | F82: 110 | G82: 116 | H82: 116 | I82: 116 | J82: 116 | K82: El Camino Real | L82: Silva Ave | M82: Mateo Ave | N82: 8 | O82: NA | P82: NA | Q82: NA | R82: NA | S82: NA | T82: 8 | U82: 1 | V82: 1 | W82: NA | X82: NA | Y82: 13 | Z82: 13 | AA82: 0 | AB82: 0 | AC82: 0 | AD82: 2 | AE82: 6 | AF82: 3 | AG82: NA | AH82: 27 | AI82: 80 | AJ82: 40 | AK82: 0 | AL82: 1 | AM82: 1 | AN82: 2 | AO82: 0 | AP82: 0 | AQ82: 1 | AR82: 1 | AS82: 1 | AT82: 0 | AU82: 0 | AV82: 1 | AW82: 5 | AX82: 1 | AY82: 0 | AZ82: 0 | BA82: 0 | BB82: 0 | BC82: 0 | BD82: 0 | BE82: 0 | BF82: 0 | BG82: 6 | BH82: 0.8 | BI82: 0.0 - 1.0 | BJ82: 3 | BK82: 3 | BL82: 6 | BM82: 6 | BN82: 6 | BO82: 6 | BP82: 3 | BQ82: 3 | BR82: 3 | BS82: 3 | BT82: 3 | BU82: 3 | BV82: 5 | BW82: 0 | BX82: 1 | BY82: 1 | BZ82: 1 | CA82: 0 | CB82: 0 | CC82: 0 | CD82: 14 | CE82: 1.9 | CF82: 1.0 - 2.0 | CG82: E | CH82: 0.000507 | CI82: 1 | CJ82: 2 | CK82: <Null> | CL82: <Null> | CM82: 161.84465 | CN82: 1 | CO82: 1 | CP82: <Null> | CQ82: <Null> | CR82: =IF(COUNTIF(Incl!A:A,Raw!J82),1, "")
A83: 80 | B83: 1 | C83: 195.38544 | D83: 83 | E83: 1 | F83: 112 | G83: 118 | H83: 118 | I83: 118 | J83: 118 | K83: El Camino Real | L83: Hermosa Ave | M83: Silva Ave | N83: 6 | O83: NA | P83: NA | Q83: NA | R83: NA | S83: NA | T83: 6 | U83: 1 | V83: 3 | W83: 5 | X83: NA | Y83: 16 | Z83: 49 | AA83: 81 | AB83: 0 | AC83: 1 | AD83: 0 | AE83: 0 | AF83: 5 | AG83: NA | AH83: 0 | AI83: 0 | AJ83: 81 | AK83: 0 | AL83: 1 | AM83: 1 | AN83: 5 | AO83: 2 | AP83: 3 | AQ83: 3 | AR83: 2 | AS83: 2 | AT83: 3 | AU83: 5 | AV83: 5 | AW83: 6 | AX83: 6 | AY83: 1 | AZ83: 0 | BA83: 0 | BB83: 0 | BC83: 0 | BD83: 0 | BE83: 0 | BF83: 1 | BG83: 14 | BH83: 2.3 | BI83: 2.0 - 3.0 | BJ83: 0 | BK83: 0 | BL83: 0 | BM83: 0 | BN83: 0 | BO83: 6 | BP83: 6 | BQ83: 4 | BR83: 5 | BS83: 2 | BT83: 2 | BU83: 4 | BV83: 0 | BW83: 2 | BX83: 1 | BY83: 0 | BZ83: 0 | CA83: 0 | CB83: 0 | CC83: 0 | CD83: 9 | CE83: 1.5 | CF83: 1.0 - 2.0 | CG83: E | CH83: 0.000567 | CI83: 2 | CJ83: 2 | CK83: <Null> | CL83: <Null> | CM83: 176.93692 | CN83: 1 | CO83: 1 | CP83: <Null> | CQ83: <Null> | CR83: =IF(COUNTIF(Incl!A:A,Raw!J83),1, "")
A84: 81 | B84: 1 | C84: 453.95804 | D84: 84 | E84: 1 | F84: 113 | G84: 117 | H84: 117 | I84: 117 | J84: 117 | K84: El Camino Real | L84: Silva Ave | M84: Taylor Blvd | N84: NA | O84: NA | P84: 6 | Q84: NA | R84: NA | S84: NA | T84: 6 | U84: 4 | V84: 4 | W84: 3 | X84: NA | Y84: 70 | Z84: 70 | AA84: 53 | AB84: 0 | AC84: 0 | AD84: 4 | AE84: 3 | AF84: 2 | AG84: NA | AH84: 70 | AI84: 53 | AJ84: 35 | AK84: 0 | AL84: 0 | AM84: 4 | AN84: 4 | AO84: 4 | AP84: 4 | AQ84: 4 | AR84: 3 | AS84: 3 | AT84: 3 | AU84: 3 | AV84: 3 | AW84: 0 | AX84: 0 | AY84: 0 | AZ84: 0 | BA84: 1 | BB84: 0 | BC84: 0 | BD84: 0 | BE84: 0 | BF84: 3 | BG84: 4 | BH84: 0.7 | BI84: 0.0 - 1.0 | BJ84: 4 | BK84: 4 | BL84: 3 | BM84: 3 | BN84: 3 | BO84: 3 | BP84: 3 | BQ84: 3 | BR84: 2 | BS84: 2 | BT84: 0 | BU84: 1 | BV84: 0 | BW84: 0 | BX84: 0 | BY84: 0 | BZ84: 0 | CA84: 1 | CB84: 0 | CC84: 2 | CD84: 4 | CE84: 0.7 | CF84: 0.0 - 1.0 | CG84: W | CH84: 0.001457 | CI84: 0 | CJ84: 1 | CK84: 1 | CL84: 1 | CM84: 460.61915 | CN84: 1 | CO84: 1 | CP84: <Null> | CQ84: <Null> | CR84: =IF(COUNTIF(Incl!A:A,Raw!J84),1, "") -> 1
A85: 82 | B85: 1 | C85: 175.3412 | D85: 85 | E85: 1 | F85: 114 | G85: 119 | H85: 119 | I85: 119 | J85: 119 | K85: El Camino Real | L85: Taylor Blvd | M85: Hermosa Ave | N85: 8 | O85: NA | P85: NA | Q85: NA | R85: NA | S85: NA | T85: 8 | U85: 2 | V85: 1 | W85: 6 | X85: NA | Y85: 24 | Z85: 12 | AA85: 71 | AB85: 0 | AC85: 0 | AD85: 0 | AE85: 0 | AF85: 4 | AG85: NA | AH85: 0 | AI85: 0 | AJ85: 48 | AK85: 0 | AL85: 0 | AM85: 2 | AN85: 2 | AO85: 2 | AP85: 3 | AQ85: 1 | AR85: 0 | AS85: 1 | AT85: 2 | AU85: 6 | AV85: 7 | AW85: 7 | AX85: 7 | AY85: 0 | AZ85: 0 | BA85: 1 | BB85: 0 | BC85: 0 | BD85: 0 | BE85: 0 | BF85: 0 | BG85: 15 | BH85: 1.8 | BI85: 1.0 - 2.0 | BJ85: 0 | BK85: 0 | BL85: 0 | BM85: 0 | BN85: 0 | BO85: 3 | BP85: 6 | BQ85: 6 | BR85: 4 | BS85: 1 | BT85: 2 | BU85: 2 | BV85: 2 | BW85: 2 | BX85: 0 | BY85: 0 | BZ85: 0 | CA85: 0 | CB85: 0 | CC85: 0 | CD85: 8 | CE85: 1 | CF85: 0.0 - 1.0 | CG85: E | CH85: 0.000562 | CI85: 0 | CJ85: 2 | CK85: <Null> | CL85: <Null> | CM85: 175.34127 | CN85: 1 | CO85: 1 | CP85: <Null> | CQ85: <Null> | CR85: =IF(COUNTIF(Incl!A:A,Raw!J85),1, "")
A86: 83 | B86: 1 | C86: 506.90036 | D86: 86 | E86: 1 | F86: 115 | G86: 182 | H86: 182 | I86: 182 | J86: 182 | K86: Mateo Ave | L86: Hemlock Ave | M86: El Camino Real | N86: NA | O86: NA | P86: 11 | Q86: NA | R86: NA | S86: NA | T86: 11 | U86: 11 | V86: 10 | W86: 12 | X86: 12 | Y86: 96 | Z86: 88 | AA86: 105 | AB86: 105 | AC86: 4 | AD86: 8 | AE86: 10 | AF86: 11 | AG86: 11 | AH86: 70 | AI86: 88 | AJ86: 96 | AK86: 96 | AL86: 3 | AM86: NA | AN86: NA | AO86: NA | AP86: NA | AQ86: NA | AR86: NA | AS86: NA | AT86: NA | AU86: NA | AV86: NA | AW86: NA | AX86: NA | AY86: NA | AZ86: NA | BA86: NA | BB86: NA | BC86: NA | BD86: NA | BE86: NA | BF86: NA | BG86: NA | BH86: NA | BI86: NA | BJ86: NA | BK86: NA | BL86: NA | BM86: NA | BN86: NA | BO86: NA | BP86: NA | BQ86: NA | BR86: NA | BS86: NA | BT86: NA | BU86: NA | BV86: NA | BW86: NA | BX86: NA | BY86: NA | BZ86: NA | CA86: NA | CB86: NA | CC86: NA | CD86: NA | CE86: NA | CF86: NA | CG86: N | CH86: 0.001639 | CI86: 7 | CJ86: 3 | CK86: <Null> | CL86: <Null> | CM86: 506.90053 | CN86: 2 | CO86: <Null> | CP86: <Null> | CQ86: <Null> | CR86: =IF(COUNTIF(Incl!A:A,Raw!J86),1, "")
A87: 84 | B87: 1 | C87: 496.40464 | D87: 87 | E87: 1 | F87: 116 | G87: 183 | H87: 183 | I87: 183 | J87: 183 | K87: Mateo Ave | L87: El Camino Real | M87: Hemlock Ave | N87: NA | O87: NA | P87: 19 | Q87: NA | R87: NA | S87: NA | T87: 19 | U87: 18 | V87: 18 | W87: 19 | X87: 17 | Y87: 97 | Z87: 97 | AA87: 102 | AB87: 91 | AC87: 4 | AD87: 17 | AE87: 16 | AF87: 15 | AG87: 15 | AH87: 91 | AI87: 86 | AJ87: 81 | AK87: 81 | AL87: 4 | AM87: NA | AN87: NA | AO87: NA | AP87: NA | AQ87: NA | AR87: NA | AS87: NA | AT87: NA | AU87: NA | AV87: NA | AW87: NA | AX87: NA | AY87: NA | AZ87: NA | BA87: NA | BB87: NA | BC87: NA | BD87: NA | BE87: NA | BF87: NA | BG87: NA | BH87: NA | BI87: NA | BJ87: NA | BK87: NA | BL87: NA | BM87: NA | BN87: NA | BO87: NA | BP87: NA | BQ87: NA | BR87: NA | BS87: NA | BT87: NA | BU87: NA | BV87: NA | BW87: NA | BX87: NA | BY87: NA | BZ87: NA | CA87: NA | CB87: NA | CC87: NA | CD87: NA | CE87: NA | CF87: NA | CG87: S | CH87: 0.001605 | CI87: 8 | CJ87: 3 | CK87: <Null> | CL87: <Null> | CM87: 496.40445 | CN87: 2 | CO87: <Null> | CP87: <Null> | CQ87: <Null> | CR87: =IF(COUNTIF(Incl!A:A,Raw!J87),1, "")
A88: 85 | B88: 1 | C88: 486.98463 | D88: 88 | E88: 1 | F88: 117 | G88: 184 | H88: 184 | I88: 184 | J88: 184 | K88: Silva Ave | L88: Hemlock Ave | M88: El Camino Real | N88: NA | O88: NA | P88: 15 | Q88: NA | R88: NA | S88: NA | T88: 15 | U88: 12 | V88: 9 | W88: 11 | X88: 9 | Y88: 82 | Z88: 61 | AA88: 75 | AB88: 61 | AC88: 2 | AD88: 11 | AE88: 11 | AF88: 9 | AG88: 13 | AH88: 75 | AI88: 75 | AJ88: 61 | AK88: 89 | AL88: 3 | AM88: NA | AN88: NA | AO88: NA | AP88: NA | AQ88: NA | AR88: NA | AS88: NA | AT88: NA | AU88: NA | AV88: NA | AW88: NA | AX88: NA | AY88: NA | AZ88: NA | BA88: NA | BB88: NA | BC88: NA | BD88: NA | BE88: NA | BF88: NA | BG88: NA | BH88: NA | BI88: NA | BJ88: NA | BK88: NA | BL88: NA | BM88: NA | BN88: NA | BO88: NA | BP88: NA | BQ88: NA | BR88: NA | BS88: NA | BT88: NA | BU88: NA | BV88: NA | BW88: NA | BX88: NA | BY88: NA | BZ88: NA | CA88: NA | CB88: NA | CC88: NA | CD88: NA | CE88: NA | CF88: NA | CG88: N | CH88: 0.001575 | CI88: 5 | CJ88: 3 | CK88: <Null> | CL88: <Null> | CM88: 486.98454 | CN88: 2 | CO88: <Null> | CP88: <Null> | CQ88: <Null> | CR88: =IF(COUNTIF(Incl!A:A,Raw!J88),1, "")
A89: 86 | B89: 1 | C89: 435.8019 | D89: 89 | E89: 1 | F89: 118 | G89: 185 | H89: 185 | I89: 185 | J89: 185 | K89: Silva Ave | L89: El Camino Real | M89: Hemlock Ave | N89: NA | O89: NA | P89: 13 | Q89: NA | R89: NA | S89: NA | T89: 13 | U89: 13 | V89: 13 | W89: 13 | X89: 12 | Y89: 97 | Z89: 97 | AA89: 97 | AB89: 90 | AC89: 4 | AD89: 11 | AE89: 12 | AF89: 12 | AG89: 13 | AH89: 82 | AI89: 90 | AJ89: 90 | AK89: 97 | AL89: 4 | AM89: NA | AN89: NA | AO89: NA | AP89: NA | AQ89: NA | AR89: NA | AS89: NA | AT89: NA | AU89: NA | AV89: NA | AW89: NA | AX89: NA | AY89: NA | AZ89: NA | BA89: NA | BB89: NA | BC89: NA | BD89: NA | BE89: NA | BF89: NA | BG89: NA | BH89: NA | BI89: NA | BJ89: NA | BK89: NA | BL89: NA | BM89: NA | BN89: NA | BO89: NA | BP89: NA | BQ89: NA | BR89: NA | BS89: NA | BT89: NA | BU89: NA | BV89: NA | BW89: NA | BX89: NA | BY89: NA | BZ89: NA | CA89: NA | CB89: NA | CC89: NA | CD89: NA | CE89: NA | CF89: NA | CG89: S | CH89: 0.00141 | CI89: 8 | CJ89: 3 | CK89: <Null> | CL89: <Null> | CM89: 435.8019 | CN89: 2 | CO89: <Null> | CP89: <Null> | CQ89: <Null> | CR89: =IF(COUNTIF(Incl!A:A,Raw!J89),1, "")
A90: 87 | B90: 1 | C90: 437.57265 | D90: 90 | E90: 1 | F90: 119 | G90: 186 | H90: 186 | I90: 186 | J90: 186 | K90: Hermosa Ave | L90: Hemlock Ave | M90: El Camino Real | N90: NA | O90: NA | P90: 16 | Q90: NA | R90: NA | S90: NA | T90: 16 | U90: 17 | V90: 13 | W90: 13 | X90: 12 | Y90: 104 | Z90: 79 | AA90: 79 | AB90: 73 | AC90: 3 | AD90: 14 | AE90: 14 | AF90: 13 | AG90: 16 | AH90: 85 | AI90: 85 | AJ90: 79 | AK90: 98 | AL90: 4 | AM90: NA | AN90: NA | AO90: NA | AP90: NA | AQ90: NA | AR90: NA | AS90: NA | AT90: NA | AU90: NA | AV90: NA | AW90: NA | AX90: NA | AY90: NA | AZ90: NA | BA90: NA | BB90: NA | BC90: NA | BD90: NA | BE90: NA | BF90: NA | BG90: NA | BH90: NA | BI90: NA | BJ90: NA | BK90: NA | BL90: NA | BM90: NA | BN90: NA | BO90: NA | BP90: NA | BQ90: NA | BR90: NA | BS90: NA | BT90: NA | BU90: NA | BV90: NA | BW90: NA | BX90: NA | BY90: NA | BZ90: NA | CA90: NA | CB90: NA | CC90: NA | CD90: NA | CE90: NA | CF90: NA | CG90: N | CH90: 0.001416 | CI90: 7 | CJ90: 3 | CK90: <Null> | CL90: <Null> | CM90: 437.57267 | CN90: 2 | CO90: <Null> | CP90: <Null> | CQ90: <Null> | CR90: =IF(COUNTIF(Incl!A:A,Raw!J90),1, "")
A91: 88 | B91: 1 | C91: 428.31646 | D91: 91 | E91: 1 | F91: 120 | G91: 187 | H91: 187 | I91: 187 | J91: 187 | K91: Hermosa Ave | L91: El Camino Real | M91: Hemlock Ave | N91: NA | O91: NA | P91: 18 | Q91: NA | R91: NA | S91: NA | T91: 18 | U91: 19 | V91: 17 | W91: 16 | X91: 17 | Y91: 108 | Z91: 97 | AA91: 91 | AB91: 97 | AC91: 4 | AD91: 16 | AE91: 18 | AF91: 17 | AG91: 18 | AH91: 91 | AI91: 102 | AJ91: 97 | AK91: 102 | AL91: 4 | AM91: NA | AN91: NA | AO91: NA | AP91: NA | AQ91: NA | AR91: NA | AS91: NA | AT91: NA | AU91: NA | AV91: NA | AW91: NA | AX91: NA | AY91: NA | AZ91: NA | BA91: NA | BB91: NA | BC91: NA | BD91: NA | BE91: NA | BF91: NA | BG91: NA | BH91: NA | BI91: NA | BJ91: NA | BK91: NA | BL91: NA | BM91: NA | BN91: NA | BO91: NA | BP91: NA | BQ91: NA | BR91: NA | BS91: NA | BT91: NA | BU91: NA | BV91: NA | BW91: NA | BX91: NA | BY91: NA | BZ91: NA | CA91: NA | CB91: NA | CC91: NA | CD91: NA | CE91: NA | CF91: NA | CG91: S | CH91: 0.001376 | CI91: 8 | CJ91: 3 | CK91: <Null> | CL91: <Null> | CM91: 428.31648 | CN91: 2 | CO91: <Null> | CP91: <Null> | CQ91: <Null> | CR91: =IF(COUNTIF(Incl!A:A,Raw!J91),1, "")
A92: 89 | B92: 1 | C92: 123.45095 | D92: 92 | E92: 1 | F92: 121 | G92: 136 | H92: 136 | I92: 136 | J92: 136 | K92: Hemlock Ave | L92: End | M92: Mateo Ave | N92: NA | O92: NA | P92: 5 | Q92: NA | R92: NA | S92: NA | T92: 5 | U92: 4 | V92: 3 | W92: 4 | X92: 4 | Y92: 83 | Z92: 63 | AA92: 83 | AB92: 83 | AC92: 3 | AD92: 4 | AE92: 1 | AF92: 3 | AG92: 5 | AH92: 83 | AI92: 21 | AJ92: 63 | AK92: 104 | AL92: 2 | AM92: NA | AN92: NA | AO92: NA | AP92: NA | AQ92: NA | AR92: NA | AS92: NA | AT92: NA | AU92: NA | AV92: NA | AW92: NA | AX92: NA | AY92: NA | AZ92: NA | BA92: NA | BB92: NA | BC92: NA | BD92: NA | BE92: NA | BF92: NA | BG92: NA | BH92: NA | BI92: NA | BJ92: NA | BK92: NA | BL92: NA | BM92: NA | BN92: NA | BO92: NA | BP92: NA | BQ92: NA | BR92: NA | BS92: NA | BT92: NA | BU92: NA | BV92: NA | BW92: NA | BX92: NA | BY92: NA | BZ92: NA | CA92: NA | CB92: NA | CC92: NA | CD92: NA | CE92: NA | CF92: NA | CG92: W | CH92: 0.000371 | CI92: 5 | CJ92: 3 | CK92: <Null> | CL92: <Null> | CM92: 123.45106 | CN92: 2 | CO92: <Null> | CP92: <Null> | CQ92: <Null> | CR92: =IF(COUNTIF(Incl!A:A,Raw!J92),1, "")
A93: 90 | B93: 1 | C93: 833.82225 | D93: 93 | E93: 1 | F93: 122 | G93: 138 | H93: 138 | I93: 138 | J93: 138 | K93: Hemlock Ave | L93: Curve | M93: End | N93: NA | O93: NA | P93: 32 | Q93: NA | R93: NA | S93: NA | T93: 32 | U93: 11 | V93: 11 | W93: 12 | X93: 11 | Y93: 34 | Z93: 34 | AA93: 38 | AB93: 34 | AC93: 0 | AD93: 15 | AE93: 13 | AF93: 14 | AG93: 16 | AH93: 47 | AI93: 41 | AJ93: 44 | AK93: 50 | AL93: 0 | AM93: NA | AN93: NA | AO93: NA | AP93: NA | AQ93: NA | AR93: NA | AS93: NA | AT93: NA | AU93: NA | AV93: NA | AW93: NA | AX93: NA | AY93: NA | AZ93: NA | BA93: NA | BB93: NA | BC93: NA | BD93: NA | BE93: NA | BF93: NA | BG93: NA | BH93: NA | BI93: NA | BJ93: NA | BK93: NA | BL93: NA | BM93: NA | BN93: NA | BO93: NA | BP93: NA | BQ93: NA | BR93: NA | BS93: NA | BT93: NA | BU93: NA | BV93: NA | BW93: NA | BX93: NA | BY93: NA | BZ93: NA | CA93: NA | CB93: NA | CC93: NA | CD93: NA | CE93: NA | CF93: NA | CG93: E | CH93: 0.002538 | CI93: 0 | CJ93: 3 | CK93: <Null> | CL93: <Null> | CM93: 833.82243 | CN93: 2 | CO93: <Null> | CP93: <Null> | CQ93: <Null> | CR93: =IF(COUNTIF(Incl!A:A,Raw!J93),1, "")
A94: 91 | B94: 1 | C94: 499.7872 | D94: 94 | E94: 1 | F94: 123 | G94: 141 | H94: 141 | I94: 141 | J94: 141 | K94: Hemlock Ave | L94: Hillcrest Blvd | M94: Curve | N94: NA | O94: NA | P94: NA | Q94: NA | R94: NA | S94: 13 | T94: 13 | U94: 9 | V94: 3 | W94: 3 | X94: 4 | Y94: 67 | Z94: 22 | AA94: 22 | AB94: 30 | AC94: 0 | AD94: 9 | AE94: 7 | AF94: 9 | AG94: 12 | AH94: 67 | AI94: 52 | AJ94: 67 | AK94: 90 | AL94: 1 | AM94: NA | AN94: NA | AO94: NA | AP94: NA | AQ94: NA | AR94: NA | AS94: NA | AT94: NA | AU94: NA | AV94: NA | AW94: NA | AX94: NA | AY94: NA | AZ94: NA | BA94: NA | BB94: NA | BC94: NA | BD94: NA | BE94: NA | BF94: NA | BG94: NA | BH94: NA | BI94: NA | BJ94: NA | BK94: NA | BL94: NA | BM94: NA | BN94: NA | BO94: NA | BP94: NA | BQ94: NA | BR94: NA | BS94: NA | BT94: NA | BU94: NA | BV94: NA | BW94: NA | BX94: NA | BY94: NA | BZ94: NA | CA94: NA | CB94: NA | CC94: NA | CD94: NA | CE94: NA | CF94: NA | CG94: E | CH94: 0.00147 | CI94: 1 | CJ94: 3 | CK94: <Null> | CL94: <Null> | CM94: 499.78747 | CN94: 2 | CO94: <Null> | CP94: <Null> | CQ94: <Null> | CR94: =IF(COUNTIF(Incl!A:A,Raw!J94),1, "")
A95: 92 | B95: 1 | C95: 696.57728 | D95: 95 | E95: 1 | F95: 124 | G95: 140 | H95: 140 | I95: 140 | J95: 140 | K95: Hemlock Ave | L95: Hermosa Ave | M95: Hillcrest Blvd | N95: NA | O95: NA | P95: NA | Q95: NA | R95: NA | S95: 15 | T95: 15 | U95: 2 | V95: 8 | W95: 10 | X95: 11 | Y95: 13 | Z95: 52 | AA95: 65 | AB95: 72 | AC95: 0 | AD95: 8 | AE95: 6 | AF95: 10 | AG95: 13 | AH95: 52 | AI95: 39 | AJ95: 65 | AK95: 85 | AL95: 1 | AM95: NA | AN95: NA | AO95: NA | AP95: NA | AQ95: NA | AR95: NA | AS95: NA | AT95: NA | AU95: NA | AV95: NA | AW95: NA | AX95: NA | AY95: NA | AZ95: NA | BA95: NA | BB95: NA | BC95: NA | BD95: NA | BE95: NA | BF95: NA | BG95: NA | BH95: NA | BI95: NA | BJ95: NA | BK95: NA | BL95: NA | BM95: NA | BN95: NA | BO95: NA | BP95: NA | BQ95: NA | BR95: NA | BS95: NA | BT95: NA | BU95: NA | BV95: NA | BW95: NA | BX95: NA | BY95: NA | BZ95: NA | CA95: NA | CB95: NA | CC95: NA | CD95: NA | CE95: NA | CF95: NA | CG95: W | CH95: 0.002093 | CI95: 1 | CJ95: 3 | CK95: <Null> | CL95: <Null> | CM95: 696.57728 | CN95: 2 | CO95: <Null> | CP95: <Null> | CQ95: <Null> | CR95: =IF(COUNTIF(Incl!A:A,Raw!J95),1, "")
A96: 93 | B96: 1 | C96: 444.39958 | D96: 96 | E96: 1 | F96: 125 | G96: 122 | H96: 122 | I96: 122 | J96: 122 | K96: El Camino Real | L96: Hillcrest Blvd | M96: Taylor Blvd | N96: 10 | O96: NA | P96: NA | Q96: NA | R96: NA | S96: NA | T96: 10 | U96: 6 | V96: 6 | W96: 7 | X96: NA | Y96: 59 | Z96: 59 | AA96: 69 | AB96: 0 | AC96: 0 | AD96: 0 | AE96: 0 | AF96: 0 | AG96: NA | AH96: 0 | AI96: 0 | AJ96: 0 | AK96: 0 | AL96: 0 | AM96: 6 | AN96: 6 | AO96: 8 | AP96: 6 | AQ96: 6 | AR96: 4 | AS96: 5 | AT96: 7 | AU96: 7 | AV96: 7 | AW96: 12 | AX96: 1 | AY96: 6 | AZ96: 5 | BA96: 2 | BB96: 0 | BC96: 0 | BD96: 0 | BE96: 0 | BF96: 0 | BG96: 26 | BH96: 2.6 | BI96: 2.0 - 3.0 | BJ96: 0 | BK96: 0 | BL96: 0 | BM96: 0 | BN96: 0 | BO96: 0 | BP96: 0 | BQ96: 0 | BR96: 0 | BS96: 0 | BT96: 0 | BU96: 0 | BV96: 0 | BW96: 0 | BX96: 0 | BY96: 0 | BZ96: 0 | CA96: 0 | CB96: 0 | CC96: 0 | CD96: 0 | CE96: 0 | CF96: 0.0 - 1.0 | CG96: E | CH96: 0.001398 | CI96: 0 | CJ96: 2 | CK96: <Null> | CL96: <Null> | CM96: 444.39943 | CN96: 1 | CO96: 1 | CP96: <Null> | CQ96: <Null> | CR96: =IF(COUNTIF(Incl!A:A,Raw!J96),1, "")
A97: 94 | B97: 1 | C97: 170.98382 | D97: 97 | E97: 1 | F97: 126 | G97: 196 | H97: 196 | I97: 196 | J97: 196 | K97: Taylor Blvd | L97: El Camino Real | M97: Broadway | N97: 5 | O97: NA | P97: NA | Q97: NA | R97: NA | S97: NA | T97: 5 | U97: 5 | V97: 4 | W97: 2 | X97: NA | Y97: 93 | Z97: 74 | AA97: 37 | AB97: 0 | AC97: 1 | AD97: 3 | AE97: 2 | AF97: 1 | AG97: NA | AH97: 56 | AI97: 37 | AJ97: 19 | AK97: 0 | AL97: 0 | AM97: 5 | AN97: 5 | AO97: 4 | AP97: 5 | AQ97: 4 | AR97: 3 | AS97: 4 | AT97: 2 | AU97: 2 | AV97: 4 | AW97: 13 | AX97: 5 | AY97: 0 | AZ97: 0 | BA97: 0 | BB97: 0 | BC97: 1 | BD97: 1 | BE97: 0 | BF97: 0 | BG97: 20 | BH97: 3.7 | BI97: 3.0 - 4.0 | BJ97: 3 | BK97: 1 | BL97: 3 | BM97: 4 | BN97: 2 | BO97: 4 | BP97: 4 | BQ97: 3 | BR97: 1 | BS97: 3 | BT97: 8 | BU97: 3 | BV97: 2 | BW97: 0 | BX97: 0 | BY97: 0 | BZ97: 0 | CA97: 1 | CB97: 0 | CC97: 0 | CD97: 14 | CE97: 2.6 | CF97: 2.0 - 3.0 | CG97: N | CH97: 0.000598 | CI97: 1 | CJ97: 1 | CK97: 1 | CL97: 1 | CM97: 185.36315 | CN97: 1 | CO97: 1 | CP97: <Null> | CQ97: <Null> | CR97: =IF(COUNTIF(Incl!A:A,Raw!J97),1, "") -> 1
A98: 95 | B98: 1 | C98: 569.04486 | D98: 98 | E98: 1 | F98: 127 | G98: 193 | H98: 193 | I98: 193 | J98: 193 | K98: Taylor Blvd | L98: Poplar Ave | M98: Magnolia Ave | N98: NA | O98: NA | P98: NA | Q98: NA | R98: NA | S98: 21 | T98: 21 | U98: 9 | V98: 9 | W98: 10 | X98: 12 | Y98: 42 | Z98: 42 | AA98: 47 | AB98: 57 | AC98: 0 | AD98: 9 | AE98: 10 | AF98: 8 | AG98: 13 | AH98: 42 | AI98: 47 | AJ98: 38 | AK98: 61 | AL98: 0 | AM98: NA | AN98: NA | AO98: NA | AP98: NA | AQ98: NA | AR98: NA | AS98: NA | AT98: NA | AU98: NA | AV98: NA | AW98: NA | AX98: NA | AY98: NA | AZ98: NA | BA98: NA | BB98: NA | BC98: NA | BD98: NA | BE98: NA | BF98: NA | BG98: NA | BH98: NA | BI98: NA | BJ98: NA | BK98: NA | BL98: NA | BM98: NA | BN98: NA | BO98: NA | BP98: NA | BQ98: NA | BR98: NA | BS98: NA | BT98: NA | BU98: NA | BV98: NA | BW98: NA | BX98: NA | BY98: NA | BZ98: NA | CA98: NA | CB98: NA | CC98: NA | CD98: NA | CE98: NA | CF98: NA | CG98: S | CH98: 0.001742 | CI98: 0 | CJ98: 3 | CK98: <Null> | CL98: <Null> | CM98: 565.34123 | CN98: 2 | CO98: <Null> | CP98: <Null> | CQ98: <Null> | CR98: =IF(COUNTIF(Incl!A:A,Raw!J98),1, "")
A99: 96 | B99: 1 | C99: 191.40633 | D99: 99 | E99: 1 | F99: 128 | G99: 195 | H99: 195 | I99: 195 | J99: 195 | K99: Taylor Blvd | L99: Magnolia Ave | M99: Broadway | N99: 4 | O99: NA | P99: NA | Q99: NA | R99: NA | S99: NA | T99: 4 | U99: 3 | V99: 3 | W99: 1 | X99: NA | Y99: 78 | Z99: 78 | AA99: 26 | AB99: 0 | AC99: 2 | AD99: 3 | AE99: 4 | AF99: 3 | AG99: NA | AH99: 78 | AI99: 104 | AJ99: 78 | AK99: 0 | AL99: 3 | AM99: 3 | AN99: 2 | AO99: 3 | AP99: 3 | AQ99: 3 | AR99: 1 | AS99: 2 | AT99: 2 | AU99: 1 | AV99: 2 | AW99: 9 | AX99: 0 | AY99: 0 | AZ99: 0 | BA99: 1 | BB99: 0 | BC99: 0 | BD99: 1 | BE99: 0 | BF99: 0 | BG99: 11 | BH99: 2.9 | BI99: 2.0 - 3.0 | BJ99: 3 | BK99: 4 | BL99: 3 | BM99: 4 | BN99: 4 | BO99: 3 | BP99: 3 | BQ99: 4 | BR99: 3 | BS99: 2 | BT99: 10 | BU99: 2 | BV99: 1 | BW99: 1 | BX99: 0 | BY99: 2 | BZ99: 0 | CA99: 0 | CB99: 0 | CC99: 0 | CD99: 16 | CE99: 4.2 | CF99: 4.0 - 5.0 | CG99: S | CH99: 0.000613 | CI99: 5 | CJ99: 1 | CK99: 1 | CL99: 1 | CM99: 189.72935 | CN99: 1 | CO99: 1 | CP99: <Null> | CQ99: <Null> | CR99: =IF(COUNTIF(Incl!A:A,Raw!J99),1, "") -> 1
A100: 97 | B100: 1 | C100: 232.56561 | D100: 100 | E100: 1 | F100: 129 | G100: 197 | H100: 197 | I100: 197 | J100: 197 | K100: Taylor Blvd | L100: Broadway | M100: El Camino Real | N100: 3 | O100: NA | P100: NA | Q100: NA | R100: NA | S100: NA | T100: 3 | U100: 2 | V100: 1 | W100: 3 | X100: NA | Y100: 59 | Z100: 29 | AA100: 88 | AB100: 0 | AC100: 1 | AD100: 2 | AE100: 0 | AF100: 1 | AG100: NA | AH100: 59 | AI100: 0 | AJ100: 29 | AK100: 0 | AL100: 0 | AM100: 2 | AN100: 1 | AO100: 2 | AP100: 3 | AQ100: 1 | AR100: 1 | AS100: 1 | AT100: 2 | AU100: 3 | AV100: 3 | AW100: 6 | AX100: 2 | AY100: 0 | AZ100: 0 | BA100: 0 | BB100: 0 | BC100: 0 | BD100: 0 | BE100: 1 | BF100: 0 | BG100: 9 | BH100: 2.6 | BI100: 2.0 - 3.0 | BJ100: 2 | BK100: 2 | BL100: 2 | BM100: 3 | BN100: 0 | BO100: 2 | BP100: 1 | BQ100: 1 | BR100: 1 | BS100: 1 | BT100: 5 | BU100: 1 | BV100: 0 | BW100: 2 | BX100: 0 | BY100: 0 | BZ100: 0 | CA100: 0 | CB100: 0 | CC100: 0 | CD100: 8 | CE100: 2.4 | CF100: 2.0 - 3.0 | CG100: S | CH100: 0.000741 | CI100: 1 | CJ100: 1 | CK100: 1 | CL100: 1 | CM100: 232.56556 | CN100: 1 | CO100: 1 | CP100: <Null> | CQ100: <Null> | CR100: =IF(COUNTIF(Incl!A:A,Raw!J100),1, "") -> 1
...

Sheet All
G1: Observations Where Occupancy > 75% | J1: Vehicles parking 1hr | L1: Turnover Rate | N1: Total Vehicles Count | P1: Total Vehicle Hours | X1: Hourly Chargeable Hours | Z1: Revenue | AD1: Hourly Chargeable Hours (w/ Reduction) | AF1: Revenue | AI1: Long-Term Vehicle Count | AK1: Revenue
A2: Segment | B2: Street | C2: From | D2: To | E2: Side | F2: Parking Supply | G2: Weekday | H2: Weekend | I2: Combined | J2: Weekday | K2: Weekend | L2: Weekday | M2: Weekend | N2: Weekday | O2: Weekend | P2: Weekday | Q2: Weekend | R2: Paid Parking Type | S2: 2-hr Parking | T2: 8-hr Parking | U2: Reduction | X2: Weekday | Y2: Weekend | Z2: Weekly | AA2: Annual | AC2: Supply | AD2: Weekday | AE2: Weekend | AF2: Weekly | AG2: Annual | AI2: Weekday | AJ2: Weekend | AK2: Weekly | AL2: Annual
A3: =Raw!J4 -> 154 | B3: =Raw!K4 -> Park Pl | C3: =Raw!L4 -> El Camino Real | D3: =Raw!M4 -> Park Blvd | E3: =Raw!CG4 -> N | F3: 8 | G3: =Raw!AL4 -> 1 | H3: =Raw!AC4 -> 1 | I3: =SUM(G3:H3) -> 2 | J3: =Raw!BT4 -> 13 | K3: =Raw!AW4 -> 25 | L3: =IF(Raw!CE4 = "NA", "-", Raw!CE4) -> 2 | M3: =IF(Raw!BH4 = "NA", "-", Raw!BH4) -> 2.9 | N3: 16 | O3: 23 | P3: 52 | Q3: 63 | R3: {=_xlfn.IFS(S3="YES", "Hourly", T3="YES", "Flat Rate")} -> Hourly | S3: =IF(Raw!CO4=1, "YES", "") -> YES | T3: =IF(Raw!CO4=2, "YES", "") | U3: =IF(Raw!CP4=1, "YES", "") | V3: Halved! | X3: 25 | Y3: 47 | Z3: =X3*5+Y3 -> 172 | AA3: =X3*261+Y3*52 -> 8969 | AC3: =IF(U3="YES", F3*0.6, F3) -> 8 | AD3: 25 | AE3: 47 | AF3: =AD3*5+AE3 -> 172 | AG3: =AD3*261+AE3*52 -> 8969 | AI3: =N3 -> 16 | AJ3: =O3 -> 23 | AK3: =(AI3*5+AJ3)*5.5 -> 566.5 | AL3: =(AI3*261+AJ3*52)*5.5 -> 29546
A4: =Raw!J5 -> 155 | B4: =Raw!K5 -> Park Pl | C4: =Raw!L5 -> Park Blvd | D4: =Raw!M5 -> El Camino Real | E4: =Raw!CG5 -> S | F4: 9 | G4: =Raw!AL5 -> 2 | H4: =Raw!AC5 -> 2 | I4: =SUM(G4:H4) -> 4 | J4: =Raw!BT5 -> 17 | K4: =Raw!AW5 -> 43 | L4: =IF(Raw!CE5 = "NA", "-", Raw!CE5) -> 2.3 | M4: =IF(Raw!BH5 = "NA", "-", Raw!BH5) -> 3.8 | N4: 20 | O4: 34 | P4: 67 | Q4: 77 | R4: {=_xlfn.IFS(S4="YES", "Hourly", T4="YES", "Flat Rate")} -> Hourly | S4: =IF(Raw!CO5=1, "YES", "") -> YES | T4: =IF(Raw!CO5=2, "YES", "") | U4: =IF(Raw!CP5=1, "YES", "") | V4: Halved! | X4: 32 | Y4: 61 | Z4: =X4*5+Y4 -> 221 | AA4: =X4*261+Y4*52 -> 11524 | AC4: =IF(U4="YES", F4*0.6, F4) -> 9 | AD4: 32 | AE4: 61 | AF4: =AD4*5+AE4 -> 221 | AG4: =AD4*261+AE4*52 -> 11524 | AI4: =N4 -> 20 | AJ4: =O4 -> 34 | AK4: =(AI4*5+AJ4)*5.5 -> 737 | AL4: =(AI4*261+AJ4*52)*5.5 -> 38434
A5: =Raw!J6 -> 156 | B5: =Raw!K6 -> Park Blvd | C5: =Raw!L6 -> Park Pl | D5: =Raw!M6 -> El Camino Real | E5: =Raw!CG6 -> N | F5: 12 | G5: =Raw!AL6 -> 0 | H5: =Raw!AC6 -> 2 | I5: =SUM(G5:H5) -> 2 | J5: =Raw!BT6 -> 19 | K5: =Raw!AW6 -> 82 | L5: =IF(Raw!CE6 = "NA", "-", Raw!CE6) -> 1.7 | M5: =IF(Raw!BH6 = "NA", "-", Raw!BH6) -> 4.4 | N5: 21 | O5: 55 | P5: 61 | Q5: 92 | R5: {=_xlfn.IFS(S5="YES", "Hourly", T5="YES", "Flat Rate")} -> Hourly | S5: =IF(Raw!CO6=1, "YES", "") -> YES | T5: =IF(Raw!CO6=2, "YES", "") | U5: =IF(Raw!CP6=1, "YES", "") | V5: Halved! | X5: 33 | Y5: 61 | Z5: =X5*5+Y5 -> 226 | AA5: =X5*261+Y5*52 -> 11785 | AC5: =IF(U5="YES", F5*0.6, F5) -> 12 | AD5: 33 | AE5: 61 | AF5: =AD5*5+AE5 -> 226 | AG5: =AD5*261+AE5*52 -> 11785 | AI5: =N5 -> 21 | AJ5: =O5 -> 55 | AK5: =(AI5*5+AJ5)*5.5 -> 880 | AL5: =(AI5*261+AJ5*52)*5.5 -> 45875.5
A6: =Raw!J7 -> 157 | B6: =Raw!K7 -> Park Blvd | C6: =Raw!L7 -> Magnolia Ave | D6: =Raw!M7 -> Palmito Dr | E6: =Raw!CG7 -> S | F6: =Raw!T7 -> 14 | G6: =Raw!AL7 -> 4 | H6: =Raw!AC7 -> 0 | I6: =SUM(G6:H6) -> 4 | J6: =Raw!BT7 -> NA | K6: =Raw!AW7 -> NA | L6: =IF(Raw!CE7 = "NA", "-", Raw!CE7) -> - | M6: =IF(Raw!BH7 = "NA", "-", Raw!BH7) -> - | N6: =IF(Raw!CD7 = "NA", "-", Raw!CD7) -> - | O6: =IF(Raw!BG7 = "NA", "-", Raw!BG7) -> - | P6: =IF(Raw!AW7 = "NA", "-", SUMPRODUCT(Raw!$BT$2:$CC$2, Raw!BT7:CC7)) -> - | Q6: =IF(Raw!AW7 = "NA", "-", SUMPRODUCT(Raw!$AW$2:$BF$2, Raw!AW7:BF7)) -> - | R6: {=_xlfn.IFS(S6="YES", "Hourly", T6="YES", "Flat Rate")} -> #N/A | S6: =IF(Raw!CO7=1, "YES", "") | T6: =IF(Raw!CO7=2, "YES", "") | U6: =IF(Raw!CP7=1, "YES", "") | X6: =SUMPRODUCT(Raw!$BT$3:$CC$3, Raw!BT7:CC7) -> 0 | Y6: =SUMPRODUCT(Raw!$BT$3:$CC$3, Raw!BU7:CD7) -> 0 | Z6: =X6*5+Y6 -> 0 | AA6: =X6*261+Y6*52 -> 0 | AC6: =IF(U6="YES", F6*0.6, F6) -> 14 | AD6: =IF(U6="YES",SUMPRODUCT(Raw!$BT$3:$CC$3,Raw!BT7:CC7)*0.6,SUMPRODUCT(Raw!$BT$3:$CC$3,Raw!BT7:CC7)) -> 0 | AE6: =IF(U6="YES",SUMPRODUCT(Raw!$BT$3:$CC$3,Raw!BU7:CD7)*0.6,SUMPRODUCT(Raw!$BT$3:$CC$3,Raw!BU7:CD7)) -> 0 | AF6: =AD6*5+AE6 -> 0 | AG6: =AD6*261+AE6*52 -> 0 | AI6: =N6 -> - | AJ6: =O6 -> - | AK6: =(AI6*5+AJ6)*5.5 -> #VALUE! | AL6: =(AI6*261+AJ6*52)*5.5 -> #VALUE!
A7: =Raw!J8 -> 158 | B7: =Raw!K8 -> Park Blvd | C7: =Raw!L8 -> Palmito Dr | D7: =Raw!M8 -> El Camino Real | E7: =Raw!CG8 -> S | F7: =Raw!T8 -> 11 | G7: =Raw!AL8 -> 0 | H7: =Raw!AC8 -> 1 | I7: =SUM(G7:H7) -> 1 | J7: =Raw!BT8 -> 11 | K7: =Raw!AW8 -> 39 | L7: =IF(Raw!CE8 = "NA", "-", Raw!CE8) -> 1.6 | M7: =IF(Raw!BH8 = "NA", "-", Raw!BH8) -> 4.5 | N7: =IF(Raw!CD8 = "NA", "-", Raw!CD8) -> 18 | O7: =IF(Raw!BG8 = "NA", "-", Raw!BG8) -> 50 | P7: =IF(Raw!AW8 = "NA", "-", SUMPRODUCT(Raw!$BT$2:$CC$2, Raw!BT8:CC8)) -> 41 | Q7: =IF(Raw!AW8 = "NA", "-", SUMPRODUCT(Raw!$AW$2:$BF$2, Raw!AW8:BF8)) -> 71 | R7: {=_xlfn.IFS(S7="YES", "Hourly", T7="YES", "Flat Rate")} -> Hourly | S7: =IF(Raw!CO8=1, "YES", "") -> YES | T7: =IF(Raw!CO8=2, "YES", "") | U7: =IF(Raw!CP8=1, "YES", "") | X7: =SUMPRODUCT(Raw!$BT$3:$CC$3, Raw!BT8:CC8) -> 25 | Y7: =SUMPRODUCT(Raw!$BT$3:$CC$3, Raw!BU8:CD8) -> 49 | Z7: =X7*5+Y7 -> 174 | AA7: =X7*261+Y7*52 -> 9073 | AC7: =IF(U7="YES", F7*0.6, F7) -> 11 | AD7: =IF(U7="YES",SUMPRODUCT(Raw!$BT$3:$CC$3,Raw!BT8:CC8)*0.6,SUMPRODUCT(Raw!$BT$3:$CC$3,Raw!BT8:CC8)) -> 25 | AE7: =IF(U7="YES",SUMPRODUCT(Raw!$BT$3:$CC$3,Raw!BU8:CD8)*0.6,SUMPRODUCT(Raw!$BT$3:$CC$3,Raw!BU8:CD8)) -> 49 | AF7: =AD7*5+AE7 -> 174 | AG7: =AD7*261+AE7*52 -> 9073 | AI7: =N7 -> 18 | AJ7: =O7 -> 50 | AK7: =(AI7*5+AJ7)*5.5 -> 770 | AL7: =(AI7*261+AJ7*52)*5.5 -> 40139
A8: =Raw!J9 -> 100 | B8: =Raw!K9 -> El Camino Real | C8: =Raw!L9 -> Park Pl | D8: =Raw!M9 -> Park Blvd | E8: =Raw!CG9 -> W | F8: =Raw!T9 -> 19 | G8: =Raw!AL9 -> 1 | H8: =Raw!AC9 -> 2 | I8: =SUM(G8:H8) -> 3 | J8: =Raw!BT9 -> 32 | K8: =Raw!AW9 -> 32 | L8: =IF(Raw!CE9 = "NA", "-", Raw!CE9) -> 3.4 | M8: =IF(Raw!BH9 = "NA", "-", Raw!BH9) -> 3.2 | N8: =IF(Raw!CD9 = "NA", "-", Raw!CD9) -> 64 | O8: =IF(Raw!BG9 = "NA", "-", Raw!BG9) -> 59 | P8: =IF(Raw!AW9 = "NA", "-", SUMPRODUCT(Raw!$BT$2:$CC$2, Raw!BT9:CC9)) -> 141 | Q8: =IF(Raw!AW9 = "NA", "-", SUMPRODUCT(Raw!$AW$2:$BF$2, Raw!AW9:BF9)) -> 127 | R8: {=_xlfn.IFS(S8="YES", "Hourly", T8="YES", "Flat Rate")} -> Hourly | S8: =IF(Raw!CO9=1, "YES", "") -> YES | T8: =IF(Raw!CO9=2, "YES", "") | U8: =IF(Raw!CP9=1, "YES", "") | X8: =SUMPRODUCT(Raw!$BT$3:$CC$3, Raw!BT9:CC9) -> 96 | Y8: =SUMPRODUCT(Raw!$BT$3:$CC$3, Raw!BU9:CD9) -> 177 | Z8: =X8*5+Y8 -> 657 | AA8: =X8*261+Y8*52 -> 34260 | AC8: =IF(U8="YES", F8*0.6, F8) -> 19 | AD8: =IF(U8="YES",SUMPRODUCT(Raw!$BT$3:$CC$3,Raw!BT9:CC9)*0.6,SUMPRODUCT(Raw!$BT$3:$CC$3,Raw!BT9:CC9)) -> 96 | AE8: =IF(U8="YES",SUMPRODUCT(Raw!$BT$3:$CC$3,Raw!BU9:CD9)*0.6,SUMPRODUCT(Raw!$BT$3:$CC$3,Raw!BU9:CD9)) -> 177 | AF8: =AD8*5+AE8 -> 657 | AG8: =AD8*261+AE8*52 -> 34260 | AI8: =N8 -> 64 | AJ8: =O8 -> 59 | AK8: =(AI8*5+AJ8)*5.5 -> 2084.5 | AL8: =(AI8*261+AJ8*52)*5.5 -> 108746
A9: =Raw!J10 -> 101 | B9: =Raw!K10 -> El Camino Real | C9: =Raw!L10 -> Santa Clara Ave | D9: =Raw!M10 -> Santa Inez Ave | E9: =Raw!CG10 -> E | F9: =Raw!T10 -> 5 | G9: =Raw!AL10 -> 2 | H9: =Raw!AC10 -> 1 | I9: =SUM(G9:H9) -> 3 | J9: =Raw!BT10 -> 3 | K9: =Raw!AW10 -> 8 | L9: =IF(Raw!CE10 = "NA", "-", Raw!CE10) -> 2.9 | M9: =IF(Raw!BH10 = "NA", "-", Raw!BH10) -> 2.4 | N9: =IF(Raw!CD10 = "NA", "-", Raw!CD10) -> 14 | O9: =IF(Raw!BG10 = "NA", "-", Raw!BG10) -> 12 | P9: =IF(Raw!AW10 = "NA", "-", SUMPRODUCT(Raw!$BT$2:$CC$2, Raw!BT10:CC10)) -> 38 | Q9: =IF(Raw!AW10 = "NA", "-", SUMPRODUCT(Raw!$AW$2:$BF$2, Raw!AW10:BF10)) -> 24 | R9: {=_xlfn.IFS(S9="YES", "Hourly", T9="YES", "Flat Rate")} -> Hourly | S9: =IF(Raw!CO10=1, "YES", "") -> YES | T9: =IF(Raw!CO10=2, "YES", "") | U9: =IF(Raw!CP10=1, "YES", "") | X9: =SUMPRODUCT(Raw!$BT$3:$CC$3, Raw!BT10:CC10) -> 25 | Y9: =SUMPRODUCT(Raw!$BT$3:$CC$3, Raw!BU10:CD10) -> 43 | Z9: =X9*5+Y9 -> 168 | AA9: =X9*261+Y9*52 -> 8761 | AC9: =IF(U9="YES", F9*0.6, F9) -> 5 | AD9: =IF(U9="YES",SUMPRODUCT(Raw!$BT$3:$CC$3,Raw!BT10:CC10)*0.6,SUMPRODUCT(Raw!$BT$3:$CC$3,Raw!BT10:CC10)) -> 25 | AE9: =IF(U9="YES",SUMPRODUCT(Raw!$BT$3:$CC$3,Raw!BU10:CD10)*0.6,SUMPRODUCT(Raw!$BT$3:$CC$3,Raw!BU10:CD10)) -> 43 | AF9: =AD9*5+AE9 -> 168 | AG9: =AD9*261+AE9*52 -> 8761 | AI9: =N9 -> 14 | AJ9: =O9 -> 12 | AK9: =(AI9*5+AJ9)*5.5 -> 451 | AL9: =(AI9*261+AJ9*52)*5.5 -> 23529
A10: =Raw!J11 -> 102 | B10: =Raw!K11 -> El Camino Real | C10: =Raw!L11 -> San Diego Ave | D10: =Raw!M11 -> Santa Clara Ave | E10: =Raw!CG11 -> E | F10: =Raw!T11 -> 8 | G10: =Raw!AL11 -> 1 | H10: =Raw!AC11 -> 1 | I10: =SUM(G10:H10) -> 2 | J10: =Raw!BT11 -> 7 | K10: =Raw!AW11 -> 6 | L10: =IF(Raw!CE11 = "NA", "-", Raw!CE11) -> 1.5 | M10: =IF(Raw!BH11 = "NA", "-", Raw!BH11) -> 2.4 | N10: =IF(Raw!CD11 = "NA", "-", Raw!CD11) -> 13 | O10: =IF(Raw!BG11 = "NA", "-", Raw!BG11) -> 20 | P10: =IF(Raw!AW11 = "NA", "-", SUMPRODUCT(Raw!$BT$2:$CC$2, Raw!BT11:CC11)) -> 21 | Q10: =IF(Raw!AW11 = "NA", "-", SUMPRODUCT(Raw!$AW$2:$BF$2, Raw!AW11:BF11)) -> 50 | R10: {=_xlfn.IFS(S10="YES", "Hourly", T10="YES", "Flat Rate")} -> Hourly | S10: =IF(Raw!CO11=1, "YES", "") -> YES | T10: =IF(Raw!CO11=2, "YES", "") | U10: =IF(Raw!CP11=1, "YES", "") | X10: =SUMPRODUCT(Raw!$BT$3:$CC$3, Raw!BT11:CC11) -> 19 | Y10: =SUMPRODUCT(Raw!$BT$3:$CC$3, Raw!BU11:CD11) -> 34 | Z10: =X10*5+Y10 -> 129 | AA10: =X10*261+Y10*52 -> 6727 | AC10: =IF(U10="YES", F10*0.6, F10) -> 8 | AD10: =IF(U10="YES",SUMPRODUCT(Raw!$BT$3:$CC$3,Raw!BT11:CC11)*0.6,SUMPRODUCT(Raw!$BT$3:$CC$3,Raw!BT11:CC11)) -> 19 | AE10: =IF(U10="YES",SUMPRODUCT(Raw!$BT$3:$CC$3,Raw!BU11:CD11)*0.6,SUMPRODUCT(Raw!$BT$3:$CC$3,Raw!BU11:CD11)) -> 34 | AF10: =AD10*5+AE10 -> 129 | AG10: =AD10*261+AE10*52 -> 6727 | AI10: =N10 -> 13 | AJ10: =O10 -> 20 | AK10: =(AI10*5+AJ10)*5.5 -> 467.5 | AL10: =(AI10*261+AJ10*52)*5.5 -> 24381.5
A11: =Raw!J12 -> 104 | B11: =Raw!K12 -> El Camino Real | C11: =Raw!L12 -> Santa Maria Ave | D11: =Raw!M12 -> San Diego Ave | E11: =Raw!CG12 -> E | F11: =Raw!T12 -> 5 | G11: =Raw!AL12 -> 0 | H11: =Raw!AC12 -> 0 | I11: =SUM(G11:H11) -> 0 | J11: =Raw!BT12 -> 0 | K11: =Raw!AW12 -> 6 | L11: =IF(Raw!CE12 = "NA", "-", Raw!CE12) -> 0.8 | M11: =IF(Raw!BH12 = "NA", "-", Raw!BH12) -> 1.6 | N11: =IF(Raw!CD12 = "NA", "-", Raw!CD12) -> 4 | O11: =IF(Raw!BG12 = "NA", "-", Raw!BG12) -> 8 | P11: =IF(Raw!AW12 = "NA", "-", SUMPRODUCT(Raw!$BT$2:$CC$2, Raw!BT12:CC12)) -> 25 | Q11: =IF(Raw!AW12 = "NA", "-", SUMPRODUCT(Raw!$AW$2:$BF$2, Raw!AW12:BF12)) -> 21 | R11: {=_xlfn.IFS(S11="YES", "Hourly", T11="YES", "Flat Rate")} -> Hourly | S11: =IF(Raw!CO12=1, "YES", "") -> YES | T11: =IF(Raw!CO12=2, "YES", "") | U11: =IF(Raw!CP12=1, "YES", "") | X11: =SUMPRODUCT(Raw!$BT$3:$CC$3, Raw!BT12:CC12) -> 8 | Y11: =SUMPRODUCT(Raw!$BT$3:$CC$3, Raw!BU12:CD12) -> 15 | Z11: =X11*5+Y11 -> 55 | AA11: =X11*261+Y11*52 -> 2868 | AC11: =IF(U11="YES", F11*0.6, F11) -> 5 | AD11: =IF(U11="YES",SUMPRODUCT(Raw!$BT$3:$CC$3,Raw!BT12:CC12)*0.6,SUMPRODUCT(Raw!$BT$3:$CC$3,Raw!BT12:CC12)) -> 8 | AE11: =IF(U11="YES",SUMPRODUCT(Raw!$BT$3:$CC$3,Raw!BU12:CD12)*0.6,SUMPRODUCT(Raw!$BT$3:$CC$3,Raw!BU12:CD12)) -> 15 | AF11: =AD11*5+AE11 -> 55 | AG11: =AD11*261+AE11*52 -> 2868 | AI11: =N11 -> 4 | AJ11: =O11 -> 8 | AK11: =(AI11*5+AJ11)*5.5 -> 154 | AL11: =(AI11*261+AJ11*52)*5.5 -> 8030
A12: =Raw!J13 -> 67 | B12: =Raw!K13 -> Palmito Dr | C12: =Raw!L13 -> Park Blvd | D12: =Raw!M13 -> Alley | E12: =Raw!CG13 -> W | F12: =Raw!T13 -> 4 | G12: =Raw!AL13 -> 0 | H12: =Raw!AC13 -> 3 | I12: =SUM(G12:H12) -> 3 | J12: =Raw!BT13 -> NA | K12: =Raw!AW13 -> NA | L12: =IF(Raw!CE13 = "NA", "-", Raw!CE13) -> - | M12: =IF(Raw!BH13 = "NA", "-", Raw!BH13) -> - | N12: =IF(Raw!CD13 = "NA", "-", Raw!CD13) -> - | O12: =IF(Raw!BG13 = "NA", "-", Raw!BG13) -> - | P12: =IF(Raw!AW13 = "NA", "-", SUMPRODUCT(Raw!$BT$2:$CC$2, Raw!BT13:CC13)) -> - | Q12: =IF(Raw!AW13 = "NA", "-", SUMPRODUCT(Raw!$AW$2:$BF$2, Raw!AW13:BF13)) -> - | R12: {=_xlfn.IFS(S12="YES", "Hourly", T12="YES", "Flat Rate")} -> #N/A | S12: =IF(Raw!CO13=1, "YES", "") | T12: =IF(Raw!CO13=2, "YES", "") | U12: =IF(Raw!CP13=1, "YES", "") | X12: =SUMPRODUCT(Raw!$BT$3:$CC$3, Raw!BT13:CC13) -> 0 | Y12: =SUMPRODUCT(Raw!$BT$3:$CC$3, Raw!BU13:CD13) -> 0 | Z12: =X12*5+Y12 -> 0 | AA12: =X12*261+Y12*52 -> 0 | AC12: =IF(U12="YES", F12*0.6, F12) -> 4 | AD12: =IF(U12="YES",SUMPRODUCT(Raw!$BT$3:$CC$3,Raw!BT13:CC13)*0.6,SUMPRODUCT(Raw!$BT$3:$CC$3,Raw!BT13:CC13)) -> 0 | AE12: =IF(U12="YES",SUMPRODUCT(Raw!$BT$3:$CC$3,Raw!BU13:CD13)*0.6,SUMPRODUCT(Raw!$BT$3:$CC$3,Raw!BU13:CD13)) -> 0 | AF12: =AD12*5+AE12 -> 0 | AG12: =AD12*261+AE12*52 -> 0 | AI12: =N12 -> - | AJ12: =O12 -> - | AK12: =(AI12*5+AJ12)*5.5 -> #VALUE! | AL12: =(AI12*261+AJ12*52)*5.5 -> #VALUE!
A13: =Raw!J14 -> 68 | B13: =Raw!K14 -> Palmito Dr | C13: =Raw!L14 -> Alley | D13: =Raw!M14 -> Park Blvd | E13: =Raw!CG14 -> E | F13: =Raw!T14 -> 0 | G13: =Raw!AL14 -> 0 | H13: =Raw!AC14 -> 0 | I13: =SUM(G13:H13) -> 0 | J13: =Raw!BT14 -> NA | K13: =Raw!AW14 -> NA | L13: =IF(Raw!CE14 = "NA", "-", Raw!CE14) -> - | M13: =IF(Raw!BH14 = "NA", "-", Raw!BH14) -> - | N13: =IF(Raw!CD14 = "NA", "-", Raw!CD14) -> - | O13: =IF(Raw!BG14 = "NA", "-", Raw!BG14) -> - | P13: =IF(Raw!AW14 = "NA", "-", SUMPRODUCT(Raw!$BT$2:$CC$2, Raw!BT14:CC14)) -> - | Q13: =IF(Raw!AW14 = "NA", "-", SUMPRODUCT(Raw!$AW$2:$BF$2, Raw!AW14:BF14)) -> - | R13: {=_xlfn.IFS(S13="YES", "Hourly", T13="YES", "Flat Rate")} -> #N/A | S13: =IF(Raw!CO14=1, "YES", "") | T13: =IF(Raw!CO14=2, "YES", "") | U13: =IF(Raw!CP14=1, "YES", "") | X13: =SUMPRODUCT(Raw!$BT$3:$CC$3, Raw!BT14:CC14) -> 0 | Y13: =SUMPRODUCT(Raw!$BT$3:$CC$3, Raw!BU14:CD14) -> 0 | Z13: =X13*5+Y13 -> 0 | AA13: =X13*261+Y13*52 -> 0 | AC13: =IF(U13="YES", F13*0.6, F13) -> 0 | AD13: =IF(U13="YES",SUMPRODUCT(Raw!$BT$3:$CC$3,Raw!BT14:CC14)*0.6,SUMPRODUCT(Raw!$BT$3:$CC$3,Raw!BT14:CC14)) -> 0 | AE13: =IF(U13="YES",SUMPRODUCT(Raw!$BT$3:$CC$3,Raw!BU14:CD14)*0.6,SUMPRODUCT(Raw!$BT$3:$CC$3,Raw!BU14:CD14)) -> 0 | AF13: =AD13*5+AE13 -> 0 | AG13: =AD13*261+AE13*52 -> 0 | AI13: =N13 -> - | AJ13: =O13 -> - | AK13: =(AI13*5+AJ13)*5.5 -> #VALUE! | AL13: =(AI13*261+AJ13*52)*5.5 -> #VALUE!
A14: =Raw!J15 -> 69 | B14: =Raw!K15 -> Palmito Dr | C14: =Raw!L15 -> Alley | D14: =Raw!M15 -> Capuchino Dr | E14: =Raw!CG15 -> W | F14: =Raw!T15 -> 19 | G14: =Raw!AL15 -> 0 | H14: =Raw!AC15 -> 0 | I14: =SUM(G14:H14) -> 0 | J14: =Raw!BT15 -> NA | K14: =Raw!AW15 -> NA | L14: =IF(Raw!CE15 = "NA", "-", Raw!CE15) -> - | M14: =IF(Raw!BH15 = "NA", "-", Raw!BH15) -> - | N14: =IF(Raw!CD15 = "NA", "-", Raw!CD15) -> - | O14: =IF(Raw!BG15 = "NA", "-", Raw!BG15) -> - | P14: =IF(Raw!AW15 = "NA", "-", SUMPRODUCT(Raw!$BT$2:$CC$2, Raw!BT15:CC15)) -> - | Q14: =IF(Raw!AW15 = "NA", "-", SUMPRODUCT(Raw!$AW$2:$BF$2, Raw!AW15:BF15)) -> - | R14: {=_xlfn.IFS(S14="YES", "Hourly", T14="YES", "Flat Rate")} -> #N/A | S14: =IF(Raw!CO15=1, "YES", "") | T14: =IF(Raw!CO15=2, "YES", "") | U14: =IF(Raw!CP15=1, "YES", "") | X14: =SUMPRODUCT(Raw!$BT$3:$CC$3, Raw!BT15:CC15) -> 0 | Y14: =SUMPRODUCT(Raw!$BT$3:$CC$3, Raw!BU15:CD15) -> 0 | Z14: =X14*5+Y14 -> 0 | AA14: =X14*261+Y14*52 -> 0 | AC14: =IF(U14="YES", F14*0.6, F14) -> 19 | AD14: =IF(U14="YES",SUMPRODUCT(Raw!$BT$3:$CC$3,Raw!BT15:CC15)*0.6,SUMPRODUCT(Raw!$BT$3:$CC$3,Raw!BT15:CC15)) -> 0 | AE14: =IF(U14="YES",SUMPRODUCT(Raw!$BT$3:$CC$3,Raw!BU15:CD15)*0.6,SUMPRODUCT(Raw!$BT$3:$CC$3,Raw!BU15:CD15)) -> 0 | AF14: =AD14*5+AE14 -> 0 | AG14: =AD14*261+AE14*52 -> 0 | AI14: =N14 -> - | AJ14: =O14 -> - | AK14: =(AI14*5+AJ14)*5.5 -> #VALUE! | AL14: =(AI14*261+AJ14*52)*5.5 -> #VALUE!
A15: =Raw!J16 -> 70 | B15: =Raw!K16 -> Palmito Dr | C15: =Raw!L16 -> Capuchino Dr | D15: =Raw!M16 -> Alley | E15: =Raw!CG16 -> E | F15: =Raw!T16 -> 25 | G15: =Raw!AL16 -> 0 | H15: =Raw!AC16 -> 1 | I15: =SUM(G15:H15) -> 1 | J15: =Raw!BT16 -> NA | K15: =Raw!AW16 -> NA | L15: =IF(Raw!CE16 = "NA", "-", Raw!CE16) -> - | M15: =IF(Raw!BH16 = "NA", "-", Raw!BH16) -> - | N15: =IF(Raw!CD16 = "NA", "-", Raw!CD16) -> - | O15: =IF(Raw!BG16 = "NA", "-", Raw!BG16) -> - | P15: =IF(Raw!AW16 = "NA", "-", SUMPRODUCT(Raw!$BT$2:$CC$2, Raw!BT16:CC16)) -> - | Q15: =IF(Raw!AW16 = "NA", "-", SUMPRODUCT(Raw!$AW$2:$BF$2, Raw!AW16:BF16)) -> - | R15: {=_xlfn.IFS(S15="YES", "Hourly", T15="YES", "Flat Rate")} -> #N/A | S15: =IF(Raw!CO16=1, "YES", "") | T15: =IF(Raw!CO16=2, "YES", "") | U15: =IF(Raw!CP16=1, "YES", "") | X15: =SUMPRODUCT(Raw!$BT$3:$CC$3, Raw!BT16:CC16) -> 0 | Y15: =SUMPRODUCT(Raw!$BT$3:$CC$3, Raw!BU16:CD16) -> 0 | Z15: =X15*5+Y15 -> 0 | AA15: =X15*261+Y15*52 -> 0 | AC15: =IF(U15="YES", F15*0.6, F15) -> 25 | AD15: =IF(U15="YES",SUMPRODUCT(Raw!$BT$3:$CC$3,Raw!BT16:CC16)*0.6,SUMPRODUCT(Raw!$BT$3:$CC$3,Raw!BT16:CC16)) -> 0 | AE15: =IF(U15="YES",SUMPRODUCT(Raw!$BT$3:$CC$3,Raw!BU16:CD16)*0.6,SUMPRODUCT(Raw!$BT$3:$CC$3,Raw!BU16:CD16)) -> 0 | AF15: =AD15*5+AE15 -> 0 | AG15: =AD15*261+AE15*52 -> 0 | AI15: =N15 -> - | AJ15: =O15 -> - | AK15: =(AI15*5+AJ15)*5.5 -> #VALUE! | AL15: =(AI15*261+AJ15*52)*5.5 -> #VALUE!
A16: =Raw!J17 -> 99 | B16: =Raw!K17 -> Alley | C16: =Raw!L17 -> Capuchino Dr | D16: =Raw!M17 -> Palmito Dr | E16: =Raw!CG17 -> E | F16: =Raw!T17 -> 0 | G16: =Raw!AL17 -> 0 | H16: =Raw!AC17 -> 0 | I16: =SUM(G16:H16) -> 0 | J16: =Raw!BT17 -> NA | K16: =Raw!AW17 -> NA | L16: =IF(Raw!CE17 = "NA", "-", Raw!CE17) -> - | M16: =IF(Raw!BH17 = "NA", "-", Raw!BH17) -> - | N16: =IF(Raw!CD17 = "NA", "-", Raw!CD17) -> - | O16: =IF(Raw!BG17 = "NA", "-", Raw!BG17) -> - | P16: =IF(Raw!AW17 = "NA", "-", SUMPRODUCT(Raw!$BT$2:$CC$2, Raw!BT17:CC17)) -> - | Q16: =IF(Raw!AW17 = "NA", "-", SUMPRODUCT(Raw!$AW$2:$BF$2, Raw!AW17:BF17)) -> - | R16: {=_xlfn.IFS(S16="YES", "Hourly", T16="YES", "Flat Rate")} -> #N/A | S16: =IF(Raw!CO17=1, "YES", "") | T16: =IF(Raw!CO17=2, "YES", "") | U16: =IF(Raw!CP17=1, "YES", "") | X16: =SUMPRODUCT(Raw!$BT$3:$CC$3, Raw!BT17:CC17) -> 0 | Y16: =SUMPRODUCT(Raw!$BT$3:$CC$3, Raw!BU17:CD17) -> 0 | Z16: =X16*5+Y16 -> 0 | AA16: =X16*261+Y16*52 -> 0 | AC16: =IF(U16="YES", F16*0.6, F16) -> 0 | AD16: =IF(U16="YES",SUMPRODUCT(Raw!$BT$3:$CC$3,Raw!BT17:CC17)*0.6,SUMPRODUCT(Raw!$BT$3:$CC$3,Raw!BT17:CC17)) -> 0 | AE16: =IF(U16="YES",SUMPRODUCT(Raw!$BT$3:$CC$3,Raw!BU17:CD17)*0.6,SUMPRODUCT(Raw!$BT$3:$CC$3,Raw!BU17:CD17)) -> 0 | AF16: =AD16*5+AE16 -> 0 | AG16: =AD16*261+AE16*52 -> 0 | AI16: =N16 -> - | AJ16: =O16 -> - | AK16: =(AI16*5+AJ16)*5.5 -> #VALUE! | AL16: =(AI16*261+AJ16*52)*5.5 -> #VALUE!
A17: =Raw!J18 -> 98 | B17: =Raw!K18 -> Alley | C17: =Raw!L18 -> Palmito Dr | D17: =Raw!M18 -> Capuchino Dr | E17: =Raw!CG18 -> W | F17: =Raw!T18 -> 0 | G17: =Raw!AL18 -> 0 | H17: =Raw!AC18 -> 0 | I17: =SUM(G17:H17) -> 0 | J17: =Raw!BT18 -> NA | K17: =Raw!AW18 -> NA | L17: =IF(Raw!CE18 = "NA", "-", Raw!CE18) -> - | M17: =IF(Raw!BH18 = "NA", "-", Raw!BH18) -> - | N17: =IF(Raw!CD18 = "NA", "-", Raw!CD18) -> - | O17: =IF(Raw!BG18 = "NA", "-", Raw!BG18) -> - | P17: =IF(Raw!AW18 = "NA", "-", SUMPRODUCT(Raw!$BT$2:$CC$2, Raw!BT18:CC18)) -> - | Q17: =IF(Raw!AW18 = "NA", "-", SUMPRODUCT(Raw!$AW$2:$BF$2, Raw!AW18:BF18)) -> - | R17: {=_xlfn.IFS(S17="YES", "Hourly", T17="YES", "Flat Rate")} -> #N/A | S17: =IF(Raw!CO18=1, "YES", "") | T17: =IF(Raw!CO18=2, "YES", "") | U17: =IF(Raw!CP18=1, "YES", "") | X17: =SUMPRODUCT(Raw!$BT$3:$CC$3, Raw!BT18:CC18) -> 0 | Y17: =SUMPRODUCT(Raw!$BT$3:$CC$3, Raw!BU18:CD18) -> 0 | Z17: =X17*5+Y17 -> 0 | AA17: =X17*261+Y17*52 -> 0 | AC17: =IF(U17="YES", F17*0.6, F17) -> 0 | AD17: =IF(U17="YES",SUMPRODUCT(Raw!$BT$3:$CC$3,Raw!BT18:CC18)*0.6,SUMPRODUCT(Raw!$BT$3:$CC$3,Raw!BT18:CC18)) -> 0 | AE17: =IF(U17="YES",SUMPRODUCT(Raw!$BT$3:$CC$3,Raw!BU18:CD18)*0.6,SUMPRODUCT(Raw!$BT$3:$CC$3,Raw!BU18:CD18)) -> 0 | AF17: =AD17*5+AE17 -> 0 | AG17: =AD17*261+AE17*52 -> 0 | AI17: =N17 -> - | AJ17: =O17 -> - | AK17: =(AI17*5+AJ17)*5.5 -> #VALUE! | AL17: =(AI17*261+AJ17*52)*5.5 -> #VALUE!
... A265: =Raw!J266 -> 148 | B265: =Raw!K266 -> Irwin Pl | C265: =Raw!L266 -> Murchison Dr | D265: =Raw!M266 -> California Dr | E265: =Raw!CG266 -> E | F265: =Raw!T266 -> 21 | G265: =Raw!AL266 -> 0 | H265: =Raw!AC266 -> 0 | I265: =SUM(G265:H265) -> 0 | J265: =Raw!BT266 -> 11 | K265: =Raw!AW266 -> 10 | L265: =IF(Raw!CE266 = "NA", "-", Raw!CE266) -> 1.4 | M265: =IF(Raw!BH266 = "NA", "-", Raw!BH266) -> 1 | N265: =IF(Raw!CD266 = "NA", "-", Raw!CD266) -> 28 | O265: =IF(Raw!BG266 = "NA", "-", Raw!BG266) -> 21 | P265: =IF(Raw!AW266 = "NA", "-", SUMPRODUCT(Raw!$BT$2:$CC$2, Raw!BT266:CC266)) -> 95 | Q265: =IF(Raw!AW266 = "NA", "-", SUMPRODUCT(Raw!$AW$2:$BF$2, Raw!AW266:BF266)) -> 46 | R265: {=_xlfn.IFS(S265="YES", "Hourly", T265="YES", "Flat Rate")} -> #N/A | S265: =IF(Raw!CO266=1, "YES", "") | T265: =IF(Raw!CO266=2, "YES", "") | U265: =IF(Raw!CP266=1, "YES", "") | X265: =SUMPRODUCT(Raw!$BT$3:$CC$3, Raw!BT266:CC266) -> 45 | Y265: =SUMPRODUCT(Raw!$BT$3:$CC$3, Raw!BU266:CD266) -> 83 | Z265: =X265*5+Y265 -> 308 | AA265: =X265*261+Y265*52 -> 16061 | AC265: =IF(U265="YES", F265*0.6, F265) -> 21 | AD265: =IF(U265="YES",SUMPRODUCT(Raw!$BT$3:$CC$3,Raw!BT266:CC266)*0.6,SUMPRODUCT(Raw!$BT$3:$CC$3,Raw!BT266:CC266)) -> 45 | AE265: =IF(U265="YES",SUMPRODUCT(Raw!$BT$3:$CC$3,Raw!BU266:CD266)*0.6,SUMPRODUCT(Raw!$BT$3:$CC$3,Raw!BU266:CD266)) -> 83 | AF265: =AD265*5+AE265 -> 308 | AG265: =AD265*261+AE265*52 -> 16061 | AI265: =N265 -> 28 | AJ265: =O265 -> 21 | AK265: =(AI265*5+AJ265)*5.5 -> 885.5 | AL265: =(AI265*261+AJ265*52)*5.5 -> 46200
A266: =Raw!J268 -> 902 | B266: =Raw!K268 -> 0 | C266: =Raw!L268 -> 300 Magnolia Lot | D266: =Raw!M268 -> 0 | E266: =Raw!CG268 -> 0 | F266: =Raw!T268 -> 104 | G266: =Raw!AL268 -> 1 | H266: =Raw!AC268 -> 2 | I266: =SUM(G266:H266) -> 3 | J266: =Raw!BT267 -> 0 | K266: =Raw!AW267 -> 0 | L266: =IF(Raw!CE268 = "NA", "-", Raw!CE268) -> 2 | M266: =IF(Raw!BH268 = "NA", "-", Raw!BH268) -> 6.8 | N266: =IF(Raw!CD268 = "NA", "-", Raw!CD268) -> 212 | O266: =IF(Raw!BG268 = "NA", "-", Raw!BG268) -> 705 | P266: =IF(Raw!AW268 = "NA", "-", SUMPRODUCT(Raw!$BT$2:$CC$2, Raw!BT268:CC268)) -> 774 | Q266: =IF(Raw!AW268 = "NA", "-", SUMPRODUCT(Raw!$AW$2:$BF$2, Raw!AW268:BF268)) -> 1687 | R266: {=_xlfn.IFS(S266="YES", "Hourly", T266="YES", "Flat Rate")} -> Hourly | S266: =IF(Raw!CO268=1, "YES", "") -> YES | T266: =IF(Raw!CO268=2, "YES", "") | U266: =IF(Raw!CP268=1, "YES", "") | X266: =SUMPRODUCT(Raw!$BT$3:$CC$3, Raw!BT268:CC268) -> 370 | Y266: =SUMPRODUCT(Raw!$BT$3:$CC$3, Raw!BU268:CD268) -> 703 | Z266: =X266*5+Y266 -> 2553 | AA266: =X266*261+Y266*52 -> 133126 | AC266: =IF(U266="YES", F266*0.6, F266) -> 104 | AD266: =IF(U266="YES",SUMPRODUCT(Raw!$BT$3:$CC$3,Raw!BT268:CC268)*0.6,SUMPRODUCT(Raw!$BT$3:$CC$3,Raw!BT268:CC268)) -> 370 | AE266: =IF(U266="YES",SUMPRODUCT(Raw!$BT$3:$CC$3,Raw!BU268:CD268)*0.6,SUMPRODUCT(Raw!$BT$3:$CC$3,Raw!BU268:CD268)) -> 703 | AF266: =AD266*5+AE266 -> 2553 | AG266: =AD266*261+AE266*52 -> 133126 | AI266: =N266 -> 212 | AJ266: =O266 -> 705 | AK266: =(AI266*5+AJ266)*5.5 -> 9707.5 | AL266: =(AI266*261+AJ266*52)*5.5 -> 505956
A267: =Raw!J269 -> 903 | B267: =Raw!K269 -> 0 | C267: =Raw!L269 -> 446 Broadway Lot | D267: =Raw!M269 -> 0 | E267: =Raw!CG269 -> 0 | F267: =Raw!T269 -> 62 | G267: =Raw!AL269 -> 0 | H267: =Raw!AC269 -> 1 | I267: =SUM(G267:H267) -> 1 | J267: =Raw!BT268 -> 54 | K267: =Raw!AW268 -> 393 | L267: =IF(Raw!CE269 = "NA", "-", Raw!CE269) -> 2.5 | M267: =IF(Raw!BH269 = "NA", "-", Raw!BH269) -> 5 | N267: =IF(Raw!CD269 = "NA", "-", Raw!CD269) -> 158 | O267: =IF(Raw!BG269 = "NA", "-", Raw!BG269) -> 310 | P267: =IF(Raw!AW269 = "NA", "-", SUMPRODUCT(Raw!$BT$2:$CC$2, Raw!BT269:CC269)) -> 414 | Q267: =IF(Raw!AW269 = "NA", "-", SUMPRODUCT(Raw!$AW$2:$BF$2, Raw!AW269:BF269)) -> 914 | R267: {=_xlfn.IFS(S267="YES", "Hourly", T267="YES", "Flat Rate")} -> Hourly | S267: =IF(Raw!CO269=1, "YES", "") -> YES | T267: =IF(Raw!CO269=2, "YES", "") | U267: =IF(Raw!CP269=1, "YES", "") | X267: =SUMPRODUCT(Raw!$BT$3:$CC$3, Raw!BT269:CC269) -> 233 | Y267: =SUMPRODUCT(Raw!$BT$3:$CC$3, Raw!BU269:CD269) -> 442 | Z267: =X267*5+Y267 -> 1607 | AA267: =X267*261+Y267*52 -> 83797 | AC267: =IF(U267="YES", F267*0.6, F267) -> 62 | AD267: =IF(U267="YES",SUMPRODUCT(Raw!$BT$3:$CC$3,Raw!BT269:CC269)*0.6,SUMPRODUCT(Raw!$BT$3:$CC$3,Raw!BT269:CC269)) -> 233 | AE267: =IF(U267="YES",SUMPRODUCT(Raw!$BT$3:$CC$3,Raw!BU269:CD269)*0.6,SUMPRODUCT(Raw!$BT$3:$CC$3,Raw!BU269:CD269)) -> 442 | AF267: =AD267*5+AE267 -> 1607 | AG267: =AD267*261+AE267*52 -> 83797 | AI267: =N267 -> 158 | AJ267: =O267 -> 310 | AK267: =(AI267*5+AJ267)*5.5 -> 6050 | AL267: =(AI267*261+AJ267*52)*5.5 -> 315469
A268: =Raw!J270 -> 904 | B268: =Raw!K270 -> 0 | C268: =Raw!L270 -> 238 Broadway Lot | D268: =Raw!M270 -> 0 | E268: =Raw!CG270 -> 0 | F268: =Raw!T270 -> 50 | G268: =Raw!AL270 -> 2 | H268: =Raw!AC270 -> 2 | I268: =SUM(G268:H268) -> 4 | J268: =Raw!BT269 -> 83 | K268: =Raw!AW269 -> 114 | L268: =IF(Raw!CE270 = "NA", "-", Raw!CE270) -> 2.5 | M268: =IF(Raw!BH270 = "NA", "-", Raw!BH270) -> 4.0322581 | N268: =IF(Raw!CD270 = "NA", "-", Raw!CD270) -> 127.41935 | O268: =IF(Raw!BG270 = "NA", "-", Raw!BG270) -> 250 | P268: =IF(Raw!AW270 = "NA", "-", SUMPRODUCT(Raw!$BT$2:$CC$2, Raw!BT270:CC270)) -> 333.87097 | Q268: =IF(Raw!AW270 = "NA", "-", SUMPRODUCT(Raw!$AW$2:$BF$2, Raw!AW270:BF270)) -> 737.09677 | R268: {=_xlfn.IFS(S268="YES", "Hourly", T268="YES", "Flat Rate")} -> Hourly | S268: =IF(Raw!CO270=1, "YES", "") -> YES | T268: =IF(Raw!CO270=2, "YES", "") | U268: =IF(Raw!CP270=1, "YES", "") | X268: =SUMPRODUCT(Raw!$BT$3:$CC$3, Raw!BT270:CC270) -> 187.90323 | Y268: =SUMPRODUCT(Raw!$BT$3:$CC$3, Raw!BU270:CD270) -> 356.45161 | Z268: =X268*5+Y268 -> 1295.9677 | AA268: =X268*261+Y268*52 -> 67578.226 | AC268: =IF(U268="YES", F268*0.6, F268) -> 50 | AD268: =IF(U268="YES",SUMPRODUCT(Raw!$BT$3:$CC$3,Raw!BT270:CC270)*0.6,SUMPRODUCT(Raw!$BT$3:$CC$3,Raw!BT270:CC270)) -> 187.90323 | AE268: =IF(U268="YES",SUMPRODUCT(Raw!$BT$3:$CC$3,Raw!BU270:CD270)*0.6,SUMPRODUCT(Raw!$BT$3:$CC$3,Raw!BU270:CD270)) -> 356.45161 | AF268: =AD268*5+AE268 -> 1295.9677 | AG268: =AD268*261+AE268*52 -> 67578.226 | AI268: =N268 -> 127.41935 | AJ268: =O268 -> 250 | AK268: =(AI268*5+AJ268)*5.5 -> 4879.0323 | AL268: =(AI268*261+AJ268*52)*5.5 -> 254410.48
A269: =Raw!J271 -> 905 | B269: =Raw!K271 -> 0 | C269: =Raw!L271 -> Park Pl Lot | D269: =Raw!M271 -> 0 | E269: =Raw!CG271 -> 0 | F269: =Raw!T271 -> 55 | G269: =Raw!AL271 -> 0 | H269: =Raw!AC271 -> 1 | I269: =SUM(G269:H269) -> 1 | J269: =Raw!BT270 -> 66.935484 | K269: =Raw!AW270 -> 91.935484 | L269: =IF(Raw!CE271 = "NA", "-", Raw!CE271) -> 2.5 | M269: =IF(Raw!BH271 = "NA", "-", Raw!BH271) -> 4.4354839 | N269: =IF(Raw!CD271 = "NA", "-", Raw!CD271) -> 140.16129 | O269: =IF(Raw!BG271 = "NA", "-", Raw!BG271) -> 275 | P269: =IF(Raw!AW271 = "NA", "-", SUMPRODUCT(Raw!$BT$2:$CC$2, Raw!BT271:CC271)) -> 367.25806 | Q269: =IF(Raw!AW271 = "NA", "-", SUMPRODUCT(Raw!$AW$2:$BF$2, Raw!AW271:BF271)) -> 810.80645 | R269: {=_xlfn.IFS(S269="YES", "Hourly", T269="YES", "Flat Rate")} -> Hourly | S269: =IF(Raw!CO271=1, "YES", "") -> YES | T269: =IF(Raw!CO271=2, "YES", "") | U269: =IF(Raw!CP271=1, "YES", "") | X269: =SUMPRODUCT(Raw!$BT$3:$CC$3, Raw!BT271:CC271) -> 206.69355 | Y269: =SUMPRODUCT(Raw!$BT$3:$CC$3, Raw!BU271:CD271) -> 392.09677 | Z269: =X269*5+Y269 -> 1425.5645 | AA269: =X269*261+Y269*52 -> 74336.048 | AC269: =IF(U269="YES", F269*0.6, F269) -> 55 | AD269: =IF(U269="YES",SUMPRODUCT(Raw!$BT$3:$CC$3,Raw!BT271:CC271)*0.6,SUMPRODUCT(Raw!$BT$3:$CC$3,Raw!BT271:CC271)) -> 206.69355 | AE269: =IF(U269="YES",SUMPRODUCT(Raw!$BT$3:$CC$3,Raw!BU271:CD271)*0.6,SUMPRODUCT(Raw!$BT$3:$CC$3,Raw!BU271:CD271)) -> 392.09677 | AF269: =AD269*5+AE269 -> 1425.5645 | AG269: =AD269*261+AE269*52 -> 74336.048 | AI269: =N269 -> 140.16129 | AJ269: =O269 -> 275 | AK269: =(AI269*5+AJ269)*5.5 -> 5366.9355 | AL269: =(AI269*261+AJ269*52)*5.5 -> 279851.53
A270: =Raw!J272 -> 906 | B270: =Raw!K272 -> 0 | C270: =Raw!L272 -> Station Lot | D270: =Raw!M272 -> 0 | E270: =Raw!CG272 -> 0 | F270: =Raw!T272 -> 28 | G270: =Raw!AL272 -> 0 | H270: =Raw!AC272 -> 0 | I270: =SUM(G270:H270) -> 0 | J270: =Raw!BT271 -> 73.629032 | K270: =Raw!AW271 -> 101.12903 | L270: =IF(Raw!CE272 = "NA", "-", Raw!CE272) -> 0 | M270: =IF(Raw!BH272 = "NA", "-", Raw!BH272) -> 0 | N270: =IF(Raw!CD272 = "NA", "-", Raw!CD272) -> 23 | O270: =IF(Raw!BG272 = "NA", "-", Raw!BG272) -> 23 | P270: =IF(Raw!AW272 = "NA", "-", SUMPRODUCT(Raw!$BT$2:$CC$2, Raw!BT272:CC272)) -> 0 | Q270: =IF(Raw!AW272 = "NA", "-", SUMPRODUCT(Raw!$AW$2:$BF$2, Raw!AW272:BF272)) -> 0 | R270: {=_xlfn.IFS(S270="YES", "Hourly", T270="YES", "Flat Rate")} -> Flat Rate | S270: =IF(Raw!CO272=1, "YES", "") | T270: =IF(Raw!CO272=2, "YES", "") -> YES | U270: =IF(Raw!CP272=1, "YES", "") | X270: =SUMPRODUCT(Raw!$BT$3:$CC$3, Raw!BT272:CC272) -> 0 | Y270: =SUMPRODUCT(Raw!$BT$3:$CC$3, Raw!BU272:CD272) -> 46 | Z270: =X270*5+Y270 -> 46 | AA270: =X270*261+Y270*52 -> 2392 | AC270: =IF(U270="YES", F270*0.6, F270) -> 28 | AD270: =IF(U270="YES",SUMPRODUCT(Raw!$BT$3:$CC$3,Raw!BT272:CC272)*0.6,SUMPRODUCT(Raw!$BT$3:$CC$3,Raw!BT272:CC272)) -> 0 | AE270: =IF(U270="YES",SUMPRODUCT(Raw!$BT$3:$CC$3,Raw!BU272:CD272)*0.6,SUMPRODUCT(Raw!$BT$3:$CC$3,Raw!BU272:CD272)) -> 46 | AF270: =AD270*5+AE270 -> 46 | AG270: =AD270*261+AE270*52 -> 2392 | AI270: =N270 -> 23 | AJ270: =O270 -> 23 | AK270: =(AI270*5+AJ270)*5.5 -> 759 | AL270: =(AI270*261+AJ270*52)*5.5 -> 39594.5
A271: =Raw!J273 -> 0 | B271: =Raw!K273 -> 0 | C271: =Raw!L273 -> 0 | D271: =Raw!M273 -> 0 | E271: =Raw!CG273 -> 0 | F271: =Raw!T273 -> 0 | G271: =Raw!AL273 -> 0 | H271: =Raw!AC273 -> 0 | I271: =SUM(G271:H271) -> 0 | J271: =Raw!BT272 -> 0 | K271: =Raw!AW272 -> 0 | L271: =IF(Raw!CE273 = "NA", "-", Raw!CE273) -> 0 | M271: =IF(Raw!BH273 = "NA", "-", Raw!BH273) -> 0 | N271: =IF(Raw!CD273 = "NA", "-", Raw!CD273) -> 0 | O271: =IF(Raw!BG273 = "NA", "-", Raw!BG273) -> 0 | P271: =IF(Raw!AW273 = "NA", "-", SUMPRODUCT(Raw!$BT$2:$CC$2, Raw!BT273:CC273)) -> 0 | Q271: =IF(Raw!AW273 = "NA", "-", SUMPRODUCT(Raw!$AW$2:$BF$2, Raw!AW273:BF273)) -> 0 | R271: {=_xlfn.IFS(S271="YES", "Hourly", T271="YES", "Flat Rate")} -> #N/A | S271: =IF(Raw!CO273=1, "YES", "") | T271: =IF(Raw!CO273=2, "YES", "") | U271: =IF(Raw!CP273=1, "YES", "") | AI271: =N271 -> 0 | AJ271: =O271 -> 0 | AK271: =(AI271*5+AJ271)*5.5 -> 0 | AL271: =(AI271*261+AJ271*52)*5.5 -> 0
A272: =Raw!J274 -> 0 | B272: =Raw!K274 -> 0 | C272: =Raw!L274 -> 0 | D272: =Raw!M274 -> 0 | E272: =Raw!CG274 -> 0 | F272: =Raw!T274 -> 0 | G272: =Raw!AL274 -> 0 | H272: =Raw!AC274 -> 0 | I272: =SUM(G272:H272) -> 0 | J272: =Raw!BT273 -> 0 | K272: =Raw!AW273 -> 0 | L272: =IF(Raw!CE274 = "NA", "-", Raw!CE274) -> 0 | M272: =IF(Raw!BH274 = "NA", "-", Raw!BH274) -> 0 | N272: =IF(Raw!CD274 = "NA", "-", Raw!CD274) -> 0 | O272: =IF(Raw!BG274 = "NA", "-", Raw!BG274) -> 0 | P272: =IF(Raw!AW274 = "NA", "-", SUMPRODUCT(Raw!$BT$2:$CC$2, Raw!BT274:CC274)) -> 0 | Q272: =IF(Raw!AW274 = "NA", "-", SUMPRODUCT(Raw!$AW$2:$BF$2, Raw!AW274:BF274)) -> 0 | R272: {=_xlfn.IFS(S272="YES", "Hourly", T272="YES", "Flat Rate")} -> #N/A | S272: =IF(Raw!CO274=1, "YES", "") | T272: =IF(Raw!CO274=2, "YES", "") | U272: =IF(Raw!CP274=1, "YES", "")
A273: =Raw!J275 -> 0 | B273: =Raw!K275 -> 0 | C273: =Raw!L275 -> 0 | D273: =Raw!M275 -> 0 | E273: =Raw!CG275 -> 0 | F273: =Raw!T275 -> 0 | G273: =Raw!AL275 -> 0 | H273: =Raw!AC275 -> 0 | I273: =SUM(G273:H273) -> 0 | J273: =Raw!BT274 -> 0 | K273: =Raw!AW274 -> 0 | L273: =IF(Raw!CE275 = "NA", "-", Raw!CE275) -> 0 | M273: =IF(Raw!BH275 = "NA", "-", Raw!BH275) -> 0 | N273: =IF(Raw!CD275 = "NA", "-", Raw!CD275) -> 0 | O273: =IF(Raw!BG275 = "NA", "-", Raw!BG275) -> 0 | P273: =IF(Raw!AW275 = "NA", "-", SUMPRODUCT(Raw!$BT$2:$CC$2, Raw!BT275:CC275)) -> 0 | Q273: =IF(Raw!AW275 = "NA", "-", SUMPRODUCT(Raw!$AW$2:$BF$2, Raw!AW275:BF275)) -> 0 | R273: {=_xlfn.IFS(S273="YES", "Hourly", T273="YES", "Flat Rate")} -> #N/A | S273: =IF(Raw!CO275=1, "YES", "") | T273: =IF(Raw!CO275=2, "YES", "") | U273: =IF(Raw!CP275=1, "YES", "")
A274: =Raw!J276 -> 0 | B274: =Raw!K276 -> 0 | C274: =Raw!L276 -> 0 | D274: =Raw!M276 -> 0 | E274: =Raw!CG276 -> 0 | F274: =Raw!T276 -> 0 | G274: =Raw!AL276 -> 0 | H274: =Raw!AC276 -> 0 | I274: =SUM(G274:H274) -> 0 | J274: =Raw!BT275 -> 0 | K274: =Raw!AW275 -> 0 | L274: =IF(Raw!CE276 = "NA", "-", Raw!CE276) -> 0 | M274: =IF(Raw!BH276 = "NA", "-", Raw!BH276) -> 0 | N274: =IF(Raw!CD276 = "NA", "-", Raw!CD276) -> 0 | O274: =IF(Raw!BG276 = "NA", "-", Raw!BG276) -> 0 | P274: =IF(Raw!AW276 = "NA", "-", SUMPRODUCT(Raw!$BT$2:$CC$2, Raw!BT276:CC276)) -> 0 | Q274: =IF(Raw!AW276 = "NA", "-", SUMPRODUCT(Raw!$AW$2:$BF$2, Raw!AW276:BF276)) -> 0 | R274: {=_xlfn.IFS(S274="YES", "Hourly", T274="YES", "Flat Rate")} -> #N/A | S274: =IF(Raw!CO276=1, "YES", "") | T274: =IF(Raw!CO276=2, "YES", "") | U274: =IF(Raw!CP276=1, "YES", "")

Sheet Hourly
G1: Observations Where Occupancy > 75% | L1: Turnover Rate | N1: Total Vehicles Count | P1: Total Vehicle Hours | R1: Total Chargeable Vehicle Hours | T1: $1/hr Revenue
A2: Segment | B2: Street | C2: From | D2: To | E2: Side | F2: Parking Supply | G2: Weekday | H2: Weekend | I2: Combined | L2: Weekday | M2: Weekend | N2: Weekday | O2: Weekend | P2: Weekday | Q2: Weekend | R2: Weekday | S2: Weekend | T2: Weekly | U2: Annual
A3: {=_xlfn._xlws.FILTER(All!A3:Q269, All!S3:S269 = "Yes", "")} -> 154 | B3: Park Pl | C3: El Camino Real | D3: Park Blvd | E3: N | F3: 8 | G3: 1 | H3: 1 | I3: 2 | J3: 13 | K3: 25 | L3: 2 | M3: 2.9 | N3: 16 | O3: 23 | P3: 52 | Q3: 63 | R3: {=_xlfn._xlws.FILTER(All!X3:AA269, All!S3:S269 = "Yes", "")} -> 25 | S3: 47 | T3: 172 | U3: 8969 | W3: Total Paid Parking Supply | Y3: =SUM(F:F) -> 1094
A4: 155 | B4: Park Pl | C4: Park Blvd | D4: El Camino Real | E4: S | F4: 9 | G4: 2 | H4: 2 | I4: 4 | J4: 17 | K4: 43 | L4: 2.3 | M4: 3.8 | N4: 20 | O4: 34 | P4: 67 | Q4: 77 | R4: 32 | S4: 61 | T4: 221 | U4: 11524 | W4: Total Vehicle Count | X4: Weekday | Y4: =SUM(M:M) -> 244.16774
A5: 156 | B5: Park Blvd | C5: Park Pl | D5: El Camino Real | E5: N | F5: 12 | G5: 0 | H5: 2 | I5: 2 | J5: 19 | K5: 82 | L5: 1.7 | M5: 4.4 | N5: 21 | O5: 55 | P5: 61 | Q5: 92 | R5: 33 | S5: 61 | T5: 226 | U5: 11785 | X5: Weekend | Y5: =SUM(N:N) -> 2992.5806
A6: 158 | B6: Park Blvd | C6: Palmito Dr | D6: El Camino Real | E6: S | F6: 11 | G6: 0 | H6: 1 | I6: 1 | J6: 11 | K6: 39 | L6: 1.6 | M6: 4.5 | N6: 18 | O6: 50 | P6: 41 | Q6: 71 | R6: 25 | S6: 49 | T6: 174 | U6: 9073 | W6: Total Vehicle Hours | X6: Weekday | Y6: =SUM(O:O) -> 4592
A7: 100 | B7: El Camino Real | C7: Park Pl | D7: Park Blvd | E7: W | F7: 19 | G7: 1 | H7: 2 | I7: 3 | J7: 32 | K7: 32 | L7: 3.4 | M7: 3.2 | N7: 64 | O7: 59 | P7: 141 | Q7: 127 | R7: 96 | S7: 177 | T7: 657 | U7: 34260 | X7: Weekend | Y7: =SUM(P:P) -> 6502.129
A8: 101 | B8: El Camino Real | C8: Santa Clara Ave | D8: Santa Inez Ave | E8: E | F8: 5 | G8: 2 | H8: 1 | I8: 3 | J8: 3 | K8: 8 | L8: 2.9 | M8: 2.4 | N8: 14 | O8: 12 | P8: 38 | Q8: 24 | R8: 25 | S8: 43 | T8: 168 | U8: 8761
A9: 102 | B9: El Camino Real | C9: San Diego Ave | D9: Santa Clara Ave | E9: E | F9: 8 | G9: 1 | H9: 1 | I9: 2 | J9: 7 | K9: 6 | L9: 1.5 | M9: 2.4 | N9: 13 | O9: 20 | P9: 21 | Q9: 50 | R9: 19 | S9: 34 | T9: 129 | U9: 6727
A10: 104 | B10: El Camino Real | C10: Santa Maria Ave | D10: San Diego Ave | E10: E | F10: 5 | G10: 0 | H10: 0 | I10: 0 | J10: 0 | K10: 6 | L10: 0.8 | M10: 1.6 | N10: 4 | O10: 8 | P10: 25 | Q10: 21 | R10: 8 | S10: 15 | T10: 55 | U10: 2868 | Y10: $0/hr | Z10: $1/hr | AA10: $1.5/hr | AB10: $2/hr | AC10: $3/hr
A11: 103 | B11: El Camino Real | C11: Park Blvd | D11: Capuchino Dr | E11: W | F11: 15 | G11: 1 | H11: 0 | I11: 1 | J11: 48 | K11: 33 | L11: 4.4 | M11: 2.7 | N11: 65 | O11: 40 | P11: 95 | Q11: 72 | R11: 82 | S11: 155 | T11: 565 | U11: 29462 | W11: Total Chargeable Hours | X11: Weekday | Y11: =SUM(R:R) -> 4235.5968 | Z11: =SUM(R:R)*0.92 -> 3896.749 | AA11: =Z11*0.98 -> 3818.8141 | AB11: =$Z11*0.96 -> 3740.8791 | AC11: =$Z11*0.92 -> 3585.0091
A12: 105 | B12: El Camino Real | C12: Santa Helena Ave | D12: Santa Maria Ave | E12: E | F12: 9 | G12: 0 | H12: 0 | I12: 0 | J12: 8 | K12: 10 | L12: 1.2 | M12: 1.3 | N12: 11 | O12: 12 | P12: 17 | Q12: 19 | R12: 14 | S12: 27 | T12: 97 | U12: 5058 | X12: Weekend | Y12: =SUM(S:S) -> 7967.5484 | Z12: =SUM(S:S)*0.92 -> 7330.1445 | AA12: =Z12*0.98 -> 7183.5416 | AB12: =$Z12*0.96 -> 7036.9387 | AC12: =$Z12*0.92 -> 6743.733
A13: 106 | B13: El Camino Real | C13: San Juan Ave | D13: Santa Helena Ave | E13: E | F13: 9 | G13: 0 | H13: 0 | I13: 0 | J13: 16 | K13: 20 | L13: 2.7 | M13: 2.9 | N13: 25 | O13: 27 | P13: 42 | Q13: 38 | R13: 34 | S13: 63 | T13: 233 | U13: 12150 | W13: Total Weekly Revenue | Y13: - | Z13: =SUM(T:T)*0.92 -> 26813.89 | AA13: =Z13*0.98*1.5 -> 39416.418 | AB13: =$Z13*0.96*2 -> 51482.668 | AC13: =$Z13*0.92*3 -> 74006.336
A14: 107 | B14: El Camino Real | C14: Capuchino Dr | D14: Millwood Dr | E14: W | F14: 7 | G14: 0 | H14: 0 | I14: 0 | J14: 4 | K14: 1 | L14: 0.6 | M14: 0.1 | N14: 4 | O14: 1 | P14: 4 | Q14: 1 | R14: 4 | S14: 8 | T14: 28 | U14: 1460 | W14: Total Annual Revenue | Y14: - | Z14: =SUM(U:U)*0.92 -> 1398219 | AA14: =Z14*0.98*1.5 -> 2055381.9 | AB14: =$Z14*0.96*2 -> 2684580.5 | AC14: =$Z14*0.92*3 -> 3859084.5
A15: 108 | B15: El Camino Real | C15: Center St | D15: San Juan Ave | E15: E | F15: 35 | G15: 2 | H15: 1 | I15: 3 | J15: 63 | K15: 58 | L15: 3.2 | M15: 2.8 | N15: 114 | O15: 100 | P15: 272 | Q15: 202 | R15: 165 | S15: 302 | T15: 1127 | U15: 58769
A16: 109 | B16: El Camino Real | C16: Millwood Dr | D16: Ludeman Ln | E16: W | F16: 26 | G16: 1 | H16: 0 | I16: 1 | J16: 54 | K16: 26 | L16: 3.1 | M16: 2 | N16: 79 | O16: 52 | P16: 170 | Q16: 129 | R16: 104 | S16: 199 | T16: 719 | U16: 37492
A17: 110 | B17: El Camino Real | C17: Ludeman Ln | D17: Center St | E17: W | F17: 11 | G17: 0 | H17: 0 | I17: 0 | J17: 11 | K17: 8 | L17: 2 | M17: 1.1 | N17: 22 | O17: 12 | P17: 54 | Q17: 19 | R17: 33 | S17: 60 | T17: 225 | U17: 11733
A18: 111 | B18: El Camino Real | C18: Center St | D18: Meadow Glen Ave | E18: W | F18: 23 | G18: 0 | H18: 0 | I18: 0 | J18: 6 | K18: 7 | L18: 0.4 | M18: 0.4 | N18: 8 | O18: 9 | P18: 21 | Q18: 11 | R18: 10 | S18: 20 | T18: 70 | U18: 3650
A19: 112 | B19: El Camino Real | C19: Meadow Glen Ave | D19: Center St | E19: E | F19: 26 | G19: 0 | H19: 0 | I19: 0 | J19: 5 | K19: 13 | L19: 0.3 | M19: 1.2 | N19: 9 | O19: 31 | P19: 21 | Q19: 50 | R19: 13 | S19: 24 | T19: 89 | U19: 4641
A20: 172 | B20: Meadow Glen Ave | C20: El Camino Real | D20: Broadway | E20: N | F20: 3 | G20: 1 | H20: 1 | I20: 2 | J20: 5 | K20: 7 | L20: 2.4 | M20: 2.6 | N20: 8 | O20: 9 | P20: 17 | Q20: 13 | R20: 11 | S20: 21 | T20: 76 | U20: 3963
A21: 173 | B21: Meadow Glen Ave | C21: Broadway | D21: El Camino Real | E21: S | F21: 0 | G21: 0 | H21: 0 | I21: 0 | J21: 0 | K21: 0 | L21: 0 | M21: 0 | N21: 0 | O21: 0 | P21: 0 | Q21: 0 | R21: 0 | S21: 0 | T21: 0 | U21: 0
A22: 80 | B22: Broadway | C22: Meadow Glen Ave | D22: Parking Lot | E22: W | F22: 21 | G22: 3 | H22: 3 | I22: 6 | J22: 86 | K22: 102 | L22: 6.3 | M22: 6.4 | N22: 132 | O22: 135 | P22: 190 | Q22: 185 | R22: 178 | S22: 322 | T22: 1212 | U22: 63202
A23: 81 | B23: Broadway | C23: Crosswalk | D23: Meadow Glen Ave | E23: E | F23: 18 | G23: 1 | H23: 0 | I23: 1 | J23: 47 | K23: 62 | L23: 4.4 | M23: 4.2 | N23: 80 | O23: 75 | P23: 127 | Q23: 96 | R23: 113 | S23: 204 | T23: 769 | U23: 40101
A24: 82 | B24: Broadway | C24: Parking Lot | D24: Silva Ave | E24: W | F24: 9 | G24: 2 | H24: 3 | I24: 5 | J24: 36 | K24: 74 | L24: 5 | M24: 8.8 | N24: 45 | O24: 79 | P24: 70 | Q24: 85 | R24: 54 | S24: 107 | T24: 377 | U24: 19658
A25: 83 | B25: Broadway | C25: Silva Ave | D25: Crosswalk | E25: E | F25: 24 | G25: 0 | H25: 0 | I25: 0 | J25: 75 | K25: 117 | L25: 3.8 | M25: 5.3 | N25: 92 | O25: 127 | P25: 110 | Q25: 144 | R25: 109 | S25: 202 | T25: 747 | U25: 38953
A26: 84 | B26: Broadway | C26: Crosswalk | D26: Taylor Blvd | E26: W | F26: 19 | G26: 1 | H26: 2 | I26: 3 | J26: 52 | K26: 148 | L26: 4.1 | M26: 8.2 | N26: 77 | O26: 156 | P26: 144 | Q26: 166 | R26: 102 | S26: 196 | T26: 706 | U26: 36814
... A45: 208 | B45: Hillcrest Blvd | C45: Broadway | D45: El Camino Real | E45: N | F45: 4 | G45: 3 | H45: 3 | I45: 6 | J45: 3 | K45: 1 | L45: 2.8 | M45: 2.5 | N45: 10 | O45: 9 | P45: 40 | Q45: 40 | R45: 17 | S45: 32 | T45: 117 | U45: 6101
A46: 57 | B46: Magnolia Ave | C46: La Cruz Ave | D46: Hillcrest Blvd | E46: E | F46: 11 | G46: 2 | H46: 4 | I46: 6 | J46: NA | K46: NA | L46: - | M46: - | N46: - | O46: - | P46: - | Q46: - | R46: 0 | S46: 0 | T46: 0 | U46: 0
A47: 216 | B47: La Cruz Ave | C47: Magnolia Ave | D47: Broadway | E47: N | F47: 6 | G47: 0 | H47: 2 | I47: 2 | J47: 0 | K47: 21 | L47: 0 | M47: 4.7 | N47: 0 | O47: 28 | P47: 0 | Q47: 48 | R47: 0 | S47: 0 | T47: 0 | U47: 0
A48: 88 | B48: Broadway | C48: Hillcrest Blvd | D48: La Cruz Ave | E48: W | F48: 15 | G48: 2 | H48: 3 | I48: 5 | J48: 57 | K48: 96 | L48: 5.1 | M48: 7.6 | N48: 77 | O48: 114 | P48: 118 | Q48: 135 | R48: 97 | S48: 185 | T48: 670 | U48: 34937
A49: 89 | B49: Broadway | C49: La Cruz Ave | D49: Hillcrest Blvd | E49: E | F49: 18 | G49: 1 | H49: 3 | I49: 4 | J49: 103 | K49: 102 | L49: 6.6 | M49: 7.2 | N49: 118 | O49: 129 | P49: 143 | Q49: 165 | R49: 133 | S49: 257 | T49: 922 | U49: 48077
A50: 209 | B50: Hillcrest Blvd | C50: Broadway | D50: El Camino Real | E50: S | F50: 5 | G50: 3 | H50: 3 | I50: 6 | J50: 5 | K50: 1 | L50: 2.4 | M50: 2.6 | N50: 12 | O50: 13 | P50: 44 | Q50: 50 | R50: 19 | S50: 35 | T50: 130 | U50: 6779
A51: 218 | B51: La Cruz Ave | C51: El Camino Real | D51: Broadway | E51: N | F51: 8 | G51: 2 | H51: 3 | I51: 5 | J51: 21 | K51: 6 | L51: 4.1 | M51: 3.4 | N51: 33 | O51: 27 | P51: 70 | Q51: 79 | R51: 45 | S51: 87 | T51: 312 | U51: 16269
A52: 123 | B52: El Camino Real | C52: Hillcrest Blvd | D52: La Cruz Ave | E52: W | F52: 13 | G52: 2 | H52: 2 | I52: 4 | J52: 17 | K52: 17 | L52: 2.6 | M52: 3.5 | N52: 34 | O52: 46 | P52: 79 | Q52: 109 | R52: 51 | S52: 96 | T52: 351 | U52: 18303
A53: 124 | B53: El Camino Real E | C53: Hillcrest Blvd | D53: La Cruz Ave | E53: W | F53: 10 | G53: 3 | H53: 3 | I53: 6 | J53: 10 | K53: 6 | L53: 2.8 | M53: 2.9 | N53: 28 | O53: 29 | P53: 94 | Q53: 100 | R53: 46 | S53: 89 | T53: 319 | U53: 16634
A54: 125 | B54: El Camino Real | C54: La Cruz Ave | D54: Hillcrest Blvd | E54: E | F54: 6 | G54: 0 | H54: 3 | I54: 3 | J54: 0 | K54: 1 | L54: 1.1 | M54: 1.7 | N54: 7 | O54: 11 | P54: 37 | Q54: 70 | R54: 14 | S54: 28 | T54: 98 | U54: 5110
A55: 128 | B55: El Camino Real | C55: Sierra Ave | D55: La Cruz Ave | E55: E | F55: 9 | G55: 0 | H55: 0 | I55: 0 | J55: 0 | K55: 3 | L55: 0.6 | M55: 1.7 | N55: 5 | O55: 15 | P55: 30 | Q55: 59 | R55: 10 | S55: 20 | T55: 70 | U55: 3650
A56: 217 | B56: La Cruz Ave | C56: Broadway | D56: Magnolia Ave | E56: S | F56: 6 | G56: 0 | H56: 1 | I56: 1 | J56: 0 | K56: 27 | L56: 0 | M56: 5.5 | N56: 0 | O56: 33 | P56: 0 | Q56: 47 | R56: 0 | S56: 0 | T56: 0 | U56: 0
A57: 219 | B57: La Cruz Ave | C57: Broadway | D57: El Camino Real | E57: S | F57: 7 | G57: 2 | H57: 3 | I57: 5 | J57: 10 | K57: 4 | L57: 3.4 | M57: 3.1 | N57: 24 | O57: 22 | P57: 64 | Q57: 66 | R57: 38 | S57: 73 | T57: 263 | U57: 13714
A58: 126 | B58: El Camino Real | C58: La Cruz Ave | D58: Victoria Ave | E58: W | F58: 20 | G58: 0 | H58: 1 | I58: 1 | J58: 30 | K58: 23 | L58: 3.2 | M58: 3.3 | N58: 64 | O58: 65 | P58: 139 | Q58: 145 | R58: 98 | S58: 176 | T58: 666 | U58: 34730
... A72: 207 | B72: Hillcrest Blvd | C72: Magnolia Ave | D72: Broadway | E72: S | F72: 6 | G72: 1 | H72: 1 | I72: 2 | J72: 18 | K72: 11 | L72: 4.3 | M72: 3.5 | N72: 25 | O72: 20 | P72: 41 | Q72: 36 | R72: 32 | S72: 62 | T72: 222 | U72: 11576
A73: 902 | B73: 0 | C73: 300 Magnolia Lot | D73: 0 | E73: 0 | F73: 104 | G73: 1 | H73: 2 | I73: 3 | J73: 0 | K73: 0 | L73: 2 | M73: 6.8 | N73: 212 | O73: 705 | P73: 774 | Q73: 1687 | R73: 370 | S73: 703 | T73: 2553 | U73: 133126
A74: 903 | B74: 0 | C74: 446 Broadway Lot | D74: 0 | E74: 0 | F74: 62 | G74: 0 | H74: 1 | I74: 1 | J74: 54 | K74: 393 | L74: 2.5 | M74: 5 | N74: 158 | O74: 310 | P74: 414 | Q74: 914 | R74: 233 | S74: 442 | T74: 1607 | U74: 83797
A75: 904 | B75: 0 | C75: 238 Broadway Lot | D75: 0 | E75: 0 | F75: 50 | G75: 2 | H75: 2 | I75: 4 | J75: 83 | K75: 114 | L75: 2.5 | M75: 4.0322581 | N75: 127.41935 | O75: 250 | P75: 333.87097 | Q75: 737.09677 | R75: 187.90323 | S75: 356.45161 | T75: 1295.9677 | U75: 67578.226
A76: 905 | B76: 0 | C76: Park Pl Lot | D76: 0 | E76: 0 | F76: 55 | G76: 0 | H76: 1 | I76: 1 | J76: 66.935484 | K76: 91.935484 | L76: 2.5 | M76: 4.4354839 | N76: 140.16129 | O76: 275 | P76: 367.25806 | Q76: 810.80645 | R76: 206.69355 | S76: 392.09677 | T76: 1425.5645 | U76: 74336.048

Sheet Hourly (Reduction)
G1: Observations Where Occupancy > 75% | L1: Turnover Rate | N1: Total Vehicles Count | P1: Total Vehicle Hours | R1: Total Chargeable Vehicle Hours | T1: $1/hr Revenue
A2: Segment | B2: Street | C2: From | D2: To | E2: Side | F2: Parking Supply | G2: Weekday | H2: Weekend | I2: Combined | L2: Weekday | M2: Weekend | N2: Weekday | O2: Weekend | P2: Weekday | Q2: Weekend | R2: Weekday | S2: Weekend | T2: Weekly | U2: Annual
A3: {=_xlfn._xlws.FILTER(All!A3:E269, All!S3:S269 = "Yes", "")} -> 154 | B3: Park Pl | C3: El Camino Real | D3: Park Blvd | E3: N | F3: {=_xlfn._xlws.FILTER(All!AC3:AC269,All!S3:S269="Yes","")} -> 8 | G3: {=_xlfn._xlws.FILTER(All!G3:Q269, All!S3:S269 = "Yes", "")} -> 1 | H3: 1 | I3: 2 | J3: 13 | K3: 25 | L3: 2 | M3: 2.9 | N3: 16 | O3: 23 | P3: 52 | Q3: 63 | R3: {=_xlfn._xlws.FILTER(All!AD3:AG269, All!S3:S269 = "Yes", "")} -> 25 | S3: 47 | T3: 172 | U3: 8969 | W3: Total Paid Parking Supply | Y3: =SUM(F:F) -> 1044.4
A4: 155 | B4: Park Pl | C4: Park Blvd | D4: El Camino Real | E4: S | F4: 9 | G4: 2 | H4: 2 | I4: 4 | J4: 17 | K4: 43 | L4: 2.3 | M4: 3.8 | N4: 20 | O4: 34 | P4: 67 | Q4: 77 | R4: 32 | S4: 61 | T4: 221 | U4: 11524 | W4: Total Vehicle Count | X4: Weekday | Y4: =SUM(M:M) -> 244.16774
A5: 156 | B5: Park Blvd | C5: Park Pl | D5: El Camino Real | E5: N | F5: 12 | G5: 0 | H5: 2 | I5: 2 | J5: 19 | K5: 82 | L5: 1.7 | M5: 4.4 | N5: 21 | O5: 55 | P5: 61 | Q5: 92 | R5: 33 | S5: 61 | T5: 226 | U5: 11785 | X5: Weekend | Y5: =SUM(N:N) -> 2992.5806
A6: 158 | B6: Park Blvd | C6: Palmito Dr | D6: El Camino Real | E6: S | F6: 11 | G6: 0 | H6: 1 | I6: 1 | J6: 11 | K6: 39 | L6: 1.6 | M6: 4.5 | N6: 18 | O6: 50 | P6: 41 | Q6: 71 | R6: 25 | S6: 49 | T6: 174 | U6: 9073 | W6: Total Vehicle Hours | X6: Weekday | Y6: =SUM(O:O) -> 4592
A7: 100 | B7: El Camino Real | C7: Park Pl | D7: Park Blvd | E7: W | F7: 19 | G7: 1 | H7: 2 | I7: 3 | J7: 32 | K7: 32 | L7: 3.4 | M7: 3.2 | N7: 64 | O7: 59 | P7: 141 | Q7: 127 | R7: 96 | S7: 177 | T7: 657 | U7: 34260 | X7: Weekend | Y7: =SUM(P:P) -> 6502.129
A8: 101 | B8: El Camino Real | C8: Santa Clara Ave | D8: Santa Inez Ave | E8: E | F8: 5 | G8: 2 | H8: 1 | I8: 3 | J8: 3 | K8: 8 | L8: 2.9 | M8: 2.4 | N8: 14 | O8: 12 | P8: 38 | Q8: 24 | R8: 25 | S8: 43 | T8: 168 | U8: 8761
A9: 102 | B9: El Camino Real | C9: San Diego Ave | D9: Santa Clara Ave | E9: E | F9: 8 | G9: 1 | H9: 1 | I9: 2 | J9: 7 | K9: 6 | L9: 1.5 | M9: 2.4 | N9: 13 | O9: 20 | P9: 21 | Q9: 50 | R9: 19 | S9: 34 | T9: 129 | U9: 6727
A10: 104 | B10: El Camino Real | C10: Santa Maria Ave | D10: San Diego Ave | E10: E | F10: 5 | G10: 0 | H10: 0 | I10: 0 | J10: 0 | K10: 6 | L10: 0.8 | M10: 1.6 | N10: 4 | O10: 8 | P10: 25 | Q10: 21 | R10: 8 | S10: 15 | T10: 55 | U10: 2868 | Y10: $0/hr | Z10: $1/hr | AA10: $1.5/hr | AB10: $2/hr | AC10: $3/hr
A11: 103 | B11: El Camino Real | C11: Park Blvd | D11: Capuchino Dr | E11: W | F11: 15 | G11: 1 | H11: 0 | I11: 1 | J11: 48 | K11: 33 | L11: 4.4 | M11: 2.7 | N11: 65 | O11: 40 | P11: 95 | Q11: 72 | R11: 82 | S11: 155 | T11: 565 | U11: 29462 | W11: Total Chargeable Hours | X11: Weekday | Y11: =SUM(R:R) -> 3922.7968 | Z11: =SUM(R:R)*0.92 -> 3608.973 | AA11: =Z11*0.98 -> 3536.7936 | AB11: =$Z11*0.96 -> 3464.6141 | AC11: =$Z11*0.92 -> 3320.2552
A12: 105 | B12: El Camino Real | C12: Santa Helena Ave | D12: Santa Maria Ave | E12: E | F12: 9 | G12: 0 | H12: 0 | I12: 0 | J12: 8 | K12: 10 | L12: 1.2 | M12: 1.3 | N12: 11 | O12: 12 | P12: 17 | Q12: 19 | R12: 14 | S12: 27 | T12: 97 | U12: 5058 | X12: Weekend | Y12: =SUM(S:S) -> 7371.5484 | Z12: =SUM(S:S)*0.92 -> 6781.8245 | AA12: =Z12*0.98 -> 6646.188 | AB12: =$Z12*0.96 -> 6510.5515 | AC12: =$Z12*0.92 -> 6239.2786
A13: 106 | B13: El Camino Real | C13: San Juan Ave | D13: Santa Helena Ave | E13: E | F13: 9 | G13: 0 | H13: 0 | I13: 0 | J13: 16 | K13: 20 | L13: 2.7 | M13: 2.9 | N13: 25 | O13: 27 | P13: 42 | Q13: 38 | R13: 34 | S13: 63 | T13: 233 | U13: 12150 | W13: Total Weekly Revenue | Y13: 0 | Z13: =SUM(T:T)*0.92 -> 24826.69 | AA13: =Z13*0.98*1.5 -> 36495.234 | AB13: =$Z13*0.96*2 -> 47667.244 | AC13: =$Z13*0.92*3 -> 68521.664
A14: 107 | B14: El Camino Real | C14: Capuchino Dr | D14: Millwood Dr | E14: W | F14: 7 | G14: 0 | H14: 0 | I14: 0 | J14: 4 | K14: 1 | L14: 0.6 | M14: 0.1 | N14: 4 | O14: 1 | P14: 4 | Q14: 1 | R14: 4 | S14: 8 | T14: 28 | U14: 1460 | W14: Total Annual Revenue | Y14: 0 | Z14: =SUM(U:U)*0.92 -> 1294596.8 | AA14: =Z14*0.98*1.5 -> 1903057.3 | AB14: =$Z14*0.96*2 -> 2485625.9 | AC14: =$Z14*0.92*3 -> 3573087.3
A15: 108 | B15: El Camino Real | C15: Center St | D15: San Juan Ave | E15: E | F15: 35 | G15: 2 | H15: 1 | I15: 3 | J15: 63 | K15: 58 | L15: 3.2 | M15: 2.8 | N15: 114 | O15: 100 | P15: 272 | Q15: 202 | R15: 165 | S15: 302 | T15: 1127 | U15: 58769
A16: 109 | B16: El Camino Real | C16: Millwood Dr | D16: Ludeman Ln | E16: W | F16: 26 | G16: 1 | H16: 0 | I16: 1 | J16: 54 | K16: 26 | L16: 3.1 | M16: 2 | N16: 79 | O16: 52 | P16: 170 | Q16: 129 | R16: 104 | S16: 199 | T16: 719 | U16: 37492
A17: 110 | B17: El Camino Real | C17: Ludeman Ln | D17: Center St | E17: W | F17: 11 | G17: 0 | H17: 0 | I17: 0 | J17: 11 | K17: 8 | L17: 2 | M17: 1.1 | N17: 22 | O17: 12 | P17: 54 | Q17: 19 | R17: 33 | S17: 60 | T17: 225 | U17: 11733
A18: 111 | B18: El Camino Real | C18: Center St | D18: Meadow Glen Ave | E18: W | F18: 23 | G18: 0 | H18: 0 | I18: 0 | J18: 6 | K18: 7 | L18: 0.4 | M18: 0.4 | N18: 8 | O18: 9 | P18: 21 | Q18: 11 | R18: 10 | S18: 20 | T18: 70 | U18: 3650
A19: 112 | B19: El Camino Real | C19: Meadow Glen Ave | D19: Center St | E19: E | F19: 26 | G19: 0 | H19: 0 | I19: 0 | J19: 5 | K19: 13 | L19: 0.3 | M19: 1.2 | N19: 9 | O19: 31 | P19: 21 | Q19: 50 | R19: 13 | S19: 24 | T19: 89 | U19: 4641
A20: 172 | B20: Meadow Glen Ave | C20: El Camino Real | D20: Broadway | E20: N | F20: 3 | G20: 1 | H20: 1 | I20: 2 | J20: 5 | K20: 7 | L20: 2.4 | M20: 2.6 | N20: 8 | O20: 9 | P20: 17 | Q20: 13 | R20: 11 | S20: 21 | T20: 76 | U20: 3963
A21: 173 | B21: Meadow Glen Ave | C21: Broadway | D21: El Camino Real | E21: S | F21: 0 | G21: 0 | H21: 0 | I21: 0 | J21: 0 | K21: 0 | L21: 0 | M21: 0 | N21: 0 | O21: 0 | P21: 0 | Q21: 0 | R21: 0 | S21: 0 | T21: 0 | U21: 0
A22: 80 | B22: Broadway | C22: Meadow Glen Ave | D22: Parking Lot | E22: W | F22: 21 | G22: 3 | H22: 3 | I22: 6 | J22: 86 | K22: 102 | L22: 6.3 | M22: 6.4 | N22: 132 | O22: 135 | P22: 190 | Q22: 185 | R22: 178 | S22: 322 | T22: 1212 | U22: 63202
A23: 81 | B23: Broadway | C23: Crosswalk | D23: Meadow Glen Ave | E23: E | F23: 18 | G23: 1 | H23: 0 | I23: 1 | J23: 47 | K23: 62 | L23: 4.4 | M23: 4.2 | N23: 80 | O23: 75 | P23: 127 | Q23: 96 | R23: 113 | S23: 204 | T23: 769 | U23: 40101
A24: 82 | B24: Broadway | C24: Parking Lot | D24: Silva Ave | E24: W | F24: 9 | G24: 2 | H24: 3 | I24: 5 | J24: 36 | K24: 74 | L24: 5 | M24: 8.8 | N24: 45 | O24: 79 | P24: 70 | Q24: 85 | R24: 54 | S24: 107 | T24: 377 | U24: 19658
A25: 83 | B25: Broadway | C25: Silva Ave | D25: Crosswalk | E25: E | F25: 24 | G25: 0 | H25: 0 | I25: 0 | J25: 75 | K25: 117 | L25: 3.8 | M25: 5.3 | N25: 92 | O25: 127 | P25: 110 | Q25: 144 | R25: 109 | S25: 202 | T25: 747 | U25: 38953
A26: 84 | B26: Broadway | C26: Crosswalk | D26: Taylor Blvd | E26: W | F26: 19 | G26: 1 | H26: 2 | I26: 3 | J26: 52 | K26: 148 | L26: 4.1 | M26: 8.2 | N26: 77 | O26: 156 | P26: 144 | Q26: 166 | R26: 102 | S26: 196 | T26: 706 | U26: 36814
... A45: 208 | B45: Hillcrest Blvd | C45: Broadway | D45: El Camino Real | E45: N | F45: 4 | G45: 3 | H45: 3 | I45: 6 | J45: 3 | K45: 1 | L45: 2.8 | M45: 2.5 | N45: 10 | O45: 9 | P45: 40 | Q45: 40 | R45: 17 | S45: 32 | T45: 117 | U45: 6101
A46: 57 | B46: Magnolia Ave | C46: La Cruz Ave | D46: Hillcrest Blvd | E46: E | F46: 11 | G46: 2 | H46: 4 | I46: 6 | J46: NA | K46: NA | L46: - | M46: - | N46: - | O46: - | P46: - | Q46: - | R46: 0 | S46: 0 | T46: 0 | U46: 0
A47: 216 | B47: La Cruz Ave | C47: Magnolia Ave | D47: Broadway | E47: N | F47: 6 | G47: 0 | H47: 2 | I47: 2 | J47: 0 | K47: 21 | L47: 0 | M47: 4.7 | N47: 0 | O47: 28 | P47: 0 | Q47: 48 | R47: 0 | S47: 0 | T47: 0 | U47: 0
A48: 88 | B48: Broadway | C48: Hillcrest Blvd | D48: La Cruz Ave | E48: W | F48: 9 | G48: 2 | H48: 3 | I48: 5 | J48: 57 | K48: 96 | L48: 5.1 | M48: 7.6 | N48: 77 | O48: 114 | P48: 118 | Q48: 135 | R48: 58.2 | S48: 111 | T48: 402 | U48: 20962.2
A49: 89 | B49: Broadway | C49: La Cruz Ave | D49: Hillcrest Blvd | E49: E | F49: 10.8 | G49: 1 | H49: 3 | I49: 4 | J49: 103 | K49: 102 | L49: 6.6 | M49: 7.2 | N49: 118 | O49: 129 | P49: 143 | Q49: 165 | R49: 79.8 | S49: 154.2 | T49: 553.2 | U49: 28846.2
A50: 209 | B50: Hillcrest Blvd | C50: Broadway | D50: El Camino Real | E50: S | F50: 5 | G50: 3 | H50: 3 | I50: 6 | J50: 5 | K50: 1 | L50: 2.4 | M50: 2.6 | N50: 12 | O50: 13 | P50: 44 | Q50: 50 | R50: 19 | S50: 35 | T50: 130 | U50: 6779
A51: 218 | B51: La Cruz Ave | C51: El Camino Real | D51: Broadway | E51: N | F51: 8 | G51: 2 | H51: 3 | I51: 5 | J51: 21 | K51: 6 | L51: 4.1 | M51: 3.4 | N51: 33 | O51: 27 | P51: 70 | Q51: 79 | R51: 45 | S51: 87 | T51: 312 | U51: 16269
A52: 123 | B52: El Camino Real | C52: Hillcrest Blvd | D52: La Cruz Ave | E52: W | F52: 13 | G52: 2 | H52: 2 | I52: 4 | J52: 17 | K52: 17 | L52: 2.6 | M52: 3.5 | N52: 34 | O52: 46 | P52: 79 | Q52: 109 | R52: 51 | S52: 96 | T52: 351 | U52: 18303
A53: 124 | B53: El Camino Real E | C53: Hillcrest Blvd | D53: La Cruz Ave | E53: W | F53: 10 | G53: 3 | H53: 3 | I53: 6 | J53: 10 | K53: 6 | L53: 2.8 | M53: 2.9 | N53: 28 | O53: 29 | P53: 94 | Q53: 100 | R53: 46 | S53: 89 | T53: 319 | U53: 16634
A54: 125 | B54: El Camino Real | C54: La Cruz Ave | D54: Hillcrest Blvd | E54: E | F54: 6 | G54: 0 | H54: 3 | I54: 3 | J54: 0 | K54: 1 | L54: 1.1 | M54: 1.7 | N54: 7 | O54: 11 | P54: 37 | Q54: 70 | R54: 14 | S54: 28 | T54: 98 | U54: 5110
A55: 128 | B55: El Camino Real | C55: Sierra Ave | D55: La Cruz Ave | E55: E | F55: 9 | G55: 0 | H55: 0 | I55: 0 | J55: 0 | K55: 3 | L55: 0.6 | M55: 1.7 | N55: 5 | O55: 15 | P55: 30 | Q55: 59 | R55: 10 | S55: 20 | T55: 70 | U55: 3650
A56: 217 | B56: La Cruz Ave | C56: Broadway | D56: Magnolia Ave | E56: S | F56: 6 | G56: 0 | H56: 1 | I56: 1 | J56: 0 | K56: 27 | L56: 0 | M56: 5.5 | N56: 0 | O56: 33 | P56: 0 | Q56: 47 | R56: 0 | S56: 0 | T56: 0 | U56: 0
A57: 219 | B57: La Cruz Ave | C57: Broadway | D57: El Camino Real | E57: S | F57: 7 | G57: 2 | H57: 3 | I57: 5 | J57: 10 | K57: 4 | L57: 3.4 | M57: 3.1 | N57: 24 | O57: 22 | P57: 64 | Q57: 66 | R57: 38 | S57: 73 | T57: 263 | U57: 13714
A58: 126 | B58: El Camino Real | C58: La Cruz Ave | D58: Victoria Ave | E58: W | F58: 20 | G58: 0 | H58: 1 | I58: 1 | J58: 30 | K58: 23 | L58: 3.2 | M58: 3.3 | N58: 64 | O58: 65 | P58: 139 | Q58: 145 | R58: 98 | S58: 176 | T58: 666 | U58: 34730
... A72: 207 | B72: Hillcrest Blvd | C72: Magnolia Ave | D72: Broadway | E72: S | F72: 6 | G72: 1 | H72: 1 | I72: 2 | J72: 18 | K72: 11 | L72: 4.3 | M72: 3.5 | N72: 25 | O72: 20 | P72: 41 | Q72: 36 | R72: 32 | S72: 62 | T72: 222 | U72: 11576
A73: 902 | B73: 0 | C73: 300 Magnolia Lot | D73: 0 | E73: 0 | F73: 104 | G73: 1 | H73: 2 | I73: 3 | J73: 0 | K73: 0 | L73: 2 | M73: 6.8 | N73: 212 | O73: 705 | P73: 774 | Q73: 1687 | R73: 370 | S73: 703 | T73: 2553 | U73: 133126
A74: 903 | B74: 0 | C74: 446 Broadway Lot | D74: 0 | E74: 0 | F74: 62 | G74: 0 | H74: 1 | I74: 1 | J74: 54 | K74: 393 | L74: 2.5 | M74: 5 | N74: 158 | O74: 310 | P74: 414 | Q74: 914 | R74: 233 | S74: 442 | T74: 1607 | U74: 83797
A75: 904 | B75: 0 | C75: 238 Broadway Lot | D75: 0 | E75: 0 | F75: 50 | G75: 2 | H75: 2 | I75: 4 | J75: 83 | K75: 114 | L75: 2.5 | M75: 4.0322581 | N75: 127.41935 | O75: 250 | P75: 333.87097 | Q75: 737.09677 | R75: 187.90323 | S75: 356.45161 | T75: 1295.9677 | U75: 67578.226
A76: 905 | B76: 0 | C76: Park Pl Lot | D76: 0 | E76: 0 | F76: 55 | G76: 0 | H76: 1 | I76: 1 | J76: 66.935484 | K76: 91.935484 | L76: 2.5 | M76: 4.4354839 | N76: 140.16129 | O76: 275 | P76: 367.25806 | Q76: 810.80645 | R76: 206.69355 | S76: 392.09677 | T76: 1425.5645 | U76: 74336.048

Sheet Long-Term
G1: Observations Where Occupancy > 75% | J1: Total Vehicles Count | L1: Revenue
A2: Segment | B2: Street | C2: From | D2: To | E2: Side | F2: Parking Supply | G2: Weekday | H2: Weekend | I2: Combined | J2: Weekday | K2: Weekend | L2: Weekly | M2: Annual
A3: {=_xlfn._xlws.FILTER(All!A3:I270, All!T3:T270 = "Yes", "")} -> 146 | B3: Sierra Ave | C3: Linden Ave | D3: End | E3: W | F3: 2 | G3: 0 | H3: 1 | I3: 1 | J3: {=_xlfn._xlws.FILTER(All!N3:O270, All!T3:T270 = "Yes", "")} -> 0 | K3: 7 | L3: {=_xlfn._xlws.FILTER(All!AK3:AL270, All!T3:T270 = "Yes", "")} -> 38.5 | M3: 2002 | O3: Total Paid Parking Supply | Q3: =SUM(F:F) -> 59
A4: 147 | B4: Sierra Ave | C4: End | D4: Linden Ave | E4: E | F4: 3 | G4: 0 | H4: 0 | I4: 0 | J4: 0 | K4: 3 | L4: 16.5 | M4: 858 | O4: Total Vehicle Count | P4: Weekday | Q4: =SUM(J:J) -> 61
A5: 150 | B5: California Dr | C5: Murchison Dr | D5: Sierra Ave | E5: E | F5: 20 | G5: 0 | H5: 0 | I5: 0 | J5: 28 | K5: 40 | L5: 990 | M5: 51634 | P5: Weekend | Q5: =SUM(K:K) -> 78
A6: 149 | B6: California Dr | C6: Sierra Ave | D6: Irwin Pl | E6: W | F6: 6 | G6: 1 | H6: 0 | I6: 1 | J6: 10 | K6: 5 | L6: 302.5 | M6: 15785
A7: 906 | B7: 0 | C7: Station Lot | D7: 0 | E7: 0 | F7: 28 | G7: 0 | H7: 0 | I7: 0 | J7: 23 | K7: 23 | L7: 759 | M7: 39594.5
O8: 10-hr max | Q8: $5.50 flat rate
O9: Total Weekly Revenue | Q9: =SUM(L3:L7) -> 2106.5
O10: Total Annual Revenue | Q10: =SUM(M3:M7) -> 109873.5

Sheet Space & Elasticitiy
G1: 2hr Parking | I1: $0/hr | J1: $1/hr | K1: $1.5/hr | L1: $2/hr | M1: $3/hr | P1: 2hr Parking | R1: $0/hr | S1: $1.5/hr | T1: $2/hr
B2: On-Street | C2: Off-Street | D2: Space Total | E2: Kiosk Count | G2: Total Chargeable Hours | H2: Weekday | I2: =Hourly!Y11 -> 4235.5968 | J2: =Hourly!Z11 -> 3896.749 | K2: =Hourly!AA11 -> 3818.8141 | L2: =Hourly!AB11 -> 3740.8791 | M2: =Hourly!AC11 -> 3585.0091 | P2: Total Chargeable Hours | Q2: Per Weekday | R2: 4328.5968 | S2: 3902.6629 | T2: 3823.0167
A3: Hourly Parking | B3: =SUM(Hourly!F3:F72) -> 823 | C3: =SUM(Hourly!F73:F76) -> 271 | D3: =SUM(Hourly!F:F) -> 1094 | E3: 45 | H3: Weekend | I3: =Hourly!Y12 -> 7967.5484 | J3: =Hourly!Z12 -> 7330.1445 | K3: =Hourly!AA12 -> 7183.5416 | L3: =Hourly!AB12 -> 7036.9387 | M3: =Hourly!AC12 -> 6743.733 | Q3: Per Weekday | R3: 8139.5484 | S3: 7338.6168 | T3: 7188.8491
A4: Long-Term Parking | B4: =SUM('Long-Term'!F3:F6) -> 31 | C4: =SUM('Long-Term'!F7) -> 28 | D4: =SUM('Long-Term'!F3:F7) -> 59 | E4: 5 | G4: Weekly Revenue | I4: =Hourly!Y13 -> - | J4: =Hourly!Z13 -> 26813.89 | K4: =Hourly!AA13 -> 39416.418 | L4: =Hourly!AB13 -> 51482.668 | M4: =Hourly!AC13 -> 74006.336 | P4: Weekly Revenue | R4: - | S4: 40277.897 | T4: 52607.865
A5: Total | B5: =SUM(B3:B4) -> 854 | C5: =SUM(C3:C4) -> 299 | D5: =SUM(D3:D4) -> 1153 | E5: 49 | G5: Annual Revenue | I5: =Hourly!Y14 -> - | J5: =Hourly!Z14 -> 1398219 | K5: =Hourly!AA14 -> 2055381.9 | L5: =Hourly!AB14 -> 2684580.5 | M5: =Hourly!AC14 -> 3859084.5 | P5: Annual Revenue | R5: - | S5: 2100304.6 | T5: 2743255
B7: On-Street | C7: Off-Street | D7: Space Total | E7: Kiosk Count
A8: Hourly Parking (Reduced) | B8: =SUM('Hourly (Reduction)'!F3:F72) -> 773.4 | C8: =SUM('Hourly (Reduction)'!F73:F77) -> 271 | D8: =SUM('Hourly (Reduction)'!F:F) -> 1044.4 | E8: 45 | G8: 10hr Parking | I8: $5.50 flat rate
A9: Long-Term Parking | B9: =SUM('Long-Term'!F3:F6) -> 31 | C9: =SUM('Long-Term'!F7) -> 28 | D9: =SUM('Long-Term'!F3:F7) -> 59 | E9: 4 | G9: Total Vehicle Count | H9: Weekday | I9: ='Long-Term'!Q4 -> 61
A10: Total | B10: =SUM(B8:B9) -> 804.4 | C10: =SUM(C8:C9) -> 299 | D10: =SUM(D8:D9) -> 1103.4 | E10: 49 | H10: Weekend | I10: ='Long-Term'!Q5 -> 78
G11: Total Weekly Revenue | I11: ='Long-Term'!Q9 -> 2106.5
G12: Total Annual Revenue | I12: ='Long-Term'!Q10 -> 109873.5
G15: 2hr Parking (Reduction) | I15: $0/hr | J15: $1/hr | K15: $1.5/hr | L15: $2/hr | M15: $3/hr
G16: Total Chargeable Hours | H16: Weekday | I16: ='Hourly (Reduction)'!Y11 -> 3922.7968 | J16: ='Hourly (Reduction)'!Z11 -> 3608.973 | K16: ='Hourly (Reduction)'!AA11 -> 3536.7936 | L16: ='Hourly (Reduction)'!AB11 -> 3464.6141 | M16: ='Hourly (Reduction)'!AC11 -> 3320.2552
H17: Weekend | I17: ='Hourly (Reduction)'!Y12 -> 7371.5484 | J17: ='Hourly (Reduction)'!Z12 -> 6781.8245 | K17: ='Hourly (Reduction)'!AA12 -> 6646.188 | L17: ='Hourly (Reduction)'!AB12 -> 6510.5515 | M17: ='Hourly (Reduction)'!AC12 -> 6239.2786
G18: Weekly Revenue | I18: ='Hourly (Reduction)'!Y13 -> 0 | J18: ='Hourly (Reduction)'!Z13 -> 24826.69 | K18: ='Hourly (Reduction)'!AA13 -> 36495.234 | L18: ='Hourly (Reduction)'!AB13 -> 47667.244 | M18: ='Hourly (Reduction)'!AC13 -> 68521.664
G19: Annual Revenue | I19: ='Hourly (Reduction)'!Y14 -> 0 | J19: ='Hourly (Reduction)'!Z14 -> 1294596.8 | K19: ='Hourly (Reduction)'!AA14 -> 1903057.3 | L19: ='Hourly (Reduction)'!AB14 -> 2485625.9 | M19: ='Hourly (Reduction)'!AC14 -> 3573087.3

Sheet $1.5 per hr + $0.5 Projection
C1: Diff here | D1: Diff here | E1: Diff here | F1: - | G1: - | H1: - | I1: - | J1: - | K1: - | L1: Diff here | M1: - | N1: - | O1: - | P1: - | Q1: - | R1: - | S1: - | T1: - | U1: - | V1: Diff here | W1: - | X1: - | Y1: - | Z1: - | AA1: -
A3: Future Value | B3: 2025 | C3: 2026 | D3: 2027 | E3: 2028 | F3: 2029 | G3: 2030 | H3: 2031 | I3: 2032 | J3: 2033 | K3: 2034 | L3: 2035 | M3: 2036 | N3: 2037 | O3: 2038 | P3: 2039 | Q3: 2040 | R3: 2041 | S3: 2042 | T3: 2043 | U3: 2044 | V3: 2045 | W3: 2046 | X3: 2047 | Y3: 2048 | Z3: 2049 | AA3: 2050
A4: Revenue
A5: Paid Parking Revenue | B5: 0 | C5: =('Space & Elasticitiy'!K5+'Space & Elasticitiy'!I12)*(1.005^(C$3-2024)) -> 2186962.1 | D5: =('Space & Elasticitiy'!K19+'Space & Elasticitiy'!I12)*(1.005^(D$3-2024)) -> 2043276 | E5: =$D5*(1.005^(E$3-2027)) -> 2053492.4 | F5: =$D5*(1.005^(F$3-2027)) -> 2063759.9 | G5: =$D5*(1.005^(G$3-2027)) -> 2074078.7 | H5: =$D5*(1.005^(H$3-2027)) -> 2084449.1 | I5: =$D5*(1.005^(I$3-2027)) -> 2094871.3 | J5: =$D5*(1.005^(J$3-2027)) -> 2105345.7 | K5: =$D5*(1.005^(K$3-2027)) -> 2115872.4 | L5: =$K5*(1-0.04*1/3)*(1+1/3)*(1.005^(L$3-2034)) -> 2797465.4 | M5: =$K5*(1-0.04*1/3)*(1+1/3)*(1.005^(M$3-2034)) -> 2811452.8 | N5: =$K5*(1-0.04*1/3)*(1+1/3)*(1.005^(N$3-2034)) -> 2825510 | O5: =$K5*(1-0.04*1/3)*(1+1/3)*(1.005^(O$3-2034)) -> 2839637.6 | P5: =$K5*(1-0.04*1/3)*(1+1/3)*(1.005^(P$3-2034)) -> 2853835.8 | Q5: =$K5*(1-0.04*1/3)*(1+1/3)*(1.005^(Q$3-2034)) -> 2868104.9 | R5: =$K5*(1-0.04*1/3)*(1+1/3)*(1.005^(R$3-2034)) -> 2882445.5 | S5: =$K5*(1-0.04*1/3)*(1+1/3)*(1.005^(S$3-2034)) -> 2896857.7 | ... U5: =$K5*(1-0.04*1/3)*(1+1/3)*(1.005^(U$3-2034)) -> 2925898.7 | V5: =$U5*(1-0.04*1/4)*(1+1/4)*(1.005^(V$3-2044)) -> 3638903.6 | W5: =$U5*(1-0.04*1/4)*(1+1/4)*(1.005^(W$3-2044)) -> 3657098.1 | X5: =$U5*(1-0.04*1/4)*(1+1/4)*(1.005^(X$3-2044)) -> 3675383.6 | Y5: =$U5*(1-0.04*1/4)*(1+1/4)*(1.005^(Y$3-2044)) -> 3693760.5 | Z5: =$U5*(1-0.04*1/4)*(1+1/4)*(1.005^(Z$3-2044)) -> 3712229.4 | AA5: =$U5*(1-0.04*1/4)*(1+1/4)*(1.005^(AA$3-2044)) -> 3730790.5
A6: Citation Revenue | B6: 0 | D6: =$C$6*(1.005^(D$3-2026)) -> 0 | E6: =$C$6*(1.005^(E$3-2026)) -> 0 | F6: =$C$6*(1.005^(F$3-2026)) -> 0 | G6: =$C$6*(1.005^(G$3-2026)) -> 0 | H6: =$C$6*(1.005^(H$3-2026)) -> 0 | I6: =$C$6*(1.005^(I$3-2026)) -> 0 | J6: =$C$6*(1.005^(J$3-2026)) -> 0 | K6: =$C$6*(1.005^(K$3-2026)) -> 0 | ... AA6: =$C$6*(1.005^(AA$3-2026)) -> 0
A7: Revenue Total | B7: =B5 -> 0 | C7: =SUM(C5:C6) -> 2186962.1 | D7: =SUM(D5:D6) -> 2043276 | E7: =SUM(E5:E6) -> 2053492.4 | F7: =SUM(F5:F6) -> 2063759.9 | G7: =SUM(G5:G6) -> 2074078.7 | H7: =SUM(H5:H6) -> 2084449.1 | I7: =SUM(I5:I6) -> 2094871.3 | J7: =SUM(J5:J6) -> 2105345.7 | ... AA7: =SUM(AA5:AA6) -> 3730790.5
A9: Expenses
A10: Parking Kiosks Procurement | B10: =49*10000 -> 490000 | C10: 0 | D10: 0 | E10: 0 | F10: 0 | G10: 0 | H10: 0 | I10: 0 | J10: 0 | K10: 0 | L10: =$B10*(1.03^(L$3-$B$3)) -> 658519.03 | M10: 0 | N10: 0 | O10: 0 | P10: 0 | Q10: 0 | R10: 0 | S10: 0 | T10: 0 | U10: 0 | V10: =$B10*(1.03^(V$3-$B$3)) -> 884994.5 | W10: 0 | X10: 0 | Y10: 0 | Z10: 0 | AA10: 0
A11: Signage | B11: =176*1000 -> 176000 | C11: 0 | D11: 0 | E11: 0 | F11: 0 | G11: 0 | H11: 0 | I11: 0 | J11: 0 | K11: 0 | L11: =$B11*(1.03^(L$3-$B$3)) -> 236529.28 | M11: 0 | N11: 0 | O11: 0 | P11: 0 | Q11: 0 | R11: 0 | S11: 0 | T11: 0 | U11: 0 | V11: =$B11*(1.03^(V$3-$B$3)) -> 317875.58 | W11: 0 | X11: 0 | Y11: 0 | Z11: 0 | AA11: 0
A12: Construction Cost | B12: =56*2000 -> 112000 | C12: 0 | D12: 0 | E12: 0 | F12: 0 | G12: 0 | H12: 0 | I12: 0 | J12: 0 | K12: 0 | L12: =$B12*(1.03^(L$3-$B$3)) -> 150518.63 | M12: 0 | N12: 0 | O12: 0 | P12: 0 | Q12: 0 | R12: 0 | S12: 0 | T12: 0 | U12: 0 | V12: =$B12*(1.03^(V$3-$B$3)) -> 202284.46 | W12: 0 | X12: 0 | Y12: 0 | Z12: 0 | AA12: 0
A13: Third Party Enforcement Contract Cost | B13: 0 | C13: 750000 | D13: =$C13*(1.03^(D$3-$C$3)) -> 772500 | E13: =$C13*(1.03^(E$3-$C$3)) -> 795675 | F13: =$C13*(1.03^(F$3-$C$3)) -> 819545.25 | G13: =$C13*(1.03^(G$3-$C$3)) -> 844131.61 | H13: =$C13*(1.03^(H$3-$C$3)) -> 869455.56 | I13: =$C13*(1.03^(I$3-$C$3)) -> 895539.22 | J13: =$C13*(1.03^(J$3-$C$3)) -> 922405.4 | K13: =$C13*(1.03^(K$3-$C$3)) -> 950077.56 | ... AA13: =$C13*(1.03^(AA$3-$C$3)) -> 1524595.6
A14: Parking Kiosks Operating Cost | B14: 0 | C14: 76000 | D14: =$C14*(1.03^(D$3-$C$3)) -> 78280 | E14: =$C14*(1.03^(E$3-$C$3)) -> 80628.4 | F14: =$C14*(1.03^(F$3-$C$3)) -> 83047.252 | G14: =$C14*(1.03^(G$3-$C$3)) -> 85538.67 | H14: =$C14*(1.03^(H$3-$C$3)) -> 88104.83 | I14: =$C14*(1.03^(I$3-$C$3)) -> 90747.975 | J14: =$C14*(1.03^(J$3-$C$3)) -> 93470.414 | K14: =$C14*(1.03^(K$3-$C$3)) -> 96274.526 | ... AA14: =$C14*(1.03^(AA$3-$C$3)) -> 154492.35
A15: Credit Card Transaction Fee | B15: 0 | C15: =C7*0.03*0.9 -> 59047.978 | D15: =D7*0.03*0.9 -> 55168.453 | E15: =E7*0.03*0.9 -> 55444.295 | F15: =F7*0.03*0.9 -> 55721.517 | G15: =G7*0.03*0.9 -> 56000.124 | H15: =H7*0.03*0.9 -> 56280.125 | I15: =I7*0.03*0.9 -> 56561.525 | J15: =J7*0.03*0.9 -> 56844.333 | ... AA15: =AA7*0.03*0.9 -> 100731.34
A16: Contribution to Community Benefits District | B16: 0 | D16: =$C16*(1.03^(D$3-$C$3)) -> 0 | E16: =$C16*(1.03^(E$3-$C$3)) -> 0 | F16: =$C16*(1.03^(F$3-$C$3)) -> 0 | G16: =$C16*(1.03^(G$3-$C$3)) -> 0 | H16: =$C16*(1.03^(H$3-$C$3)) -> 0 | I16: =$C16*(1.03^(I$3-$C$3)) -> 0 | J16: =$C16*(1.03^(J$3-$C$3)) -> 0 | K16: =$C16*(1.03^(K$3-$C$3)) -> 0 | ... AA16: =$C16*(1.03^(AA$3-$C$3)) -> 0
A17: Expenses Total | B17: =SUM(B10:B16) -> 778000 | C17: =SUM(C10:C16) -> 885047.98 | D17: =SUM(D10:D16) -> 905948.45 | E17: =SUM(E10:E16) -> 931747.7 | F17: =SUM(F10:F16) -> 958314.02 | G17: =SUM(G10:G16) -> 985670.4 | H17: =SUM(H10:H16) -> 1013840.5 | I17: =SUM(I10:I16) -> 1042848.7 | ... AA17: =SUM(AA10:AA16) -> 1779819.3
A19: Net Income | B19: =B7-B17 -> -778000 | C19: =C7-C17 -> 1301914.2 | D19: =D7-D17 -> 1137327.6 | E19: =E7-E17 -> 1121744.7 | F19: =F7-F17 -> 1105445.9 | G19: =G7-G17 -> 1088408.3 | H19: =H7-H17 -> 1070608.6 | I19: =I7-I17 -> 1052022.6 | ... AA19: =AA7-AA17 -> 1950971.2
A22: In 2025 Dollars | B22: 2025 | C22: 2026 | D22: 2027 | E22: 2028 | F22: 2029 | G22: 2030 | H22: 2031 | I22: 2032 | J22: 2033 | K22: 2034 | L22: 2035 | M22: 2036 | N22: 2037 | O22: 2038 | P22: 2039 | Q22: 2040 | R22: 2041 | S22: 2042 | T22: 2043 | U22: 2044 | V22: 2045 | W22: 2046 | X22: 2047 | Y22: 2048 | Z22: 2049 | AA22: 2050
A23: Revenue | B23: =B7/(1.03^(B$22-2025)) -> 0 | C23: =C7/(1.03^(C22-2025)) -> 2123264.2 | D23: =D7/(1.03^(D22-2025)) -> 1925983.6 | E23: =E7/(1.03^(E22-2025)) -> 1879236.5 | F23: =F7/(1.03^(F22-2025)) -> 1833623.9 | G23: =G7/(1.03^(G22-2025)) -> 1789118.5 | H23: =H7/(1.03^(H22-2025)) -> 1745693.3 | I23: =I7/(1.03^(I22-2025)) -> 1703322.1 | J23: =J7/(1.03^(J22-2025)) -> 1661979.3 | ... AA23: =AA7/(1.03^(AA22-2025)) -> 1781846.3
A24: Expenses | B24: =B17/(1.03^(B$22-2025)) -> 778000 | C24: =C17/(1.03^(C$22-2025)) -> 859269.88 | D24: =D17/(1.03^(D$22-2025)) -> 853943.31 | E24: =E17/(1.03^(E$22-2025)) -> 852681.13 | F24: =F17/(1.03^(F$22-2025)) -> 851449.59 | G24: =G17/(1.03^(G$22-2025)) -> 850247.95 | H24: =H17/(1.03^(H$22-2025)) -> 849075.47 | I24: =I17/(1.03^(I$22-2025)) -> 847931.44 | ... AA24: =AA17/(1.03^(AA$22-2025)) -> 850051.6
A25: Net Income | B25: =B19/(1.03^(B$22-2025)) -> -778000 | C25: =C19/(1.03^(C$22-2025)) -> 1263994.3 | D25: =D19/(1.03^(D$22-2025)) -> 1072040.3 | E25: =E19/(1.03^(E$22-2025)) -> 1026555.3 | F25: =F19/(1.03^(F$22-2025)) -> 982174.33 | G25: =G19/(1.03^(G$22-2025)) -> 938870.54 | H25: =H19/(1.03^(H$22-2025)) -> 896617.81 | I25: =I19/(1.03^(I$22-2025)) -> 855390.64 | ... AA25: =AA19/(1.03^(AA$22-2025)) -> 931794.72
A28: Item | B28: Amount (2025)
A29: Total Revenue | B29: =SUM(B23:AA23) -> 46345562
A30: Total Expenses | B30: =SUM(B24:AA24) -> 23633874
A31: Total Net Income | B31: =SUM(B25:AA25) -> 22711688

Sheet $1.5 per hr + $1 Projection
C1: Diff here | D1: Diff here | E1: Diff here | F1: - | G1: - | H1: - | I1: - | J1: - | K1: - | L1: Diff here | M1: - | N1: - | O1: - | P1: - | Q1: - | R1: - | S1: - | T1: - | U1: - | V1: Diff here | W1: - | X1: - | Y1: - | Z1: - | AA1: -
A3: Future Value | B3: 2025 | C3: 2026 | D3: 2027 | E3: 2028 | F3: 2029 | G3: 2030 | H3: 2031 | I3: 2032 | J3: 2033 | K3: 2034 | L3: 2035 | M3: 2036 | N3: 2037 | O3: 2038 | P3: 2039 | Q3: 2040 | R3: 2041 | S3: 2042 | T3: 2043 | U3: 2044 | V3: 2045 | W3: 2046 | X3: 2047 | Y3: 2048 | Z3: 2049 | AA3: 2050
A4: Revenue
A5: Paid Parking Revenue | B5: 0 | C5: =('Space & Elasticitiy'!K5+'Space & Elasticitiy'!I12)*(1.005^(C$3-2024)) -> 2186962.1 | D5: =('Space & Elasticitiy'!K19+'Space & Elasticitiy'!I12)*(1.005^(D$3-2024)) -> 2043276 | E5: =$D5*(1.005^(E$3-2027)) -> 2053492.4 | F5: =$D5*(1.005^(F$3-2027)) -> 2063759.9 | G5: =$D5*(1.005^(G$3-2027)) -> 2074078.7 | H5: =$D5*(1.005^(H$3-2027)) -> 2084449.1 | I5: =$D5*(1.005^(I$3-2027)) -> 2094871.3 | J5: =$D5*(1.005^(J$3-2027)) -> 2105345.7 | K5: =$D5*(1.005^(K$3-2027)) -> 2115872.4 | L5: =$K5*(1-0.04*2/3)*(1+2/3)*(1.005^(L$3-2034)) -> 3449577.3 | M5: =$K5*(1-0.04*2/3)*(1+2/3)*(1.005^(M$3-2034)) -> 3466825.2 | N5: =$K5*(1-0.04*2/3)*(1+2/3)*(1.005^(N$3-2034)) -> 3484159.3 | O5: =$K5*(1-0.04*2/3)*(1+2/3)*(1.005^(O$3-2034)) -> 3501580.1 | P5: =$K5*(1-0.04*2/3)*(1+2/3)*(1.005^(P$3-2034)) -> 3519088 | Q5: =$K5*(1-0.04*2/3)*(1+2/3)*(1.005^(Q$3-2034)) -> 3536683.5 | R5: =$K5*(1-0.04*2/3)*(1+2/3)*(1.005^(R$3-2034)) -> 3554366.9 | S5: =$K5*(1-0.04*2/3)*(1+2/3)*(1.005^(S$3-2034)) -> 3572138.7 | ... U5: =$K5*(1-0.04*2/3)*(1+2/3)*(1.005^(U$3-2034)) -> 3607949.4 | V5: =$U5*(1-0.04*2/5)*(1+2/5)*(1.005^(V$3-2044)) -> 4995162.6 | W5: =$U5*(1-0.04*2/5)*(1+2/5)*(1.005^(W$3-2044)) -> 5020138.5 | X5: =$U5*(1-0.04*2/5)*(1+2/5)*(1.005^(X$3-2044)) -> 5045239.1 | Y5: =$U5*(1-0.04*2/5)*(1+2/5)*(1.005^(Y$3-2044)) -> 5070465.3 | Z5: =$U5*(1-0.04*2/5)*(1+2/5)*(1.005^(Z$3-2044)) -> 5095817.7 | AA5: =$U5*(1-0.04*2/5)*(1+2/5)*(1.005^(AA$3-2044)) -> 5121296.8
A6: Citation Revenue | B6: 0 | C6: 450000 | D6: =$C$6*(1.005^(D$3-2026)) -> 452250 | E6: =$C$6*(1.005^(E$3-2026)) -> 454511.25 | F6: =$C$6*(1.005^(F$3-2026)) -> 456783.81 | G6: =$C$6*(1.005^(G$3-2026)) -> 459067.73 | H6: =$C$6*(1.005^(H$3-2026)) -> 461363.06 | I6: =$C$6*(1.005^(I$3-2026)) -> 463669.88 | J6: =$C$6*(1.005^(J$3-2026)) -> 465988.23 | K6: =$C$6*(1.005^(K$3-2026)) -> 468318.17 | ... AA6: =$C$6*(1.005^(AA$3-2026)) -> 507221.9
A7: Revenue Total | B7: =SUM(B5:B6) -> 0 | C7: =SUM(C5:C6) -> 2636962.1 | D7: =SUM(D5:D6) -> 2495526 | E7: =SUM(E5:E6) -> 2508003.7 | F7: =SUM(F5:F6) -> 2520543.7 | G7: =SUM(G5:G6) -> 2533146.4 | H7: =SUM(H5:H6) -> 2545812.1 | I7: =SUM(I5:I6) -> 2558541.2 | ... AA7: =SUM(AA5:AA6) -> 5628518.7
A9: Expenses
A10: Parking Kiosks Procurement | B10: =56*10000 -> 560000 | C10: 0 | D10: 0 | E10: 0 | F10: 0 | G10: 0 | H10: 0 | I10: 0 | J10: 0 | K10: 0 | L10: =$B10*(1.03^(L$3-$B$3)) -> 752593.17 | M10: 0 | N10: 0 | O10: 0 | P10: 0 | Q10: 0 | R10: 0 | S10: 0 | T10: 0 | U10: 0 | V10: =$B10*(1.03^(V$3-$B$3)) -> 1011422.3 | W10: 0 | X10: 0 | Y10: 0 | Z10: 0 | AA10: 0
A11: Signage | B11: =176*1000 -> 176000 | C11: 0 | D11: 0 | E11: 0 | F11: 0 | G11: 0 | H11: 0 | I11: 0 | J11: 0 | K11: 0 | L11: =$B11*(1.03^(L$3-$B$3)) -> 236529.28 | M11: 0 | N11: 0 | O11: 0 | P11: 0 | Q11: 0 | R11: 0 | S11: 0 | T11: 0 | U11: 0 | V11: =$B11*(1.03^(V$3-$B$3)) -> 317875.58 | W11: 0 | X11: 0 | Y11: 0 | Z11: 0 | AA11: 0
A12: Construction Cost | B12: =56*2000 -> 112000 | C12: 0 | D12: 0 | E12: 0 | F12: 0 | G12: 0 | H12: 0 | I12: 0 | J12: 0 | K12: 0 | L12: =$B12*(1.03^(L$3-$B$3)) -> 150518.63 | M12: 0 | N12: 0 | O12: 0 | P12: 0 | Q12: 0 | R12: 0 | S12: 0 | T12: 0 | U12: 0 | V12: =$B12*(1.03^(V$3-$B$3)) -> 202284.46 | W12: 0 | X12: 0 | Y12: 0 | Z12: 0 | AA12: 0
A13: Third Party Enforcement Contract Cost | B13: 0 | C13: 750000 | D13: =$C13*(1.03^(D$3-$C$3)) -> 772500 | E13: =$C13*(1.03^(E$3-$C$3)) -> 795675 | F13: =$C13*(1.03^(F$3-$C$3)) -> 819545.25 | G13: =$C13*(1.03^(G$3-$C$3)) -> 844131.61 | H13: =$C13*(1.03^(H$3-$C$3)) -> 869455.56 | I13: =$C13*(1.03^(I$3-$C$3)) -> 895539.22 | J13: =$C13*(1.03^(J$3-$C$3)) -> 922405.4 | K13: =$C13*(1.03^(K$3-$C$3)) -> 950077.56 | ... AA13: =$C13*(1.03^(AA$3-$C$3)) -> 1524595.6
A14: Parking Kiosks Operating Cost | B14: 0 | C14: 76000 | D14: =$C14*(1.03^(D$3-$C$3)) -> 78280 | E14: =$C14*(1.03^(E$3-$C$3)) -> 80628.4 | F14: =$C14*(1.03^(F$3-$C$3)) -> 83047.252 | G14: =$C14*(1.03^(G$3-$C$3)) -> 85538.67 | H14: =$C14*(1.03^(H$3-$C$3)) -> 88104.83 | I14: =$C14*(1.03^(I$3-$C$3)) -> 90747.975 | J14: =$C14*(1.03^(J$3-$C$3)) -> 93470.414 | K14: =$C14*(1.03^(K$3-$C$3)) -> 96274.526 | ... AA14: =$C14*(1.03^(AA$3-$C$3)) -> 154492.35
A15: Credit Card Transaction Fee | B15: 0 | C15: =C7*0.03*0.9 -> 71197.978 | D15: =D7*0.03*0.9 -> 67379.203 | E15: =E7*0.03*0.9 -> 67716.099 | F15: =F7*0.03*0.9 -> 68054.679 | G15: =G7*0.03*0.9 -> 68394.953 | H15: =H7*0.03*0.9 -> 68736.928 | I15: =I7*0.03*0.9 -> 69080.612 | J15: =J7*0.03*0.9 -> 69426.015 | ... AA15: =AA7*0.03*0.9 -> 151970
A16: Contribution to Community Benefits District | B16: 0 | C16: 250000 | D16: =$C16*(1.03^(D$3-$C$3)) -> 257500 | E16: =$C16*(1.03^(E$3-$C$3)) -> 265225 | F16: =$C16*(1.03^(F$3-$C$3)) -> 273181.75 | G16: =$C16*(1.03^(G$3-$C$3)) -> 281377.2 | H16: =$C16*(1.03^(H$3-$C$3)) -> 289818.52 | I16: =$C16*(1.03^(I$3-$C$3)) -> 298513.07 | J16: =$C16*(1.03^(J$3-$C$3)) -> 307468.47 | K16: =$C16*(1.03^(K$3-$C$3)) -> 316692.52 | ... AA16: =$C16*(1.03^(AA$3-$C$3)) -> 508198.53
A17: Expenses Total | B17: =SUM(B10:B16) -> 848000 | C17: =SUM(C10:C16) -> 1147198 | D17: =SUM(D10:D16) -> 1175659.2 | E17: =SUM(E10:E16) -> 1209244.5 | F17: =SUM(F10:F16) -> 1243828.9 | G17: =SUM(G10:G16) -> 1279442.4 | H17: =SUM(H10:H16) -> 1316115.8 | I17: =SUM(I10:I16) -> 1353880.9 | ... AA17: =SUM(AA10:AA16) -> 2339256.5
A19: Net Income | B19: =B7-B17 -> -848000 | C19: =C7-C17 -> 1489764.2 | D19: =D7-D17 -> 1319866.8 | E19: =E7-E17 -> 1298759.2 | F19: =F7-F17 -> 1276714.8 | G19: =G7-G17 -> 1253704 | H19: =H7-H17 -> 1229696.3 | I19: =I7-I17 -> 1204660.3 | ... AA19: =AA7-AA17 -> 3289262.2
A22: In 2025 Dollars | B22: 2025 | C22: 2026 | D22: 2027 | E22: 2028 | F22: 2029 | G22: 2030 | H22: 2031 | I22: 2032 | J22: 2033 | K22: 2034 | L22: 2035 | M22: 2036 | N22: 2037 | O22: 2038 | P22: 2039 | Q22: 2040 | R22: 2041 | S22: 2042 | T22: 2043 | U22: 2044 | V22: 2045 | W22: 2046 | X22: 2047 | Y22: 2048 | Z22: 2049 | AA22: 2050
A23: Revenue | B23: =B7/(1.03^(B$22-2025)) -> 0 | C23: =C7/(1.03^(C22-2025)) -> 2560157.4 | D23: =D7/(1.03^(D22-2025)) -> 2352272.6 | E23: =E7/(1.03^(E22-2025)) -> 2295178.6 | F23: =F7/(1.03^(F22-2025)) -> 2239470.4 | G23: =G7/(1.03^(G22-2025)) -> 2185114.3 | H23: =H7/(1.03^(H22-2025)) -> 2132077.6 | I23: =I7/(1.03^(I22-2025)) -> 2080328.1 | J23: =J7/(1.03^(J22-2025)) -> 2029834.7 | ... AA23: =AA7/(1.03^(AA22-2025)) -> 2688211.9
A24: Expenses | B24: =B17/(1.03^(B$22-2025)) -> 848000 | C24: =C17/(1.03^(C$22-2025)) -> 1113784.4 | D24: =D17/(1.03^(D$22-2025)) -> 1108171.6 | E24: =E17/(1.03^(E$22-2025)) -> 1106630 | F24: =F17/(1.03^(F$22-2025)) -> 1105125.9 | G24: =G17/(1.03^(G$22-2025)) -> 1103658.3 | H24: =H17/(1.03^(H$22-2025)) -> 1102226.3 | I24: =I17/(1.03^(I$22-2025)) -> 1100829.1 | ... AA24: =AA17/(1.03^(AA$22-2025)) -> 1117241.9
A25: Net Income | B25: =B19/(1.03^(B$22-2025)) -> -848000 | C25: =C19/(1.03^(C$22-2025)) -> 1446373 | D25: =D19/(1.03^(D$22-2025)) -> 1244101.1 | E25: =E19/(1.03^(E$22-2025)) -> 1188548.6 | F25: =F19/(1.03^(F$22-2025)) -> 1134344.5 | G25: =G19/(1.03^(G$22-2025)) -> 1081456.1 | H25: =H19/(1.03^(H$22-2025)) -> 1029851.3 | I25: =I19/(1.03^(I$22-2025)) -> 979499.07 | ... AA25: =AA19/(1.03^(AA$22-2025)) -> 1570969.9
A27: Item | B27: Amount (2025)
A28: Total Revenue | B28: =SUM(B23:AA23) -> 63203116
A29: Total Expenses | B29: =SUM(B24:AA24) -> 30366989
A30: Total Net Income | B30: =SUM(B25:AA25) -> 32836127

Sheet $2 per hr + $0.5 Projection
C1: Diff here | D1: Diff here | E1: Diff here | F1: - | G1: - | H1: - | I1: - | J1: - | K1: - | L1: Diff here | M1: - | N1: - | O1: - | P1: - | Q1: - | R1: - | S1: - | T1: - | U1: - | V1: Diff here | W1: - | X1: - | Y1: - | Z1: - | AA1: -
A3: Future Value | B3: 2025 | C3: 2026 | D3: 2027 | E3: 2028 | F3: 2029 | G3: 2030 | H3: 2031 | I3: 2032 | J3: 2033 | K3: 2034 | L3: 2035 | M3: 2036 | N3: 2037 | O3: 2038 | P3: 2039 | Q3: 2040 | R3: 2041 | S3: 2042 | T3: 2043 | U3: 2044 | V3: 2045 | W3: 2046 | X3: 2047 | Y3: 2048 | Z3: 2049 | AA3: 2050
A4: Revenue
A5: Paid Parking Revenue | B5: 0 | C5: =('Space & Elasticitiy'!L5+'Space & Elasticitiy'!I12)*(1.005^(C$3-2024)) -> 2822468.4 | D5: =('Space & Elasticitiy'!L19+'Space & Elasticitiy'!I12)*(1.005^(D$3-2024)) -> 2634626.9 | E5: =$D5*(1.005^(E$3-2027)) -> 2647800 | F5: =$D5*(1.005^(F$3-2027)) -> 2661039 | G5: =$D5*(1.005^(G$3-2027)) -> 2674344.2 | H5: =$D5*(1.005^(H$3-2027)) -> 2687716 | I5: =$D5*(1.005^(I$3-2027)) -> 2701154.5 | J5: =$D5*(1.005^(J$3-2027)) -> 2714660.3 | K5: =$D5*(1.005^(K$3-2027)) -> 2728233.6 | L5: =$K5*(1-0.04*1/4)*(1+1/4)*(1.005^(L$3-2034)) -> 3393070 | M5: =$K5*(1-0.04*1/4)*(1+1/4)*(1.005^(M$3-2034)) -> 3410035.4 | N5: =$K5*(1-0.04*1/4)*(1+1/4)*(1.005^(N$3-2034)) -> 3427085.6 | O5: =$K5*(1-0.04*1/4)*(1+1/4)*(1.005^(O$3-2034)) -> 3444221 | P5: =$K5*(1-0.04*1/4)*(1+1/4)*(1.005^(P$3-2034)) -> 3461442.1 | Q5: =$K5*(1-0.04*1/4)*(1+1/4)*(1.005^(Q$3-2034)) -> 3478749.3 | R5: =$K5*(1-0.04*1/4)*(1+1/4)*(1.005^(R$3-2034)) -> 3496143.1 | S5: =$K5*(1-0.04*1/4)*(1+1/4)*(1.005^(S$3-2034)) -> 3513623.8 | ... U5: =$K5*(1-0.04*1/4)*(1+1/4)*(1.005^(U$3-2034)) -> 3548847.8 | V5: =$U5*(1-0.04*1/5)*(1+1/5)*(1.005^(V$3-2044)) -> 4245671.2 | W5: =$U5*(1-0.04*1/5)*(1+1/5)*(1.005^(W$3-2044)) -> 4266899.6 | X5: =$U5*(1-0.04*1/5)*(1+1/5)*(1.005^(X$3-2044)) -> 4288234.1 | Y5: =$U5*(1-0.04*1/5)*(1+1/5)*(1.005^(Y$3-2044)) -> 4309675.2 | Z5: =$U5*(1-0.04*1/5)*(1+1/5)*(1.005^(Z$3-2044)) -> 4331223.6 | AA5: =$U5*(1-0.04*1/5)*(1+1/5)*(1.005^(AA$3-2044)) -> 4352879.7
A6: Citation Revenue | B6: 0 | C6: 450000 | D6: =$C$6*(1.005^(D$3-2026)) -> 452250 | E6: =$C$6*(1.005^(E$3-2026)) -> 454511.25 | F6: =$C$6*(1.005^(F$3-2026)) -> 456783.81 | G6: =$C$6*(1.005^(G$3-2026)) -> 459067.73 | H6: =$C$6*(1.005^(H$3-2026)) -> 461363.06 | I6: =$C$6*(1.005^(I$3-2026)) -> 463669.88 | J6: =$C$6*(1.005^(J$3-2026)) -> 465988.23 | K6: =$C$6*(1.005^(K$3-2026)) -> 468318.17 | ... AA6: =$C$6*(1.005^(AA$3-2026)) -> 507221.9
A7: Revenue Total | B7: =SUM(B5:B6) -> 0 | C7: =SUM(C5:C6) -> 3272468.4 | D7: =SUM(D5:D6) -> 3086876.9 | E7: =SUM(E5:E6) -> 3102311.3 | F7: =SUM(F5:F6) -> 3117822.8 | G7: =SUM(G5:G6) -> 3133412 | H7: =SUM(H5:H6) -> 3149079 | I7: =SUM(I5:I6) -> 3164824.4 | ... AA7: =SUM(AA5:AA6) -> 4860101.6
A9: Expenses
A10: Parking Kiosks Procurement | B10: =56*10000 -> 560000 | C10: 0 | D10: 0 | E10: 0 | F10: 0 | G10: 0 | H10: 0 | I10: 0 | J10: 0 | K10: 0 | L10: =$B10*(1.03^(L$3-$B$3)) -> 752593.17 | M10: 0 | N10: 0 | O10: 0 | P10: 0 | Q10: 0 | R10: 0 | S10: 0 | T10: 0 | U10: 0 | V10: =$B10*(1.03^(V$3-$B$3)) -> 1011422.3 | W10: 0 | X10: 0 | Y10: 0 | Z10: 0 | AA10: 0
A11: Signage | B11: =176*1000 -> 176000 | C11: 0 | D11: 0 | E11: 0 | F11: 0 | G11: 0 | H11: 0 | I11: 0 | J11: 0 | K11: 0 | L11: =$B11*(1.03^(L$3-$B$3)) -> 236529.28 | M11: 0 | N11: 0 | O11: 0 | P11: 0 | Q11: 0 | R11: 0 | S11: 0 | T11: 0 | U11: 0 | V11: =$B11*(1.03^(V$3-$B$3)) -> 317875.58 | W11: 0 | X11: 0 | Y11: 0 | Z11: 0 | AA11: 0
A12: Construction Cost | B12: =56*2000 -> 112000 | C12: 0 | D12: 0 | E12: 0 | F12: 0 | G12: 0 | H12: 0 | I12: 0 | J12: 0 | K12: 0 | L12: =$B12*(1.03^(L$3-$B$3)) -> 150518.63 | M12: 0 | N12: 0 | O12: 0 | P12: 0 | Q12: 0 | R12: 0 | S12: 0 | T12: 0 | U12: 0 | V12: =$B12*(1.03^(V$3-$B$3)) -> 202284.46 | W12: 0 | X12: 0 | Y12: 0 | Z12: 0 | AA12: 0
A13: Third Party Enforcement Contract Cost | B13: 0 | C13: 750000 | D13: =$C13*(1.03^(D$3-$C$3)) -> 772500 | E13: =$C13*(1.03^(E$3-$C$3)) -> 795675 | F13: =$C13*(1.03^(F$3-$C$3)) -> 819545.25 | G13: =$C13*(1.03^(G$3-$C$3)) -> 844131.61 | H13: =$C13*(1.03^(H$3-$C$3)) -> 869455.56 | I13: =$C13*(1.03^(I$3-$C$3)) -> 895539.22 | J13: =$C13*(1.03^(J$3-$C$3)) -> 922405.4 | K13: =$C13*(1.03^(K$3-$C$3)) -> 950077.56 | ... AA13: =$C13*(1.03^(AA$3-$C$3)) -> 1524595.6
A14: Parking Kiosks Operating Cost | B14: 0 | C14: 76000 | D14: =$C14*(1.03^(D$3-$C$3)) -> 78280 | E14: =$C14*(1.03^(E$3-$C$3)) -> 80628.4 | F14: =$C14*(1.03^(F$3-$C$3)) -> 83047.252 | G14: =$C14*(1.03^(G$3-$C$3)) -> 85538.67 | H14: =$C14*(1.03^(H$3-$C$3)) -> 88104.83 | I14: =$C14*(1.03^(I$3-$C$3)) -> 90747.975 | J14: =$C14*(1.03^(J$3-$C$3)) -> 93470.414 | K14: =$C14*(1.03^(K$3-$C$3)) -> 96274.526 | ... AA14: =$C14*(1.03^(AA$3-$C$3)) -> 154492.35
A15: Credit Card Transaction Fee | B15: 0 | C15: =C7*0.03*0.9 -> 88356.647 | D15: =D7*0.03*0.9 -> 83345.676 | E15: =E7*0.03*0.9 -> 83762.405 | F15: =F7*0.03*0.9 -> 84181.217 | G15: =G7*0.03*0.9 -> 84602.123 | H15: =H7*0.03*0.9 -> 85025.134 | I15: =I7*0.03*0.9 -> 85450.259 | J15: =J7*0.03*0.9 -> 85877.51 | ... AA15: =AA7*0.03*0.9 -> 131222.74
A16: Contribution to Community Benefits District | B16: 0 | C16: 250000 | D16: =$C16*(1.03^(D$3-$C$3)) -> 257500 | E16: =$C16*(1.03^(E$3-$C$3)) -> 265225 | F16: =$C16*(1.03^(F$3-$C$3)) -> 273181.75 | G16: =$C16*(1.03^(G$3-$C$3)) -> 281377.2 | H16: =$C16*(1.03^(H$3-$C$3)) -> 289818.52 | I16: =$C16*(1.03^(I$3-$C$3)) -> 298513.07 | J16: =$C16*(1.03^(J$3-$C$3)) -> 307468.47 | K16: =$C16*(1.03^(K$3-$C$3)) -> 316692.52 | ... AA16: =$C16*(1.03^(AA$3-$C$3)) -> 508198.53
A17: Expenses Total | B17: =SUM(B10:B16) -> 848000 | C17: =SUM(C10:C16) -> 1164356.6 | D17: =SUM(D10:D16) -> 1191625.7 | E17: =SUM(E10:E16) -> 1225290.8 | F17: =SUM(F10:F16) -> 1259955.5 | G17: =SUM(G10:G16) -> 1295649.6 | H17: =SUM(H10:H16) -> 1332404 | I17: =SUM(I10:I16) -> 1370250.5 | ... AA17: =SUM(AA10:AA16) -> 2318509.2
A19: Net Income | B19: =B7-B17 -> -848000 | C19: =C7-C17 -> 2108111.8 | D19: =D7-D17 -> 1895251.2 | E19: =E7-E17 -> 1877020.5 | F19: =F7-F17 -> 1857867.4 | G19: =G7-G17 -> 1837762.4 | H19: =H7-H17 -> 1816675 | I19: =I7-I17 -> 1794573.9 | ... AA19: =AA7-AA17 -> 2541592.4
A22: In 2025 Dollars | B22: 2025 | C22: 2026 | D22: 2027 | E22: 2028 | F22: 2029 | G22: 2030 | H22: 2031 | I22: 2032 | J22: 2033 | K22: 2034 | L22: 2035 | M22: 2036 | N22: 2037 | O22: 2038 | P22: 2039 | Q22: 2040 | R22: 2041 | S22: 2042 | T22: 2043 | U22: 2044 | V22: 2045 | W22: 2046 | X22: 2047 | Y22: 2048 | Z22: 2049 | AA22: 2050
A23: Revenue | B23: =B7/(1.03^(B$22-2025)) -> 0 | C23: =C7/(1.03^(C22-2025)) -> 3177153.8 | D23: =D7/(1.03^(D22-2025)) -> 2909677.5 | E23: =E7/(1.03^(E22-2025)) -> 2839054.3 | F23: =F7/(1.03^(F22-2025)) -> 2770145.2 | G23: =G7/(1.03^(G22-2025)) -> 2702908.7 | H23: =H7/(1.03^(H22-2025)) -> 2637304.1 | I23: =I7/(1.03^(I22-2025)) -> 2573291.9 | J23: =J7/(1.03^(J22-2025)) -> 2510833.3 | ... AA23: =AA7/(1.03^(AA22-2025)) -> 2321211.6
A24: Expenses | B24: =B17/(1.03^(B$22-2025)) -> 848000 | C24: =C17/(1.03^(C$22-2025)) -> 1130443.3 | D24: =D17/(1.03^(D$22-2025)) -> 1123221.5 | E24: =E17/(1.03^(E$22-2025)) -> 1121314.7 | F24: =F17/(1.03^(F$22-2025)) -> 1119454.1 | G24: =G17/(1.03^(G$22-2025)) -> 1117638.7 | H24: =H17/(1.03^(H$22-2025)) -> 1115867.4 | I24: =I17/(1.03^(I$22-2025)) -> 1114139.1 | ... AA24: =AA17/(1.03^(AA$22-2025)) -> 1107332.9
A25: Net Income | B25: =B19/(1.03^(B$22-2025)) -> -848000 | C25: =C19/(1.03^(C$22-2025)) -> 2046710.4 | D25: =D19/(1.03^(D$22-2025)) -> 1786456.1 | E25: =E19/(1.03^(E$22-2025)) -> 1717739.6 | F25: =F19/(1.03^(F$22-2025)) -> 1650691.1 | G25: =G19/(1.03^(G$22-2025)) -> 1585270 | H25: =H19/(1.03^(H$22-2025)) -> 1521436.7 | I25: =I19/(1.03^(I$22-2025)) -> 1459152.8 | ... AA25: =AA19/(1.03^(AA$22-2025)) -> 1213878.7
A27: Item | B27: Amount (2025)
A28: Total Revenue | B28: =SUM(B23:AA23) -> 65197413
A29: Total Expenses | B29: =SUM(B24:AA24) -> 30420835
A30: Total Net Income | B30: =SUM(B25:AA25) -> 34776578

Sheet $2 per hr + $1 Projection
C1: Diff here | D1: Diff here | E1: Diff here | F1: - | G1: - | H1: - | I1: - | J1: - | K1: - | L1: Diff here | M1: - | N1: - | O1: - | P1: - | Q1: - | R1: - | S1: - | T1: - | U1: - | V1: Diff here | W1: - | X1: - | Y1: - | Z1: - | AA1: -
A3: Future Value | B3: 2025 | C3: 2026 | D3: 2027 | E3: 2028 | F3: 2029 | G3: 2030 | H3: 2031 | I3: 2032 | J3: 2033 | K3: 2034 | L3: 2035 | M3: 2036 | N3: 2037 | O3: 2038 | P3: 2039 | Q3: 2040 | R3: 2041 | S3: 2042 | T3: 2043 | U3: 2044 | V3: 2045 | W3: 2046 | X3: 2047 | Y3: 2048 | Z3: 2049 | AA3: 2050
A4: Revenue
A5: Paid Parking Revenue | B5: 0 | C5: =('Space & Elasticitiy'!L5+'Space & Elasticitiy'!I12)*(1.005^(C$3-2024)) -> 2822468.4 | D5: =('Space & Elasticitiy'!L19+'Space & Elasticitiy'!I12)*(1.005^(D$3-2024)) -> 2634626.9 | E5: =$D5*(1.005^(E$3-2027)) -> 2647800 | F5: =$D5*(1.005^(F$3-2027)) -> 2661039 | G5: =$D5*(1.005^(G$3-2027)) -> 2674344.2 | H5: =$D5*(1.005^(H$3-2027)) -> 2687716 | I5: =$D5*(1.005^(I$3-2027)) -> 2701154.5 | J5: =$D5*(1.005^(J$3-2027)) -> 2714660.3 | K5: =$D5*(1.005^(K$3-2027)) -> 2728233.6 | L5: =$K5*(1-0.04*1/2)*(1+1/2)*(1.005^(L$3-2034)) -> 4030555.9 | M5: =$K5*(1-0.04*1/2)*(1+1/2)*(1.005^(M$3-2034)) -> 4050708.7 | N5: =$K5*(1-0.04*1/2)*(1+1/2)*(1.005^(N$3-2034)) -> 4070962.2 | O5: =$K5*(1-0.04*1/2)*(1+1/2)*(1.005^(O$3-2034)) -> 4091317.1 | P5: =$K5*(1-0.04*1/2)*(1+1/2)*(1.005^(P$3-2034)) -> 4111773.6 | Q5: =$K5*(1-0.04*1/2)*(1+1/2)*(1.005^(Q$3-2034)) -> 4132332.5 | R5: =$K5*(1-0.04*1/2)*(1+1/2)*(1.005^(R$3-2034)) -> 4152994.2 | S5: =$K5*(1-0.04*1/2)*(1+1/2)*(1.005^(S$3-2034)) -> 4173759.1 | ... U5: =$K5*(1-0.04*1/2)*(1+1/2)*(1.005^(U$3-2034)) -> 4215601.1 | V5: =$U5*(1-0.04*1/3)*(1+1/3)*(1.005^(V$3-2044)) -> 5573586.7 | W5: =$U5*(1-0.04*1/3)*(1+1/3)*(1.005^(W$3-2044)) -> 5601454.6 | X5: =$U5*(1-0.04*1/3)*(1+1/3)*(1.005^(X$3-2044)) -> 5629461.9 | Y5: =$U5*(1-0.04*1/3)*(1+1/3)*(1.005^(Y$3-2044)) -> 5657609.2 | Z5: =$U5*(1-0.04*1/3)*(1+1/3)*(1.005^(Z$3-2044)) -> 5685897.3 | AA5: =$U5*(1-0.04*1/3)*(1+1/3)*(1.005^(AA$3-2044)) -> 5714326.8
A6: Citation Revenue | B6: 0 | C6: 450000 | D6: =$C$6*(1.005^(D$3-2026)) -> 452250 | E6: =$C$6*(1.005^(E$3-2026)) -> 454511.25 | F6: =$C$6*(1.005^(F$3-2026)) -> 456783.81 | G6: =$C$6*(1.005^(G$3-2026)) -> 459067.73 | H6: =$C$6*(1.005^(H$3-2026)) -> 461363.06 | I6: =$C$6*(1.005^(I$3-2026)) -> 463669.88 | J6: =$C$6*(1.005^(J$3-2026)) -> 465988.23 | K6: =$C$6*(1.005^(K$3-2026)) -> 468318.17 | ... AA6: =$C$6*(1.005^(AA$3-2026)) -> 507221.9
A7: Revenue Total | B7: =SUM(B5:B6) -> 0 | C7: =SUM(C5:C6) -> 3272468.4 | D7: =SUM(D5:D6) -> 3086876.9 | E7: =SUM(E5:E6) -> 3102311.3 | F7: =SUM(F5:F6) -> 3117822.8 | G7: =SUM(G5:G6) -> 3133412 | H7: =SUM(H5:H6) -> 3149079 | I7: =SUM(I5:I6) -> 3164824.4 | ... AA7: =SUM(AA5:AA6) -> 6221548.7
A9: Expenses
A10: Parking Kiosks Procurement | B10: =56*10000 -> 560000 | C10: 0 | D10: 0 | E10: 0 | F10: 0 | G10: 0 | H10: 0 | I10: 0 | J10: 0 | K10: 0 | L10: =$B10*(1.03^(L$3-$B$3)) -> 752593.17 | M10: 0 | N10: 0 | O10: 0 | P10: 0 | Q10: 0 | R10: 0 | S10: 0 | T10: 0 | U10: 0 | V10: =$B10*(1.03^(V$3-$B$3)) -> 1011422.3 | W10: 0 | X10: 0 | Y10: 0 | Z10: 0 | AA10: 0
A11: Signage | B11: =176*1000 -> 176000 | C11: 0 | D11: 0 | E11: 0 | F11: 0 | G11: 0 | H11: 0 | I11: 0 | J11: 0 | K11: 0 | L11: =$B11*(1.03^(L$3-$B$3)) -> 236529.28 | M11: 0 | N11: 0 | O11: 0 | P11: 0 | Q11: 0 | R11: 0 | S11: 0 | T11: 0 | U11: 0 | V11: =$B11*(1.03^(V$3-$B$3)) -> 317875.58 | W11: 0 | X11: 0 | Y11: 0 | Z11: 0 | AA11: 0
A12: Construction Cost | B12: =56*2000 -> 112000 | C12: 0 | D12: 0 | E12: 0 | F12: 0 | G12: 0 | H12: 0 | I12: 0 | J12: 0 | K12: 0 | L12: =$B12*(1.03^(L$3-$B$3)) -> 150518.63 | M12: 0 | N12: 0 | O12: 0 | P12: 0 | Q12: 0 | R12: 0 | S12: 0 | T12: 0 | U12: 0 | V12: =$B12*(1.03^(V$3-$B$3)) -> 202284.46 | W12: 0 | X12: 0 | Y12: 0 | Z12: 0 | AA12: 0
A13: Third Party Enforcement Contract Cost | B13: 0 | C13: 750000 | D13: =$C13*(1.03^(D$3-$C$3)) -> 772500 | E13: =$C13*(1.03^(E$3-$C$3)) -> 795675 | F13: =$C13*(1.03^(F$3-$C$3)) -> 819545.25 | G13: =$C13*(1.03^(G$3-$C$3)) -> 844131.61 | H13: =$C13*(1.03^(H$3-$C$3)) -> 869455.56 | I13: =$C13*(1.03^(I$3-$C$3)) -> 895539.22 | J13: =$C13*(1.03^(J$3-$C$3)) -> 922405.4 | K13: =$C13*(1.03^(K$3-$C$3)) -> 950077.56 | ... AA13: =$C13*(1.03^(AA$3-$C$3)) -> 1524595.6
A14: Parking Kiosks Operating Cost | B14: 0 | C14: 76000 | D14: =$C14*(1.03^(D$3-$C$3)) -> 78280 | E14: =$C14*(1.03^(E$3-$C$3)) -> 80628.4 | F14: =$C14*(1.03^(F$3-$C$3)) -> 83047.252 | G14: =$C14*(1.03^(G$3-$C$3)) -> 85538.67 | H14: =$C14*(1.03^(H$3-$C$3)) -> 88104.83 | I14: =$C14*(1.03^(I$3-$C$3)) -> 90747.975 | J14: =$C14*(1.03^(J$3-$C$3)) -> 93470.414 | K14: =$C14*(1.03^(K$3-$C$3)) -> 96274.526 | ... AA14: =$C14*(1.03^(AA$3-$C$3)) -> 154492.35
A15: Credit Card Transaction Fee | B15: 0 | C15: =C7*0.03*0.9 -> 88356.647 | D15: =D7*0.03*0.9 -> 83345.676 | E15: =E7*0.03*0.9 -> 83762.405 | F15: =F7*0.03*0.9 -> 84181.217 | G15: =G7*0.03*0.9 -> 84602.123 | H15: =H7*0.03*0.9 -> 85025.134 | I15: =I7*0.03*0.9 -> 85450.259 | J15: =J7*0.03*0.9 -> 85877.51 | ... AA15: =AA7*0.03*0.9 -> 167981.81
